Workbook

Sheet Summary
A1: lululemon athletica: what the business is worth, on its own filings
A2: A discounted cash flow valuation as of 2026-03-17, from the FY2025 10-K. Not investment advice: a worked valuation whose every input is sourced and whose every output is a formula.
B4: Bear | C4: Base | D4: Bull
A5: Value per share (USD) | B5: =DCF_Bear!B36 -> 171.39585 | C5: =DCF_Base!B36 -> 277.87694 | D5: =DCF_Bull!B36 -> 369.16779
A6: Enterprise value (USD M) | B6: =DCF_Bear!B31 -> 1.8005923e+10 | C6: =DCF_Base!B31 -> 3.0314992e+10 | D6: =DCF_Bull!B31 -> 4.0868089e+10
A7: Equity value (USD M) | B7: =DCF_Bear!B34 -> 1.9813125e+10 | C7: =DCF_Base!B34 -> 3.2122194e+10 | D7: =DCF_Bull!B34 -> 4.2675291e+10
A8: Terminal value, share of EV | B8: =DCF_Bear!B37 -> 0.7532227 | C8: =DCF_Base!B37 -> 0.78702732 | D8: =DCF_Bull!B37 -> 0.8111072
A9: Implied exit EV / EBITDA | B9: =DCF_Bear!B38 -> 8.1143857 | C9: =DCF_Base!B38 -> 9.8816999 | D9: =DCF_Bull!B38 -> 11.231328
A10: Cost of equity = WACC | B10: =DCF_Bear!B24 -> 0.077234 | C10: =DCF_Base!B24 -> 0.077234 | D10: =DCF_Bull!B24 -> 0.077234
A11: Terminal growth | B11: =DCF_Bear!B25 -> 0.02 | C11: =DCF_Base!B25 -> 0.025 | D11: =DCF_Bull!B25 -> 0.03
A14: FY2025 as filed
A15: Revenue (USD M) | B15: =History!F5 -> 11102600000
A16: Revenue growth | B16: =History!F6 -> 0.048589713
A17: EBIT margin | B17: =History!F9 -> 0.19910787
A18: Operating working capital, % of revenue | B18: =History!F15 -> 0.095894565
A20: Checks passing | B20: =Checks!B24 -> 18 | C20: of 18

Sheet Inputs
A1: Inputs: market data and the three scenarios
A2: Blue on yellow is an input. Every market input names its source; every driver is a judgement, stated.
A4: Market input | B4: Value | C4: Source
A5: Valuation date | B5: 46098 | C5: the day lululemon filed its FY2025 10-K (accession 0001397187-26-000020): the first day the market had the full year
A6: Middle of FY2026 | B6: 46236 | C6: cash flows arrive, on average, mid-year
A7: Risk-free rate | B7: 0.042 | C7: U.S. Department of the Treasury, Daily Treasury Par Yield Curve Rates, March 2026 (home.treasury.gov)
A8: Equity risk premium | B8: 0.0446 | C8: Aswath Damodaran, Country Default Spreads and Risk Premiums, January 2026 (pages.stern.nyu.edu/~adamodar, ctryprem.html)
A9: Beta | B9: 0.79 | C9: Apparel industry (US, 35 firms), unlevered beta corrected for cash, January 2026; Aswath Damodaran, Betas by Sector (US), January 2026 (pages.stern.nyu.edu/~adamodar, Betas.html)
A10: Beta, alternative | B10: 1 | C10: Retail (Special Lines), the same measure, for the sensitivity
A11: Debt | B11: 0 | C11: no borrowings at FY2025 year end (OtherBorrowings 0; the revolving facility undrawn)
A12: Common shares | B12: 110482671 | C12: FY2025 10-K cover page, accession 0001397187-26-000020
A13: Exchangeable shares | B13: 5115961 | C13: common stock plus exchangeable shares of Lulu Canadian Holding, which convert one for one
A16: Driver | B16: Year | C16: Bear | D16: Base | E16: Bull
A17: Revenue growth | B17: FY2026 | C17: -0.01 | D17: 0.03 | E17: 0.06
A18: Revenue growth | B18: FY2027 | C18: 0.01 | D18: 0.05 | E18: 0.08
A19: Revenue growth | B19: FY2028 | C19: 0.02 | D19: 0.06 | E19: 0.09
A20: Revenue growth | B20: FY2029 | C20: 0.03 | D20: 0.06 | E20: 0.08
A21: Revenue growth | B21: FY2030 | C21: 0.03 | D21: 0.05 | E21: 0.07
A22: Operating (EBIT) margin | B22: FY2026 | C22: 0.16 | D22: 0.185 | E22: 0.2
A23: Operating (EBIT) margin | B23: FY2027 | C23: 0.155 | D23: 0.19 | E23: 0.21
A24: Operating (EBIT) margin | B24: FY2028 | C24: 0.155 | D24: 0.195 | E24: 0.215
A25: Operating (EBIT) margin | B25: FY2029 | C25: 0.155 | D25: 0.2 | E25: 0.22
A26: Operating (EBIT) margin | B26: FY2030 | C26: 0.155 | D26: 0.2 | E26: 0.22
A27: Capex, % of revenue | B27: FY2026 | C27: 0.06 | D27: 0.06 | E27: 0.06
A28: Capex, % of revenue | B28: FY2027 | C28: 0.06 | D28: 0.06 | E28: 0.06
... A36: Return on new capital, terminal | B36: all years | C36: 0.12 | D36: 0.2 | E36: 0.25
A38: The story behind each case
A39: Bear | B39: the margin reset of FY2025 keeps going: markdowns and tariffs take another 50 bps, growth stalls in the Americas
A40: Base | B40: FY2025's 4.9% growth and 19.9% operating margin hold roughly where they are: growth recovers to mid-single digits on international stores, the margin climbs back to 20%
A41: Bull | B41: international keeps compounding and the margin recovers most of the way to FY2024's 23.7%
A44: Sensitivity axes
A45: WACC | B45: 0.065 | C45: 0.07 | D45: 0.075 | E45: 0.08 | F45: 0.085 | G45: 0.09 | H45: 0.095 | I45: 0.1
A46: Terminal growth | B46: 0.015 | C46: 0.02 | D46: 0.025 | E46: 0.03 | F46: 0.035

Sheet DCF_Base
A1: DCF, base case: free cash flow to the firm, FY2026 to FY2030
A2: Every cell is a formula over Inputs, History and Data_EDGAR. Money in USD millions.
B4: FY2025 (filed) | C4: FY2026 | D4: FY2027 | E4: FY2028 | F4: FY2029 | G4: FY2030
A5: Revenue | B5: =History!F5 -> 11102600000 | C5: =B5*(1+Inputs!$D$17) -> 11435678000 | D5: =C5*(1+Inputs!$D$18) -> 12007461900 | E5: =D5*(1+Inputs!$D$19) -> 12727909614 | F5: =E5*(1+Inputs!$D$20) -> 1.3491584e+10 | G5: =F5*(1+Inputs!$D$21) -> 1.4166163e+10
A6: Revenue growth | C6: =C5/B5-1 -> 0.03 | D6: =D5/C5-1 -> 0.05 | E6: =E5/D5-1 -> 0.06 | F6: =F5/E5-1 -> 0.06 | G6: =G5/F5-1 -> 0.05
A7: EBIT | B7: =History!F8 -> 2210615000 | C7: =C5*Inputs!$D$22 -> 2115600430 | D7: =D5*Inputs!$D$23 -> 2281417761 | E7: =E5*Inputs!$D$24 -> 2.4819424e+09 | F7: =F5*Inputs!$D$25 -> 2.6983168e+09 | G7: =G5*Inputs!$D$26 -> 2.8332327e+09
A8: EBIT margin | B8: =B7/B5 -> 0.19910787 | C8: =C7/C5 -> 0.185 | D8: =D7/D5 -> 0.19 | E8: =E7/E5 -> 0.195 | F8: =F7/F5 -> 0.2 | G8: =G7/G5 -> 0.2
A9: Tax on EBIT | C9: =-C7*Inputs!$D$34 -> -6.2410213e+08 | D9: =-D7*Inputs!$D$34 -> -6.7301824e+08 | E9: =-E7*Inputs!$D$34 -> -7.32173e+08 | F9: =-F7*Inputs!$D$34 -> -7.9600347e+08 | G9: =-G7*Inputs!$D$34 -> -8.3580364e+08
A10: NOPAT | C10: =C7+C9 -> 1.4914983e+09 | D10: =D7+D9 -> 1.6083995e+09 | E10: =E7+E9 -> 1.7497694e+09 | F10: =F7+F9 -> 1.9023134e+09 | G10: =G7+G9 -> 1.997429e+09
A11: D&A | C11: =C5*Inputs!$D$32 -> 514605510 | D11: =D5*Inputs!$D$32 -> 5.4033579e+08 | E11: =E5*Inputs!$D$32 -> 5.7275593e+08 | F11: =F5*Inputs!$D$32 -> 6.0712129e+08 | G11: =G5*Inputs!$D$32 -> 6.3747735e+08
A12: Capex | C12: =-C5*Inputs!$D$27 -> -686140680 | D12: =-D5*Inputs!$D$28 -> -720447714 | E12: =-E5*Inputs!$D$29 -> -7.318548e+08 | F12: =-F5*Inputs!$D$30 -> -7.4203713e+08 | G12: =-G5*Inputs!$D$31 -> -7.7913899e+08
A13: Operating working capital | B13: =History!F14 -> 1064679000 | C13: =C5*Inputs!$D$33 -> 1029211020 | D13: =D5*Inputs!$D$33 -> 1080671571 | E13: =E5*Inputs!$D$33 -> 1.1455119e+09 | F13: =F5*Inputs!$D$33 -> 1.2142426e+09 | G13: =G5*Inputs!$D$33 -> 1.2749547e+09
A14: Increase in working capital | C14: =-(C13-B13) -> 35467980 | D14: =-(D13-C13) -> -51460551 | E14: =-(E13-D13) -> -64840294 | F14: =-(F13-E13) -> -68730712 | G14: =-(G13-F13) -> -60712129
A15: Free cash flow to the firm | C15: =C10+C11+C12+C14 -> 1.3554311e+09 | D15: =D10+D11+D12+D14 -> 1.376827e+09 | E15: =E10+E11+E12+E14 -> 1.5258302e+09 | F15: =F10+F11+F12+F14 -> 1.6986668e+09 | G15: =G10+G11+G12+G14 -> 1.7950553e+09
A16: Years from the valuation date | C16: =(Inputs!$B$6-Inputs!$B$5)/365.25+0 -> 0.37782341 | D16: =(Inputs!$B$6-Inputs!$B$5)/365.25+1 -> 1.3778234 | E16: =(Inputs!$B$6-Inputs!$B$5)/365.25+2 -> 2.3778234 | F16: =(Inputs!$B$6-Inputs!$B$5)/365.25+3 -> 3.3778234 | G16: =(Inputs!$B$6-Inputs!$B$5)/365.25+4 -> 4.3778234
A17: Discount factor | C17: =1/(1+$B$24)^C16 -> 0.97228258 | D17: =1/(1+$B$24)^D16 -> 0.90257324 | E17: =1/(1+$B$24)^E16 -> 0.83786182 | F17: =1/(1+$B$24)^F16 -> 0.77778999 | G17: =1/(1+$B$24)^G16 -> 0.7220251
A18: Present value | C18: =C15*C17 -> 1.3178621e+09 | D18: =D15*D17 -> 1.2426872e+09 | E18: =E15*E17 -> 1.2784349e+09 | F18: =F15*F17 -> 1.321206e+09 | G18: =G15*G17 -> 1.296075e+09
A24: Cost of equity = risk-free + beta x ERP (no debt, so the WACC) | B24: =Inputs!$B$7+Inputs!$B$9*Inputs!$B$8 -> 0.077234
A25: Terminal growth | B25: =Inputs!$D$35 -> 0.025
A26: Return on new capital, terminal | B26: =Inputs!$D$36 -> 0.2
A27: NOPAT, FY2031 | B27: =G7*(1+B25)*(1-Inputs!$D$34) -> 2.0473648e+09
A28: Terminal value at end FY2030 = NOPAT x (1 - g/RONIC) / (WACC - g) | B28: =B27*(1-B25/B26)/(B24-B25) -> 3.4296515e+10
A29: Present value of the terminal value | B29: =B28/(1+B24)^(G16+0.5) -> 2.3858727e+10
A30: Present value of FY2026-FY2030 cash flows | B30: =SUM(C18:G18) -> 6.4562652e+09
A31: Enterprise value | B31: =B29+B30 -> 3.0314992e+10
A32: Cash (incl. restricted), FY2025 year end | B32: =Data_EDGAR!$G$20 -> 1807202000
A33: Debt | B33: =-Inputs!$B$11 -> 0
A34: Equity value | B34: =B31+B32+B33 -> 3.2122194e+10
A35: Shares: common plus exchangeable | B35: =Inputs!$B$12+Inputs!$B$13 -> 115598632
A36: Value per share (USD) | B36: =B34/B35 -> 277.87694
A37: Terminal value, share of enterprise value | B37: =B29/B31 -> 0.78702732
A38: Implied exit multiple: terminal value / FY2030 EBITDA | B38: =B28/(G7+G11) -> 9.8816999
A39: Enterprise value / FY2025 EBIT | B39: =B31/Data_EDGAR!$G$10 -> 13.713375

Sheet DCF_Bear
A1: DCF, bear case: free cash flow to the firm, FY2026 to FY2030
A2: Every cell is a formula over Inputs, History and Data_EDGAR. Money in USD millions.
B4: FY2025 (filed) | C4: FY2026 | D4: FY2027 | E4: FY2028 | F4: FY2029 | G4: FY2030
A5: Revenue | B5: =History!F5 -> 11102600000 | C5: =B5*(1+Inputs!$C$17) -> 10991574000 | D5: =C5*(1+Inputs!$C$18) -> 11101489740 | E5: =D5*(1+Inputs!$C$19) -> 1.132352e+10 | F5: =E5*(1+Inputs!$C$20) -> 1.1663225e+10 | G5: =F5*(1+Inputs!$C$21) -> 1.2013122e+10
A6: Revenue growth | C6: =C5/B5-1 -> -0.01 | D6: =D5/C5-1 -> 0.01 | E6: =E5/D5-1 -> 0.02 | F6: =F5/E5-1 -> 0.03 | G6: =G5/F5-1 -> 0.03
A7: EBIT | B7: =History!F8 -> 2210615000 | C7: =C5*Inputs!$C$22 -> 1758651840 | D7: =D5*Inputs!$C$23 -> 1.7207309e+09 | E7: =E5*Inputs!$C$24 -> 1.7551455e+09 | F7: =F5*Inputs!$C$25 -> 1.8077999e+09 | G7: =G5*Inputs!$C$26 -> 1.8620339e+09
A8: EBIT margin | B8: =B7/B5 -> 0.19910787 | C8: =C7/C5 -> 0.16 | D8: =D7/D5 -> 0.155 | E8: =E7/E5 -> 0.155 | F8: =F7/F5 -> 0.155 | G8: =G7/G5 -> 0.155
A9: Tax on EBIT | C9: =-C7*Inputs!$C$34 -> -5.1880229e+08 | D9: =-D7*Inputs!$C$34 -> -5.0761562e+08 | E9: =-E7*Inputs!$C$34 -> -5.1776793e+08 | F9: =-F7*Inputs!$C$34 -> -5.3330097e+08 | G9: =-G7*Inputs!$C$34 -> -5.493e+08
A10: NOPAT | C10: =C7+C9 -> 1.2398495e+09 | D10: =D7+D9 -> 1.2131153e+09 | E10: =E7+E9 -> 1.2373776e+09 | F10: =F7+F9 -> 1.2744989e+09 | G10: =G7+G9 -> 1.3127339e+09
A11: D&A | C11: =C5*Inputs!$C$32 -> 494620830 | D11: =D5*Inputs!$C$32 -> 4.9956704e+08 | E11: =E5*Inputs!$C$32 -> 5.0955838e+08 | F11: =F5*Inputs!$C$32 -> 5.2484513e+08 | G11: =G5*Inputs!$C$32 -> 5.4059048e+08
A12: Capex | C12: =-C5*Inputs!$C$27 -> -659494440 | D12: =-D5*Inputs!$C$28 -> -6.6608938e+08 | E12: =-E5*Inputs!$C$29 -> -6.7941117e+08 | F12: =-F5*Inputs!$C$30 -> -6.9979351e+08 | G12: =-G5*Inputs!$C$31 -> -7.2078731e+08
A13: Operating working capital | B13: =History!F14 -> 1064679000 | C13: =C5*Inputs!$C$33 -> 1099157400 | D13: =D5*Inputs!$C$33 -> 1110148974 | E13: =E5*Inputs!$C$33 -> 1.132352e+09 | F13: =F5*Inputs!$C$33 -> 1.1663225e+09 | G13: =G5*Inputs!$C$33 -> 1.2013122e+09
A14: Increase in working capital | C14: =-(C13-B13) -> -34478400 | D14: =-(D13-C13) -> -10991574 | E14: =-(E13-D13) -> -22202979 | F14: =-(F13-E13) -> -33970559 | G14: =-(G13-F13) -> -34989675
A15: Free cash flow to the firm | C15: =C10+C11+C12+C14 -> 1.0404975e+09 | D15: =D10+D11+D12+D14 -> 1.0356014e+09 | E15: =E10+E11+E12+E14 -> 1.0453218e+09 | F15: =F10+F11+F12+F14 -> 1.06558e+09 | G15: =G10+G11+G12+G14 -> 1.0975474e+09
A16: Years from the valuation date | C16: =(Inputs!$B$6-Inputs!$B$5)/365.25+0 -> 0.37782341 | D16: =(Inputs!$B$6-Inputs!$B$5)/365.25+1 -> 1.3778234 | E16: =(Inputs!$B$6-Inputs!$B$5)/365.25+2 -> 2.3778234 | F16: =(Inputs!$B$6-Inputs!$B$5)/365.25+3 -> 3.3778234 | G16: =(Inputs!$B$6-Inputs!$B$5)/365.25+4 -> 4.3778234
A17: Discount factor | C17: =1/(1+$B$24)^C16 -> 0.97228258 | D17: =1/(1+$B$24)^D16 -> 0.90257324 | E17: =1/(1+$B$24)^E16 -> 0.83786182 | F17: =1/(1+$B$24)^F16 -> 0.77778999 | G17: =1/(1+$B$24)^G16 -> 0.7220251
A18: Present value | C18: =C15*C17 -> 1.0116576e+09 | D18: =D15*D17 -> 9.3470609e+08 | E18: =E15*E17 -> 8.7583525e+08 | F18: =F15*F17 -> 8.2879745e+08 | G18: =G15*G17 -> 7.9245677e+08
A24: Cost of equity = risk-free + beta x ERP (no debt, so the WACC) | B24: =Inputs!$B$7+Inputs!$B$9*Inputs!$B$8 -> 0.077234
A25: Terminal growth | B25: =Inputs!$C$35 -> 0.02
A26: Return on new capital, terminal | B26: =Inputs!$C$36 -> 0.12
A27: NOPAT, FY2031 | B27: =G7*(1+B25)*(1-Inputs!$C$34) -> 1.3389886e+09
A28: Terminal value at end FY2030 = NOPAT x (1 - g/RONIC) / (WACC - g) | B28: =B27*(1-B25/B26)/(B24-B25) -> 1.9495821e+10
A29: Present value of the terminal value | B29: =B28/(1+B24)^(G16+0.5) -> 1.356247e+10
A30: Present value of FY2026-FY2030 cash flows | B30: =SUM(C18:G18) -> 4.4434532e+09
A31: Enterprise value | B31: =B29+B30 -> 1.8005923e+10
A32: Cash (incl. restricted), FY2025 year end | B32: =Data_EDGAR!$G$20 -> 1807202000
A33: Debt | B33: =-Inputs!$B$11 -> 0
A34: Equity value | B34: =B31+B32+B33 -> 1.9813125e+10
A35: Shares: common plus exchangeable | B35: =Inputs!$B$12+Inputs!$B$13 -> 115598632
A36: Value per share (USD) | B36: =B34/B35 -> 171.39585
A37: Terminal value, share of enterprise value | B37: =B29/B31 -> 0.7532227
A38: Implied exit multiple: terminal value / FY2030 EBITDA | B38: =B28/(G7+G11) -> 8.1143857
A39: Enterprise value / FY2025 EBIT | B39: =B31/Data_EDGAR!$G$10 -> 8.14521

Sheet DCF_Bull
A1: DCF, bull case: free cash flow to the firm, FY2026 to FY2030
A2: Every cell is a formula over Inputs, History and Data_EDGAR. Money in USD millions.
B4: FY2025 (filed) | C4: FY2026 | D4: FY2027 | E4: FY2028 | F4: FY2029 | G4: FY2030
A5: Revenue | B5: =History!F5 -> 11102600000 | C5: =B5*(1+Inputs!$E$17) -> 11768756000 | D5: =C5*(1+Inputs!$E$18) -> 12710256480 | E5: =D5*(1+Inputs!$E$19) -> 1.385418e+10 | F5: =E5*(1+Inputs!$E$20) -> 1.4962514e+10 | G5: =F5*(1+Inputs!$E$21) -> 1.600989e+10
A6: Revenue growth | C6: =C5/B5-1 -> 0.06 | D6: =D5/C5-1 -> 0.08 | E6: =E5/D5-1 -> 0.09 | F6: =F5/E5-1 -> 0.08 | G6: =G5/F5-1 -> 0.07
A7: EBIT | B7: =History!F8 -> 2210615000 | C7: =C5*Inputs!$E$22 -> 2353751200 | D7: =D5*Inputs!$E$23 -> 2.6691539e+09 | E7: =E5*Inputs!$E$24 -> 2.9786486e+09 | F7: =F5*Inputs!$E$25 -> 3.2917531e+09 | G7: =G5*Inputs!$E$26 -> 3.5221758e+09
A8: EBIT margin | B8: =B7/B5 -> 0.19910787 | C8: =C7/C5 -> 0.2 | D8: =D7/D5 -> 0.21 | E8: =E7/E5 -> 0.215 | F8: =F7/F5 -> 0.22 | G8: =G7/G5 -> 0.22
A9: Tax on EBIT | C9: =-C7*Inputs!$E$34 -> -694356604 | D9: =-D7*Inputs!$E$34 -> -7.8740039e+08 | E9: =-E7*Inputs!$E$34 -> -8.7870134e+08 | F9: =-F7*Inputs!$E$34 -> -9.7106715e+08 | G9: =-G7*Inputs!$E$34 -> -1.0390419e+09
A10: NOPAT | C10: =C7+C9 -> 1659394596 | D10: =D7+D9 -> 1.8817535e+09 | E10: =E7+E9 -> 2.0999473e+09 | F10: =F7+F9 -> 2.3206859e+09 | G10: =G7+G9 -> 2.4831339e+09
A11: D&A | C11: =C5*Inputs!$E$32 -> 529594020 | D11: =D5*Inputs!$E$32 -> 5.7196154e+08 | E11: =E5*Inputs!$E$32 -> 6.2343808e+08 | F11: =F5*Inputs!$E$32 -> 6.7331313e+08 | G11: =G5*Inputs!$E$32 -> 7.2044505e+08
A12: Capex | C12: =-C5*Inputs!$E$27 -> -706125360 | D12: =-D5*Inputs!$E$28 -> -7.6261539e+08 | E12: =-E5*Inputs!$E$29 -> -7.9661532e+08 | F12: =-F5*Inputs!$E$30 -> -8.2293827e+08 | G12: =-G5*Inputs!$E$31 -> -8.8054394e+08
A13: Operating working capital | B13: =History!F14 -> 1064679000 | C13: =C5*Inputs!$E$33 -> 1000344260 | D13: =D5*Inputs!$E$33 -> 1.0803718e+09 | E13: =E5*Inputs!$E$33 -> 1.1776053e+09 | F13: =F5*Inputs!$E$33 -> 1.2718137e+09 | G13: =G5*Inputs!$E$33 -> 1.3608406e+09
A14: Increase in working capital | C14: =-(C13-B13) -> 64334740 | D14: =-(D13-C13) -> -80027541 | E14: =-(E13-D13) -> -97233462 | F14: =-(F13-E13) -> -94208421 | G14: =-(G13-F13) -> -89026958
A15: Free cash flow to the firm | C15: =C10+C11+C12+C14 -> 1547197996 | D15: =D10+D11+D12+D14 -> 1.6110721e+09 | E15: =E10+E11+E12+E14 -> 1.8295366e+09 | F15: =F10+F11+F12+F14 -> 2.0768523e+09 | G15: =G10+G11+G12+G14 -> 2.2340081e+09
A16: Years from the valuation date | C16: =(Inputs!$B$6-Inputs!$B$5)/365.25+0 -> 0.37782341 | D16: =(Inputs!$B$6-Inputs!$B$5)/365.25+1 -> 1.3778234 | E16: =(Inputs!$B$6-Inputs!$B$5)/365.25+2 -> 2.3778234 | F16: =(Inputs!$B$6-Inputs!$B$5)/365.25+3 -> 3.3778234 | G16: =(Inputs!$B$6-Inputs!$B$5)/365.25+4 -> 4.3778234
A17: Discount factor | C17: =1/(1+$B$24)^C16 -> 0.97228258 | D17: =1/(1+$B$24)^D16 -> 0.90257324 | E17: =1/(1+$B$24)^E16 -> 0.83786182 | F17: =1/(1+$B$24)^F16 -> 0.77778999 | G17: =1/(1+$B$24)^G16 -> 0.7220251
A18: Present value | C18: =C15*C17 -> 1.5043137e+09 | D18: =D15*D17 -> 1.4541106e+09 | E18: =E15*E17 -> 1.5328988e+09 | F18: =F15*F17 -> 1.615355e+09 | G18: =G15*G17 -> 1.6130099e+09
A24: Cost of equity = risk-free + beta x ERP (no debt, so the WACC) | B24: =Inputs!$B$7+Inputs!$B$9*Inputs!$B$8 -> 0.077234
A25: Terminal growth | B25: =Inputs!$E$35 -> 0.03
A26: Return on new capital, terminal | B26: =Inputs!$E$36 -> 0.25
A27: NOPAT, FY2031 | B27: =G7*(1+B25)*(1-Inputs!$E$34) -> 2.5576279e+09
A28: Terminal value at end FY2030 = NOPAT x (1 - g/RONIC) / (WACC - g) | B28: =B27*(1-B25/B26)/(B24-B25) -> 4.7650264e+10
A29: Present value of the terminal value | B29: =B28/(1+B24)^(G16+0.5) -> 3.3148401e+10
A30: Present value of FY2026-FY2030 cash flows | B30: =SUM(C18:G18) -> 7.7196879e+09
A31: Enterprise value | B31: =B29+B30 -> 4.0868089e+10
A32: Cash (incl. restricted), FY2025 year end | B32: =Data_EDGAR!$G$20 -> 1807202000
A33: Debt | B33: =-Inputs!$B$11 -> 0
A34: Equity value | B34: =B31+B32+B33 -> 4.2675291e+10
A35: Shares: common plus exchangeable | B35: =Inputs!$B$12+Inputs!$B$13 -> 115598632
A36: Value per share (USD) | B36: =B34/B35 -> 369.16779
A37: Terminal value, share of enterprise value | B37: =B29/B31 -> 0.8111072
A38: Implied exit multiple: terminal value / FY2030 EBITDA | B38: =B28/(G7+G11) -> 11.231328
A39: Enterprise value / FY2025 EBIT | B39: =B31/Data_EDGAR!$G$10 -> 18.487203

Sheet Sensitivity
A1: Sensitivity, base case: value per share by WACC and terminal growth
A2: Each cell re-discounts the base case's free cash flows and terminal value at its own WACC and growth.
A4: WACC \ terminal growth | B4: =Inputs!B$46 -> 0.015 | C4: =Inputs!C$46 -> 0.02 | D4: =Inputs!D$46 -> 0.025 | E4: =Inputs!E$46 -> 0.03 | F4: =Inputs!F$46 -> 0.035
A5: =Inputs!B$45 -> 0.065 | B5: =(SUMPRODUCT(DCF_Base!$C$15:$G$15,(1+$A5)^(-DCF_Base!$C$16:$G$16))+DCF_Base!$G$7*(1+B$4)*(1-Inputs!$D$34)*(1-B$4/Inputs!$D$36)/($A5-B$4)/(1+$A5)^(DCF_Base!$G$16+0.5)+DCF_Base!$B$32+DCF_Base!$B$33)/DCF_Base!$B$35 -> 311.67651 | C5: =(SUMPRODUCT(DCF_Base!$C$15:$G$15,(1+$A5)^(-DCF_Base!$C$16:$G$16))+DCF_Base!$G$7*(1+C$4)*(1-Inputs!$D$34)*(1-C$4/Inputs!$D$36)/($A5-C$4)/(1+$A5)^(DCF_Base!$G$16+0.5)+DCF_Base!$B$32+DCF_Base!$B$33)/DCF_Base!$B$35 -> 332.2969 | D5: =(SUMPRODUCT(DCF_Base!$C$15:$G$15,(1+$A5)^(-DCF_Base!$C$16:$G$16))+DCF_Base!$G$7*(1+D$4)*(1-Inputs!$D$34)*(1-D$4/Inputs!$D$36)/($A5-D$4)/(1+$A5)^(DCF_Base!$G$16+0.5)+DCF_Base!$B$32+DCF_Base!$B$33)/DCF_Base!$B$35 -> 357.99295 | E5: =(SUMPRODUCT(DCF_Base!$C$15:$G$15,(1+$A5)^(-DCF_Base!$C$16:$G$16))+DCF_Base!$G$7*(1+E$4)*(1-Inputs!$D$34)*(1-E$4/Inputs!$D$36)/($A5-E$4)/(1+$A5)^(DCF_Base!$G$16+0.5)+DCF_Base!$B$32+DCF_Base!$B$33)/DCF_Base!$B$35 -> 390.93996 | F5: =(SUMPRODUCT(DCF_Base!$C$15:$G$15,(1+$A5)^(-DCF_Base!$C$16:$G$16))+DCF_Base!$G$7*(1+F$4)*(1-Inputs!$D$34)*(1-F$4/Inputs!$D$36)/($A5-F$4)/(1+$A5)^(DCF_Base!$G$16+0.5)+DCF_Base!$B$32+DCF_Base!$B$33)/DCF_Base!$B$35 -> 434.76338
A6: =Inputs!C$45 -> 0.07 | B6: =(SUMPRODUCT(DCF_Base!$C$15:$G$15,(1+$A6)^(-DCF_Base!$C$16:$G$16))+DCF_Base!$G$7*(1+B$4)*(1-Inputs!$D$34)*(1-B$4/Inputs!$D$36)/($A6-B$4)/(1+$A6)^(DCF_Base!$G$16+0.5)+DCF_Base!$B$32+DCF_Base!$B$33)/DCF_Base!$B$35 -> 284.43917 | C6: =(SUMPRODUCT(DCF_Base!$C$15:$G$15,(1+$A6)^(-DCF_Base!$C$16:$G$16))+DCF_Base!$G$7*(1+C$4)*(1-Inputs!$D$34)*(1-C$4/Inputs!$D$36)/($A6-C$4)/(1+$A6)^(DCF_Base!$G$16+0.5)+DCF_Base!$B$32+DCF_Base!$B$33)/DCF_Base!$B$35 -> 300.45783 | D6: =(SUMPRODUCT(DCF_Base!$C$15:$G$15,(1+$A6)^(-DCF_Base!$C$16:$G$16))+DCF_Base!$G$7*(1+D$4)*(1-Inputs!$D$34)*(1-D$4/Inputs!$D$36)/($A6-D$4)/(1+$A6)^(DCF_Base!$G$16+0.5)+DCF_Base!$B$32+DCF_Base!$B$33)/DCF_Base!$B$35 -> 319.9672 | E6: =(SUMPRODUCT(DCF_Base!$C$15:$G$15,(1+$A6)^(-DCF_Base!$C$16:$G$16))+DCF_Base!$G$7*(1+E$4)*(1-Inputs!$D$34)*(1-E$4/Inputs!$D$36)/($A6-E$4)/(1+$A6)^(DCF_Base!$G$16+0.5)+DCF_Base!$B$32+DCF_Base!$B$33)/DCF_Base!$B$35 -> 344.27626 | F6: =(SUMPRODUCT(DCF_Base!$C$15:$G$15,(1+$A6)^(-DCF_Base!$C$16:$G$16))+DCF_Base!$G$7*(1+F$4)*(1-Inputs!$D$34)*(1-F$4/Inputs!$D$36)/($A6-F$4)/(1+$A6)^(DCF_Base!$G$16+0.5)+DCF_Base!$B$32+DCF_Base!$B$33)/DCF_Base!$B$35 -> 375.44205
A7: =Inputs!D$45 -> 0.075 | B7: =(SUMPRODUCT(DCF_Base!$C$15:$G$15,(1+$A7)^(-DCF_Base!$C$16:$G$16))+DCF_Base!$G$7*(1+B$4)*(1-Inputs!$D$34)*(1-B$4/Inputs!$D$36)/($A7-B$4)/(1+$A7)^(DCF_Base!$G$16+0.5)+DCF_Base!$B$32+DCF_Base!$B$33)/DCF_Base!$B$35 -> 261.76866 | C7: =(SUMPRODUCT(DCF_Base!$C$15:$G$15,(1+$A7)^(-DCF_Base!$C$16:$G$16))+DCF_Base!$G$7*(1+C$4)*(1-Inputs!$D$34)*(1-C$4/Inputs!$D$36)/($A7-C$4)/(1+$A7)^(DCF_Base!$G$16+0.5)+DCF_Base!$B$32+DCF_Base!$B$33)/DCF_Base!$B$35 -> 274.43336 | D7: =(SUMPRODUCT(DCF_Base!$C$15:$G$15,(1+$A7)^(-DCF_Base!$C$16:$G$16))+DCF_Base!$G$7*(1+D$4)*(1-Inputs!$D$34)*(1-D$4/Inputs!$D$36)/($A7-D$4)/(1+$A7)^(DCF_Base!$G$16+0.5)+DCF_Base!$B$32+DCF_Base!$B$33)/DCF_Base!$B$35 -> 289.57029 | E7: =(SUMPRODUCT(DCF_Base!$C$15:$G$15,(1+$A7)^(-DCF_Base!$C$16:$G$16))+DCF_Base!$G$7*(1+E$4)*(1-Inputs!$D$34)*(1-E$4/Inputs!$D$36)/($A7-E$4)/(1+$A7)^(DCF_Base!$G$16+0.5)+DCF_Base!$B$32+DCF_Base!$B$33)/DCF_Base!$B$35 -> 308.00351 | F7: =(SUMPRODUCT(DCF_Base!$C$15:$G$15,(1+$A7)^(-DCF_Base!$C$16:$G$16))+DCF_Base!$G$7*(1+F$4)*(1-Inputs!$D$34)*(1-F$4/Inputs!$D$36)/($A7-F$4)/(1+$A7)^(DCF_Base!$G$16+0.5)+DCF_Base!$B$32+DCF_Base!$B$33)/DCF_Base!$B$35 -> 330.96916
A8: =Inputs!E$45 -> 0.08 | B8: =(SUMPRODUCT(DCF_Base!$C$15:$G$15,(1+$A8)^(-DCF_Base!$C$16:$G$16))+DCF_Base!$G$7*(1+B$4)*(1-Inputs!$D$34)*(1-B$4/Inputs!$D$36)/($A8-B$4)/(1+$A8)^(DCF_Base!$G$16+0.5)+DCF_Base!$B$32+DCF_Base!$B$33)/DCF_Base!$B$35 -> 242.61016 | C8: =(SUMPRODUCT(DCF_Base!$C$15:$G$15,(1+$A8)^(-DCF_Base!$C$16:$G$16))+DCF_Base!$G$7*(1+C$4)*(1-Inputs!$D$34)*(1-C$4/Inputs!$D$36)/($A8-C$4)/(1+$A8)^(DCF_Base!$G$16+0.5)+DCF_Base!$B$32+DCF_Base!$B$33)/DCF_Base!$B$35 -> 252.7689 | D8: =(SUMPRODUCT(DCF_Base!$C$15:$G$15,(1+$A8)^(-DCF_Base!$C$16:$G$16))+DCF_Base!$G$7*(1+D$4)*(1-Inputs!$D$34)*(1-D$4/Inputs!$D$36)/($A8-D$4)/(1+$A8)^(DCF_Base!$G$16+0.5)+DCF_Base!$B$32+DCF_Base!$B$33)/DCF_Base!$B$35 -> 264.72074 | E8: =(SUMPRODUCT(DCF_Base!$C$15:$G$15,(1+$A8)^(-DCF_Base!$C$16:$G$16))+DCF_Base!$G$7*(1+E$4)*(1-Inputs!$D$34)*(1-E$4/Inputs!$D$36)/($A8-E$4)/(1+$A8)^(DCF_Base!$G$16+0.5)+DCF_Base!$B$32+DCF_Base!$B$33)/DCF_Base!$B$35 -> 279.00358 | F8: =(SUMPRODUCT(DCF_Base!$C$15:$G$15,(1+$A8)^(-DCF_Base!$C$16:$G$16))+DCF_Base!$G$7*(1+F$4)*(1-Inputs!$D$34)*(1-F$4/Inputs!$D$36)/($A8-F$4)/(1+$A8)^(DCF_Base!$G$16+0.5)+DCF_Base!$B$32+DCF_Base!$B$33)/DCF_Base!$B$35 -> 296.39445
A9: =Inputs!F$45 -> 0.085 | B9: =(SUMPRODUCT(DCF_Base!$C$15:$G$15,(1+$A9)^(-DCF_Base!$C$16:$G$16))+DCF_Base!$G$7*(1+B$4)*(1-Inputs!$D$34)*(1-B$4/Inputs!$D$36)/($A9-B$4)/(1+$A9)^(DCF_Base!$G$16+0.5)+DCF_Base!$B$32+DCF_Base!$B$33)/DCF_Base!$B$35 -> 226.21022 | C9: =(SUMPRODUCT(DCF_Base!$C$15:$G$15,(1+$A9)^(-DCF_Base!$C$16:$G$16))+DCF_Base!$G$7*(1+C$4)*(1-Inputs!$D$34)*(1-C$4/Inputs!$D$36)/($A9-C$4)/(1+$A9)^(DCF_Base!$G$16+0.5)+DCF_Base!$B$32+DCF_Base!$B$33)/DCF_Base!$B$35 -> 234.45748 | D9: =(SUMPRODUCT(DCF_Base!$C$15:$G$15,(1+$A9)^(-DCF_Base!$C$16:$G$16))+DCF_Base!$G$7*(1+D$4)*(1-Inputs!$D$34)*(1-D$4/Inputs!$D$36)/($A9-D$4)/(1+$A9)^(DCF_Base!$G$16+0.5)+DCF_Base!$B$32+DCF_Base!$B$33)/DCF_Base!$B$35 -> 244.03093 | E9: =(SUMPRODUCT(DCF_Base!$C$15:$G$15,(1+$A9)^(-DCF_Base!$C$16:$G$16))+DCF_Base!$G$7*(1+E$4)*(1-Inputs!$D$34)*(1-E$4/Inputs!$D$36)/($A9-E$4)/(1+$A9)^(DCF_Base!$G$16+0.5)+DCF_Base!$B$32+DCF_Base!$B$33)/DCF_Base!$B$35 -> 255.29224 | F9: =(SUMPRODUCT(DCF_Base!$C$15:$G$15,(1+$A9)^(-DCF_Base!$C$16:$G$16))+DCF_Base!$G$7*(1+F$4)*(1-Inputs!$D$34)*(1-F$4/Inputs!$D$36)/($A9-F$4)/(1+$A9)^(DCF_Base!$G$16+0.5)+DCF_Base!$B$32+DCF_Base!$B$33)/DCF_Base!$B$35 -> 268.74779
A10: =Inputs!G$45 -> 0.09 | B10: =(SUMPRODUCT(DCF_Base!$C$15:$G$15,(1+$A10)^(-DCF_Base!$C$16:$G$16))+DCF_Base!$G$7*(1+B$4)*(1-Inputs!$D$34)*(1-B$4/Inputs!$D$36)/($A10-B$4)/(1+$A10)^(DCF_Base!$G$16+0.5)+DCF_Base!$B$32+DCF_Base!$B$33)/DCF_Base!$B$35 -> 212.01638 | C10: =(SUMPRODUCT(DCF_Base!$C$15:$G$15,(1+$A10)^(-DCF_Base!$C$16:$G$16))+DCF_Base!$G$7*(1+C$4)*(1-Inputs!$D$34)*(1-C$4/Inputs!$D$36)/($A10-C$4)/(1+$A10)^(DCF_Base!$G$16+0.5)+DCF_Base!$B$32+DCF_Base!$B$33)/DCF_Base!$B$35 -> 218.77986 | D10: =(SUMPRODUCT(DCF_Base!$C$15:$G$15,(1+$A10)^(-DCF_Base!$C$16:$G$16))+DCF_Base!$G$7*(1+D$4)*(1-Inputs!$D$34)*(1-D$4/Inputs!$D$36)/($A10-D$4)/(1+$A10)^(DCF_Base!$G$16+0.5)+DCF_Base!$B$32+DCF_Base!$B$33)/DCF_Base!$B$35 -> 226.54023 | E10: =(SUMPRODUCT(DCF_Base!$C$15:$G$15,(1+$A10)^(-DCF_Base!$C$16:$G$16))+DCF_Base!$G$7*(1+E$4)*(1-Inputs!$D$34)*(1-E$4/Inputs!$D$36)/($A10-E$4)/(1+$A10)^(DCF_Base!$G$16+0.5)+DCF_Base!$B$32+DCF_Base!$B$33)/DCF_Base!$B$35 -> 235.54671 | F10: =(SUMPRODUCT(DCF_Base!$C$15:$G$15,(1+$A10)^(-DCF_Base!$C$16:$G$16))+DCF_Base!$G$7*(1+F$4)*(1-Inputs!$D$34)*(1-F$4/Inputs!$D$36)/($A10-F$4)/(1+$A10)^(DCF_Base!$G$16+0.5)+DCF_Base!$B$32+DCF_Base!$B$33)/DCF_Base!$B$35 -> 246.13913
A11: =Inputs!H$45 -> 0.095 | B11: =(SUMPRODUCT(DCF_Base!$C$15:$G$15,(1+$A11)^(-DCF_Base!$C$16:$G$16))+DCF_Base!$G$7*(1+B$4)*(1-Inputs!$D$34)*(1-B$4/Inputs!$D$36)/($A11-B$4)/(1+$A11)^(DCF_Base!$G$16+0.5)+DCF_Base!$B$32+DCF_Base!$B$33)/DCF_Base!$B$35 -> 199.6143 | C11: =(SUMPRODUCT(DCF_Base!$C$15:$G$15,(1+$A11)^(-DCF_Base!$C$16:$G$16))+DCF_Base!$G$7*(1+C$4)*(1-Inputs!$D$34)*(1-C$4/Inputs!$D$36)/($A11-C$4)/(1+$A11)^(DCF_Base!$G$16+0.5)+DCF_Base!$B$32+DCF_Base!$B$33)/DCF_Base!$B$35 -> 205.20862 | D11: =(SUMPRODUCT(DCF_Base!$C$15:$G$15,(1+$A11)^(-DCF_Base!$C$16:$G$16))+DCF_Base!$G$7*(1+D$4)*(1-Inputs!$D$34)*(1-D$4/Inputs!$D$36)/($A11-D$4)/(1+$A11)^(DCF_Base!$G$16+0.5)+DCF_Base!$B$32+DCF_Base!$B$33)/DCF_Base!$B$35 -> 211.56251 | E11: =(SUMPRODUCT(DCF_Base!$C$15:$G$15,(1+$A11)^(-DCF_Base!$C$16:$G$16))+DCF_Base!$G$7*(1+E$4)*(1-Inputs!$D$34)*(1-E$4/Inputs!$D$36)/($A11-E$4)/(1+$A11)^(DCF_Base!$G$16+0.5)+DCF_Base!$B$32+DCF_Base!$B$33)/DCF_Base!$B$35 -> 218.85122 | F11: =(SUMPRODUCT(DCF_Base!$C$15:$G$15,(1+$A11)^(-DCF_Base!$C$16:$G$16))+DCF_Base!$G$7*(1+F$4)*(1-Inputs!$D$34)*(1-F$4/Inputs!$D$36)/($A11-F$4)/(1+$A11)^(DCF_Base!$G$16+0.5)+DCF_Base!$B$32+DCF_Base!$B$33)/DCF_Base!$B$35 -> 227.30848
A12: =Inputs!I$45 -> 0.1 | B12: =(SUMPRODUCT(DCF_Base!$C$15:$G$15,(1+$A12)^(-DCF_Base!$C$16:$G$16))+DCF_Base!$G$7*(1+B$4)*(1-Inputs!$D$34)*(1-B$4/Inputs!$D$36)/($A12-B$4)/(1+$A12)^(DCF_Base!$G$16+0.5)+DCF_Base!$B$32+DCF_Base!$B$33)/DCF_Base!$B$35 -> 188.68716 | C12: =(SUMPRODUCT(DCF_Base!$C$15:$G$15,(1+$A12)^(-DCF_Base!$C$16:$G$16))+DCF_Base!$G$7*(1+C$4)*(1-Inputs!$D$34)*(1-C$4/Inputs!$D$36)/($A12-C$4)/(1+$A12)^(DCF_Base!$G$16+0.5)+DCF_Base!$B$32+DCF_Base!$B$33)/DCF_Base!$B$35 -> 193.34824 | D12: =(SUMPRODUCT(DCF_Base!$C$15:$G$15,(1+$A12)^(-DCF_Base!$C$16:$G$16))+DCF_Base!$G$7*(1+D$4)*(1-Inputs!$D$34)*(1-D$4/Inputs!$D$36)/($A12-D$4)/(1+$A12)^(DCF_Base!$G$16+0.5)+DCF_Base!$B$32+DCF_Base!$B$33)/DCF_Base!$B$35 -> 198.59461 | E12: =(SUMPRODUCT(DCF_Base!$C$15:$G$15,(1+$A12)^(-DCF_Base!$C$16:$G$16))+DCF_Base!$G$7*(1+E$4)*(1-Inputs!$D$34)*(1-E$4/Inputs!$D$36)/($A12-E$4)/(1+$A12)^(DCF_Base!$G$16+0.5)+DCF_Base!$B$32+DCF_Base!$B$33)/DCF_Base!$B$35 -> 204.5517 | F12: =(SUMPRODUCT(DCF_Base!$C$15:$G$15,(1+$A12)^(-DCF_Base!$C$16:$G$16))+DCF_Base!$G$7*(1+F$4)*(1-Inputs!$D$34)*(1-F$4/Inputs!$D$36)/($A12-F$4)/(1+$A12)^(DCF_Base!$G$16+0.5)+DCF_Base!$B$32+DCF_Base!$B$33)/DCF_Base!$B$35 -> 211.38352
A15: Beta of Retail (Special Lines) instead of Apparel, base case | B15: =(SUMPRODUCT(DCF_Base!$C$15:$G$15,(1+B16)^(-DCF_Base!$C$16:$G$16))+DCF_Base!$B$27*(1-DCF_Base!$B$25/DCF_Base!$B$26)/(B16-DCF_Base!$B$25)/(1+B16)^(DCF_Base!$G$16+0.5)+DCF_Base!$B$32+DCF_Base!$B$33)/DCF_Base!$B$35 -> 238.12317
A16: its cost of equity | B16: =Inputs!$B$7+Inputs!$B$10*Inputs!$B$8 -> 0.0866

Sheet History
A1: History: what the filings say, FY2021 to FY2025
A2: Ratios over the filed figures. 'Other operating items' is gross profit less SG&A, impairment and restructuring, and operating income: amortization and acquisition costs the filings report on other lines.
B4: FY2021 | C4: FY2022 | D4: FY2023 | E4: FY2024 | F4: FY2025
A5: Revenue | B5: =Data_EDGAR!$C$5 -> 6256617000 | C5: =Data_EDGAR!$D$5 -> 8110518000 | D5: =Data_EDGAR!$E$5 -> 9619278000 | E5: =Data_EDGAR!$F$5 -> 10588126000 | F5: =Data_EDGAR!$G$5 -> 11102600000
A6: Revenue growth | C6: =C5/B5-1 -> 0.29631045 | D6: =D5/C5-1 -> 0.18602511 | E6: =E5/D5-1 -> 0.10071941 | F6: =F5/E5-1 -> 0.048589713
A7: Gross margin | B7: =Data_EDGAR!$C$7/B5 -> 0.57675977 | C7: =Data_EDGAR!$D$7/C5 -> 0.55389064 | D7: =Data_EDGAR!$E$7/D5 -> 0.583142 | E7: =Data_EDGAR!$F$7/E5 -> 0.59224937 | F7: =Data_EDGAR!$G$7/F5 -> 0.56600544
A8: Operating income (EBIT) | B8: =Data_EDGAR!$C$10 -> 1333355000 | C8: =Data_EDGAR!$D$10 -> 1328408000 | D8: =Data_EDGAR!$E$10 -> 2132676000 | E8: =Data_EDGAR!$F$10 -> 2505697000 | F8: =Data_EDGAR!$G$10 -> 2210615000
A9: EBIT margin | B9: =B8/B5 -> 0.21311117 | C9: =C8/C5 -> 0.16378831 | D9: =D8/D5 -> 0.22170853 | E9: =E8/E5 -> 0.2366516 | F9: =F8/F5 -> 0.19910787
A10: Other operating items | B10: =Data_EDGAR!$C$7-Data_EDGAR!$C$8-Data_EDGAR!$C$9-Data_EDGAR!$C$10 -> 50176000 | C10: =Data_EDGAR!$D$7-Data_EDGAR!$D$8-Data_EDGAR!$D$9-Data_EDGAR!$D$10 -> -1428000 | D10: =Data_EDGAR!$E$7-Data_EDGAR!$E$8-Data_EDGAR!$E$9-Data_EDGAR!$E$10 -> 5010000 | E10: =Data_EDGAR!$F$7-Data_EDGAR!$F$8-Data_EDGAR!$F$9-Data_EDGAR!$F$10 -> 2735000 | F10: =Data_EDGAR!$G$7-Data_EDGAR!$G$8-Data_EDGAR!$G$9-Data_EDGAR!$G$10 -> 6961000
A11: Effective tax rate | B11: =Data_EDGAR!$C$12/Data_EDGAR!$C$11 -> 0.26880226 | C11: =Data_EDGAR!$D$12/Data_EDGAR!$D$11 -> 0.35853324 | D11: =Data_EDGAR!$E$12/Data_EDGAR!$E$11 -> 0.28750974 | E11: =Data_EDGAR!$F$12/Data_EDGAR!$F$11 -> 0.29558938 | F11: =Data_EDGAR!$G$12/Data_EDGAR!$G$11 -> 0.29468232
A12: D&A, % of revenue | B12: =Data_EDGAR!$C$14/B5 -> 0.035835021 | C12: =Data_EDGAR!$D$14/C5 -> 0.035976864 | D12: =Data_EDGAR!$E$14/D5 -> 0.039439966 | E12: =Data_EDGAR!$F$14/E5 -> 0.042172146 | F12: =Data_EDGAR!$G$14/F5 -> 0.044694756
A13: Capex, % of revenue | B13: =Data_EDGAR!$C$17/B5 -> 0.063053564 | C13: =Data_EDGAR!$D$17/C5 -> 0.078744292 | D13: =Data_EDGAR!$E$17/D5 -> 0.067766521 | E13: =Data_EDGAR!$F$17/E5 -> 0.065094805 | F13: =Data_EDGAR!$G$17/F5 -> 0.06131915
A14: Operating working capital | B14: =Data_EDGAR!$C$21+Data_EDGAR!$C$22+Data_EDGAR!$C$23-Data_EDGAR!$C$24-Data_EDGAR!$C$25-Data_EDGAR!$C$26 -> 481674000 | C14: =Data_EDGAR!$D$21+Data_EDGAR!$D$22+Data_EDGAR!$D$23-Data_EDGAR!$D$24-Data_EDGAR!$D$25-Data_EDGAR!$D$26 -> 1072769000 | D14: =Data_EDGAR!$E$21+Data_EDGAR!$E$22+Data_EDGAR!$E$23-Data_EDGAR!$E$24-Data_EDGAR!$E$25-Data_EDGAR!$E$26 -> 923779000 | E14: =Data_EDGAR!$F$21+Data_EDGAR!$F$22+Data_EDGAR!$F$23-Data_EDGAR!$F$24-Data_EDGAR!$F$25-Data_EDGAR!$F$26 -> 799718000 | F14: =Data_EDGAR!$G$21+Data_EDGAR!$G$22+Data_EDGAR!$G$23-Data_EDGAR!$G$24-Data_EDGAR!$G$25-Data_EDGAR!$G$26 -> 1064679000
A15: Operating working capital, % of revenue | B15: =B14/B5 -> 0.076986333 | C15: =C14/C5 -> 0.13226886 | D15: =D14/D5 -> 0.096034131 | E15: =E14/E5 -> 0.075529702 | F15: =F14/F5 -> 0.095894565
A16: Share-based compensation, % of revenue | B16: =Data_EDGAR!$C$15/B5 -> 0.011050221 | C16: =Data_EDGAR!$D$15/C5 -> 0.0096263888 | D16: =Data_EDGAR!$E$15/D5 -> 0.0097263017 | E16: =Data_EDGAR!$F$15/E5 -> 0.0085011266 | F16: =Data_EDGAR!$G$15/F5 -> 0.0056025616
A17: Cash from operations less capex | B17: =Data_EDGAR!$C$16-Data_EDGAR!$C$17 -> 994606000 | C17: =Data_EDGAR!$D$16-Data_EDGAR!$D$17 -> 327806000 | D17: =Data_EDGAR!$E$16-Data_EDGAR!$E$17 -> 1644299000 | E17: =Data_EDGAR!$F$16-Data_EDGAR!$F$17 -> 1583481000 | F17: =Data_EDGAR!$G$16-Data_EDGAR!$G$17 -> 921675000
A18: Share repurchases | B18: =Data_EDGAR!$C$18 -> 812602000 | C18: =Data_EDGAR!$D$18 -> 444001000 | D18: =Data_EDGAR!$E$18 -> 558652000 | E18: =Data_EDGAR!$F$18 -> 1636879000 | F18: =Data_EDGAR!$G$18 -> 1178349000
A21: Money in USD millions.

Sheet Data_EDGAR
A1: lululemon athletica: filed figures (USD, shares) from SEC EDGAR XBRL
A2: CIK 0001397187. For each fiscal year end, the value as presented in the latest 10-K that reports that period (so a recast comparative wins over the original); durations of 350 to 380 days only. The accession number is the filing the value was taken from.
A4: Item | B4: XBRL tag | C4: FY2021 | D4: FY2022 | E4: FY2023 | F4: FY2024 | G4: FY2025 | H4: FY2021 accession | I4: FY2022 accession | J4: FY2023 accession | K4: FY2024 accession | L4: FY2025 accession
A5: revenue | B5: RevenueFromContractWithCustomerExcludingAssessedTax | C5: 6256617000 | D5: 8110518000 | E5: 9619278000 | F5: 10588126000 | G5: 11102600000 | H5: 0001397187-24-000010 | I5: 0001397187-25-000013 | J5: 0001397187-26-000020 | K5: 0001397187-26-000020 | L5: 0001397187-26-000020
A6: cost_of_goods_sold | B6: CostOfGoodsAndServicesSold | C6: 2648052000 | D6: 3618178000 | E6: 4009873000 | F6: 4317315000 | G6: 4818468000 | H6: 0001397187-24-000010 | I6: 0001397187-25-000013 | J6: 0001397187-26-000020 | K6: 0001397187-26-000020 | L6: 0001397187-26-000020
A7: gross_profit | B7: GrossProfit | C7: 3608565000 | D7: 4492340000 | E7: 5609405000 | F7: 6270811000 | G7: 6284132000 | H7: 0001397187-24-000010 | I7: 0001397187-25-000013 | J7: 0001397187-26-000020 | K7: 0001397187-26-000020 | L7: 0001397187-26-000020
A8: sga | B8: SellingGeneralAndAdministrativeExpense | C8: 2225034000 | D8: 2757447000 | E8: 3397218000 | F8: 3762379000 | G8: 4066556000 | H8: 0001397187-24-000010 | I8: 0001397187-25-000013 | J8: 0001397187-26-000020 | K8: 0001397187-26-000020 | L8: 0001397187-26-000020
A9: impairment_and_restructuring | B9: RestructuringCostsAndAssetImpairmentCharges | C9: 0 | D9: 407913000 | E9: 74501000 | F9: 0 | G9: 0 | H9: 0001397187-24-000010 | I9: 0001397187-25-000013 | J9: 0001397187-26-000020 | K9: 0001397187-26-000020 | L9: 0001397187-26-000020
A10: operating_income | B10: OperatingIncomeLoss | C10: 1333355000 | D10: 1328408000 | E10: 2132676000 | F10: 2505697000 | G10: 2210615000 | H10: 0001397187-24-000010 | I10: 0001397187-25-000013 | J10: 0001397187-26-000020 | K10: 0001397187-26-000020 | L10: 0001397187-26-000020
A11: pretax_income | B11: IncomeLossFromContinuingOperationsBeforeIncomeTaxesExtraordinaryItemsNoncontrollingInterest | C11: 1333869000 | D11: 1332571000 | E11: 2175735000 | F11: 2576077000 | G11: 2238967000 | H11: 0001397187-24-000010 | I11: 0001397187-25-000013 | J11: 0001397187-26-000020 | K11: 0001397187-26-000020 | L11: 0001397187-26-000020
A12: income_tax | B12: IncomeTaxExpenseBenefit | C12: 358547000 | D12: 477771000 | E12: 625545000 | F12: 761461000 | G12: 659784000 | H12: 0001397187-24-000010 | I12: 0001397187-25-000013 | J12: 0001397187-26-000020 | K12: 0001397187-26-000020 | L12: 0001397187-26-000020
A13: net_income | B13: NetIncomeLoss | C13: 975322000 | D13: 854800000 | E13: 1550190000 | F13: 1814616000 | G13: 1579183000 | H13: 0001397187-24-000010 | I13: 0001397187-25-000013 | J13: 0001397187-26-000020 | K13: 0001397187-26-000020 | L13: 0001397187-26-000020
A14: depreciation_and_amortization | B14: DepreciationDepletionAndAmortization | C14: 224206000 | D14: 291791000 | E14: 379384000 | F14: 446524000 | G14: 496228000 | H14: 0001397187-24-000010 | I14: 0001397187-25-000013 | J14: 0001397187-26-000020 | K14: 0001397187-26-000020 | L14: 0001397187-26-000020
A15: share_based_compensation | B15: ShareBasedCompensation | C15: 69137000 | D15: 78075000 | E15: 93560000 | F15: 90011000 | G15: 62203000 | H15: 0001397187-24-000010 | I15: 0001397187-25-000013 | J15: 0001397187-26-000020 | K15: 0001397187-26-000020 | L15: 0001397187-26-000020
A16: cash_from_operations | B16: NetCashProvidedByUsedInOperatingActivities | C16: 1389108000 | D16: 966463000 | E16: 2296164000 | F16: 2272713000 | G16: 1602477000 | H16: 0001397187-24-000010 | I16: 0001397187-25-000013 | J16: 0001397187-26-000020 | K16: 0001397187-26-000020 | L16: 0001397187-26-000020
... A28: lease_liabilities_noncurrent | B28: OperatingLeaseLiabilityNoncurrent | C28: 692056000 | D28: 862362000 | E28: 1154012000 | F28: 1300637000 | G28: 1499717000 | H28: 0001397187-23-000012 | I28: 0001397187-24-000010 | J28: 0001397187-25-000013 | K28: 0001397187-26-000020 | L28: 0001397187-26-000020

Sheet Checks
A1: Checks
A2: Each row is PASS or FAIL, computed by formula.
A4: Check | B4: Status
A5: FY2021: gross profit = revenue - cost of goods sold, as filed | B5: =IF(ABS(Data_EDGAR!$C$7-(Data_EDGAR!$C$5-Data_EDGAR!$C$6))<1,"PASS","FAIL") -> PASS
A6: FY2021: net income = pre-tax income - income tax, as filed | B6: =IF(ABS(Data_EDGAR!$C$13-(Data_EDGAR!$C$11-Data_EDGAR!$C$12))<1,"PASS","FAIL") -> PASS
A7: FY2022: gross profit = revenue - cost of goods sold, as filed | B7: =IF(ABS(Data_EDGAR!$D$7-(Data_EDGAR!$D$5-Data_EDGAR!$D$6))<1,"PASS","FAIL") -> PASS
A8: FY2022: net income = pre-tax income - income tax, as filed | B8: =IF(ABS(Data_EDGAR!$D$13-(Data_EDGAR!$D$11-Data_EDGAR!$D$12))<1,"PASS","FAIL") -> PASS
A9: FY2023: gross profit = revenue - cost of goods sold, as filed | B9: =IF(ABS(Data_EDGAR!$E$7-(Data_EDGAR!$E$5-Data_EDGAR!$E$6))<1,"PASS","FAIL") -> PASS
A10: FY2023: net income = pre-tax income - income tax, as filed | B10: =IF(ABS(Data_EDGAR!$E$13-(Data_EDGAR!$E$11-Data_EDGAR!$E$12))<1,"PASS","FAIL") -> PASS
A11: FY2024: gross profit = revenue - cost of goods sold, as filed | B11: =IF(ABS(Data_EDGAR!$F$7-(Data_EDGAR!$F$5-Data_EDGAR!$F$6))<1,"PASS","FAIL") -> PASS
A12: FY2024: net income = pre-tax income - income tax, as filed | B12: =IF(ABS(Data_EDGAR!$F$13-(Data_EDGAR!$F$11-Data_EDGAR!$F$12))<1,"PASS","FAIL") -> PASS
A13: FY2025: gross profit = revenue - cost of goods sold, as filed | B13: =IF(ABS(Data_EDGAR!$G$7-(Data_EDGAR!$G$5-Data_EDGAR!$G$6))<1,"PASS","FAIL") -> PASS
A14: FY2025: net income = pre-tax income - income tax, as filed | B14: =IF(ABS(Data_EDGAR!$G$13-(Data_EDGAR!$G$11-Data_EDGAR!$G$12))<1,"PASS","FAIL") -> PASS
A15: bear: enterprise value = PV of cash flows + PV of terminal value | B15: =IF(ABS(DCF_Bear!B31-SUM(DCF_Bear!C18:G18)-DCF_Bear!B29)<0.01,"PASS","FAIL") -> PASS
A16: bear: WACC above terminal growth | B16: =IF(DCF_Bear!B24>DCF_Bear!B25,"PASS","FAIL") -> PASS
A17: base: enterprise value = PV of cash flows + PV of terminal value | B17: =IF(ABS(DCF_Base!B31-SUM(DCF_Base!C18:G18)-DCF_Base!B29)<0.01,"PASS","FAIL") -> PASS
A18: base: WACC above terminal growth | B18: =IF(DCF_Base!B24>DCF_Base!B25,"PASS","FAIL") -> PASS
A19: bull: enterprise value = PV of cash flows + PV of terminal value | B19: =IF(ABS(DCF_Bull!B31-SUM(DCF_Bull!C18:G18)-DCF_Bull!B29)<0.01,"PASS","FAIL") -> PASS
A20: bull: WACC above terminal growth | B20: =IF(DCF_Bull!B24>DCF_Bull!B25,"PASS","FAIL") -> PASS
A21: Bear < base < bull, per share | B21: =IF(AND(DCF_Bear!B36<DCF_Base!B36,DCF_Base!B36<DCF_Bull!B36),"PASS","FAIL") -> PASS
A22: Sensitivity: lower WACC is always worth more | B22: =IF(AND(Sensitivity!D5>Sensitivity!D6,Sensitivity!D6>Sensitivity!D7,Sensitivity!D7>Sensitivity!D8,Sensitivity!D8>Sensitivity!D9,Sensitivity!D9>Sensitivity!D10,Sensitivity!D10>Sensitivity!D11,Sensitivity!D11>Sensitivity!D12),"PASS","FAIL") -> PASS
A24: Checks passing | B24: =COUNTIF(B5:B22,"PASS") -> 18
