Workbook
Name AsOfMonth: Assumptions!$C$6
Name breakeven_gap: Scenarios!$C$44
Name breakeven_revenue: Scenarios!$C$45
Name breakeven_uplift: Scenarios!$C$46
Name breakeven_volume: Scenarios!$C$47
Name bridge_ebitda: PVM!$F$84:$F$91
Name bridge_gm: PVM!$C$84:$C$89
Name budget_bias: Forecast!$D$110
Name budget_wape: Forecast!$D$109
Name ch_cube_years: Channels!$C$34:$E$38
Name ch_cube_yoy: Channels!$F$34:$H$38
Name ch_formulas: Channels!$C$6:$P$9
Name ch_total: Channels!$C$10:$P$10
Name checks_status: Checks!$G$6:$G$36
Name checks_summary: Checks!$B$2
Name cover_answers: Cover!$C$12:$C$16
Name ctrl_sales_revenue: Checks!$D$43
Name ctrl_sales_rows: Checks!$D$41
Name ctrl_sales_units: Checks!$D$42
Name dash_commentary: Dashboard!$B$11:$B$15
Name dash_movers: Dashboard!$B$57:$J$61
Name dash_scenarios: Dashboard!$K$57:$S$60
Name DAYSOF: _xlfn.LAMBDA(_xlpm.balance,_xlpm.flow,_xlpm.days,IF(_xlpm.flow=0,0,_xlpm.balance/_xlpm.flow*_xlpm.days))
Name FAVVAR: _xlfn.LAMBDA(_xlpm.actual,_xlpm.plan,_xlpm.is_cost,IF(_xlpm.is_cost,_xlpm.plan-_xlpm.actual,_xlpm.actual-_xlpm.plan))
Name fc_basis: Forecast!$B$6:$M$11
Name fc_cogs: Forecast!$D$57:$O$62
Name fc_ets: Forecast!$D$116:$O$116
Name fc_ets_gap: Forecast!$P$117
Name fc_freight: Forecast!$D$67:$O$72
Name fc_opex: Forecast!$D$85:$O$88
Name fc_opex_basis: Forecast!$B$16:$E$19
Name fc_opex0: Forecast!$D$77:$O$80
Name fc_revenue: Forecast!$D$47:$O$52
Name fc_u0: Forecast!$D$27:$O$32
Name fc_units: Forecast!$D$37:$O$42
Name FiscalYear: Assumptions!$C$7
Name FYStart: Assumptions!$C$8
Name ISCLOSED: _xlfn.LAMBDA(_xlpm.month,_xlpm.month<=AsOfMonth)
Name kpi_breakeven: Dashboard!$N$5
Name kpi_ccc: Dashboard!$Q$5
Name kpi_ebitda_fy: Dashboard!$K$5
Name kpi_ebitda_ytd: Dashboard!$H$5
Name kpi_gm_pct_ytd: Dashboard!$E$5
Name kpi_revenue_ytd: Dashboard!$B$5
Name LastDataMonth: Assumptions!$C$15
Name MONEY: _xlfn.LAMBDA(_xlpm.x,IF(ABS(_xlpm.x)>=999500,TEXT(_xlpm.x/1000000,"$#,##0.0")&"M",TEXT(_xlpm.x/1000,"$#,##0")&"K"))
Name MonthsClosed: Assumptions!$C$9
Name pnl_budget: PnL!$D$24:$O$37
Name pnl_fy_budget: PnL!$P$24:$P$37
Name pnl_fy_outlook: PnL!$P$7:$P$20
Name pnl_fy_py: PnL!$P$41:$P$54
Name pnl_fy_variance: PnL!$P$58:$P$71
Name pnl_months: PnL!$D$4:$O$4
Name pnl_outlook: PnL!$D$7:$O$20
Name pnl_py: PnL!$D$41:$O$54
Name pnl_summary: PnL!$P$7:$AB$20
Name pnl_variance: PnL!$D$58:$O$71
Name pvm_by_category: PVM!$B$64:$J$69
Name pvm_by_channel: PVM!$B$75:$J$78
Name pvm_month: PVM!$B$6:$W$29

Sheet Cover
B2: Kestrel Bay Provisions
B3: ="FY"&FiscalYear&" financial planning & analysis model" -> FY2026 financial planning & analysis model
B4: Budget vs actual · price-volume-mix · rolling 8+4 forecast · scenarios · working capital · channel economics
B6: A fictional BC specialty-food distributor: 24 products, 4 channels, 3 regions, 32 months of synthetic data. Every figure is a live formula, Power Query step or DAX measure over the source tables. Nothing is pasted in.
B7: Built by Kush Patel · github.com/KushPatel29/excel-fpa-model
B9: Model status | C9: =checks_summary -> All 31 checks pass | D9: Open the checks →
B11: Five questions it answers, live from the model
B12: Are we on budget, and if not, why? | C12: {="YTD revenue "&TEXT(PnL!Z8,"+0.0%;-0.0%")&" against budget, EBITDA "&TEXT(PnL!Z19,"+0.0%;-0.0%")&". Biggest gross-margin drag: "&INDEX({"volume","mix","price","unit cost"},_xlfn.XMATCH(MIN(PVM!P59:S59),PVM!P59:S59))&"."} -> YTD revenue +3.6% against budget, EBITDA -13.2%. Biggest gross-margin drag: unit cost. | D12: PVM →
B13: Where will the year land? | C13: {="EBITDA "&MONEY(PnL!P19)&" on the "&ScenarioName&" scenario, against a budget of "&MONEY(PnL!Q19)&"."} -> EBITDA $2.3M on the Base scenario, against a budget of $2.7M. | D13: Forecast →
B14: What would it take to hit budget? | C14: =IF(breakeven_gap>0,"A "&TEXT(breakeven_uplift,"0.0%")&" price rise on the open months, or "&TEXT(breakeven_volume,"0%")&" more volume.","Nothing: the outlook is at or above budget.") -> A 2.6% price rise on the open months, or 11% more volume. | D14: Scenarios →
B15: Where is cash tied up? | C15: {="A "&TEXT(WorkingCapital!O15,"0.0")&"-day cash cycle; "&MONEY(wc_at_risk_value)&" of stock sits above its shelf-life risk line."} -> A 20.6-day cash cycle; $58K of stock sits above its shelf-life risk line. | D15: WorkingCapital →
B16: Which channels earn the growth? | C16: {=_xlfn.LET(_xlpm.c,Channels!B6:B9,_xlpm.g,Channels!M6:M9,_xlpm.j,Channels!J6:J9,_xlpm.k,_xlfn.XMATCH(MAX(_xlpm.g),_xlpm.g),INDEX(_xlpm.c,_xlpm.k)&" grew cases most ("&TEXT(MAX(_xlpm.g),"+0%")&" vs budget) at "&TEXT(INDEX(_xlpm.j,_xlpm.k),"$0.00")&" contribution a case; "&INDEX(_xlpm.c,_xlfn.XMATCH(MAX(_xlpm.j),_xlpm.j))&" earns most, "&TEXT(MAX(_xlpm.j),"$0.00")&".")} -> Grocery Retail grew cases most (+16% vs budget) at $21.58 contribution a case; Online Direct earns most, $50.91. | D16: Channels →
B18: Sheets
B19: Sheet | C19: What it shows | D19: Excel on show
B20: Dashboard | C20: One page for the board: KPIs, bridges, scenarios and a written summary that rewrites itself. | D20: Formula-driven narrative, waterfall and combo charts, sparklines, LET, SORTBY, named LAMBDAs
B21: PnL | C21: Monthly P&L: outlook (actuals + forecast), budget, prior year, variances, YTD. | D21: SUMIFS over tables, FAVVAR / SAFEDIV LAMBDAs, conditional formatting, sparklines
B22: PVM | C22: Price-volume-mix on 24 segments; gross-margin and EBITDA bridges. | D22: Exact four-effect decomposition, XMATCH driver tags, waterfall
B23: Forecast | C23: 8+4 driver forecast by category, budget accuracy, statistical cross-check. | D23: XLOOKUP, WAPE and bias, FORECAST.ETS
B24: Scenarios | C24: Base / upside / downside, price × volume grid, tornado, gap to budget. | D24: What-if data tables (1- and 2-variable), data validation, SORTBY + HSTACK
B25: WorkingCapital | C25: DSO, DIO, DPO and the cash cycle; stock against shelf life. | D25: DAYSOF LAMBDA, trailing windows, data bars, risk flags
B26: Channels | C26: Channel economics by formula and by data model, reconciled. | D26: Power Pivot + DAX (TREATAS), PivotTable with slicers, CUBEVALUE
B27: Checks | C27: 31 controls that prove the model ties out. | D27: Reconciliations with a tolerance
B28: Assumptions | C28: Every input and scenario driver in one place. | D28: Named inputs, validation
B29: PQ_Budget | C29: The budget, unpivoted and priced. | D29: Power Query (M): unpivot, merges, types
B30: Data_Sales | C30: Source tables, loaded unchanged from the CSVs. | D30: Excel tables, structured references
B32: How to use it
B33: 1 Pick a scenario | C33: Scenarios!C4. Every sheet, chart and sentence follows.
B34: 2 Test your own view | C34: Price and volume overlays in Scenarios!C5:C6, on top of the scenario.
B35: 3 Re-cut from an earlier close | C35: Change the as-of month on Assumptions, then Data > Refresh All.
B36: 4 Explore the data model | C36: The slicers on Channels filter a PivotTable built on DAX measures.
B38: Conventions
B39: 0.015 | C39: Input: blue on yellow. Change these; everything else is calculated.
B40: 1234 | C40: Calculated: black. Links from another sheet are green on Scenarios.
B41: Forecast month | C41: Blue shading marks forecast months; unshaded months are actuals.
B42: +1,234 (1,234) | C42: Variances are signed so favourable is positive (green) and unfavourable is in brackets (red), for revenue and cost lines alike.

Sheet Dashboard
B1: ="Kestrel Bay Provisions: FY"&FiscalYear&" performance and outlook" -> Kestrel Bay Provisions: FY2026 performance and outlook
B2: ="Actuals through "&TEXT(AsOfMonth,"mmmm yyyy")&IF(MonthsClosed<12," · forecast "&TEXT(EDATE(AsOfMonth,1),"mmmm")&" to December","")&" · scenario: "&ScenarioName&" · "&checks_summary -> Actuals through August 2026 · forecast September to December · scenario: Base · All 31 checks pass
B4: REVENUE, YEAR TO DATE | E4: GROSS MARGIN %, YTD | H4: EBITDA, YEAR TO DATE | K4: EBITDA, FULL-YEAR OUTLOOK | N4: PRICE RISE TO REACH BUDGET | Q4: CASH CONVERSION CYCLE
B5: =PnL!W8 -> 31533631 | E5: =PnL!W11 -> 0.25853248 | H5: =PnL!W19 -> 1525950.5 | K5: =PnL!P19 -> 2319179.9 | N5: =breakeven_uplift -> 0.02598493 | Q5: =WorkingCapital!O15 -> 20.640439
B6: =PnL!Y8 -> 1110250.1 | E6: =PnL!Y11*100 -> -1.0002666 | H6: =PnL!Y19 -> -231735.84 | K6: =PnL!R19 -> -412477.17 | N6: ="on the "&(12-MonthsClosed)&" open months" -> on the 4 open months | Q6: =WorkingCapital!O15-WorkingCapital!C15 -> 1.8371229
K7: ="scenario: "&ScenarioName -> scenario: Base
B8: ="vs prior year "&TEXT(PnL!AB8,"+0.0%;-0.0%") -> vs prior year +10.9% | E8: ="budget "&TEXT(PnL!X11,"0.0%") -> budget 26.9% | H8: ="margin "&TEXT(PnL!W20,"0.0%")&" vs "&TEXT(PnL!X20,"0.0%")&" budget" -> margin 4.8% vs 5.8% budget | K8: {="budget "&MONEY(PnL!Q19)} -> budget $2.7M | N8: ="or "&TEXT(breakeven_volume,"0%")&" more volume" -> or 11% more volume | Q8: {=_xlfn.LET(_xlpm.u,WorkingCapital!G38:G43,_xlpm.c,WorkingCapital!B38:B43,INDEX(_xlpm.c,_xlfn.XMATCH(MAX(_xlpm.u),_xlpm.u))&": "&TEXT(MAX(_xlpm.u),"0%")&" of shelf life")} -> Cheese & Dairy: 58% of shelf life
B10: What the numbers say
B11: {="Revenue is "&MONEY(ABS(PnL!Y8))&IF(PnL!Y8>=0," ahead of"," behind")&" budget through "&TEXT(AsOfMonth,"mmmm")&" ("&TEXT(PnL!Z8,"+0.0%;-0.0%")&"), yet EBITDA is "&MONEY(ABS(PnL!Y19))&IF(PnL!Y19>=0," ahead"," behind")&" ("&TEXT(PnL!Z19,"+0.0%;-0.0%")&")."&IF(AND(PnL!Y8>0,PnL!Y19<0)," The growth has not reached the bottom line.","")} -> Revenue is $1.1M ahead of budget through August (+3.6%), yet EBITDA is $232K behind (-13.2%). The growth has not reached the bottom line.
B12: {=_xlfn.LET(_xlpm.v,PVM!C70,_xlpm.m,PVM!D70,_xlpm.pr,PVM!E70,_xlpm.c,PVM!F70,_xlpm.chm,PVM!D75:D78,_xlpm.chn,PVM!B75:B78,_xlpm.mixch,INDEX(_xlpm.chn,_xlfn.XMATCH(MIN(_xlpm.chm),_xlpm.chm)),_xlpm.low,INDEX(Channels!B6:B9,_xlfn.XMATCH(MIN(Channels!J6:J9),Channels!J6:J9)),_xlpm.cc,PVM!$F$64:$F$69,_xlpm.cp,PVM!$E$64:$E$69,_xlpm.cn,PVM!$B$64:$B$69,_xlpm.k,_xlfn.XMATCH(MIN(_xlpm.cc),_xlpm.cc),"Gross margin, year to date: volume "&SIGNMONEY(_xlpm.v)&", price "&SIGNMONEY(_xlpm.pr)&", mix "&SIGNMONEY(_xlpm.m)&", unit cost "&SIGNMONEY(_xlpm.c)&". Mix is negative because volume shifted toward "&_xlpm.mixch&IF(_xlpm.mixch=_xlpm.low,", the channel that earns least per case","")&"; "&INDEX(_xlpm.cn,_xlpm.k)&" costs rose"&IF(INDEX(_xlpm.cc,_xlpm.k)+INDEX(_xlpm.cp,_xlpm.k)<0," faster than its prices.","."))} -> Gross margin, year to date: volume +$290K, price +$238K, mix −$173K, unit cost −$372K. Mix is negative because volume shifted toward Grocery Retail, the channel that earns least per case; Beef costs rose faster than its prices.
B13: {="Below gross margin, freight "&SIGNMONEY(PnL!Y12)&" and operating expenses "&SIGNMONEY(PnL!Y18)&" (mostly "&INDEX(TRIM(PnL!B14:B17),_xlfn.XMATCH(MIN(PnL!Y14:Y17),PnL!Y14:Y17))&") leave EBITDA at "&MONEY(PnL!W19)&" against a budget of "&MONEY(PnL!X19)&"."} -> Below gross margin, freight −$36K and operating expenses −$178K (mostly Warehouse & Logistics) leave EBITDA at $1.5M against a budget of $1.8M.
B14: {=IF(breakeven_gap>0,"Full year on the "&ScenarioName&" scenario: EBITDA "&MONEY(PnL!P19)&" against a budget of "&MONEY(PnL!Q19)&". Closing the "&MONEY(breakeven_gap)&" gap takes a "&TEXT(breakeven_uplift,"0.0%")&" price rise on the "&(12-MonthsClosed)&" open months, or "&TEXT(breakeven_volume,"0%")&" more volume: price is the realistic lever.","Full year on the "&ScenarioName&" scenario: EBITDA "&MONEY(PnL!P19)&", "&MONEY(-breakeven_gap)&" above budget.")} -> Full year on the Base scenario: EBITDA $2.3M against a budget of $2.7M. Closing the $412K gap takes a 2.6% price rise on the 4 open months, or 11% more volume: price is the realistic lever.
B15: ="Cash: DSO "&TEXT(WorkingCapital!O12,"0")&" days, DIO "&TEXT(WorkingCapital!O13,"0")&", DPO "&TEXT(WorkingCapital!O14,"0")&", a "&TEXT(WorkingCapital!O15,"0.0")&"-day cycle. "&WorkingCapital!B46 -> Cash: DSO 32 days, DIO 16, DPO 27, a 20.6-day cycle. Cheese & Dairy holds 52 days of stock, 58% of its 90-day shelf life: $58K of it sits above the 50% risk line, stock that needs a markdown or a slower buy before it becomes a write-off.
B55: Largest gross-margin movers against budget, year to date | K55: Full year by scenario
B56: Segment | G56: Main driver | J56: GM vs budget | K56: Scenario | M56: Revenue | O56: EBITDA | Q56: Margin | S56: vs budget
B57: {=_xlfn.LET(_xlpm.seg,PVM!$B$35:$B$58&" · "&PVM!$C$35:$C$58,_xlpm.v,PVM!$U$35:$U$58,INDEX(_xlfn.SORTBY(_xlpm.seg,ABS(_xlpm.v),-1),ROWS(B$57:B57)))} -> Beef · Restaurants | G57: {=_xlfn.LET(_xlpm.d,PVM!$W$35:$W$58,_xlpm.v,PVM!$U$35:$U$58,INDEX(_xlfn.SORTBY(_xlpm.d,ABS(_xlpm.v),-1),ROWS(G$57:G57)))} -> Unit cost | J57: {=_xlfn.LET(_xlpm.v,PVM!$U$35:$U$58,INDEX(_xlfn.SORTBY(_xlpm.v,ABS(_xlpm.v),-1),ROWS(J$57:J57)))} -> -151620.28 | K57: =Scenarios!B18 -> Base | M57: =Scenarios!C18 -> 47407338 | O57: =Scenarios!E18 -> 2319179.9 | Q57: =Scenarios!F18 -> 0.048920272 | S57: =Scenarios!G18 -> -412477.17
B58: {=_xlfn.LET(_xlpm.seg,PVM!$B$35:$B$58&" · "&PVM!$C$35:$C$58,_xlpm.v,PVM!$U$35:$U$58,INDEX(_xlfn.SORTBY(_xlpm.seg,ABS(_xlpm.v),-1),ROWS(B$57:B58)))} -> Seafood · Grocery Retail | G58: {=_xlfn.LET(_xlpm.d,PVM!$W$35:$W$58,_xlpm.v,PVM!$U$35:$U$58,INDEX(_xlfn.SORTBY(_xlpm.d,ABS(_xlpm.v),-1),ROWS(G$57:G58)))} -> Price | J58: {=_xlfn.LET(_xlpm.v,PVM!$U$35:$U$58,INDEX(_xlfn.SORTBY(_xlpm.v,ABS(_xlpm.v),-1),ROWS(J$57:J58)))} -> 71982.43 | K58: =Scenarios!B19 -> Upside | M58: =Scenarios!C19 -> 48128798 | O58: =Scenarios!E19 -> 2836094 | Q58: =Scenarios!F19 -> 0.058927173 | S58: =Scenarios!G19 -> 104436.97
B59: {=_xlfn.LET(_xlpm.seg,PVM!$B$35:$B$58&" · "&PVM!$C$35:$C$58,_xlpm.v,PVM!$U$35:$U$58,INDEX(_xlfn.SORTBY(_xlpm.seg,ABS(_xlpm.v),-1),ROWS(B$57:B59)))} -> Beef · Hotels & Institutions | G59: {=_xlfn.LET(_xlpm.d,PVM!$W$35:$W$58,_xlpm.v,PVM!$U$35:$U$58,INDEX(_xlfn.SORTBY(_xlpm.d,ABS(_xlpm.v),-1),ROWS(G$57:G59)))} -> Unit cost | J59: {=_xlfn.LET(_xlpm.v,PVM!$U$35:$U$58,INDEX(_xlfn.SORTBY(_xlpm.v,ABS(_xlpm.v),-1),ROWS(J$57:J59)))} -> -59108 | K59: =Scenarios!B20 -> Downside | M59: =Scenarios!C20 -> 46620002 | O59: =Scenarios!E20 -> 1656743 | Q59: =Scenarios!F20 -> 0.035537171 | S59: =Scenarios!G20 -> -1074914
B60: {=_xlfn.LET(_xlpm.seg,PVM!$B$35:$B$58&" · "&PVM!$C$35:$C$58,_xlpm.v,PVM!$U$35:$U$58,INDEX(_xlfn.SORTBY(_xlpm.seg,ABS(_xlpm.v),-1),ROWS(B$57:B60)))} -> Poultry · Grocery Retail | G60: {=_xlfn.LET(_xlpm.d,PVM!$W$35:$W$58,_xlpm.v,PVM!$U$35:$U$58,INDEX(_xlfn.SORTBY(_xlpm.d,ABS(_xlpm.v),-1),ROWS(G$57:G60)))} -> Volume | J60: {=_xlfn.LET(_xlpm.v,PVM!$U$35:$U$58,INDEX(_xlfn.SORTBY(_xlpm.v,ABS(_xlpm.v),-1),ROWS(J$57:J60)))} -> 51866.77 | K60: Budget | M60: =Scenarios!C21 -> 45768802 | O60: =Scenarios!E21 -> 2731657 | Q60: =Scenarios!F21 -> 0.059683822
B61: {=_xlfn.LET(_xlpm.seg,PVM!$B$35:$B$58&" · "&PVM!$C$35:$C$58,_xlpm.v,PVM!$U$35:$U$58,INDEX(_xlfn.SORTBY(_xlpm.seg,ABS(_xlpm.v),-1),ROWS(B$57:B61)))} -> Seafood · Restaurants | G61: {=_xlfn.LET(_xlpm.d,PVM!$W$35:$W$58,_xlpm.v,PVM!$U$35:$U$58,INDEX(_xlfn.SORTBY(_xlpm.d,ABS(_xlpm.v),-1),ROWS(G$57:G61)))} -> Price | J61: {=_xlfn.LET(_xlpm.v,PVM!$U$35:$U$58,INDEX(_xlfn.SORTBY(_xlpm.v,ABS(_xlpm.v),-1),ROWS(J$57:J61)))} -> 51479
B62: Kestrel Bay Provisions is fictional and every figure is synthetic. Built in Excel by Kush Patel: github.com/KushPatel29/excel-fpa-model
B68: Chart data: the charts above read these cells, which read the model.
B71: Month | C71: Actual | D71: Forecast | E71: Budget | F71: Prior year
B72: {=TRANSPOSE(TEXT(pnl_months,"mmm"))} -> Jan | C72: {=TRANSPOSE(IF(pnl_months<=AsOfMonth,PnL!$D$8:$O$8,""))} -> 3392254.2 | D72: {=TRANSPOSE(IF(pnl_months>AsOfMonth,PnL!$D$8:$O$8,""))} | E72: {=TRANSPOSE(PnL!$D$25:$O$25)} -> 3439390.9 | F72: {=TRANSPOSE(PnL!$D$42:$O$42)} -> 3218241.6
B73: Feb | C73: 3483944 | E73: 3351624.8 | F73: 3130900.3
B74: Mar | C74: 3722609.1 | E74: 3562620.3 | F74: 3334202.5
B75: Apr | C75: 3897955.2 | E75: 3745449.1 | F75: 3503499.3
B76: May | C76: 4188761.9 | E76: 4031810.3 | F76: 3770601.9
B77: Jun | C77: 4343870.5 | E77: 4156915.1 | F77: 3886478.4
B78: Jul | C78: 4313685.7 | E78: 4127204 | F78: 3854332.6
B79: Aug | C79: 4190550.5 | E79: 4008366.5 | F79: 3747572.4
B80: Sep | D80: 3894907.9 | E80: 3766953.7 | F80: 3522865.4
B81: Oct | D81: 3843015.5 | E81: 3712316.4 | F81: 3470892.5
B82: Nov | D82: 3886984.6 | E82: 3756857.5 | F82: 3514051.6
B83: Dec | D83: 4248799 | E83: 4109293.5 | F83: 3837508.8
B86: =PVM!E84 -> Budget EBITDA | C86: =PVM!F84 -> 1757686.4
B87: =PVM!E85 -> Volume | C87: =PVM!F85 -> 289952.84
B88: =PVM!E86 -> Mix | C88: =PVM!F86 -> -173287.14
B89: =PVM!E87 -> Price | C89: =PVM!F87 -> 238025.89
B90: =PVM!E88 -> Unit cost | C90: =PVM!F88 -> -371970.8
B91: =PVM!E89 -> Freight | C91: =PVM!F89 -> -36270.05
B92: =PVM!E90 -> Operating expenses | C92: =PVM!F90 -> -178186.57
B93: =PVM!E91 -> Actual EBITDA | C93: =PVM!F91 -> 1525950.5
B96: Category | C96: Volume | D96: Mix | E96: Price | F96: Unit cost
B97: =PVM!B64 -> Beef | C97: =PVM!C64 -> 40085.824 | D97: =PVM!D64 -> -41929.15 | E97: =PVM!E64 -> 92468.853 | F97: =PVM!F64 -> -368914.72
B98: =PVM!B65 -> Pork | C98: =PVM!C65 -> 83741.732 | D98: =PVM!D65 -> -38130.102 | E98: =PVM!E65 -> -652.99818 | F98: =PVM!F65 -> 603.87856
B99: =PVM!B66 -> Poultry | C99: =PVM!C66 -> 108344.26 | D99: =PVM!D66 -> -63445.249 | E99: =PVM!E66 -> 3559.207 | F99: =PVM!F66 -> -2873.6493
B100: =PVM!B67 -> Seafood | C100: =PVM!C67 -> 35856.052 | D100: =PVM!D67 -> -18326.646 | E100: =PVM!E67 -> 137156.28 | F100: =PVM!F67 -> -1630.1055
B101: =PVM!B68 -> Charcuterie | C101: =PVM!C68 -> 24447.308 | D101: =PVM!D68 -> 3771.9399 | E101: =PVM!E68 -> 3446.8365 | F101: =PVM!F68 -> -119.15448
B102: =PVM!B69 -> Cheese & Dairy | C102: =PVM!C69 -> -2522.3413 | D102: =PVM!D69 -> -15227.936 | E102: =PVM!E69 -> 2047.711 | F102: =PVM!F69 -> 962.94624
B105: Scenario | C105: FY EBITDA
B106: Budget | C106: =PnL!Q19 -> 2731657
B107: =Scenarios!B18 -> Base | C107: =Scenarios!E18 -> 2319179.9
B108: =Scenarios!B19 -> Upside | C108: =Scenarios!E19 -> 2836094
B109: =Scenarios!B20 -> Downside | C109: =Scenarios!E20 -> 1656743

Sheet PnL
B1: ="Profit and loss, FY"&FiscalYear&": outlook against budget and prior year" -> Profit and loss, FY2026: outlook against budget and prior year
B2: ="Actuals through "&TEXT(AsOfMonth,"mmmm yyyy")&", forecast after (shaded). Scenario: "&ScenarioName&". Favourable variances are positive; unfavourable ones in brackets." -> Actuals through August 2026, forecast after (shaded). Scenario: Base. Favourable variances are positive; unfavourable ones in brackets.
B4: Month | D4: =FYStart -> 46023 | E4: =EDATE(D4,1) -> 46054 | F4: =EDATE(E4,1) -> 46082 | G4: =EDATE(F4,1) -> 46113 | H4: =EDATE(G4,1) -> 46143 | I4: =EDATE(H4,1) -> 46174 | J4: =EDATE(I4,1) -> 46204 | K4: =EDATE(J4,1) -> 46235 | L4: =EDATE(K4,1) -> 46266 | ... O4: =EDATE(N4,1) -> 46357 | P4: FY outlook | Q4: FY budget | R4: Fav / (unfav) | S4: Var % | T4: Prior year | U4: vs PY | V4: Trend | W4: YTD actual | X4: YTD budget | Y4: Fav / (unfav) | Z4: Var % | AA4: YTD prior year | AB4: YTD vs PY
D5: {=IF(ISCLOSED(D$4),"Actual","Forecast")} -> Actual | E5: {=IF(ISCLOSED(E$4),"Actual","Forecast")} -> Actual | F5: {=IF(ISCLOSED(F$4),"Actual","Forecast")} -> Actual | G5: {=IF(ISCLOSED(G$4),"Actual","Forecast")} -> Actual | H5: {=IF(ISCLOSED(H$4),"Actual","Forecast")} -> Actual | I5: {=IF(ISCLOSED(I$4),"Actual","Forecast")} -> Actual | J5: {=IF(ISCLOSED(J$4),"Actual","Forecast")} -> Actual | K5: {=IF(ISCLOSED(K$4),"Actual","Forecast")} -> Actual | ... O5: {=IF(ISCLOSED(O$4),"Actual","Forecast")} -> Forecast | P5: all 12 months | W5: ="Jan–"&TEXT(AsOfMonth,"mmm") -> Jan–Aug
B6: Outlook: actuals to the as-of month, driver forecast after
B7: Cases sold | D7: {=IF(ISCLOSED(D$4),SUMIFS(tbl_Sales[units],tbl_Sales[month],D$4),Forecast!D$43)} -> 23802 | E7: {=IF(ISCLOSED(E$4),SUMIFS(tbl_Sales[units],tbl_Sales[month],E$4),Forecast!E$43)} -> 24533 | F7: {=IF(ISCLOSED(F$4),SUMIFS(tbl_Sales[units],tbl_Sales[month],F$4),Forecast!F$43)} -> 26034 | G7: {=IF(ISCLOSED(G$4),SUMIFS(tbl_Sales[units],tbl_Sales[month],G$4),Forecast!G$43)} -> 27099 | H7: {=IF(ISCLOSED(H$4),SUMIFS(tbl_Sales[units],tbl_Sales[month],H$4),Forecast!H$43)} -> 28691 | I7: {=IF(ISCLOSED(I$4),SUMIFS(tbl_Sales[units],tbl_Sales[month],I$4),Forecast!I$43)} -> 29597 | J7: {=IF(ISCLOSED(J$4),SUMIFS(tbl_Sales[units],tbl_Sales[month],J$4),Forecast!J$43)} -> 29433 | K7: {=IF(ISCLOSED(K$4),SUMIFS(tbl_Sales[units],tbl_Sales[month],K$4),Forecast!K$43)} -> 28815 | ... O7: {=IF(ISCLOSED(O$4),SUMIFS(tbl_Sales[units],tbl_Sales[month],O$4),Forecast!O$43)} -> 29931.599 | P7: =SUM(D7:O7) -> 329092.52 | Q7: =P24 -> 317860 | R7: =P7-Q7 -> 11232.521 | S7: {=SAFEDIV(R7,ABS(Q7))} -> 0.035337951 | T7: =P41 -> 309144 | U7: {=SAFEDIV(P7-T7,ABS(T7))} -> 0.064528249 | W7: =SUMIFS(D7:O7,$D$4:$O$4,"<="&AsOfMonth) -> 218004 | X7: =SUMIFS(D24:O24,$D$4:$O$4,"<="&AsOfMonth) -> 210532 | Y7: =W7-X7 -> 7472 | Z7: {=SAFEDIV(Y7,ABS(X7))} -> 0.035491042 | AA7: =SUMIFS(D41:O41,$D$4:$O$4,"<="&AsOfMonth) -> 204784 | AB7: {=SAFEDIV(W7-AA7,ABS(AA7))} -> 0.064555825
B8: Revenue | D8: {=IF(ISCLOSED(D$4),SUMIFS(tbl_Sales[net_revenue],tbl_Sales[month],D$4),Forecast!D$53)} -> 3392254.2 | E8: {=IF(ISCLOSED(E$4),SUMIFS(tbl_Sales[net_revenue],tbl_Sales[month],E$4),Forecast!E$53)} -> 3483944 | F8: {=IF(ISCLOSED(F$4),SUMIFS(tbl_Sales[net_revenue],tbl_Sales[month],F$4),Forecast!F$53)} -> 3722609.1 | G8: {=IF(ISCLOSED(G$4),SUMIFS(tbl_Sales[net_revenue],tbl_Sales[month],G$4),Forecast!G$53)} -> 3897955.2 | H8: {=IF(ISCLOSED(H$4),SUMIFS(tbl_Sales[net_revenue],tbl_Sales[month],H$4),Forecast!H$53)} -> 4188761.9 | I8: {=IF(ISCLOSED(I$4),SUMIFS(tbl_Sales[net_revenue],tbl_Sales[month],I$4),Forecast!I$53)} -> 4343870.5 | J8: {=IF(ISCLOSED(J$4),SUMIFS(tbl_Sales[net_revenue],tbl_Sales[month],J$4),Forecast!J$53)} -> 4313685.7 | K8: {=IF(ISCLOSED(K$4),SUMIFS(tbl_Sales[net_revenue],tbl_Sales[month],K$4),Forecast!K$53)} -> 4190550.5 | ... O8: {=IF(ISCLOSED(O$4),SUMIFS(tbl_Sales[net_revenue],tbl_Sales[month],O$4),Forecast!O$53)} -> 4248799 | P8: =SUM(D8:O8) -> 47407338 | Q8: =P25 -> 45768802 | R8: {=FAVVAR(P8,Q8,FALSE)} -> 1638536.2 | S8: {=SAFEDIV(R8,ABS(Q8))} -> 0.035800285 | T8: =P42 -> 42791147 | U8: {=SAFEDIV(P8-T8,ABS(T8))} -> 0.10787724 | W8: =SUMIFS(D8:O8,$D$4:$O$4,"<="&AsOfMonth) -> 31533631 | X8: =SUMIFS(D25:O25,$D$4:$O$4,"<="&AsOfMonth) -> 30423381 | Y8: {=FAVVAR(W8,X8,FALSE)} -> 1110250.1 | Z8: {=SAFEDIV(Y8,ABS(X8))} -> 0.036493316 | AA8: =SUMIFS(D42:O42,$D$4:$O$4,"<="&AsOfMonth) -> 28445829 | AB8: {=SAFEDIV(W8-AA8,ABS(AA8))} -> 0.10855026
B9: Cost of goods sold | D9: {=IF(ISCLOSED(D$4),SUMIFS(tbl_Sales[cogs],tbl_Sales[month],D$4),Forecast!D$63)} -> 2470958.3 | E9: {=IF(ISCLOSED(E$4),SUMIFS(tbl_Sales[cogs],tbl_Sales[month],E$4),Forecast!E$63)} -> 2555340.9 | F9: {=IF(ISCLOSED(F$4),SUMIFS(tbl_Sales[cogs],tbl_Sales[month],F$4),Forecast!F$63)} -> 2733364.1 | G9: {=IF(ISCLOSED(G$4),SUMIFS(tbl_Sales[cogs],tbl_Sales[month],G$4),Forecast!G$63)} -> 2871704.4 | H9: {=IF(ISCLOSED(H$4),SUMIFS(tbl_Sales[cogs],tbl_Sales[month],H$4),Forecast!H$63)} -> 3130924.7 | I9: {=IF(ISCLOSED(I$4),SUMIFS(tbl_Sales[cogs],tbl_Sales[month],I$4),Forecast!I$63)} -> 3251870.7 | J9: {=IF(ISCLOSED(J$4),SUMIFS(tbl_Sales[cogs],tbl_Sales[month],J$4),Forecast!J$63)} -> 3230095.7 | K9: {=IF(ISCLOSED(K$4),SUMIFS(tbl_Sales[cogs],tbl_Sales[month],K$4),Forecast!K$63)} -> 3136904.4 | ... O9: {=IF(ISCLOSED(O$4),SUMIFS(tbl_Sales[cogs],tbl_Sales[month],O$4),Forecast!O$63)} -> 3121278.3 | P9: =SUM(D9:O9) -> 35106482 | Q9: =P26 -> 33378999 | R9: {=FAVVAR(P9,Q9,TRUE)} -> -1727483.4 | S9: {=SAFEDIV(R9,ABS(Q9))} -> -0.051753601 | T9: =P43 -> 31512171 | U9: {=SAFEDIV(P9-T9,ABS(T9))} -> 0.11406104 | W9: =SUMIFS(D9:O9,$D$4:$O$4,"<="&AsOfMonth) -> 23381163 | X9: =SUMIFS(D26:O26,$D$4:$O$4,"<="&AsOfMonth) -> 22253634 | Y9: {=FAVVAR(W9,X9,TRUE)} -> -1127529.3 | Z9: {=SAFEDIV(Y9,ABS(X9))} -> -0.050667198 | AA9: =SUMIFS(D43:O43,$D$4:$O$4,"<="&AsOfMonth) -> 21010123 | AB9: {=SAFEDIV(W9-AA9,ABS(AA9))} -> 0.11285227
B10: Gross margin | D10: =D8-D9 -> 921295.89 | E10: =E8-E9 -> 928603.04 | F10: =F8-F9 -> 989245.02 | G10: =G8-G9 -> 1026250.9 | H10: =H8-H9 -> 1057837.2 | I10: =I8-I9 -> 1091999.8 | J10: =J8-J9 -> 1083590 | K10: =K8-K9 -> 1053646.1 | ... O10: =O8-O9 -> 1127520.7 | P10: =SUM(D10:O10) -> 12300856 | Q10: =P27 -> 12389803 | R10: {=FAVVAR(P10,Q10,FALSE)} -> -88947.21 | S10: {=SAFEDIV(R10,ABS(Q10))} -> -0.0071790655 | T10: =P44 -> 11278976 | U10: {=SAFEDIV(P10-T10,ABS(T10))} -> 0.090600427 | W10: =SUMIFS(D10:O10,$D$4:$O$4,"<="&AsOfMonth) -> 8152467.9 | X10: =SUMIFS(D27:O27,$D$4:$O$4,"<="&AsOfMonth) -> 8169747.1 | Y10: {=FAVVAR(W10,X10,FALSE)} -> -17279.22 | Z10: {=SAFEDIV(Y10,ABS(X10))} -> -0.0021150251 | AA10: =SUMIFS(D44:O44,$D$4:$O$4,"<="&AsOfMonth) -> 7435705.8 | AB10: {=SAFEDIV(W10-AA10,ABS(AA10))} -> 0.096394629
B11: Gross margin % | D11: {=SAFEDIV(D10,D8)} -> 0.2715881 | E11: {=SAFEDIV(E10,E8)} -> 0.26653788 | F11: {=SAFEDIV(F10,F8)} -> 0.2657397 | G11: {=SAFEDIV(G10,G8)} -> 0.26327928 | H11: {=SAFEDIV(H10,H8)} -> 0.25254174 | I11: {=SAFEDIV(I10,I8)} -> 0.25138866 | J11: {=SAFEDIV(J10,J8)} -> 0.25119817 | K11: {=SAFEDIV(K10,K8)} -> 0.25143381 | ... P11: {=SAFEDIV(P10,P8)} -> 0.25947156 | Q11: =P28 -> 0.27070412 | R11: =P11-Q11 -> -0.011232559 | T11: =P45 -> 0.263582 | U11: =P11-T11 -> -0.0041104352 | W11: {=SAFEDIV(W10,W8)} -> 0.25853248 | X11: {=SAFEDIV(X10,X8)} -> 0.26853515 | Y11: =W11-X11 -> -0.010002666 | AA11: {=SAFEDIV(AA10,AA8)} -> 0.26139881 | AB11: =W11-AA11 -> -0.0028663272
B12: Freight | D12: {=IF(ISCLOSED(D$4),SUMIFS(tbl_Sales[freight],tbl_Sales[month],D$4),Forecast!D$73)} -> 79628.36 | E12: {=IF(ISCLOSED(E$4),SUMIFS(tbl_Sales[freight],tbl_Sales[month],E$4),Forecast!E$73)} -> 80812.44 | F12: {=IF(ISCLOSED(F$4),SUMIFS(tbl_Sales[freight],tbl_Sales[month],F$4),Forecast!F$73)} -> 85861.18 | G12: {=IF(ISCLOSED(G$4),SUMIFS(tbl_Sales[freight],tbl_Sales[month],G$4),Forecast!G$73)} -> 89538.75 | H12: {=IF(ISCLOSED(H$4),SUMIFS(tbl_Sales[freight],tbl_Sales[month],H$4),Forecast!H$73)} -> 95117.83 | I12: {=IF(ISCLOSED(I$4),SUMIFS(tbl_Sales[freight],tbl_Sales[month],I$4),Forecast!I$73)} -> 97563.18 | J12: {=IF(ISCLOSED(J$4),SUMIFS(tbl_Sales[freight],tbl_Sales[month],J$4),Forecast!J$73)} -> 97225.71 | K12: {=IF(ISCLOSED(K$4),SUMIFS(tbl_Sales[freight],tbl_Sales[month],K$4),Forecast!K$73)} -> 94942.85 | ... O12: {=IF(ISCLOSED(O$4),SUMIFS(tbl_Sales[freight],tbl_Sales[month],O$4),Forecast!O$73)} -> 98731.859 | P12: =SUM(D12:O12) -> 1087116.2 | Q12: =P29 -> 1033566.9 | R12: {=FAVVAR(P12,Q12,TRUE)} -> -53549.279 | S12: {=SAFEDIV(R12,ABS(Q12))} -> -0.051810172 | T12: =P46 -> 986287.3 | U12: {=SAFEDIV(P12-T12,ABS(T12))} -> 0.10223074 | W12: =SUMIFS(D12:O12,$D$4:$O$4,"<="&AsOfMonth) -> 720690.3 | X12: =SUMIFS(D29:O29,$D$4:$O$4,"<="&AsOfMonth) -> 684420.25 | Y12: {=FAVVAR(W12,X12,TRUE)} -> -36270.05 | Z12: {=SAFEDIV(Y12,ABS(X12))} -> -0.052993829 | AA12: =SUMIFS(D46:O46,$D$4:$O$4,"<="&AsOfMonth) -> 653290.26 | AB12: {=SAFEDIV(W12-AA12,ABS(AA12))} -> 0.10317013
B13: Contribution | D13: =D10-D12 -> 841667.53 | E13: =E10-E12 -> 847790.6 | F13: =F10-F12 -> 903383.84 | G13: =G10-G12 -> 936712.1 | H13: =H10-H12 -> 962719.41 | I13: =I10-I12 -> 994436.61 | J13: =J10-J12 -> 986364.26 | K13: =K10-K12 -> 958703.23 | ... O13: =O10-O12 -> 1028788.9 | P13: =SUM(D13:O13) -> 11213740 | Q13: =P30 -> 11356237 | R13: {=FAVVAR(P13,Q13,FALSE)} -> -142496.49 | S13: {=SAFEDIV(R13,ABS(Q13))} -> -0.012547862 | T13: =P47 -> 10292689 | U13: {=SAFEDIV(P13-T13,ABS(T13))} -> 0.089485964 | W13: =SUMIFS(D13:O13,$D$4:$O$4,"<="&AsOfMonth) -> 7431777.6 | X13: =SUMIFS(D30:O30,$D$4:$O$4,"<="&AsOfMonth) -> 7485326.9 | Y13: {=FAVVAR(W13,X13,FALSE)} -> -53549.27 | Z13: {=SAFEDIV(Y13,ABS(X13))} -> -0.0071538987 | AA13: =SUMIFS(D47:O47,$D$4:$O$4,"<="&AsOfMonth) -> 6782415.5 | AB13: {=SAFEDIV(W13-AA13,ABS(AA13))} -> 0.095742005
B14: Sales & Marketing | D14: {=IF(ISCLOSED(D$4),SUMIFS(tbl_Opex[amount],tbl_Opex[month],D$4,tbl_Opex[dept],TRIM($B14),tbl_Opex[scenario],"Actual"),_xlfn.XLOOKUP(TRIM($B14),Forecast!$B$85:$B$88,Forecast!D$85:D$88))} -> 200502.67 | E14: {=IF(ISCLOSED(E$4),SUMIFS(tbl_Opex[amount],tbl_Opex[month],E$4,tbl_Opex[dept],TRIM($B14),tbl_Opex[scenario],"Actual"),_xlfn.XLOOKUP(TRIM($B14),Forecast!$B$85:$B$88,Forecast!E$85:E$88))} -> 197737.12 | F14: {=IF(ISCLOSED(F$4),SUMIFS(tbl_Opex[amount],tbl_Opex[month],F$4,tbl_Opex[dept],TRIM($B14),tbl_Opex[scenario],"Actual"),_xlfn.XLOOKUP(TRIM($B14),Forecast!$B$85:$B$88,Forecast!F$85:F$88))} -> 196749.42 | G14: {=IF(ISCLOSED(G$4),SUMIFS(tbl_Opex[amount],tbl_Opex[month],G$4,tbl_Opex[dept],TRIM($B14),tbl_Opex[scenario],"Actual"),_xlfn.XLOOKUP(TRIM($B14),Forecast!$B$85:$B$88,Forecast!G$85:G$88))} -> 199514.98 | H14: {=IF(ISCLOSED(H$4),SUMIFS(tbl_Opex[amount],tbl_Opex[month],H$4,tbl_Opex[dept],TRIM($B14),tbl_Opex[scenario],"Actual"),_xlfn.XLOOKUP(TRIM($B14),Forecast!$B$85:$B$88,Forecast!H$85:H$88))} -> 199712.52 | I14: {=IF(ISCLOSED(I$4),SUMIFS(tbl_Opex[amount],tbl_Opex[month],I$4,tbl_Opex[dept],TRIM($B14),tbl_Opex[scenario],"Actual"),_xlfn.XLOOKUP(TRIM($B14),Forecast!$B$85:$B$88,Forecast!I$85:I$88))} -> 198922.36 | J14: {=IF(ISCLOSED(J$4),SUMIFS(tbl_Opex[amount],tbl_Opex[month],J$4,tbl_Opex[dept],TRIM($B14),tbl_Opex[scenario],"Actual"),_xlfn.XLOOKUP(TRIM($B14),Forecast!$B$85:$B$88,Forecast!J$85:J$88))} -> 194971.57 | K14: {=IF(ISCLOSED(K$4),SUMIFS(tbl_Opex[amount],tbl_Opex[month],K$4,tbl_Opex[dept],TRIM($B14),tbl_Opex[scenario],"Actual"),_xlfn.XLOOKUP(TRIM($B14),Forecast!$B$85:$B$88,Forecast!K$85:K$88))} -> 194971.57 | ... O14: {=IF(ISCLOSED(O$4),SUMIFS(tbl_Opex[amount],tbl_Opex[month],O$4,tbl_Opex[dept],TRIM($B14),tbl_Opex[scenario],"Actual"),_xlfn.XLOOKUP(TRIM($B14),Forecast!$B$85:$B$88,Forecast!O$85:O$88))} -> 197885.28 | P14: =SUM(D14:O14) -> 2374623.3 | Q14: =P31 -> 2419456.7 | R14: {=FAVVAR(P14,Q14,TRUE)} -> 44833.365 | S14: {=SAFEDIV(R14,ABS(Q14))} -> 0.018530344 | T14: =P48 -> 2348987.1 | U14: {=SAFEDIV(P14-T14,ABS(T14))} -> 0.010913732 | W14: =SUMIFS(D14:O14,$D$4:$O$4,"<="&AsOfMonth) -> 1583082.2 | X14: =SUMIFS(D31:O31,$D$4:$O$4,"<="&AsOfMonth) -> 1612971.1 | Y14: {=FAVVAR(W14,X14,TRUE)} -> 29888.91 | Z14: {=SAFEDIV(Y14,ABS(X14))} -> 0.018530344 | AA14: =SUMIFS(D48:O48,$D$4:$O$4,"<="&AsOfMonth) -> 1565404.3 | AB14: {=SAFEDIV(W14-AA14,ABS(AA14))} -> 0.011292872
B15: Warehouse & Logistics | D15: {=IF(ISCLOSED(D$4),SUMIFS(tbl_Opex[amount],tbl_Opex[month],D$4,tbl_Opex[dept],TRIM($B15),tbl_Opex[scenario],"Actual"),_xlfn.XLOOKUP(TRIM($B15),Forecast!$B$85:$B$88,Forecast!D$85:D$88))} -> 300283.93 | E15: {=IF(ISCLOSED(E$4),SUMIFS(tbl_Opex[amount],tbl_Opex[month],E$4,tbl_Opex[dept],TRIM($B15),tbl_Opex[scenario],"Actual"),_xlfn.XLOOKUP(TRIM($B15),Forecast!$B$85:$B$88,Forecast!E$85:E$88))} -> 302071.33 | F15: {=IF(ISCLOSED(F$4),SUMIFS(tbl_Opex[amount],tbl_Opex[month],F$4,tbl_Opex[dept],TRIM($B15),tbl_Opex[scenario],"Actual"),_xlfn.XLOOKUP(TRIM($B15),Forecast!$B$85:$B$88,Forecast!F$85:F$88))} -> 301177.63 | G15: {=IF(ISCLOSED(G$4),SUMIFS(tbl_Opex[amount],tbl_Opex[month],G$4,tbl_Opex[dept],TRIM($B15),tbl_Opex[scenario],"Actual"),_xlfn.XLOOKUP(TRIM($B15),Forecast!$B$85:$B$88,Forecast!G$85:G$88))} -> 298496.52 | H15: {=IF(ISCLOSED(H$4),SUMIFS(tbl_Opex[amount],tbl_Opex[month],H$4,tbl_Opex[dept],TRIM($B15),tbl_Opex[scenario],"Actual"),_xlfn.XLOOKUP(TRIM($B15),Forecast!$B$85:$B$88,Forecast!H$85:H$88))} -> 295517.51 | I15: {=IF(ISCLOSED(I$4),SUMIFS(tbl_Opex[amount],tbl_Opex[month],I$4,tbl_Opex[dept],TRIM($B15),tbl_Opex[scenario],"Actual"),_xlfn.XLOOKUP(TRIM($B15),Forecast!$B$85:$B$88,Forecast!I$85:I$88))} -> 293730.11 | J15: {=IF(ISCLOSED(J$4),SUMIFS(tbl_Opex[amount],tbl_Opex[month],J$4,tbl_Opex[dept],TRIM($B15),tbl_Opex[scenario],"Actual"),_xlfn.XLOOKUP(TRIM($B15),Forecast!$B$85:$B$88,Forecast!J$85:J$88))} -> 299986.03 | K15: {=IF(ISCLOSED(K$4),SUMIFS(tbl_Opex[amount],tbl_Opex[month],K$4,tbl_Opex[dept],TRIM($B15),tbl_Opex[scenario],"Actual"),_xlfn.XLOOKUP(TRIM($B15),Forecast!$B$85:$B$88,Forecast!K$85:K$88))} -> 296709.12 | ... O15: {=IF(ISCLOSED(O$4),SUMIFS(tbl_Opex[amount],tbl_Opex[month],O$4,tbl_Opex[dept],TRIM($B15),tbl_Opex[scenario],"Actual"),_xlfn.XLOOKUP(TRIM($B15),Forecast!$B$85:$B$88,Forecast!O$85:O$88))} -> 316406.31 | P15: =SUM(D15:O15) -> 3617777.9 | Q15: =P32 -> 3344994.8 | R15: {=FAVVAR(P15,Q15,TRUE)} -> -272783.05 | S15: {=SAFEDIV(R15,ABS(Q15))} -> -0.081549619 | T15: =P49 -> 3247567.7 | U15: {=SAFEDIV(P15-T15,ABS(T15))} -> 0.11399611 | W15: =SUMIFS(D15:O15,$D$4:$O$4,"<="&AsOfMonth) -> 2387972.2 | X15: =SUMIFS(D32:O32,$D$4:$O$4,"<="&AsOfMonth) -> 2207917.4 | Y15: {=FAVVAR(W15,X15,TRUE)} -> -180054.82 | Z15: {=SAFEDIV(Y15,ABS(X15))} -> -0.081549619 | AA15: =SUMIFS(D49:O49,$D$4:$O$4,"<="&AsOfMonth) -> 2141596.6 | AB15: {=SAFEDIV(W15-AA15,ABS(AA15))} -> 0.11504295
B16: General & Admin | D16: {=IF(ISCLOSED(D$4),SUMIFS(tbl_Opex[amount],tbl_Opex[month],D$4,tbl_Opex[dept],TRIM($B16),tbl_Opex[scenario],"Actual"),_xlfn.XLOOKUP(TRIM($B16),Forecast!$B$85:$B$88,Forecast!D$85:D$88))} -> 183249.47 | E16: {=IF(ISCLOSED(E$4),SUMIFS(tbl_Opex[amount],tbl_Opex[month],E$4,tbl_Opex[dept],TRIM($B16),tbl_Opex[scenario],"Actual"),_xlfn.XLOOKUP(TRIM($B16),Forecast!$B$85:$B$88,Forecast!E$85:E$88))} -> 180152.81 | F16: {=IF(ISCLOSED(F$4),SUMIFS(tbl_Opex[amount],tbl_Opex[month],F$4,tbl_Opex[dept],TRIM($B16),tbl_Opex[scenario],"Actual"),_xlfn.XLOOKUP(TRIM($B16),Forecast!$B$85:$B$88,Forecast!F$85:F$88))} -> 184342.41 | G16: {=IF(ISCLOSED(G$4),SUMIFS(tbl_Opex[amount],tbl_Opex[month],G$4,tbl_Opex[dept],TRIM($B16),tbl_Opex[scenario],"Actual"),_xlfn.XLOOKUP(TRIM($B16),Forecast!$B$85:$B$88,Forecast!G$85:G$88))} -> 184888.88 | H16: {=IF(ISCLOSED(H$4),SUMIFS(tbl_Opex[amount],tbl_Opex[month],H$4,tbl_Opex[dept],TRIM($B16),tbl_Opex[scenario],"Actual"),_xlfn.XLOOKUP(TRIM($B16),Forecast!$B$85:$B$88,Forecast!H$85:H$88))} -> 184524.56 | I16: {=IF(ISCLOSED(I$4),SUMIFS(tbl_Opex[amount],tbl_Opex[month],I$4,tbl_Opex[dept],TRIM($B16),tbl_Opex[scenario],"Actual"),_xlfn.XLOOKUP(TRIM($B16),Forecast!$B$85:$B$88,Forecast!I$85:I$88))} -> 184888.88 | J16: {=IF(ISCLOSED(J$4),SUMIFS(tbl_Opex[amount],tbl_Opex[month],J$4,tbl_Opex[dept],TRIM($B16),tbl_Opex[scenario],"Actual"),_xlfn.XLOOKUP(TRIM($B16),Forecast!$B$85:$B$88,Forecast!J$85:J$88))} -> 183431.63 | K16: {=IF(ISCLOSED(K$4),SUMIFS(tbl_Opex[amount],tbl_Opex[month],K$4,tbl_Opex[dept],TRIM($B16),tbl_Opex[scenario],"Actual"),_xlfn.XLOOKUP(TRIM($B16),Forecast!$B$85:$B$88,Forecast!K$85:K$88))} -> 183431.63 | ... O16: {=IF(ISCLOSED(O$4),SUMIFS(tbl_Opex[amount],tbl_Opex[month],O$4,tbl_Opex[dept],TRIM($B16),tbl_Opex[scenario],"Actual"),_xlfn.XLOOKUP(TRIM($B16),Forecast!$B$85:$B$88,Forecast!O$85:O$88))} -> 183613.78 | P16: =SUM(D16:O16) -> 2203365.4 | Q16: =P33 -> 2160809.3 | R16: {=FAVVAR(P16,Q16,TRUE)} -> -42556.125 | S16: {=SAFEDIV(R16,ABS(Q16))} -> -0.019694531 | T16: =P50 -> 2097873.1 | U16: {=SAFEDIV(P16-T16,ABS(T16))} -> 0.05028536 | W16: =SUMIFS(D16:O16,$D$4:$O$4,"<="&AsOfMonth) -> 1468910.3 | X16: =SUMIFS(D33:O33,$D$4:$O$4,"<="&AsOfMonth) -> 1440539.5 | Y16: {=FAVVAR(W16,X16,TRUE)} -> -28370.75 | Z16: {=SAFEDIV(Y16,ABS(X16))} -> -0.019694531 | AA16: =SUMIFS(D50:O50,$D$4:$O$4,"<="&AsOfMonth) -> 1396947.8 | AB16: {=SAFEDIV(W16-AA16,ABS(AA16))} -> 0.051514072
B17: Technology | D17: {=IF(ISCLOSED(D$4),SUMIFS(tbl_Opex[amount],tbl_Opex[month],D$4,tbl_Opex[dept],TRIM($B17),tbl_Opex[scenario],"Actual"),_xlfn.XLOOKUP(TRIM($B17),Forecast!$B$85:$B$88,Forecast!D$85:D$88))} -> 58991.34 | E17: {=IF(ISCLOSED(E$4),SUMIFS(tbl_Opex[amount],tbl_Opex[month],E$4,tbl_Opex[dept],TRIM($B17),tbl_Opex[scenario],"Actual"),_xlfn.XLOOKUP(TRIM($B17),Forecast!$B$85:$B$88,Forecast!E$85:E$88))} -> 57941.05 | F17: {=IF(ISCLOSED(F$4),SUMIFS(tbl_Opex[amount],tbl_Opex[month],F$4,tbl_Opex[dept],TRIM($B17),tbl_Opex[scenario],"Actual"),_xlfn.XLOOKUP(TRIM($B17),Forecast!$B$85:$B$88,Forecast!F$85:F$88))} -> 58991.34 | G17: {=IF(ISCLOSED(G$4),SUMIFS(tbl_Opex[amount],tbl_Opex[month],G$4,tbl_Opex[dept],TRIM($B17),tbl_Opex[scenario],"Actual"),_xlfn.XLOOKUP(TRIM($B17),Forecast!$B$85:$B$88,Forecast!G$85:G$88))} -> 58116.1 | H17: {=IF(ISCLOSED(H$4),SUMIFS(tbl_Opex[amount],tbl_Opex[month],H$4,tbl_Opex[dept],TRIM($B17),tbl_Opex[scenario],"Actual"),_xlfn.XLOOKUP(TRIM($B17),Forecast!$B$85:$B$88,Forecast!H$85:H$88))} -> 57824.35 | I17: {=IF(ISCLOSED(I$4),SUMIFS(tbl_Opex[amount],tbl_Opex[month],I$4,tbl_Opex[dept],TRIM($B17),tbl_Opex[scenario],"Actual"),_xlfn.XLOOKUP(TRIM($B17),Forecast!$B$85:$B$88,Forecast!I$85:I$88))} -> 58291.15 | J17: {=IF(ISCLOSED(J$4),SUMIFS(tbl_Opex[amount],tbl_Opex[month],J$4,tbl_Opex[dept],TRIM($B17),tbl_Opex[scenario],"Actual"),_xlfn.XLOOKUP(TRIM($B17),Forecast!$B$85:$B$88,Forecast!J$85:J$88))} -> 57474.26 | K17: {=IF(ISCLOSED(K$4),SUMIFS(tbl_Opex[amount],tbl_Opex[month],K$4,tbl_Opex[dept],TRIM($B17),tbl_Opex[scenario],"Actual"),_xlfn.XLOOKUP(TRIM($B17),Forecast!$B$85:$B$88,Forecast!K$85:K$88))} -> 58232.8 | ... O17: {=IF(ISCLOSED(O$4),SUMIFS(tbl_Opex[amount],tbl_Opex[month],O$4,tbl_Opex[dept],TRIM($B17),tbl_Opex[scenario],"Actual"),_xlfn.XLOOKUP(TRIM($B17),Forecast!$B$85:$B$88,Forecast!O$85:O$88))} -> 58232.799 | P17: =SUM(D17:O17) -> 698793.58 | Q17: =P34 -> 699318.72 | R17: {=FAVVAR(P17,Q17,TRUE)} -> 525.135 | S17: {=SAFEDIV(R17,ABS(Q17))} -> 0.0007509237 | T17: =P51 -> 678950.25 | U17: {=SAFEDIV(P17-T17,ABS(T17))} -> 0.029226493 | W17: =SUMIFS(D17:O17,$D$4:$O$4,"<="&AsOfMonth) -> 465862.39 | X17: =SUMIFS(D34:O34,$D$4:$O$4,"<="&AsOfMonth) -> 466212.48 | Y17: {=FAVVAR(W17,X17,TRUE)} -> 350.09 | Z17: {=SAFEDIV(Y17,ABS(X17))} -> 0.0007509237 | AA17: =SUMIFS(D51:O51,$D$4:$O$4,"<="&AsOfMonth) -> 452690.15 | AB17: {=SAFEDIV(W17-AA17,ABS(AA17))} -> 0.029097695
B18: Total operating expenses | D18: =SUM(D14:D17) -> 743027.41 | E18: =SUM(E14:E17) -> 737902.31 | F18: =SUM(F14:F17) -> 741260.8 | G18: =SUM(G14:G17) -> 741016.48 | H18: =SUM(H14:H17) -> 737578.94 | I18: =SUM(I14:I17) -> 735832.5 | J18: =SUM(J14:J17) -> 735863.49 | K18: =SUM(K14:K17) -> 733345.12 | ... O18: =SUM(O14:O17) -> 756138.17 | P18: =SUM(D18:O18) -> 8894560.2 | Q18: =P35 -> 8624579.5 | R18: {=FAVVAR(P18,Q18,TRUE)} -> -269980.68 | S18: {=SAFEDIV(R18,ABS(Q18))} -> -0.031303634 | T18: =P52 -> 8373378.2 | U18: {=SAFEDIV(P18-T18,ABS(T18))} -> 0.062242735 | W18: =SUMIFS(D18:O18,$D$4:$O$4,"<="&AsOfMonth) -> 5905827 | X18: =SUMIFS(D35:O35,$D$4:$O$4,"<="&AsOfMonth) -> 5727640.5 | Y18: {=FAVVAR(W18,X18,TRUE)} -> -178186.57 | Z18: {=SAFEDIV(Y18,ABS(X18))} -> -0.031109943 | AA18: =SUMIFS(D52:O52,$D$4:$O$4,"<="&AsOfMonth) -> 5556638.9 | AB18: {=SAFEDIV(W18-AA18,ABS(AA18))} -> 0.062841622
B19: EBITDA | D19: =D13-D18 -> 98640.12 | E19: =E13-E18 -> 109888.29 | F19: =F13-F18 -> 162123.04 | G19: =G13-G18 -> 195695.62 | H19: =H13-H18 -> 225140.47 | I19: =I13-I18 -> 258604.11 | J19: =J13-J18 -> 250500.77 | K19: =K13-K18 -> 225358.11 | ... O19: =O13-O18 -> 272650.71 | P19: =SUM(D19:O19) -> 2319179.9 | Q19: =P36 -> 2731657 | R19: {=FAVVAR(P19,Q19,FALSE)} -> -412477.17 | S19: {=SAFEDIV(R19,ABS(Q19))} -> -0.15099889 | T19: =P53 -> 1919310.6 | U19: {=SAFEDIV(P19-T19,ABS(T19))} -> 0.20834002 | W19: =SUMIFS(D19:O19,$D$4:$O$4,"<="&AsOfMonth) -> 1525950.5 | X19: =SUMIFS(D36:O36,$D$4:$O$4,"<="&AsOfMonth) -> 1757686.4 | Y19: {=FAVVAR(W19,X19,FALSE)} -> -231735.84 | Z19: {=SAFEDIV(Y19,ABS(X19))} -> -0.1318414 | AA19: =SUMIFS(D53:O53,$D$4:$O$4,"<="&AsOfMonth) -> 1225776.7 | AB19: {=SAFEDIV(W19-AA19,ABS(AA19))} -> 0.24488462
B20: EBITDA margin % | D20: {=SAFEDIV(D19,D8)} -> 0.029078045 | E20: {=SAFEDIV(E19,E8)} -> 0.031541348 | F20: {=SAFEDIV(F19,F8)} -> 0.043550917 | G20: {=SAFEDIV(G19,G8)} -> 0.050204687 | H20: {=SAFEDIV(H19,H8)} -> 0.053748691 | I20: {=SAFEDIV(I19,I8)} -> 0.059533107 | J20: {=SAFEDIV(J19,J8)} -> 0.058071169 | K20: {=SAFEDIV(K19,K8)} -> 0.053777687 | ... P20: {=SAFEDIV(P19,P8)} -> 0.048920272 | Q20: =P37 -> 0.059683822 | R20: =P20-Q20 -> -0.01076355 | T20: =P54 -> 0.044852984 | U20: =P20-T20 -> 0.0040672877 | W20: {=SAFEDIV(W19,W8)} -> 0.048391209 | X20: {=SAFEDIV(X19,X8)} -> 0.057774196 | Y20: =W20-X20 -> -0.0093829868 | AA20: {=SAFEDIV(AA19,AA8)} -> 0.043091614 | AB20: =W20-AA20 -> 0.0052995953
B23: Budget
B24: Cases sold | D24: =SUMIFS(tbl_Budget[units],tbl_Budget[month],D$4) -> 24262 | E24: =SUMIFS(tbl_Budget[units],tbl_Budget[month],E$4) -> 23600 | F24: =SUMIFS(tbl_Budget[units],tbl_Budget[month],F$4) -> 24954 | G24: =SUMIFS(tbl_Budget[units],tbl_Budget[month],G$4) -> 26010 | H24: =SUMIFS(tbl_Budget[units],tbl_Budget[month],H$4) -> 27666 | I24: =SUMIFS(tbl_Budget[units],tbl_Budget[month],I$4) -> 28362 | J24: =SUMIFS(tbl_Budget[units],tbl_Budget[month],J$4) -> 28149 | K24: =SUMIFS(tbl_Budget[units],tbl_Budget[month],K$4) -> 27529 | ... O24: =SUMIFS(tbl_Budget[units],tbl_Budget[month],O$4) -> 28921 | P24: =SUM(D24:O24) -> 317860
B25: Revenue | D25: =SUMIFS(tbl_Budget[revenue],tbl_Budget[month],D$4) -> 3439390.9 | E25: =SUMIFS(tbl_Budget[revenue],tbl_Budget[month],E$4) -> 3351624.8 | F25: =SUMIFS(tbl_Budget[revenue],tbl_Budget[month],F$4) -> 3562620.3 | G25: =SUMIFS(tbl_Budget[revenue],tbl_Budget[month],G$4) -> 3745449.1 | H25: =SUMIFS(tbl_Budget[revenue],tbl_Budget[month],H$4) -> 4031810.3 | I25: =SUMIFS(tbl_Budget[revenue],tbl_Budget[month],I$4) -> 4156915.1 | J25: =SUMIFS(tbl_Budget[revenue],tbl_Budget[month],J$4) -> 4127204 | K25: =SUMIFS(tbl_Budget[revenue],tbl_Budget[month],K$4) -> 4008366.5 | ... O25: =SUMIFS(tbl_Budget[revenue],tbl_Budget[month],O$4) -> 4109293.5 | P25: =SUM(D25:O25) -> 45768802
B26: Cost of goods sold | D26: =SUMIFS(tbl_Budget[cogs],tbl_Budget[month],D$4) -> 2503134.3 | E26: =SUMIFS(tbl_Budget[cogs],tbl_Budget[month],E$4) -> 2443090.8 | F26: =SUMIFS(tbl_Budget[cogs],tbl_Budget[month],F$4) -> 2599302.9 | G26: =SUMIFS(tbl_Budget[cogs],tbl_Budget[month],G$4) -> 2736112.9 | H26: =SUMIFS(tbl_Budget[cogs],tbl_Budget[month],H$4) -> 2954930.4 | I26: =SUMIFS(tbl_Budget[cogs],tbl_Budget[month],I$4) -> 3051338.8 | J26: =SUMIFS(tbl_Budget[cogs],tbl_Budget[month],J$4) -> 3028927.3 | K26: =SUMIFS(tbl_Budget[cogs],tbl_Budget[month],K$4) -> 2936796.6 | ... O26: =SUMIFS(tbl_Budget[cogs],tbl_Budget[month],O$4) -> 2966215.7 | P26: =SUM(D26:O26) -> 33378999
B27: Gross margin | D27: =D25-D26 -> 936256.58 | E27: =E25-E26 -> 908534.03 | F27: =F25-F26 -> 963317.45 | G27: =G25-G26 -> 1009336.2 | H27: =H25-H26 -> 1076879.9 | I27: =I25-I26 -> 1105576.3 | J27: =J25-J26 -> 1098276.7 | K27: =K25-K26 -> 1071569.9 | ... O27: =O25-O26 -> 1143077.9 | P27: =SUM(D27:O27) -> 12389803
B28: Gross margin % | D28: {=SAFEDIV(D27,D25)} -> 0.27221581 | E28: {=SAFEDIV(E27,E25)} -> 0.27107271 | F28: {=SAFEDIV(F27,F25)} -> 0.27039577 | G28: {=SAFEDIV(G27,G25)} -> 0.26948336 | H28: {=SAFEDIV(H27,H25)} -> 0.26709588 | I28: {=SAFEDIV(I27,I25)} -> 0.26596076 | J28: {=SAFEDIV(J27,J25)} -> 0.26610671 | K28: {=SAFEDIV(K27,K25)} -> 0.26733332 | ... P28: {=SAFEDIV(P27,P25)} -> 0.27070412
B29: Freight | D29: =SUMIFS(tbl_Budget[freight],tbl_Budget[month],D$4) -> 78834.06 | E29: =SUMIFS(tbl_Budget[freight],tbl_Budget[month],E$4) -> 76807.77 | F29: =SUMIFS(tbl_Budget[freight],tbl_Budget[month],F$4) -> 81067.93 | G29: =SUMIFS(tbl_Budget[freight],tbl_Budget[month],G$4) -> 84532.07 | H29: =SUMIFS(tbl_Budget[freight],tbl_Budget[month],H$4) -> 89908.89 | I29: =SUMIFS(tbl_Budget[freight],tbl_Budget[month],I$4) -> 92378.86 | J29: =SUMIFS(tbl_Budget[freight],tbl_Budget[month],J$4) -> 91557.37 | K29: =SUMIFS(tbl_Budget[freight],tbl_Budget[month],K$4) -> 89333.3 | ... O29: =SUMIFS(tbl_Budget[freight],tbl_Budget[month],O$4) -> 94053.98 | P29: =SUM(D29:O29) -> 1033566.9
B30: Contribution | D30: =D27-D29 -> 857422.52 | E30: =E27-E29 -> 831726.26 | F30: =F27-F29 -> 882249.52 | G30: =G27-G29 -> 924804.13 | H30: =H27-H29 -> 986971.06 | I30: =I27-I29 -> 1013197.5 | J30: =J27-J29 -> 1006719.3 | K30: =K27-K29 -> 982236.6 | ... O30: =O27-O29 -> 1049023.9 | P30: =SUM(D30:O30) -> 11356237
B31: Sales & Marketing | D31: =SUMIFS(tbl_Opex[amount],tbl_Opex[month],D$4,tbl_Opex[dept],TRIM($B31),tbl_Opex[scenario],"Budget") -> 201621.39 | E31: =SUMIFS(tbl_Opex[amount],tbl_Opex[month],E$4,tbl_Opex[dept],TRIM($B31),tbl_Opex[scenario],"Budget") -> 201621.39 | F31: =SUMIFS(tbl_Opex[amount],tbl_Opex[month],F$4,tbl_Opex[dept],TRIM($B31),tbl_Opex[scenario],"Budget") -> 201621.39 | G31: =SUMIFS(tbl_Opex[amount],tbl_Opex[month],G$4,tbl_Opex[dept],TRIM($B31),tbl_Opex[scenario],"Budget") -> 201621.39 | H31: =SUMIFS(tbl_Opex[amount],tbl_Opex[month],H$4,tbl_Opex[dept],TRIM($B31),tbl_Opex[scenario],"Budget") -> 201621.39 | I31: =SUMIFS(tbl_Opex[amount],tbl_Opex[month],I$4,tbl_Opex[dept],TRIM($B31),tbl_Opex[scenario],"Budget") -> 201621.39 | J31: =SUMIFS(tbl_Opex[amount],tbl_Opex[month],J$4,tbl_Opex[dept],TRIM($B31),tbl_Opex[scenario],"Budget") -> 201621.39 | K31: =SUMIFS(tbl_Opex[amount],tbl_Opex[month],K$4,tbl_Opex[dept],TRIM($B31),tbl_Opex[scenario],"Budget") -> 201621.39 | ... O31: =SUMIFS(tbl_Opex[amount],tbl_Opex[month],O$4,tbl_Opex[dept],TRIM($B31),tbl_Opex[scenario],"Budget") -> 201621.39 | P31: =SUM(D31:O31) -> 2419456.7
B32: Warehouse & Logistics | D32: =SUMIFS(tbl_Opex[amount],tbl_Opex[month],D$4,tbl_Opex[dept],TRIM($B32),tbl_Opex[scenario],"Budget") -> 275989.67 | E32: =SUMIFS(tbl_Opex[amount],tbl_Opex[month],E$4,tbl_Opex[dept],TRIM($B32),tbl_Opex[scenario],"Budget") -> 275989.67 | F32: =SUMIFS(tbl_Opex[amount],tbl_Opex[month],F$4,tbl_Opex[dept],TRIM($B32),tbl_Opex[scenario],"Budget") -> 275989.67 | G32: =SUMIFS(tbl_Opex[amount],tbl_Opex[month],G$4,tbl_Opex[dept],TRIM($B32),tbl_Opex[scenario],"Budget") -> 275989.67 | H32: =SUMIFS(tbl_Opex[amount],tbl_Opex[month],H$4,tbl_Opex[dept],TRIM($B32),tbl_Opex[scenario],"Budget") -> 275989.67 | I32: =SUMIFS(tbl_Opex[amount],tbl_Opex[month],I$4,tbl_Opex[dept],TRIM($B32),tbl_Opex[scenario],"Budget") -> 275989.67 | J32: =SUMIFS(tbl_Opex[amount],tbl_Opex[month],J$4,tbl_Opex[dept],TRIM($B32),tbl_Opex[scenario],"Budget") -> 275989.67 | K32: =SUMIFS(tbl_Opex[amount],tbl_Opex[month],K$4,tbl_Opex[dept],TRIM($B32),tbl_Opex[scenario],"Budget") -> 275989.67 | ... O32: =SUMIFS(tbl_Opex[amount],tbl_Opex[month],O$4,tbl_Opex[dept],TRIM($B32),tbl_Opex[scenario],"Budget") -> 292549.05 | P32: =SUM(D32:O32) -> 3344994.8
B33: General & Admin | D33: =SUMIFS(tbl_Opex[amount],tbl_Opex[month],D$4,tbl_Opex[dept],TRIM($B33),tbl_Opex[scenario],"Budget") -> 180067.44 | E33: =SUMIFS(tbl_Opex[amount],tbl_Opex[month],E$4,tbl_Opex[dept],TRIM($B33),tbl_Opex[scenario],"Budget") -> 180067.44 | F33: =SUMIFS(tbl_Opex[amount],tbl_Opex[month],F$4,tbl_Opex[dept],TRIM($B33),tbl_Opex[scenario],"Budget") -> 180067.44 | G33: =SUMIFS(tbl_Opex[amount],tbl_Opex[month],G$4,tbl_Opex[dept],TRIM($B33),tbl_Opex[scenario],"Budget") -> 180067.44 | H33: =SUMIFS(tbl_Opex[amount],tbl_Opex[month],H$4,tbl_Opex[dept],TRIM($B33),tbl_Opex[scenario],"Budget") -> 180067.44 | I33: =SUMIFS(tbl_Opex[amount],tbl_Opex[month],I$4,tbl_Opex[dept],TRIM($B33),tbl_Opex[scenario],"Budget") -> 180067.44 | J33: =SUMIFS(tbl_Opex[amount],tbl_Opex[month],J$4,tbl_Opex[dept],TRIM($B33),tbl_Opex[scenario],"Budget") -> 180067.44 | K33: =SUMIFS(tbl_Opex[amount],tbl_Opex[month],K$4,tbl_Opex[dept],TRIM($B33),tbl_Opex[scenario],"Budget") -> 180067.44 | ... O33: =SUMIFS(tbl_Opex[amount],tbl_Opex[month],O$4,tbl_Opex[dept],TRIM($B33),tbl_Opex[scenario],"Budget") -> 180067.44 | P33: =SUM(D33:O33) -> 2160809.3
B34: Technology | D34: =SUMIFS(tbl_Opex[amount],tbl_Opex[month],D$4,tbl_Opex[dept],TRIM($B34),tbl_Opex[scenario],"Budget") -> 58276.56 | E34: =SUMIFS(tbl_Opex[amount],tbl_Opex[month],E$4,tbl_Opex[dept],TRIM($B34),tbl_Opex[scenario],"Budget") -> 58276.56 | F34: =SUMIFS(tbl_Opex[amount],tbl_Opex[month],F$4,tbl_Opex[dept],TRIM($B34),tbl_Opex[scenario],"Budget") -> 58276.56 | G34: =SUMIFS(tbl_Opex[amount],tbl_Opex[month],G$4,tbl_Opex[dept],TRIM($B34),tbl_Opex[scenario],"Budget") -> 58276.56 | H34: =SUMIFS(tbl_Opex[amount],tbl_Opex[month],H$4,tbl_Opex[dept],TRIM($B34),tbl_Opex[scenario],"Budget") -> 58276.56 | I34: =SUMIFS(tbl_Opex[amount],tbl_Opex[month],I$4,tbl_Opex[dept],TRIM($B34),tbl_Opex[scenario],"Budget") -> 58276.56 | J34: =SUMIFS(tbl_Opex[amount],tbl_Opex[month],J$4,tbl_Opex[dept],TRIM($B34),tbl_Opex[scenario],"Budget") -> 58276.56 | K34: =SUMIFS(tbl_Opex[amount],tbl_Opex[month],K$4,tbl_Opex[dept],TRIM($B34),tbl_Opex[scenario],"Budget") -> 58276.56 | ... O34: =SUMIFS(tbl_Opex[amount],tbl_Opex[month],O$4,tbl_Opex[dept],TRIM($B34),tbl_Opex[scenario],"Budget") -> 58276.56 | P34: =SUM(D34:O34) -> 699318.72
B35: Total operating expenses | D35: =SUM(D31:D34) -> 715955.06 | E35: =SUM(E31:E34) -> 715955.06 | F35: =SUM(F31:F34) -> 715955.06 | G35: =SUM(G31:G34) -> 715955.06 | H35: =SUM(H31:H34) -> 715955.06 | I35: =SUM(I31:I34) -> 715955.06 | J35: =SUM(J31:J34) -> 715955.06 | K35: =SUM(K31:K34) -> 715955.06 | ... O35: =SUM(O31:O34) -> 732514.44 | P35: =SUM(D35:O35) -> 8624579.5
B36: EBITDA | D36: =D30-D35 -> 141467.46 | E36: =E30-E35 -> 115771.2 | F36: =F30-F35 -> 166294.46 | G36: =G30-G35 -> 208849.07 | H36: =H30-H35 -> 271016 | I36: =I30-I35 -> 297242.4 | J36: =J30-J35 -> 290764.24 | K36: =K30-K35 -> 266281.54 | ... O36: =O30-O35 -> 316509.43 | P36: =SUM(D36:O36) -> 2731657
B37: EBITDA margin % | D37: {=SAFEDIV(D36,D25)} -> 0.041131545 | E37: {=SAFEDIV(E36,E25)} -> 0.034541814 | F37: {=SAFEDIV(F36,F25)} -> 0.04667757 | G37: {=SAFEDIV(G36,G25)} -> 0.055760755 | H37: {=SAFEDIV(H36,H25)} -> 0.067219432 | I37: {=SAFEDIV(I36,I25)} -> 0.071505525 | J37: {=SAFEDIV(J36,J25)} -> 0.070450658 | K37: {=SAFEDIV(K36,K25)} -> 0.066431436 | ... P37: {=SAFEDIV(P36,P25)} -> 0.059683822
B40: Prior year (actuals)
B41: Cases sold | D41: =SUMIFS(tbl_Sales[units],tbl_Sales[month],EDATE(D$4,-12)) -> 23609 | E41: =SUMIFS(tbl_Sales[units],tbl_Sales[month],EDATE(E$4,-12)) -> 22956 | F41: =SUMIFS(tbl_Sales[units],tbl_Sales[month],EDATE(F$4,-12)) -> 24276 | G41: =SUMIFS(tbl_Sales[units],tbl_Sales[month],EDATE(G$4,-12)) -> 25301 | H41: =SUMIFS(tbl_Sales[units],tbl_Sales[month],EDATE(H$4,-12)) -> 26908 | I41: =SUMIFS(tbl_Sales[units],tbl_Sales[month],EDATE(I$4,-12)) -> 27577 | J41: =SUMIFS(tbl_Sales[units],tbl_Sales[month],EDATE(J$4,-12)) -> 27379 | K41: =SUMIFS(tbl_Sales[units],tbl_Sales[month],EDATE(K$4,-12)) -> 26778 | ... O41: =SUMIFS(tbl_Sales[units],tbl_Sales[month],EDATE(O$4,-12)) -> 28110 | P41: =SUM(D41:O41) -> 309144
B42: Revenue | D42: =SUMIFS(tbl_Sales[net_revenue],tbl_Sales[month],EDATE(D$4,-12)) -> 3218241.6 | E42: =SUMIFS(tbl_Sales[net_revenue],tbl_Sales[month],EDATE(E$4,-12)) -> 3130900.3 | F42: =SUMIFS(tbl_Sales[net_revenue],tbl_Sales[month],EDATE(F$4,-12)) -> 3334202.5 | G42: =SUMIFS(tbl_Sales[net_revenue],tbl_Sales[month],EDATE(G$4,-12)) -> 3503499.3 | H42: =SUMIFS(tbl_Sales[net_revenue],tbl_Sales[month],EDATE(H$4,-12)) -> 3770601.9 | I42: =SUMIFS(tbl_Sales[net_revenue],tbl_Sales[month],EDATE(I$4,-12)) -> 3886478.4 | J42: =SUMIFS(tbl_Sales[net_revenue],tbl_Sales[month],EDATE(J$4,-12)) -> 3854332.6 | K42: =SUMIFS(tbl_Sales[net_revenue],tbl_Sales[month],EDATE(K$4,-12)) -> 3747572.4 | ... O42: =SUMIFS(tbl_Sales[net_revenue],tbl_Sales[month],EDATE(O$4,-12)) -> 3837508.8 | P42: =SUM(D42:O42) -> 42791147
B43: Cost of goods sold | D43: =SUMIFS(tbl_Sales[cogs],tbl_Sales[month],EDATE(D$4,-12)) -> 2364516.3 | E43: =SUMIFS(tbl_Sales[cogs],tbl_Sales[month],EDATE(E$4,-12)) -> 2306988 | F43: =SUMIFS(tbl_Sales[cogs],tbl_Sales[month],EDATE(F$4,-12)) -> 2454814.8 | G43: =SUMIFS(tbl_Sales[cogs],tbl_Sales[month],EDATE(G$4,-12)) -> 2583957.8 | H43: =SUMIFS(tbl_Sales[cogs],tbl_Sales[month],EDATE(H$4,-12)) -> 2789435.4 | I43: =SUMIFS(tbl_Sales[cogs],tbl_Sales[month],EDATE(I$4,-12)) -> 2878998.2 | J43: =SUMIFS(tbl_Sales[cogs],tbl_Sales[month],EDATE(J$4,-12)) -> 2859812.6 | K43: =SUMIFS(tbl_Sales[cogs],tbl_Sales[month],EDATE(K$4,-12)) -> 2771600.2 | ... O43: =SUMIFS(tbl_Sales[cogs],tbl_Sales[month],EDATE(O$4,-12)) -> 2797934.9 | P43: =SUM(D43:O43) -> 31512171
B44: Gross margin | D44: =D42-D43 -> 853725.32 | E44: =E42-E43 -> 823912.31 | F44: =F42-F43 -> 879387.74 | G44: =G42-G43 -> 919541.52 | H44: =H42-H43 -> 981166.46 | I44: =I42-I43 -> 1007480.2 | J44: =J42-J43 -> 994520 | K44: =K42-K43 -> 975972.23 | ... O44: =O42-O43 -> 1039574 | P44: =SUM(D44:O44) -> 11278976
B45: Gross margin % | D45: {=SAFEDIV(D44,D42)} -> 0.26527695 | E45: {=SAFEDIV(E44,E42)} -> 0.26315508 | F45: {=SAFEDIV(F44,F42)} -> 0.26374755 | G45: {=SAFEDIV(G44,G42)} -> 0.26246374 | H45: {=SAFEDIV(H44,H42)} -> 0.26021481 | I45: {=SAFEDIV(I44,I42)} -> 0.25922702 | J45: {=SAFEDIV(J44,J42)} -> 0.25802651 | K45: {=SAFEDIV(K44,K42)} -> 0.26042785 | ... P45: {=SAFEDIV(P44,P42)} -> 0.263582
B46: Freight | D46: =SUMIFS(tbl_Sales[freight],tbl_Sales[month],EDATE(D$4,-12)) -> 75265.37 | E46: =SUMIFS(tbl_Sales[freight],tbl_Sales[month],EDATE(E$4,-12)) -> 73396.06 | F46: =SUMIFS(tbl_Sales[freight],tbl_Sales[month],EDATE(F$4,-12)) -> 77418.8 | G46: =SUMIFS(tbl_Sales[freight],tbl_Sales[month],EDATE(G$4,-12)) -> 80646.62 | H46: =SUMIFS(tbl_Sales[freight],tbl_Sales[month],EDATE(H$4,-12)) -> 85761.61 | I46: =SUMIFS(tbl_Sales[freight],tbl_Sales[month],EDATE(I$4,-12)) -> 88220.82 | J46: =SUMIFS(tbl_Sales[freight],tbl_Sales[month],EDATE(J$4,-12)) -> 87389.92 | K46: =SUMIFS(tbl_Sales[freight],tbl_Sales[month],EDATE(K$4,-12)) -> 85191.06 | ... O46: =SUMIFS(tbl_Sales[freight],tbl_Sales[month],EDATE(O$4,-12)) -> 89639.29 | P46: =SUM(D46:O46) -> 986287.3
B47: Contribution | D47: =D44-D46 -> 778459.95 | E47: =E44-E46 -> 750516.25 | F47: =F44-F46 -> 801968.94 | G47: =G44-G46 -> 838894.9 | H47: =H44-H46 -> 895404.85 | I47: =I44-I46 -> 919259.38 | J47: =J44-J46 -> 907130.08 | K47: =K44-K46 -> 890781.17 | ... O47: =O44-O46 -> 949934.68 | P47: =SUM(D47:O47) -> 10292689
B48: Sales & Marketing | D48: =SUMIFS(tbl_Opex[amount],tbl_Opex[month],EDATE(D$4,-12),tbl_Opex[dept],TRIM($B48),tbl_Opex[scenario],"Actual") -> 193938.7 | E48: =SUMIFS(tbl_Opex[amount],tbl_Opex[month],EDATE(E$4,-12),tbl_Opex[dept],TRIM($B48),tbl_Opex[scenario],"Actual") -> 198048.4 | F48: =SUMIFS(tbl_Opex[amount],tbl_Opex[month],EDATE(F$4,-12),tbl_Opex[dept],TRIM($B48),tbl_Opex[scenario],"Actual") -> 198439.8 | G48: =SUMIFS(tbl_Opex[amount],tbl_Opex[month],EDATE(G$4,-12),tbl_Opex[dept],TRIM($B48),tbl_Opex[scenario],"Actual") -> 195700 | H48: =SUMIFS(tbl_Opex[amount],tbl_Opex[month],EDATE(H$4,-12),tbl_Opex[dept],TRIM($B48),tbl_Opex[scenario],"Actual") -> 198244.1 | I48: =SUMIFS(tbl_Opex[amount],tbl_Opex[month],EDATE(I$4,-12),tbl_Opex[dept],TRIM($B48),tbl_Opex[scenario],"Actual") -> 193351.6 | J48: =SUMIFS(tbl_Opex[amount],tbl_Opex[month],EDATE(J$4,-12),tbl_Opex[dept],TRIM($B48),tbl_Opex[scenario],"Actual") -> 193938.7 | K48: =SUMIFS(tbl_Opex[amount],tbl_Opex[month],EDATE(K$4,-12),tbl_Opex[dept],TRIM($B48),tbl_Opex[scenario],"Actual") -> 193743 | ... O48: =SUMIFS(tbl_Opex[amount],tbl_Opex[month],EDATE(O$4,-12),tbl_Opex[dept],TRIM($B48),tbl_Opex[scenario],"Actual") -> 196091.4 | P48: =SUM(D48:O48) -> 2348987.1
B49: Warehouse & Logistics | D49: =SUMIFS(tbl_Opex[amount],tbl_Opex[month],EDATE(D$4,-12),tbl_Opex[dept],TRIM($B49),tbl_Opex[scenario],"Actual") -> 266728.8 | E49: =SUMIFS(tbl_Opex[amount],tbl_Opex[month],EDATE(E$4,-12),tbl_Opex[dept],TRIM($B49),tbl_Opex[scenario],"Actual") -> 271013.6 | F49: =SUMIFS(tbl_Opex[amount],tbl_Opex[month],EDATE(F$4,-12),tbl_Opex[dept],TRIM($B49),tbl_Opex[scenario],"Actual") -> 264050.8 | G49: =SUMIFS(tbl_Opex[amount],tbl_Opex[month],EDATE(G$4,-12),tbl_Opex[dept],TRIM($B49),tbl_Opex[scenario],"Actual") -> 269674.6 | H49: =SUMIFS(tbl_Opex[amount],tbl_Opex[month],EDATE(H$4,-12),tbl_Opex[dept],TRIM($B49),tbl_Opex[scenario],"Actual") -> 268067.8 | I49: =SUMIFS(tbl_Opex[amount],tbl_Opex[month],EDATE(I$4,-12),tbl_Opex[dept],TRIM($B49),tbl_Opex[scenario],"Actual") -> 263783 | J49: =SUMIFS(tbl_Opex[amount],tbl_Opex[month],EDATE(J$4,-12),tbl_Opex[dept],TRIM($B49),tbl_Opex[scenario],"Actual") -> 270478 | K49: =SUMIFS(tbl_Opex[amount],tbl_Opex[month],EDATE(K$4,-12),tbl_Opex[dept],TRIM($B49),tbl_Opex[scenario],"Actual") -> 267800 | ... O49: =SUMIFS(tbl_Opex[amount],tbl_Opex[month],EDATE(O$4,-12),tbl_Opex[dept],TRIM($B49),tbl_Opex[scenario],"Actual") -> 286422.81 | P49: =SUM(D49:O49) -> 3247567.7
B50: General & Admin | D50: =SUMIFS(tbl_Opex[amount],tbl_Opex[month],EDATE(D$4,-12),tbl_Opex[dept],TRIM($B50),tbl_Opex[scenario],"Actual") -> 172648.6 | E50: =SUMIFS(tbl_Opex[amount],tbl_Opex[month],EDATE(E$4,-12),tbl_Opex[dept],TRIM($B50),tbl_Opex[scenario],"Actual") -> 173173.9 | F50: =SUMIFS(tbl_Opex[amount],tbl_Opex[month],EDATE(F$4,-12),tbl_Opex[dept],TRIM($B50),tbl_Opex[scenario],"Actual") -> 174224.5 | G50: =SUMIFS(tbl_Opex[amount],tbl_Opex[month],EDATE(G$4,-12),tbl_Opex[dept],TRIM($B50),tbl_Opex[scenario],"Actual") -> 176675.9 | H50: =SUMIFS(tbl_Opex[amount],tbl_Opex[month],EDATE(H$4,-12),tbl_Opex[dept],TRIM($B50),tbl_Opex[scenario],"Actual") -> 176325.7 | I50: =SUMIFS(tbl_Opex[amount],tbl_Opex[month],EDATE(I$4,-12),tbl_Opex[dept],TRIM($B50),tbl_Opex[scenario],"Actual") -> 177376.3 | J50: =SUMIFS(tbl_Opex[amount],tbl_Opex[month],EDATE(J$4,-12),tbl_Opex[dept],TRIM($B50),tbl_Opex[scenario],"Actual") -> 173874.3 | K50: =SUMIFS(tbl_Opex[amount],tbl_Opex[month],EDATE(K$4,-12),tbl_Opex[dept],TRIM($B50),tbl_Opex[scenario],"Actual") -> 172648.6 | ... O50: =SUMIFS(tbl_Opex[amount],tbl_Opex[month],EDATE(O$4,-12),tbl_Opex[dept],TRIM($B50),tbl_Opex[scenario],"Actual") -> 175975.5 | P50: =SUM(D50:O50) -> 2097873.1
B51: Technology | D51: =SUMIFS(tbl_Opex[amount],tbl_Opex[month],EDATE(D$4,-12),tbl_Opex[dept],TRIM($B51),tbl_Opex[scenario],"Actual") -> 56026.85 | E51: =SUMIFS(tbl_Opex[amount],tbl_Opex[month],EDATE(E$4,-12),tbl_Opex[dept],TRIM($B51),tbl_Opex[scenario],"Actual") -> 56933.25 | F51: =SUMIFS(tbl_Opex[amount],tbl_Opex[month],EDATE(F$4,-12),tbl_Opex[dept],TRIM($B51),tbl_Opex[scenario],"Actual") -> 57443.1 | G51: =SUMIFS(tbl_Opex[amount],tbl_Opex[month],EDATE(G$4,-12),tbl_Opex[dept],TRIM($B51),tbl_Opex[scenario],"Actual") -> 56140.15 | H51: =SUMIFS(tbl_Opex[amount],tbl_Opex[month],EDATE(H$4,-12),tbl_Opex[dept],TRIM($B51),tbl_Opex[scenario],"Actual") -> 57216.5 | I51: =SUMIFS(tbl_Opex[amount],tbl_Opex[month],EDATE(I$4,-12),tbl_Opex[dept],TRIM($B51),tbl_Opex[scenario],"Actual") -> 56366.75 | J51: =SUMIFS(tbl_Opex[amount],tbl_Opex[month],EDATE(J$4,-12),tbl_Opex[dept],TRIM($B51),tbl_Opex[scenario],"Actual") -> 56366.75 | K51: =SUMIFS(tbl_Opex[amount],tbl_Opex[month],EDATE(K$4,-12),tbl_Opex[dept],TRIM($B51),tbl_Opex[scenario],"Actual") -> 56196.8 | ... O51: =SUMIFS(tbl_Opex[amount],tbl_Opex[month],EDATE(O$4,-12),tbl_Opex[dept],TRIM($B51),tbl_Opex[scenario],"Actual") -> 55913.55 | P51: =SUM(D51:O51) -> 678950.25
B52: Total operating expenses | D52: =SUM(D48:D51) -> 689342.95 | E52: =SUM(E48:E51) -> 699169.15 | F52: =SUM(F48:F51) -> 694158.2 | G52: =SUM(G48:G51) -> 698190.65 | H52: =SUM(H48:H51) -> 699854.1 | I52: =SUM(I48:I51) -> 690877.65 | J52: =SUM(J48:J51) -> 694657.75 | K52: =SUM(K48:K51) -> 690388.4 | ... O52: =SUM(O48:O51) -> 714403.26 | P52: =SUM(D52:O52) -> 8373378.2
B53: EBITDA | D53: =D47-D52 -> 89117 | E53: =E47-E52 -> 51347.1 | F53: =F47-F52 -> 107810.74 | G53: =G47-G52 -> 140704.25 | H53: =H47-H52 -> 195550.75 | I53: =I47-I52 -> 228381.73 | J53: =J47-J52 -> 212472.33 | K53: =K47-K52 -> 200392.77 | ... O53: =O47-O52 -> 235531.42 | P53: =SUM(D53:O53) -> 1919310.6
B54: EBITDA margin % | D54: {=SAFEDIV(D53,D42)} -> 0.027691209 | E54: {=SAFEDIV(E53,E42)} -> 0.016400107 | F54: {=SAFEDIV(F53,F42)} -> 0.032334791 | G54: {=SAFEDIV(G53,G42)} -> 0.040161061 | H54: {=SAFEDIV(H53,H42)} -> 0.051861945 | I54: {=SAFEDIV(I53,I42)} -> 0.058763155 | J54: {=SAFEDIV(J53,J42)} -> 0.055125582 | K54: {=SAFEDIV(K53,K42)} -> 0.053472688 | ... P54: {=SAFEDIV(P53,P42)} -> 0.044852984
B57: Variance: outlook against budget, favourable = positive
B58: Cases sold | D58: =D7-D24 -> -460 | E58: =E7-E24 -> 933 | F58: =F7-F24 -> 1080 | G58: =G7-G24 -> 1089 | H58: =H7-H24 -> 1025 | I58: =I7-I24 -> 1235 | J58: =J7-J24 -> 1284 | K58: =K7-K24 -> 1286 | ... O58: =O7-O24 -> 1010.5988 | P58: =SUM(D58:O58) -> 11232.521
B59: Revenue | D59: {=FAVVAR(D8,D25,FALSE)} -> -47136.68 | E59: {=FAVVAR(E8,E25,FALSE)} -> 132319.16 | F59: {=FAVVAR(F8,F25,FALSE)} -> 159988.83 | G59: {=FAVVAR(G8,G25,FALSE)} -> 152506.09 | H59: {=FAVVAR(H8,H25,FALSE)} -> 156951.58 | I59: {=FAVVAR(I8,I25,FALSE)} -> 186955.42 | J59: {=FAVVAR(J8,J25,FALSE)} -> 186481.69 | K59: {=FAVVAR(K8,K25,FALSE)} -> 182183.98 | ... O59: {=FAVVAR(O8,O25,FALSE)} -> 139505.54 | P59: =SUM(D59:O59) -> 1638536.2
B60: Cost of goods sold | D60: {=FAVVAR(D9,D26,TRUE)} -> 32175.99 | E60: {=FAVVAR(E9,E26,TRUE)} -> -112250.15 | F60: {=FAVVAR(F9,F26,TRUE)} -> -134061.26 | G60: {=FAVVAR(G9,G26,TRUE)} -> -135591.44 | H60: {=FAVVAR(H9,H26,TRUE)} -> -175994.29 | I60: {=FAVVAR(I9,I26,TRUE)} -> -200531.95 | J60: {=FAVVAR(J9,J26,TRUE)} -> -201168.39 | K60: {=FAVVAR(K9,K26,TRUE)} -> -200107.8 | ... O60: {=FAVVAR(O9,O26,TRUE)} -> -155062.65 | P60: =SUM(D60:O60) -> -1727483.4
B61: Gross margin | D61: {=FAVVAR(D10,D27,FALSE)} -> -14960.69 | E61: {=FAVVAR(E10,E27,FALSE)} -> 20069.01 | F61: {=FAVVAR(F10,F27,FALSE)} -> 25927.57 | G61: {=FAVVAR(G10,G27,FALSE)} -> 16914.65 | H61: {=FAVVAR(H10,H27,FALSE)} -> -19042.71 | I61: {=FAVVAR(I10,I27,FALSE)} -> -13576.53 | J61: {=FAVVAR(J10,J27,FALSE)} -> -14686.7 | K61: {=FAVVAR(K10,K27,FALSE)} -> -17923.82 | ... O61: {=FAVVAR(O10,O27,FALSE)} -> -15557.109 | P61: =SUM(D61:O61) -> -88947.21
B62: Gross margin % | D62: =D11-D28 -> -0.00062770662 | E62: =E11-E28 -> -0.0045348328 | F62: =F11-F28 -> -0.004656071 | G62: =G11-G28 -> -0.0062040741 | H62: =H11-H28 -> -0.014554141 | I62: =I11-I28 -> -0.014572105 | J62: =J11-J28 -> -0.014908534 | K62: =K11-K28 -> -0.015899502 | ... P62: =P11-P28 -> -0.011232559
B63: Freight | D63: {=FAVVAR(D12,D29,TRUE)} -> -794.3 | E63: {=FAVVAR(E12,E29,TRUE)} -> -4004.67 | F63: {=FAVVAR(F12,F29,TRUE)} -> -4793.25 | G63: {=FAVVAR(G12,G29,TRUE)} -> -5006.68 | H63: {=FAVVAR(H12,H29,TRUE)} -> -5208.94 | I63: {=FAVVAR(I12,I29,TRUE)} -> -5184.32 | J63: {=FAVVAR(J12,J29,TRUE)} -> -5668.34 | K63: {=FAVVAR(K12,K29,TRUE)} -> -5609.55 | ... O63: {=FAVVAR(O12,O29,TRUE)} -> -4677.879 | P63: =SUM(D63:O63) -> -53549.279
B64: Contribution | D64: {=FAVVAR(D13,D30,FALSE)} -> -15754.99 | E64: {=FAVVAR(E13,E30,FALSE)} -> 16064.34 | F64: {=FAVVAR(F13,F30,FALSE)} -> 21134.32 | G64: {=FAVVAR(G13,G30,FALSE)} -> 11907.97 | H64: {=FAVVAR(H13,H30,FALSE)} -> -24251.65 | I64: {=FAVVAR(I13,I30,FALSE)} -> -18760.85 | J64: {=FAVVAR(J13,J30,FALSE)} -> -20355.04 | K64: {=FAVVAR(K13,K30,FALSE)} -> -23533.37 | ... O64: {=FAVVAR(O13,O30,FALSE)} -> -20234.988 | P64: =SUM(D64:O64) -> -142496.49
B65: Sales & Marketing | D65: {=FAVVAR(D14,D31,TRUE)} -> 1118.72 | E65: {=FAVVAR(E14,E31,TRUE)} -> 3884.27 | F65: {=FAVVAR(F14,F31,TRUE)} -> 4871.97 | G65: {=FAVVAR(G14,G31,TRUE)} -> 2106.41 | H65: {=FAVVAR(H14,H31,TRUE)} -> 1908.87 | I65: {=FAVVAR(I14,I31,TRUE)} -> 2699.03 | J65: {=FAVVAR(J14,J31,TRUE)} -> 6649.82 | K65: {=FAVVAR(K14,K31,TRUE)} -> 6649.82 | ... O65: {=FAVVAR(O14,O31,TRUE)} -> 3736.1137 | P65: =SUM(D65:O65) -> 44833.365
B66: Warehouse & Logistics | D66: {=FAVVAR(D15,D32,TRUE)} -> -24294.26 | E66: {=FAVVAR(E15,E32,TRUE)} -> -26081.66 | F66: {=FAVVAR(F15,F32,TRUE)} -> -25187.96 | G66: {=FAVVAR(G15,G32,TRUE)} -> -22506.85 | H66: {=FAVVAR(H15,H32,TRUE)} -> -19527.84 | I66: {=FAVVAR(I15,I32,TRUE)} -> -17740.44 | J66: {=FAVVAR(J15,J32,TRUE)} -> -23996.36 | K66: {=FAVVAR(K15,K32,TRUE)} -> -20719.45 | ... O66: {=FAVVAR(O15,O32,TRUE)} -> -23857.264 | P66: =SUM(D66:O66) -> -272783.05
B67: General & Admin | D67: {=FAVVAR(D16,D33,TRUE)} -> -3182.03 | E67: {=FAVVAR(E16,E33,TRUE)} -> -85.37 | F67: {=FAVVAR(F16,F33,TRUE)} -> -4274.97 | G67: {=FAVVAR(G16,G33,TRUE)} -> -4821.44 | H67: {=FAVVAR(H16,H33,TRUE)} -> -4457.12 | I67: {=FAVVAR(I16,I33,TRUE)} -> -4821.44 | J67: {=FAVVAR(J16,J33,TRUE)} -> -3364.19 | K67: {=FAVVAR(K16,K33,TRUE)} -> -3364.19 | ... O67: {=FAVVAR(O16,O33,TRUE)} -> -3546.3438 | P67: =SUM(D67:O67) -> -42556.125
B68: Technology | D68: {=FAVVAR(D17,D34,TRUE)} -> -714.78 | E68: {=FAVVAR(E17,E34,TRUE)} -> 335.51 | F68: {=FAVVAR(F17,F34,TRUE)} -> -714.78 | G68: {=FAVVAR(G17,G34,TRUE)} -> 160.46 | H68: {=FAVVAR(H17,H34,TRUE)} -> 452.21 | I68: {=FAVVAR(I17,I34,TRUE)} -> -14.59 | J68: {=FAVVAR(J17,J34,TRUE)} -> 802.3 | K68: {=FAVVAR(K17,K34,TRUE)} -> 43.76 | ... O68: {=FAVVAR(O17,O34,TRUE)} -> 43.76125 | P68: =SUM(D68:O68) -> 525.135
B69: Total operating expenses | D69: {=FAVVAR(D18,D35,TRUE)} -> -27072.35 | E69: {=FAVVAR(E18,E35,TRUE)} -> -21947.25 | F69: {=FAVVAR(F18,F35,TRUE)} -> -25305.74 | G69: {=FAVVAR(G18,G35,TRUE)} -> -25061.42 | H69: {=FAVVAR(H18,H35,TRUE)} -> -21623.88 | I69: {=FAVVAR(I18,I35,TRUE)} -> -19877.44 | J69: {=FAVVAR(J18,J35,TRUE)} -> -19908.43 | K69: {=FAVVAR(K18,K35,TRUE)} -> -17390.06 | ... O69: {=FAVVAR(O18,O35,TRUE)} -> -23623.732 | P69: =SUM(D69:O69) -> -269980.68
B70: EBITDA | D70: {=FAVVAR(D19,D36,FALSE)} -> -42827.34 | E70: {=FAVVAR(E19,E36,FALSE)} -> -5882.91 | F70: {=FAVVAR(F19,F36,FALSE)} -> -4171.42 | G70: {=FAVVAR(G19,G36,FALSE)} -> -13153.45 | H70: {=FAVVAR(H19,H36,FALSE)} -> -45875.53 | I70: {=FAVVAR(I19,I36,FALSE)} -> -38638.29 | J70: {=FAVVAR(J19,J36,FALSE)} -> -40263.47 | K70: {=FAVVAR(K19,K36,FALSE)} -> -40923.43 | ... O70: {=FAVVAR(O19,O36,FALSE)} -> -43858.72 | P70: =SUM(D70:O70) -> -412477.17
B71: EBITDA margin % | D71: =D20-D37 -> -0.0120535 | E71: =E20-E37 -> -0.0030004655 | F71: =F20-F37 -> -0.0031266538 | G71: =G20-G37 -> -0.0055560681 | H71: =H20-H37 -> -0.013470741 | I71: =I20-I37 -> -0.011972418 | J71: =J20-J37 -> -0.01237949 | K71: =K20-K37 -> -0.012653749 | ... P71: =P20-P37 -> -0.01076355

Sheet PVM
B1: Price-volume-mix: why margin moved against budget
B2: Gross-margin variance split four ways on 24 category × channel segments. Each segment's change in cases is valued at the budget's average margin per case (volume) and at its own margin's distance from that average (mix); price and cost are per-case changes on actual cases. The four effects add up to every segment's variance exactly: column V is zero.
B4: ="Month: "&TEXT(AsOfMonth,"mmmm yyyy")&" against budget" -> Month: August 2026 against budget
B5: Category | C5: Channel | D5: Budget cases | E5: Budget revenue | F5: Budget COGS | G5: Actual cases | H5: Actual revenue | I5: Actual COGS | J5: Budget price / case | K5: Actual price / case | L5: Budget cost / case | M5: Actual cost / case | N5: Budget margin / case | O5: Share shift | P5: Volume | Q5: Mix | R5: Price | S5: Unit cost | T5: Effects, total | U5: GM variance | V5: Unexplained | W5: Main driver
B6: Beef | C6: Restaurants | D6: =SUMIFS(tbl_Budget[units],tbl_Budget[category],$B6,tbl_Budget[channel],$C6,tbl_Budget[month],">="&AsOfMonth,tbl_Budget[month],"<="&AsOfMonth) -> 2959 | E6: =SUMIFS(tbl_Budget[revenue],tbl_Budget[category],$B6,tbl_Budget[channel],$C6,tbl_Budget[month],">="&AsOfMonth,tbl_Budget[month],"<="&AsOfMonth) -> 583426.31 | F6: =SUMIFS(tbl_Budget[cogs],tbl_Budget[category],$B6,tbl_Budget[channel],$C6,tbl_Budget[month],">="&AsOfMonth,tbl_Budget[month],"<="&AsOfMonth) -> 431578.03 | G6: =SUMIFS(tbl_Sales[units],tbl_Sales[category],$B6,tbl_Sales[channel],$C6,tbl_Sales[month],">="&AsOfMonth,tbl_Sales[month],"<="&AsOfMonth) -> 2931 | H6: =SUMIFS(tbl_Sales[net_revenue],tbl_Sales[category],$B6,tbl_Sales[channel],$C6,tbl_Sales[month],">="&AsOfMonth,tbl_Sales[month],"<="&AsOfMonth) -> 584467.03 | I6: =SUMIFS(tbl_Sales[cogs],tbl_Sales[category],$B6,tbl_Sales[channel],$C6,tbl_Sales[month],">="&AsOfMonth,tbl_Sales[month],"<="&AsOfMonth) -> 456580.44 | J6: {=SAFEDIV(E6,D6)} -> 197.17009 | K6: {=SAFEDIV(H6,G6)} -> 199.40874 | L6: {=SAFEDIV(F6,D6)} -> 145.85266 | M6: {=SAFEDIV(I6,G6)} -> 155.77634 | N6: =J6-L6 -> 51.317432 | O6: {=SAFEDIV(G6,G$30)-SAFEDIV(D6,D$30)} -> -0.0057687952 | P6: =(G6-D6)*N$30 -> -1089.9036 | Q6: =(G6-D6)*(N6-N$30) -> -346.98445 | R6: =G6*(K6-J6) -> 6561.4826 | S6: =-G6*(M6-L6) -> -29086.285 | T6: =SUM(P6:S6) -> -23961.69 | U6: =(H6-I6)-(E6-F6) -> -23961.69 | V6: =T6-U6 -> 0 | W6: {=INDEX({"Volume","Mix","Price","Unit cost"},_xlfn.XMATCH(MAX(ABS(P6:S6)),ABS(P6:S6)))} -> Unit cost
B7: Beef | C7: Grocery Retail | D7: =SUMIFS(tbl_Budget[units],tbl_Budget[category],$B7,tbl_Budget[channel],$C7,tbl_Budget[month],">="&AsOfMonth,tbl_Budget[month],"<="&AsOfMonth) -> 2025 | E7: =SUMIFS(tbl_Budget[revenue],tbl_Budget[category],$B7,tbl_Budget[channel],$C7,tbl_Budget[month],">="&AsOfMonth,tbl_Budget[month],"<="&AsOfMonth) -> 347499.93 | F7: =SUMIFS(tbl_Budget[cogs],tbl_Budget[category],$B7,tbl_Budget[channel],$C7,tbl_Budget[month],">="&AsOfMonth,tbl_Budget[month],"<="&AsOfMonth) -> 296251.17 | G7: =SUMIFS(tbl_Sales[units],tbl_Sales[category],$B7,tbl_Sales[channel],$C7,tbl_Sales[month],">="&AsOfMonth,tbl_Sales[month],"<="&AsOfMonth) -> 2331 | H7: =SUMIFS(tbl_Sales[net_revenue],tbl_Sales[category],$B7,tbl_Sales[channel],$C7,tbl_Sales[month],">="&AsOfMonth,tbl_Sales[month],"<="&AsOfMonth) -> 402742.6 | I7: =SUMIFS(tbl_Sales[cogs],tbl_Sales[category],$B7,tbl_Sales[channel],$C7,tbl_Sales[month],">="&AsOfMonth,tbl_Sales[month],"<="&AsOfMonth) -> 364589.83 | J7: {=SAFEDIV(E7,D7)} -> 171.6049 | K7: {=SAFEDIV(H7,G7)} -> 172.77675 | L7: {=SAFEDIV(F7,D7)} -> 146.29687 | M7: {=SAFEDIV(I7,G7)} -> 156.40919 | N7: =J7-L7 -> 25.30803 | O7: {=SAFEDIV(G7,G$30)-SAFEDIV(D7,D$30)} -> 0.0073365745 | P7: =(G7-D7)*N$30 -> 11911.09 | Q7: =(G7-D7)*(N7-N$30) -> -4166.8327 | R7: =G7*(K7-J7) -> 2731.5695 | S7: =-G7*(M7-L7) -> -23571.817 | T7: =SUM(P7:S7) -> -13095.99 | U7: =(H7-I7)-(E7-F7) -> -13095.99 | V7: =T7-U7 -> -6.184564e-11 | W7: {=INDEX({"Volume","Mix","Price","Unit cost"},_xlfn.XMATCH(MAX(ABS(P7:S7)),ABS(P7:S7)))} -> Unit cost
B8: Beef | C8: Hotels & Institutions | D8: =SUMIFS(tbl_Budget[units],tbl_Budget[category],$B8,tbl_Budget[channel],$C8,tbl_Budget[month],">="&AsOfMonth,tbl_Budget[month],"<="&AsOfMonth) -> 1240 | E8: =SUMIFS(tbl_Budget[revenue],tbl_Budget[category],$B8,tbl_Budget[channel],$C8,tbl_Budget[month],">="&AsOfMonth,tbl_Budget[month],"<="&AsOfMonth) -> 231979.01 | F8: =SUMIFS(tbl_Budget[cogs],tbl_Budget[category],$B8,tbl_Budget[channel],$C8,tbl_Budget[month],">="&AsOfMonth,tbl_Budget[month],"<="&AsOfMonth) -> 180751.94 | G8: =SUMIFS(tbl_Sales[units],tbl_Sales[category],$B8,tbl_Sales[channel],$C8,tbl_Sales[month],">="&AsOfMonth,tbl_Sales[month],"<="&AsOfMonth) -> 1183 | H8: =SUMIFS(tbl_Sales[net_revenue],tbl_Sales[category],$B8,tbl_Sales[channel],$C8,tbl_Sales[month],">="&AsOfMonth,tbl_Sales[month],"<="&AsOfMonth) -> 223595.78 | I8: =SUMIFS(tbl_Sales[cogs],tbl_Sales[category],$B8,tbl_Sales[channel],$C8,tbl_Sales[month],">="&AsOfMonth,tbl_Sales[month],"<="&AsOfMonth) -> 184475.94 | J8: {=SAFEDIV(E8,D8)} -> 187.07985 | K8: {=SAFEDIV(H8,G8)} -> 189.00742 | L8: {=SAFEDIV(F8,D8)} -> 145.76769 | M8: {=SAFEDIV(I8,G8)} -> 155.93909 | N8: =J8-L8 -> 41.312153 | O8: {=SAFEDIV(G8,G$30)-SAFEDIV(D8,D$30)} -> -0.0039884027 | P8: =(G8-D8)*N$30 -> -2218.7324 | Q8: =(G8-D8)*(N8-N$30) -> -136.06033 | R8: =G8*(K8-J8) -> 2280.3213 | S8: =-G8*(M8-L8) -> -12032.759 | T8: =SUM(P8:S8) -> -12107.23 | U8: =(H8-I8)-(E8-F8) -> -12107.23 | V8: =T8-U8 -> -2.3646862e-11 | W8: {=INDEX({"Volume","Mix","Price","Unit cost"},_xlfn.XMATCH(MAX(ABS(P8:S8)),ABS(P8:S8)))} -> Unit cost
B9: Beef | C9: Online Direct | D9: =SUMIFS(tbl_Budget[units],tbl_Budget[category],$B9,tbl_Budget[channel],$C9,tbl_Budget[month],">="&AsOfMonth,tbl_Budget[month],"<="&AsOfMonth) -> 541 | E9: =SUMIFS(tbl_Budget[revenue],tbl_Budget[category],$B9,tbl_Budget[channel],$C9,tbl_Budget[month],">="&AsOfMonth,tbl_Budget[month],"<="&AsOfMonth) -> 118826.82 | F9: =SUMIFS(tbl_Budget[cogs],tbl_Budget[category],$B9,tbl_Budget[channel],$C9,tbl_Budget[month],">="&AsOfMonth,tbl_Budget[month],"<="&AsOfMonth) -> 78401.95 | G9: =SUMIFS(tbl_Sales[units],tbl_Sales[category],$B9,tbl_Sales[channel],$C9,tbl_Sales[month],">="&AsOfMonth,tbl_Sales[month],"<="&AsOfMonth) -> 531 | H9: =SUMIFS(tbl_Sales[net_revenue],tbl_Sales[category],$B9,tbl_Sales[channel],$C9,tbl_Sales[month],">="&AsOfMonth,tbl_Sales[month],"<="&AsOfMonth) -> 118874.18 | I9: =SUMIFS(tbl_Sales[cogs],tbl_Sales[category],$B9,tbl_Sales[channel],$C9,tbl_Sales[month],">="&AsOfMonth,tbl_Sales[month],"<="&AsOfMonth) -> 83168.69 | J9: {=SAFEDIV(E9,D9)} -> 219.64292 | K9: {=SAFEDIV(H9,G9)} -> 223.86851 | L9: {=SAFEDIV(F9,D9)} -> 144.92043 | M9: {=SAFEDIV(I9,G9)} -> 156.62653 | N9: =J9-L9 -> 74.722495 | O9: {=SAFEDIV(G9,G$30)-SAFEDIV(D9,D$30)} -> -0.0012241012 | P9: =(G9-D9)*N$30 -> -389.2513 | Q9: =(G9-D9)*(N9-N$30) -> -357.97366 | R9: =G9*(K9-J9) -> 2243.7892 | S9: =-G9*(M9-L9) -> -6215.9443 | T9: =SUM(P9:S9) -> -4719.38 | U9: =(H9-I9)-(E9-F9) -> -4719.38 | V9: =T9-U9 -> -1.2732926e-11 | W9: {=INDEX({"Volume","Mix","Price","Unit cost"},_xlfn.XMATCH(MAX(ABS(P9:S9)),ABS(P9:S9)))} -> Unit cost
B10: Pork | C10: Restaurants | D10: =SUMIFS(tbl_Budget[units],tbl_Budget[category],$B10,tbl_Budget[channel],$C10,tbl_Budget[month],">="&AsOfMonth,tbl_Budget[month],"<="&AsOfMonth) -> 2377 | E10: =SUMIFS(tbl_Budget[revenue],tbl_Budget[category],$B10,tbl_Budget[channel],$C10,tbl_Budget[month],">="&AsOfMonth,tbl_Budget[month],"<="&AsOfMonth) -> 296153.46 | F10: =SUMIFS(tbl_Budget[cogs],tbl_Budget[category],$B10,tbl_Budget[channel],$C10,tbl_Budget[month],">="&AsOfMonth,tbl_Budget[month],"<="&AsOfMonth) -> 206363.81 | G10: =SUMIFS(tbl_Sales[units],tbl_Sales[category],$B10,tbl_Sales[channel],$C10,tbl_Sales[month],">="&AsOfMonth,tbl_Sales[month],"<="&AsOfMonth) -> 2383 | H10: =SUMIFS(tbl_Sales[net_revenue],tbl_Sales[category],$B10,tbl_Sales[channel],$C10,tbl_Sales[month],">="&AsOfMonth,tbl_Sales[month],"<="&AsOfMonth) -> 297549.75 | I10: =SUMIFS(tbl_Sales[cogs],tbl_Sales[category],$B10,tbl_Sales[channel],$C10,tbl_Sales[month],">="&AsOfMonth,tbl_Sales[month],"<="&AsOfMonth) -> 207729.97 | J10: {=SAFEDIV(E10,D10)} -> 124.59127 | K10: {=SAFEDIV(H10,G10)} -> 124.86351 | L10: {=SAFEDIV(F10,D10)} -> 86.816916 | M10: {=SAFEDIV(I10,G10)} -> 87.17162 | N10: =J10-L10 -> 37.774358 | O10: {=SAFEDIV(G10,G$30)-SAFEDIV(D10,D$30)} -> -0.0036453259 | P10: =(G10-D10)*N$30 -> 233.55078 | Q10: =(G10-D10)*(N10-N$30) -> -6.9046286 | R10: =G10*(K10-J10) -> 648.74235 | S10: =-G10*(M10-L10) -> -845.2585 | T10: =SUM(P10:S10) -> 30.13 | U10: =(H10-I10)-(E10-F10) -> 30.13 | V10: =T10-U10 -> 2.5011104e-12 | W10: {=INDEX({"Volume","Mix","Price","Unit cost"},_xlfn.XMATCH(MAX(ABS(P10:S10)),ABS(P10:S10)))} -> Unit cost
B11: Pork | C11: Grocery Retail | D11: =SUMIFS(tbl_Budget[units],tbl_Budget[category],$B11,tbl_Budget[channel],$C11,tbl_Budget[month],">="&AsOfMonth,tbl_Budget[month],"<="&AsOfMonth) -> 1610 | E11: =SUMIFS(tbl_Budget[revenue],tbl_Budget[category],$B11,tbl_Budget[channel],$C11,tbl_Budget[month],">="&AsOfMonth,tbl_Budget[month],"<="&AsOfMonth) -> 174830.15 | F11: =SUMIFS(tbl_Budget[cogs],tbl_Budget[category],$B11,tbl_Budget[channel],$C11,tbl_Budget[month],">="&AsOfMonth,tbl_Budget[month],"<="&AsOfMonth) -> 139919.96 | G11: =SUMIFS(tbl_Sales[units],tbl_Sales[category],$B11,tbl_Sales[channel],$C11,tbl_Sales[month],">="&AsOfMonth,tbl_Sales[month],"<="&AsOfMonth) -> 1969 | H11: =SUMIFS(tbl_Sales[net_revenue],tbl_Sales[category],$B11,tbl_Sales[channel],$C11,tbl_Sales[month],">="&AsOfMonth,tbl_Sales[month],"<="&AsOfMonth) -> 211529.5 | I11: =SUMIFS(tbl_Sales[cogs],tbl_Sales[category],$B11,tbl_Sales[channel],$C11,tbl_Sales[month],">="&AsOfMonth,tbl_Sales[month],"<="&AsOfMonth) -> 171477.95 | J11: {=SAFEDIV(E11,D11)} -> 108.59016 | K11: {=SAFEDIV(H11,G11)} -> 107.42991 | L11: {=SAFEDIV(F11,D11)} -> 86.906807 | M11: {=SAFEDIV(I11,G11)} -> 87.088852 | N11: =J11-L11 -> 21.683348 | O11: {=SAFEDIV(G11,G$30)-SAFEDIV(D11,D$30)} -> 0.009848685 | P11: =(G11-D11)*N$30 -> 13974.122 | Q11: =(G11-D11)*(N11-N$30) -> -6189.7998 | R11: =G11*(K11-J11) -> -2284.5157 | S11: =-G11*(M11-L11) -> -358.44612 | T11: =SUM(P11:S11) -> 5141.36 | U11: =(H11-I11)-(E11-F11) -> 5141.36 | V11: =T11-U11 -> 1.4551915e-11 | W11: {=INDEX({"Volume","Mix","Price","Unit cost"},_xlfn.XMATCH(MAX(ABS(P11:S11)),ABS(P11:S11)))} -> Volume
B12: Pork | C12: Hotels & Institutions | D12: =SUMIFS(tbl_Budget[units],tbl_Budget[category],$B12,tbl_Budget[channel],$C12,tbl_Budget[month],">="&AsOfMonth,tbl_Budget[month],"<="&AsOfMonth) -> 994 | E12: =SUMIFS(tbl_Budget[revenue],tbl_Budget[category],$B12,tbl_Budget[channel],$C12,tbl_Budget[month],">="&AsOfMonth,tbl_Budget[month],"<="&AsOfMonth) -> 117606.51 | F12: =SUMIFS(tbl_Budget[cogs],tbl_Budget[category],$B12,tbl_Budget[channel],$C12,tbl_Budget[month],">="&AsOfMonth,tbl_Budget[month],"<="&AsOfMonth) -> 86287.99 | G12: =SUMIFS(tbl_Sales[units],tbl_Sales[category],$B12,tbl_Sales[channel],$C12,tbl_Sales[month],">="&AsOfMonth,tbl_Sales[month],"<="&AsOfMonth) -> 958 | H12: =SUMIFS(tbl_Sales[net_revenue],tbl_Sales[category],$B12,tbl_Sales[channel],$C12,tbl_Sales[month],">="&AsOfMonth,tbl_Sales[month],"<="&AsOfMonth) -> 113425.64 | I12: =SUMIFS(tbl_Sales[cogs],tbl_Sales[category],$B12,tbl_Sales[channel],$C12,tbl_Sales[month],">="&AsOfMonth,tbl_Sales[month],"<="&AsOfMonth) -> 83237 | J12: {=SAFEDIV(E12,D12)} -> 118.31641 | K12: {=SAFEDIV(H12,G12)} -> 118.39837 | L12: {=SAFEDIV(F12,D12)} -> 86.808843 | M12: {=SAFEDIV(I12,G12)} -> 86.886221 | N12: =J12-L12 -> 31.507565 | O12: {=SAFEDIV(G12,G$30)-SAFEDIV(D12,D$30)} -> -0.0028608047 | P12: =(G12-D12)*N$30 -> -1401.3047 | Q12: =(G12-D12)*(N12-N$30) -> 267.03232 | R12: =G12*(K12-J12) -> 78.520704 | S12: =-G12*(M12-L12) -> -74.12835 | T12: =SUM(P12:S12) -> -1129.88 | U12: =(H12-I12)-(E12-F12) -> -1129.88 | V12: =T12-U12 -> 7.9580786e-12 | W12: {=INDEX({"Volume","Mix","Price","Unit cost"},_xlfn.XMATCH(MAX(ABS(P12:S12)),ABS(P12:S12)))} -> Volume
B13: Pork | C13: Online Direct | D13: =SUMIFS(tbl_Budget[units],tbl_Budget[category],$B13,tbl_Budget[channel],$C13,tbl_Budget[month],">="&AsOfMonth,tbl_Budget[month],"<="&AsOfMonth) -> 432 | E13: =SUMIFS(tbl_Budget[revenue],tbl_Budget[category],$B13,tbl_Budget[channel],$C13,tbl_Budget[month],">="&AsOfMonth,tbl_Budget[month],"<="&AsOfMonth) -> 60371.86 | F13: =SUMIFS(tbl_Budget[cogs],tbl_Budget[category],$B13,tbl_Budget[channel],$C13,tbl_Budget[month],">="&AsOfMonth,tbl_Budget[month],"<="&AsOfMonth) -> 37569.22 | G13: =SUMIFS(tbl_Sales[units],tbl_Sales[category],$B13,tbl_Sales[channel],$C13,tbl_Sales[month],">="&AsOfMonth,tbl_Sales[month],"<="&AsOfMonth) -> 433 | H13: =SUMIFS(tbl_Sales[net_revenue],tbl_Sales[category],$B13,tbl_Sales[channel],$C13,tbl_Sales[month],">="&AsOfMonth,tbl_Sales[month],"<="&AsOfMonth) -> 60576.65 | I13: =SUMIFS(tbl_Sales[cogs],tbl_Sales[category],$B13,tbl_Sales[channel],$C13,tbl_Sales[month],">="&AsOfMonth,tbl_Sales[month],"<="&AsOfMonth) -> 37699.93 | J13: {=SAFEDIV(E13,D13)} -> 139.74968 | K13: {=SAFEDIV(H13,G13)} -> 139.89988 | L13: {=SAFEDIV(F13,D13)} -> 86.965787 | M13: {=SAFEDIV(I13,G13)} -> 87.066813 | N13: =J13-L13 -> 52.783889 | O13: {=SAFEDIV(G13,G$30)-SAFEDIV(D13,D$30)} -> -0.0006656467 | P13: =(G13-D13)*N$30 -> 38.92513 | Q13: =(G13-D13)*(N13-N$30) -> 13.858759 | R13: =G13*(K13-J13) -> 65.040324 | S13: =-G13*(M13-L13) -> -43.744213 | T13: =SUM(P13:S13) -> 74.08 | U13: =(H13-I13)-(E13-F13) -> 74.08 | V13: =T13-U13 -> 6.1248784e-12 | W13: {=INDEX({"Volume","Mix","Price","Unit cost"},_xlfn.XMATCH(MAX(ABS(P13:S13)),ABS(P13:S13)))} -> Price
B14: Poultry | C14: Restaurants | D14: =SUMIFS(tbl_Budget[units],tbl_Budget[category],$B14,tbl_Budget[channel],$C14,tbl_Budget[month],">="&AsOfMonth,tbl_Budget[month],"<="&AsOfMonth) -> 3305 | E14: =SUMIFS(tbl_Budget[revenue],tbl_Budget[category],$B14,tbl_Budget[channel],$C14,tbl_Budget[month],">="&AsOfMonth,tbl_Budget[month],"<="&AsOfMonth) -> 364962.76 | F14: =SUMIFS(tbl_Budget[cogs],tbl_Budget[category],$B14,tbl_Budget[channel],$C14,tbl_Budget[month],">="&AsOfMonth,tbl_Budget[month],"<="&AsOfMonth) -> 261441.24 | G14: =SUMIFS(tbl_Sales[units],tbl_Sales[category],$B14,tbl_Sales[channel],$C14,tbl_Sales[month],">="&AsOfMonth,tbl_Sales[month],"<="&AsOfMonth) -> 3261 | H14: =SUMIFS(tbl_Sales[net_revenue],tbl_Sales[category],$B14,tbl_Sales[channel],$C14,tbl_Sales[month],">="&AsOfMonth,tbl_Sales[month],"<="&AsOfMonth) -> 359161.33 | I14: =SUMIFS(tbl_Sales[cogs],tbl_Sales[category],$B14,tbl_Sales[channel],$C14,tbl_Sales[month],">="&AsOfMonth,tbl_Sales[month],"<="&AsOfMonth) -> 257683.4 | J14: {=SAFEDIV(E14,D14)} -> 110.42746 | K14: {=SAFEDIV(H14,G14)} -> 110.1384 | L14: {=SAFEDIV(F14,D14)} -> 79.104762 | M14: {=SAFEDIV(I14,G14)} -> 79.019749 | N14: =J14-L14 -> 31.322699 | O14: {=SAFEDIV(G14,G$30)-SAFEDIV(D14,D$30)} -> -0.0068849907 | P14: =(G14-D14)*N$30 -> -1712.7057 | Q14: =(G14-D14)*(N14-N$30) -> 334.50696 | R14: =G14*(K14-J14) -> -942.6217 | S14: =-G14*(M14-L14) -> 277.23045 | T14: =SUM(P14:S14) -> -2043.59 | U14: =(H14-I14)-(E14-F14) -> -2043.59 | V14: =T14-U14 -> 1.7053026e-11 | W14: {=INDEX({"Volume","Mix","Price","Unit cost"},_xlfn.XMATCH(MAX(ABS(P14:S14)),ABS(P14:S14)))} -> Volume
B15: Poultry | C15: Grocery Retail | D15: =SUMIFS(tbl_Budget[units],tbl_Budget[category],$B15,tbl_Budget[channel],$C15,tbl_Budget[month],">="&AsOfMonth,tbl_Budget[month],"<="&AsOfMonth) -> 2177 | E15: =SUMIFS(tbl_Budget[revenue],tbl_Budget[category],$B15,tbl_Budget[channel],$C15,tbl_Budget[month],">="&AsOfMonth,tbl_Budget[month],"<="&AsOfMonth) -> 208819.65 | F15: =SUMIFS(tbl_Budget[cogs],tbl_Budget[category],$B15,tbl_Budget[channel],$C15,tbl_Budget[month],">="&AsOfMonth,tbl_Budget[month],"<="&AsOfMonth) -> 172263.01 | G15: =SUMIFS(tbl_Sales[units],tbl_Sales[category],$B15,tbl_Sales[channel],$C15,tbl_Sales[month],">="&AsOfMonth,tbl_Sales[month],"<="&AsOfMonth) -> 2712 | H15: =SUMIFS(tbl_Sales[net_revenue],tbl_Sales[category],$B15,tbl_Sales[channel],$C15,tbl_Sales[month],">="&AsOfMonth,tbl_Sales[month],"<="&AsOfMonth) -> 260031.23 | I15: =SUMIFS(tbl_Sales[cogs],tbl_Sales[category],$B15,tbl_Sales[channel],$C15,tbl_Sales[month],">="&AsOfMonth,tbl_Sales[month],"<="&AsOfMonth) -> 215038.81 | J15: {=SAFEDIV(E15,D15)} -> 95.920831 | K15: {=SAFEDIV(H15,G15)} -> 95.881722 | L15: {=SAFEDIV(F15,D15)} -> 79.128622 | M15: {=SAFEDIV(I15,G15)} -> 79.291597 | N15: =J15-L15 -> 16.792209 | O15: {=SAFEDIV(G15,G$30)-SAFEDIV(D15,D$30)} -> 0.015037404 | P15: =(G15-D15)*N$30 -> 20824.944 | Q15: =(G15-D15)*(N15-N$30) -> -11841.112 | R15: =G15*(K15-J15) -> -106.06481 | S15: =-G15*(M15-L15) -> -441.98725 | T15: =SUM(P15:S15) -> 8435.78 | U15: =(H15-I15)-(E15-F15) -> 8435.78 | V15: =T15-U15 -> -1.6370905e-11 | W15: {=INDEX({"Volume","Mix","Price","Unit cost"},_xlfn.XMATCH(MAX(ABS(P15:S15)),ABS(P15:S15)))} -> Volume
B16: Poultry | C16: Hotels & Institutions | D16: =SUMIFS(tbl_Budget[units],tbl_Budget[category],$B16,tbl_Budget[channel],$C16,tbl_Budget[month],">="&AsOfMonth,tbl_Budget[month],"<="&AsOfMonth) -> 1307 | E16: =SUMIFS(tbl_Budget[revenue],tbl_Budget[category],$B16,tbl_Budget[channel],$C16,tbl_Budget[month],">="&AsOfMonth,tbl_Budget[month],"<="&AsOfMonth) -> 136559.69 | F16: =SUMIFS(tbl_Budget[cogs],tbl_Budget[category],$B16,tbl_Budget[channel],$C16,tbl_Budget[month],">="&AsOfMonth,tbl_Budget[month],"<="&AsOfMonth) -> 103104.17 | G16: =SUMIFS(tbl_Sales[units],tbl_Sales[category],$B16,tbl_Sales[channel],$C16,tbl_Sales[month],">="&AsOfMonth,tbl_Sales[month],"<="&AsOfMonth) -> 1335 | H16: =SUMIFS(tbl_Sales[net_revenue],tbl_Sales[category],$B16,tbl_Sales[channel],$C16,tbl_Sales[month],">="&AsOfMonth,tbl_Sales[month],"<="&AsOfMonth) -> 139624.43 | I16: =SUMIFS(tbl_Sales[cogs],tbl_Sales[category],$B16,tbl_Sales[channel],$C16,tbl_Sales[month],">="&AsOfMonth,tbl_Sales[month],"<="&AsOfMonth) -> 105259.39 | J16: {=SAFEDIV(E16,D16)} -> 104.48331 | K16: {=SAFEDIV(H16,G16)} -> 104.58759 | L16: {=SAFEDIV(F16,D16)} -> 78.886129 | M16: {=SAFEDIV(I16,G16)} -> 78.845985 | N16: =J16-L16 -> 25.597184 | O16: {=SAFEDIV(G16,G$30)-SAFEDIV(D16,D$30)} -> -0.0011471694 | P16: =(G16-D16)*N$30 -> 1089.9036 | Q16: =(G16-D16)*(N16-N$30) -> -373.18247 | R16: =G16*(K16-J16) -> 139.20724 | S16: =-G16*(M16-L16) -> 53.591599 | T16: =SUM(P16:S16) -> 909.52 | U16: =(H16-I16)-(E16-F16) -> 909.52 | V16: =T16-U16 -> 5.2295945e-12 | W16: {=INDEX({"Volume","Mix","Price","Unit cost"},_xlfn.XMATCH(MAX(ABS(P16:S16)),ABS(P16:S16)))} -> Volume
B17: Poultry | C17: Online Direct | D17: =SUMIFS(tbl_Budget[units],tbl_Budget[category],$B17,tbl_Budget[channel],$C17,tbl_Budget[month],">="&AsOfMonth,tbl_Budget[month],"<="&AsOfMonth) -> 577 | E17: =SUMIFS(tbl_Budget[revenue],tbl_Budget[category],$B17,tbl_Budget[channel],$C17,tbl_Budget[month],">="&AsOfMonth,tbl_Budget[month],"<="&AsOfMonth) -> 71721.46 | F17: =SUMIFS(tbl_Budget[cogs],tbl_Budget[category],$B17,tbl_Budget[channel],$C17,tbl_Budget[month],">="&AsOfMonth,tbl_Budget[month],"<="&AsOfMonth) -> 45836.34 | G17: =SUMIFS(tbl_Sales[units],tbl_Sales[category],$B17,tbl_Sales[channel],$C17,tbl_Sales[month],">="&AsOfMonth,tbl_Sales[month],"<="&AsOfMonth) -> 587 | H17: =SUMIFS(tbl_Sales[net_revenue],tbl_Sales[category],$B17,tbl_Sales[channel],$C17,tbl_Sales[month],">="&AsOfMonth,tbl_Sales[month],"<="&AsOfMonth) -> 72704.45 | I17: =SUMIFS(tbl_Sales[cogs],tbl_Sales[category],$B17,tbl_Sales[channel],$C17,tbl_Sales[month],">="&AsOfMonth,tbl_Sales[month],"<="&AsOfMonth) -> 46400.92 | J17: {=SAFEDIV(E17,D17)} -> 124.30062 | K17: {=SAFEDIV(H17,G17)} -> 123.85767 | L17: {=SAFEDIV(F17,D17)} -> 79.439064 | M17: {=SAFEDIV(I17,G17)} -> 79.047564 | N17: =J17-L17 -> 44.86156 | O17: {=SAFEDIV(G17,G$30)-SAFEDIV(D17,D$30)} -> -0.00058838083 | P17: =(G17-D17)*N$30 -> 389.2513 | Q17: =(G17-D17)*(N17-N$30) -> 59.364299 | R17: =G17*(K17-J17) -> -260.01624 | S17: =-G17*(M17-L17) -> 229.81064 | T17: =SUM(P17:S17) -> 418.41 | U17: =(H17-I17)-(E17-F17) -> 418.41 | V17: =T17-U17 -> 0 | W17: {=INDEX({"Volume","Mix","Price","Unit cost"},_xlfn.XMATCH(MAX(ABS(P17:S17)),ABS(P17:S17)))} -> Volume
... B29: Cheese & Dairy | C29: Online Direct | D29: =SUMIFS(tbl_Budget[units],tbl_Budget[category],$B29,tbl_Budget[channel],$C29,tbl_Budget[month],">="&AsOfMonth,tbl_Budget[month],"<="&AsOfMonth) -> 237 | E29: =SUMIFS(tbl_Budget[revenue],tbl_Budget[category],$B29,tbl_Budget[channel],$C29,tbl_Budget[month],">="&AsOfMonth,tbl_Budget[month],"<="&AsOfMonth) -> 36277.54 | F29: =SUMIFS(tbl_Budget[cogs],tbl_Budget[category],$B29,tbl_Budget[channel],$C29,tbl_Budget[month],">="&AsOfMonth,tbl_Budget[month],"<="&AsOfMonth) -> 19984.92 | G29: =SUMIFS(tbl_Sales[units],tbl_Sales[category],$B29,tbl_Sales[channel],$C29,tbl_Sales[month],">="&AsOfMonth,tbl_Sales[month],"<="&AsOfMonth) -> 225 | H29: =SUMIFS(tbl_Sales[net_revenue],tbl_Sales[category],$B29,tbl_Sales[channel],$C29,tbl_Sales[month],">="&AsOfMonth,tbl_Sales[month],"<="&AsOfMonth) -> 34588.74 | I29: =SUMIFS(tbl_Sales[cogs],tbl_Sales[category],$B29,tbl_Sales[channel],$C29,tbl_Sales[month],">="&AsOfMonth,tbl_Sales[month],"<="&AsOfMonth) -> 19075.05 | J29: {=SAFEDIV(E29,D29)} -> 153.06979 | K29: {=SAFEDIV(H29,G29)} -> 153.72773 | L29: {=SAFEDIV(F29,D29)} -> 84.324557 | M29: {=SAFEDIV(I29,G29)} -> 84.778 | N29: =J29-L29 -> 68.745232 | O29: {=SAFEDIV(G29,G$30)-SAFEDIV(D29,D$30)} -> -0.00080067002 | P29: =(G29-D29)*N$30 -> -467.10156 | Q29: =(G29-D29)*(N29-N$30) -> -357.84123 | R29: =G29*(K29-J29) -> 148.03747 | S29: =-G29*(M29-L29) -> -102.02468 | T29: =SUM(P29:S29) -> -778.93 | U29: =(H29-I29)-(E29-F29) -> -778.93 | V29: =T29-U29 -> 7.0485839e-12 | W29: {=INDEX({"Volume","Mix","Price","Unit cost"},_xlfn.XMATCH(MAX(ABS(P29:S29)),ABS(P29:S29)))} -> Volume
B30: All segments | D30: =SUM(D6:D29) -> 27529 | E30: =SUM(E6:E29) -> 4008366.5 | F30: =SUM(F6:F29) -> 2936796.6 | G30: =SUM(G6:G29) -> 28815 | H30: =SUM(H6:H29) -> 4190550.5 | I30: =SUM(I6:I29) -> 3136904.4 | J30: {=SAFEDIV(E30,D30)} -> 145.60523 | K30: {=SAFEDIV(H30,G30)} -> 145.42948 | L30: {=SAFEDIV(F30,D30)} -> 106.6801 | M30: {=SAFEDIV(I30,G30)} -> 108.86359 | N30: =J30-L30 -> 38.92513 | O30: =SUM(O6:O29) -> -1.2143064e-17 | P30: =SUM(P6:P29) -> 50057.717 | Q30: =SUM(Q6:Q29) -> -27182.298 | R30: =SUM(R6:R29) -> 31643.327 | S30: =SUM(S6:S29) -> -72442.565 | T30: =SUM(P30:S30) -> -17923.82 | U30: =(H30-I30)-(E30-F30) -> -17923.82 | V30: =T30-U30 -> -1.6734703e-10 | W30: {=INDEX({"Volume","Mix","Price","Unit cost"},_xlfn.XMATCH(MAX(ABS(P30:S30)),ABS(P30:S30)))} -> Unit cost
B33: ="Year to date: "&TEXT(FYStart,"mmmm")&" to "&TEXT(AsOfMonth,"mmmm yyyy")&" against budget" -> Year to date: January to August 2026 against budget
B34: Category | C34: Channel | D34: Budget cases | E34: Budget revenue | F34: Budget COGS | G34: Actual cases | H34: Actual revenue | I34: Actual COGS | J34: Budget price / case | K34: Actual price / case | L34: Budget cost / case | M34: Actual cost / case | N34: Budget margin / case | O34: Share shift | P34: Volume | Q34: Mix | R34: Price | S34: Unit cost | T34: Effects, total | U34: GM variance | V34: Unexplained | W34: Main driver
B35: Beef | C35: Restaurants | D35: =SUMIFS(tbl_Budget[units],tbl_Budget[category],$B35,tbl_Budget[channel],$C35,tbl_Budget[month],">="&FYStart,tbl_Budget[month],"<="&AsOfMonth) -> 21368 | E35: =SUMIFS(tbl_Budget[revenue],tbl_Budget[category],$B35,tbl_Budget[channel],$C35,tbl_Budget[month],">="&FYStart,tbl_Budget[month],"<="&AsOfMonth) -> 4217482.1 | F35: =SUMIFS(tbl_Budget[cogs],tbl_Budget[category],$B35,tbl_Budget[channel],$C35,tbl_Budget[month],">="&FYStart,tbl_Budget[month],"<="&AsOfMonth) -> 3119751.7 | G35: =SUMIFS(tbl_Sales[units],tbl_Sales[category],$B35,tbl_Sales[channel],$C35,tbl_Sales[month],">="&FYStart,tbl_Sales[month],"<="&AsOfMonth) -> 20709 | H35: =SUMIFS(tbl_Sales[net_revenue],tbl_Sales[category],$B35,tbl_Sales[channel],$C35,tbl_Sales[month],">="&FYStart,tbl_Sales[month],"<="&AsOfMonth) -> 4120883 | I35: =SUMIFS(tbl_Sales[cogs],tbl_Sales[category],$B35,tbl_Sales[channel],$C35,tbl_Sales[month],">="&FYStart,tbl_Sales[month],"<="&AsOfMonth) -> 3174773 | J35: {=SAFEDIV(E35,D35)} -> 197.37374 | K35: {=SAFEDIV(H35,G35)} -> 198.98996 | L35: {=SAFEDIV(F35,D35)} -> 146.00111 | M35: {=SAFEDIV(I35,G35)} -> 153.30402 | N35: =J35-L35 -> 51.372629 | O35: {=SAFEDIV(G35,G$59)-SAFEDIV(D35,D$59)} -> -0.0065015898 | P35: =(G35-D35)*N$59 -> -25572.66 | Q35: =(G35-D35)*(N35-N$59) -> -8281.9022 | R35: =G35*(K35-J35) -> 33470.265 | S35: =-G35*(M35-L35) -> -151235.98 | T35: =SUM(P35:S35) -> -151620.28 | U35: =(H35-I35)-(E35-F35) -> -151620.28 | V35: =T35-U35 -> 0 | W35: {=INDEX({"Volume","Mix","Price","Unit cost"},_xlfn.XMATCH(MAX(ABS(P35:S35)),ABS(P35:S35)))} -> Unit cost
B36: Beef | C36: Grocery Retail | D36: =SUMIFS(tbl_Budget[units],tbl_Budget[category],$B36,tbl_Budget[channel],$C36,tbl_Budget[month],">="&FYStart,tbl_Budget[month],"<="&AsOfMonth) -> 14585 | E36: =SUMIFS(tbl_Budget[revenue],tbl_Budget[category],$B36,tbl_Budget[channel],$C36,tbl_Budget[month],">="&FYStart,tbl_Budget[month],"<="&AsOfMonth) -> 2497343.5 | F36: =SUMIFS(tbl_Budget[cogs],tbl_Budget[category],$B36,tbl_Budget[channel],$C36,tbl_Budget[month],">="&FYStart,tbl_Budget[month],"<="&AsOfMonth) -> 2129200.7 | G36: =SUMIFS(tbl_Sales[units],tbl_Sales[category],$B36,tbl_Sales[channel],$C36,tbl_Sales[month],">="&FYStart,tbl_Sales[month],"<="&AsOfMonth) -> 16692 | H36: =SUMIFS(tbl_Sales[net_revenue],tbl_Sales[category],$B36,tbl_Sales[channel],$C36,tbl_Sales[month],">="&FYStart,tbl_Sales[month],"<="&AsOfMonth) -> 2887310.9 | I36: =SUMIFS(tbl_Sales[cogs],tbl_Sales[category],$B36,tbl_Sales[channel],$C36,tbl_Sales[month],">="&FYStart,tbl_Sales[month],"<="&AsOfMonth) -> 2557846.7 | J36: {=SAFEDIV(E36,D36)} -> 171.22684 | K36: {=SAFEDIV(H36,G36)} -> 172.97573 | L36: {=SAFEDIV(F36,D36)} -> 145.98565 | M36: {=SAFEDIV(I36,G36)} -> 153.23788 | N36: =J36-L36 -> 25.24119 | O36: {=SAFEDIV(G36,G$59)-SAFEDIV(D36,D$59)} -> 0.0072905229 | P36: =(G36-D36)*N$59 -> 81762.664 | Q36: =(G36-D36)*(N36-N$59) -> -28579.477 | R36: =G36*(K36-J36) -> 29192.538 | S36: =-G36*(M36-L36) -> -121054.23 | T36: =SUM(P36:S36) -> -38678.51 | U36: =(H36-I36)-(E36-F36) -> -38678.51 | V36: =T36-U36 -> 0 | W36: {=INDEX({"Volume","Mix","Price","Unit cost"},_xlfn.XMATCH(MAX(ABS(P36:S36)),ABS(P36:S36)))} -> Unit cost
B37: Beef | C37: Hotels & Institutions | D37: =SUMIFS(tbl_Budget[units],tbl_Budget[category],$B37,tbl_Budget[channel],$C37,tbl_Budget[month],">="&FYStart,tbl_Budget[month],"<="&AsOfMonth) -> 8775 | E37: =SUMIFS(tbl_Budget[revenue],tbl_Budget[category],$B37,tbl_Budget[channel],$C37,tbl_Budget[month],">="&FYStart,tbl_Budget[month],"<="&AsOfMonth) -> 1642518.6 | F37: =SUMIFS(tbl_Budget[cogs],tbl_Budget[category],$B37,tbl_Budget[channel],$C37,tbl_Budget[month],">="&FYStart,tbl_Budget[month],"<="&AsOfMonth) -> 1279824 | G37: =SUMIFS(tbl_Sales[units],tbl_Sales[category],$B37,tbl_Sales[channel],$C37,tbl_Sales[month],">="&FYStart,tbl_Sales[month],"<="&AsOfMonth) -> 8479 | H37: =SUMIFS(tbl_Sales[net_revenue],tbl_Sales[category],$B37,tbl_Sales[channel],$C37,tbl_Sales[month],">="&FYStart,tbl_Sales[month],"<="&AsOfMonth) -> 1605432.2 | I37: =SUMIFS(tbl_Sales[cogs],tbl_Sales[category],$B37,tbl_Sales[channel],$C37,tbl_Sales[month],">="&FYStart,tbl_Sales[month],"<="&AsOfMonth) -> 1301845.5 | J37: {=SAFEDIV(E37,D37)} -> 187.18161 | K37: {=SAFEDIV(H37,G37)} -> 189.34216 | L37: {=SAFEDIV(F37,D37)} -> 145.84889 | M37: {=SAFEDIV(I37,G37)} -> 153.53762 | N37: =J37-L37 -> 41.332725 | O37: {=SAFEDIV(G37,G$59)-SAFEDIV(D37,D$59)} -> -0.0027863429 | P37: =(G37-D37)*N$59 -> -11486.354 | Q37: =(G37-D37)*(N37-N$59) -> -748.13225 | R37: =G37*(K37-J37) -> 18319.287 | S37: =-G37*(M37-L37) -> -65192.801 | T37: =SUM(P37:S37) -> -59108 | U37: =(H37-I37)-(E37-F37) -> -59108 | V37: =T37-U37 -> -2.6193447e-10 | W37: {=INDEX({"Volume","Mix","Price","Unit cost"},_xlfn.XMATCH(MAX(ABS(P37:S37)),ABS(P37:S37)))} -> Unit cost
B38: Beef | C38: Online Direct | D38: =SUMIFS(tbl_Budget[units],tbl_Budget[category],$B38,tbl_Budget[channel],$C38,tbl_Budget[month],">="&FYStart,tbl_Budget[month],"<="&AsOfMonth) -> 3883 | E38: =SUMIFS(tbl_Budget[revenue],tbl_Budget[category],$B38,tbl_Budget[channel],$C38,tbl_Budget[month],">="&FYStart,tbl_Budget[month],"<="&AsOfMonth) -> 857267.6 | F38: =SUMIFS(tbl_Budget[cogs],tbl_Budget[category],$B38,tbl_Budget[channel],$C38,tbl_Budget[month],">="&FYStart,tbl_Budget[month],"<="&AsOfMonth) -> 565635.93 | G38: =SUMIFS(tbl_Sales[units],tbl_Sales[category],$B38,tbl_Sales[channel],$C38,tbl_Sales[month],">="&FYStart,tbl_Sales[month],"<="&AsOfMonth) -> 3764 | H38: =SUMIFS(tbl_Sales[net_revenue],tbl_Sales[category],$B38,tbl_Sales[channel],$C38,tbl_Sales[month],">="&FYStart,tbl_Sales[month],"<="&AsOfMonth) -> 842482.19 | I38: =SUMIFS(tbl_Sales[cogs],tbl_Sales[category],$B38,tbl_Sales[channel],$C38,tbl_Sales[month],">="&FYStart,tbl_Sales[month],"<="&AsOfMonth) -> 579732.92 | J38: {=SAFEDIV(E38,D38)} -> 220.77456 | K38: {=SAFEDIV(H38,G38)} -> 223.8263 | L38: {=SAFEDIV(F38,D38)} -> 145.66982 | M38: {=SAFEDIV(I38,G38)} -> 154.02044 | N38: =J38-L38 -> 75.104731 | O38: {=SAFEDIV(G38,G$59)-SAFEDIV(D38,D$59)} -> -0.0011780138 | P38: =(G38-D38)*N$59 -> -4617.8249 | Q38: =(G38-D38)*(N38-N$59) -> -4319.6381 | R38: =G38*(K38-J38) -> 11486.762 | S38: =-G38*(M38-L38) -> -31431.699 | T38: =SUM(P38:S38) -> -28882.4 | U38: =(H38-I38)-(E38-F38) -> -28882.4 | V38: =T38-U38 -> 0 | W38: {=INDEX({"Volume","Mix","Price","Unit cost"},_xlfn.XMATCH(MAX(ABS(P38:S38)),ABS(P38:S38)))} -> Unit cost
B39: Pork | C39: Restaurants | D39: =SUMIFS(tbl_Budget[units],tbl_Budget[category],$B39,tbl_Budget[channel],$C39,tbl_Budget[month],">="&FYStart,tbl_Budget[month],"<="&AsOfMonth) -> 18188 | E39: =SUMIFS(tbl_Budget[revenue],tbl_Budget[category],$B39,tbl_Budget[channel],$C39,tbl_Budget[month],">="&FYStart,tbl_Budget[month],"<="&AsOfMonth) -> 2270388.7 | F39: =SUMIFS(tbl_Budget[cogs],tbl_Budget[category],$B39,tbl_Budget[channel],$C39,tbl_Budget[month],">="&FYStart,tbl_Budget[month],"<="&AsOfMonth) -> 1582216 | G39: =SUMIFS(tbl_Sales[units],tbl_Sales[category],$B39,tbl_Sales[channel],$C39,tbl_Sales[month],">="&FYStart,tbl_Sales[month],"<="&AsOfMonth) -> 18131 | H39: =SUMIFS(tbl_Sales[net_revenue],tbl_Sales[category],$B39,tbl_Sales[channel],$C39,tbl_Sales[month],">="&FYStart,tbl_Sales[month],"<="&AsOfMonth) -> 2262279 | I39: =SUMIFS(tbl_Sales[cogs],tbl_Sales[category],$B39,tbl_Sales[channel],$C39,tbl_Sales[month],">="&FYStart,tbl_Sales[month],"<="&AsOfMonth) -> 1576401.7 | J39: {=SAFEDIV(E39,D39)} -> 124.82894 | K39: {=SAFEDIV(H39,G39)} -> 124.77409 | L39: {=SAFEDIV(F39,D39)} -> 86.992303 | M39: {=SAFEDIV(I39,G39)} -> 86.945107 | N39: =J39-L39 -> 37.836635 | O39: {=SAFEDIV(G39,G$59)-SAFEDIV(D39,D$59)} -> -0.0032224687 | P39: =(G39-D39)*N$59 -> -2211.8993 | Q39: =(G39-D39)*(N39-N$59) -> 55.211134 | R39: =G39*(K39-J39) -> -994.44058 | S39: =-G39*(M39-L39) -> 855.70875 | T39: =SUM(P39:S39) -> -2295.42 | U39: =(H39-I39)-(E39-F39) -> -2295.42 | V39: =T39-U39 -> -1.9963409e-10 | W39: {=INDEX({"Volume","Mix","Price","Unit cost"},_xlfn.XMATCH(MAX(ABS(P39:S39)),ABS(P39:S39)))} -> Volume
B40: Pork | C40: Grocery Retail | D40: =SUMIFS(tbl_Budget[units],tbl_Budget[category],$B40,tbl_Budget[channel],$C40,tbl_Budget[month],">="&FYStart,tbl_Budget[month],"<="&AsOfMonth) -> 12385 | E40: =SUMIFS(tbl_Budget[revenue],tbl_Budget[category],$B40,tbl_Budget[channel],$C40,tbl_Budget[month],">="&FYStart,tbl_Budget[month],"<="&AsOfMonth) -> 1345846.1 | F40: =SUMIFS(tbl_Budget[cogs],tbl_Budget[category],$B40,tbl_Budget[channel],$C40,tbl_Budget[month],">="&FYStart,tbl_Budget[month],"<="&AsOfMonth) -> 1077143.1 | G40: =SUMIFS(tbl_Sales[units],tbl_Sales[category],$B40,tbl_Sales[channel],$C40,tbl_Sales[month],">="&FYStart,tbl_Sales[month],"<="&AsOfMonth) -> 14612 | H40: =SUMIFS(tbl_Sales[net_revenue],tbl_Sales[category],$B40,tbl_Sales[channel],$C40,tbl_Sales[month],">="&FYStart,tbl_Sales[month],"<="&AsOfMonth) -> 1586922.4 | I40: =SUMIFS(tbl_Sales[cogs],tbl_Sales[category],$B40,tbl_Sales[channel],$C40,tbl_Sales[month],">="&FYStart,tbl_Sales[month],"<="&AsOfMonth) -> 1271100.9 | J40: {=SAFEDIV(E40,D40)} -> 108.66743 | K40: {=SAFEDIV(H40,G40)} -> 108.60405 | L40: {=SAFEDIV(F40,D40)} -> 86.971583 | M40: {=SAFEDIV(I40,G40)} -> 86.990206 | N40: =J40-L40 -> 21.695847 | O40: {=SAFEDIV(G40,G$59)-SAFEDIV(D40,D$59)} -> 0.0081991314 | P40: =(G40-D40)*N$59 -> 86419.294 | Q40: =(G40-D40)*(N40-N$59) -> -38102.644 | R40: =G40*(K40-J40) -> -926.07651 | S40: =-G40*(M40-L40) -> -272.11384 | T40: =SUM(P40:S40) -> 47118.46 | U40: =(H40-I40)-(E40-F40) -> 47118.46 | V40: =T40-U40 -> -1.0913936e-10 | W40: {=INDEX({"Volume","Mix","Price","Unit cost"},_xlfn.XMATCH(MAX(ABS(P40:S40)),ABS(P40:S40)))} -> Volume
B41: Pork | C41: Hotels & Institutions | D41: =SUMIFS(tbl_Budget[units],tbl_Budget[category],$B41,tbl_Budget[channel],$C41,tbl_Budget[month],">="&FYStart,tbl_Budget[month],"<="&AsOfMonth) -> 7422 | E41: =SUMIFS(tbl_Budget[revenue],tbl_Budget[category],$B41,tbl_Budget[channel],$C41,tbl_Budget[month],">="&FYStart,tbl_Budget[month],"<="&AsOfMonth) -> 880254.38 | F41: =SUMIFS(tbl_Budget[cogs],tbl_Budget[category],$B41,tbl_Budget[channel],$C41,tbl_Budget[month],">="&FYStart,tbl_Budget[month],"<="&AsOfMonth) -> 645876.19 | G41: =SUMIFS(tbl_Sales[units],tbl_Sales[category],$B41,tbl_Sales[channel],$C41,tbl_Sales[month],">="&FYStart,tbl_Sales[month],"<="&AsOfMonth) -> 7418 | H41: =SUMIFS(tbl_Sales[net_revenue],tbl_Sales[category],$B41,tbl_Sales[channel],$C41,tbl_Sales[month],">="&FYStart,tbl_Sales[month],"<="&AsOfMonth) -> 880757.45 | I41: =SUMIFS(tbl_Sales[cogs],tbl_Sales[category],$B41,tbl_Sales[channel],$C41,tbl_Sales[month],">="&FYStart,tbl_Sales[month],"<="&AsOfMonth) -> 645116.3 | J41: {=SAFEDIV(E41,D41)} -> 118.6007 | K41: {=SAFEDIV(H41,G41)} -> 118.73247 | L41: {=SAFEDIV(F41,D41)} -> 87.021853 | M41: {=SAFEDIV(I41,G41)} -> 86.966339 | N41: =J41-L41 -> 31.578845 | O41: {=SAFEDIV(G41,G$59)-SAFEDIV(D41,D$59)} -> -0.0012266496 | P41: =(G41-D41)*N$59 -> -155.221 | Q41: =(G41-D41)*(N41-N$59) -> 28.905623 | R41: =G41*(K41-J41) -> 977.47279 | S41: =-G41*(M41-L41) -> 411.80259 | T41: =SUM(P41:S41) -> 1262.96 | U41: =(H41-I41)-(E41-F41) -> 1262.96 | V41: =T41-U41 -> -5.8207661e-11 | W41: {=INDEX({"Volume","Mix","Price","Unit cost"},_xlfn.XMATCH(MAX(ABS(P41:S41)),ABS(P41:S41)))} -> Price
B42: Pork | C42: Online Direct | D42: =SUMIFS(tbl_Budget[units],tbl_Budget[category],$B42,tbl_Budget[channel],$C42,tbl_Budget[month],">="&FYStart,tbl_Budget[month],"<="&AsOfMonth) -> 3297 | E42: =SUMIFS(tbl_Budget[revenue],tbl_Budget[category],$B42,tbl_Budget[channel],$C42,tbl_Budget[month],">="&FYStart,tbl_Budget[month],"<="&AsOfMonth) -> 460494.51 | F42: =SUMIFS(tbl_Budget[cogs],tbl_Budget[category],$B42,tbl_Budget[channel],$C42,tbl_Budget[month],">="&FYStart,tbl_Budget[month],"<="&AsOfMonth) -> 286570.68 | G42: =SUMIFS(tbl_Sales[units],tbl_Sales[category],$B42,tbl_Sales[channel],$C42,tbl_Sales[month],">="&FYStart,tbl_Sales[month],"<="&AsOfMonth) -> 3289 | H42: =SUMIFS(tbl_Sales[net_revenue],tbl_Sales[category],$B42,tbl_Sales[channel],$C42,tbl_Sales[month],">="&FYStart,tbl_Sales[month],"<="&AsOfMonth) -> 459667.19 | I42: =SUMIFS(tbl_Sales[cogs],tbl_Sales[category],$B42,tbl_Sales[channel],$C42,tbl_Sales[month],">="&FYStart,tbl_Sales[month],"<="&AsOfMonth) -> 286266.85 | J42: {=SAFEDIV(E42,D42)} -> 139.67076 | K42: {=SAFEDIV(H42,G42)} -> 139.75895 | L42: {=SAFEDIV(F42,D42)} -> 86.918617 | M42: {=SAFEDIV(I42,G42)} -> 87.037656 | N42: =J42-L42 -> 52.752147 | O42: {=SAFEDIV(G42,G$59)-SAFEDIV(D42,D$59)} -> -0.00057344803 | P42: =(G42-D42)*N$59 -> -310.44201 | Q42: =(G42-D42)*(N42-N$59) -> -111.57517 | R42: =G42*(K42-J42) -> 290.04611 | S42: =-G42*(M42-L42) -> -391.51894 | T42: =SUM(P42:S42) -> -523.49 | U42: =(H42-I42)-(E42-F42) -> -523.49 | V42: =T42-U42 -> 5.968559e-11 | W42: {=INDEX({"Volume","Mix","Price","Unit cost"},_xlfn.XMATCH(MAX(ABS(P42:S42)),ABS(P42:S42)))} -> Unit cost
B43: Poultry | C43: Restaurants | D43: =SUMIFS(tbl_Budget[units],tbl_Budget[category],$B43,tbl_Budget[channel],$C43,tbl_Budget[month],">="&FYStart,tbl_Budget[month],"<="&AsOfMonth) -> 25876 | E43: =SUMIFS(tbl_Budget[revenue],tbl_Budget[category],$B43,tbl_Budget[channel],$C43,tbl_Budget[month],">="&FYStart,tbl_Budget[month],"<="&AsOfMonth) -> 2858626.8 | F43: =SUMIFS(tbl_Budget[cogs],tbl_Budget[category],$B43,tbl_Budget[channel],$C43,tbl_Budget[month],">="&FYStart,tbl_Budget[month],"<="&AsOfMonth) -> 2047708.1 | G43: =SUMIFS(tbl_Sales[units],tbl_Sales[category],$B43,tbl_Sales[channel],$C43,tbl_Sales[month],">="&FYStart,tbl_Sales[month],"<="&AsOfMonth) -> 25760 | H43: =SUMIFS(tbl_Sales[net_revenue],tbl_Sales[category],$B43,tbl_Sales[channel],$C43,tbl_Sales[month],">="&FYStart,tbl_Sales[month],"<="&AsOfMonth) -> 2845913.7 | I43: =SUMIFS(tbl_Sales[cogs],tbl_Sales[category],$B43,tbl_Sales[channel],$C43,tbl_Sales[month],">="&FYStart,tbl_Sales[month],"<="&AsOfMonth) -> 2040532 | J43: {=SAFEDIV(E43,D43)} -> 110.47406 | K43: {=SAFEDIV(H43,G43)} -> 110.47802 | L43: {=SAFEDIV(F43,D43)} -> 79.135417 | M43: {=SAFEDIV(I43,G43)} -> 79.2132 | N43: =J43-L43 -> 31.338642 | O43: {=SAFEDIV(G43,G$59)-SAFEDIV(D43,D$59)} -> -0.004744712 | P43: =(G43-D43)*N$59 -> -4501.4091 | Q43: =(G43-D43)*(N43-N$59) -> 866.12669 | R43: =G43*(K43-J43) -> 101.97084 | S43: =-G43*(M43-L43) -> -2003.6884 | T43: =SUM(P43:S43) -> -5537 | U43: =(H43-I43)-(E43-F43) -> -5537 | V43: =T43-U43 -> 6.7302608e-11 | W43: {=INDEX({"Volume","Mix","Price","Unit cost"},_xlfn.XMATCH(MAX(ABS(P43:S43)),ABS(P43:S43)))} -> Volume
B44: Poultry | C44: Grocery Retail | D44: =SUMIFS(tbl_Budget[units],tbl_Budget[category],$B44,tbl_Budget[channel],$C44,tbl_Budget[month],">="&FYStart,tbl_Budget[month],"<="&AsOfMonth) -> 17553 | E44: =SUMIFS(tbl_Budget[revenue],tbl_Budget[category],$B44,tbl_Budget[channel],$C44,tbl_Budget[month],">="&FYStart,tbl_Budget[month],"<="&AsOfMonth) -> 1684638.4 | F44: =SUMIFS(tbl_Budget[cogs],tbl_Budget[category],$B44,tbl_Budget[channel],$C44,tbl_Budget[month],">="&FYStart,tbl_Budget[month],"<="&AsOfMonth) -> 1389632 | G44: =SUMIFS(tbl_Sales[units],tbl_Sales[category],$B44,tbl_Sales[channel],$C44,tbl_Sales[month],">="&FYStart,tbl_Sales[month],"<="&AsOfMonth) -> 20497 | H44: =SUMIFS(tbl_Sales[net_revenue],tbl_Sales[category],$B44,tbl_Sales[channel],$C44,tbl_Sales[month],">="&FYStart,tbl_Sales[month],"<="&AsOfMonth) -> 1971833.3 | I44: =SUMIFS(tbl_Sales[cogs],tbl_Sales[category],$B44,tbl_Sales[channel],$C44,tbl_Sales[month],">="&FYStart,tbl_Sales[month],"<="&AsOfMonth) -> 1624960.1 | J44: {=SAFEDIV(E44,D44)} -> 95.974384 | K44: {=SAFEDIV(H44,G44)} -> 96.201067 | L44: {=SAFEDIV(F44,D44)} -> 79.167776 | M44: {=SAFEDIV(I44,G44)} -> 79.277948 | N44: =J44-L44 -> 16.806609 | O44: {=SAFEDIV(G44,G$59)-SAFEDIV(D44,D$59)} -> 0.010646712 | P44: =(G44-D44)*N$59 -> 114242.66 | Q44: =(G44-D44)*(N44-N$59) -> -64764.003 | R44: =G44*(K44-J44) -> 4646.3122 | S44: =-G44*(M44-L44) -> -2258.1978 | T44: =SUM(P44:S44) -> 51866.77 | U44: =(H44-I44)-(E44-F44) -> 51866.77 | V44: =T44-U44 -> -3.0559022e-10 | W44: {=INDEX({"Volume","Mix","Price","Unit cost"},_xlfn.XMATCH(MAX(ABS(P44:S44)),ABS(P44:S44)))} -> Volume
B45: Poultry | C45: Hotels & Institutions | D45: =SUMIFS(tbl_Budget[units],tbl_Budget[category],$B45,tbl_Budget[channel],$C45,tbl_Budget[month],">="&FYStart,tbl_Budget[month],"<="&AsOfMonth) -> 10542 | E45: =SUMIFS(tbl_Budget[revenue],tbl_Budget[category],$B45,tbl_Budget[channel],$C45,tbl_Budget[month],">="&FYStart,tbl_Budget[month],"<="&AsOfMonth) -> 1105753.3 | F45: =SUMIFS(tbl_Budget[cogs],tbl_Budget[category],$B45,tbl_Budget[channel],$C45,tbl_Budget[month],">="&FYStart,tbl_Budget[month],"<="&AsOfMonth) -> 834779.79 | G45: =SUMIFS(tbl_Sales[units],tbl_Sales[category],$B45,tbl_Sales[channel],$C45,tbl_Sales[month],">="&FYStart,tbl_Sales[month],"<="&AsOfMonth) -> 10507 | H45: =SUMIFS(tbl_Sales[net_revenue],tbl_Sales[category],$B45,tbl_Sales[channel],$C45,tbl_Sales[month],">="&FYStart,tbl_Sales[month],"<="&AsOfMonth) -> 1101898.3 | I45: =SUMIFS(tbl_Sales[cogs],tbl_Sales[category],$B45,tbl_Sales[channel],$C45,tbl_Sales[month],">="&FYStart,tbl_Sales[month],"<="&AsOfMonth) -> 830900.24 | J45: {=SAFEDIV(E45,D45)} -> 104.89027 | K45: {=SAFEDIV(H45,G45)} -> 104.87278 | L45: {=SAFEDIV(F45,D45)} -> 79.186093 | M45: {=SAFEDIV(I45,G45)} -> 79.080636 | N45: =J45-L45 -> 25.70418 | O45: {=SAFEDIV(G45,G$59)-SAFEDIV(D45,D$59)} -> -0.0018767847 | P45: =(G45-D45)*N$59 -> -1358.1838 | Q45: =(G45-D45)*(N45-N$59) -> 458.53747 | R45: =G45*(K45-J45) -> -183.78044 | S45: =-G45*(M45-L45) -> 1108.0368 | T45: =SUM(P45:S45) -> 24.61 | U45: =(H45-I45)-(E45-F45) -> 24.61 | V45: =T45-U45 -> 4.9794835e-11 | W45: {=INDEX({"Volume","Mix","Price","Unit cost"},_xlfn.XMATCH(MAX(ABS(P45:S45)),ABS(P45:S45)))} -> Volume
B46: Poultry | C46: Online Direct | D46: =SUMIFS(tbl_Budget[units],tbl_Budget[category],$B46,tbl_Budget[channel],$C46,tbl_Budget[month],">="&FYStart,tbl_Budget[month],"<="&AsOfMonth) -> 4667 | E46: =SUMIFS(tbl_Budget[revenue],tbl_Budget[category],$B46,tbl_Budget[channel],$C46,tbl_Budget[month],">="&FYStart,tbl_Budget[month],"<="&AsOfMonth) -> 578308.59 | F46: =SUMIFS(tbl_Budget[cogs],tbl_Budget[category],$B46,tbl_Budget[channel],$C46,tbl_Budget[month],">="&FYStart,tbl_Budget[month],"<="&AsOfMonth) -> 369625.39 | G46: =SUMIFS(tbl_Sales[units],tbl_Sales[category],$B46,tbl_Sales[channel],$C46,tbl_Sales[month],">="&FYStart,tbl_Sales[month],"<="&AsOfMonth) -> 4666 | H46: =SUMIFS(tbl_Sales[net_revenue],tbl_Sales[category],$B46,tbl_Sales[channel],$C46,tbl_Sales[month],">="&FYStart,tbl_Sales[month],"<="&AsOfMonth) -> 577179.38 | I46: =SUMIFS(tbl_Sales[cogs],tbl_Sales[category],$B46,tbl_Sales[channel],$C46,tbl_Sales[month],">="&FYStart,tbl_Sales[month],"<="&AsOfMonth) -> 369265.99 | J46: {=SAFEDIV(E46,D46)} -> 123.91442 | K46: {=SAFEDIV(H46,G46)} -> 123.69897 | L46: {=SAFEDIV(F46,D46)} -> 79.199784 | M46: {=SAFEDIV(I46,G46)} -> 79.139732 | N46: =J46-L46 -> 44.714635 | O46: {=SAFEDIV(G46,G$59)-SAFEDIV(D46,D$59)} -> -0.00076437447 | P46: =(G46-D46)*N$59 -> -38.805251 | Q46: =(G46-D46)*(N46-N$59) -> -5.9093837 | R46: =G46*(K46-J46) -> -1005.2956 | S46: =-G46*(M46-L46) -> 280.20022 | T46: =SUM(P46:S46) -> -769.81 | U46: =(H46-I46)-(E46-F46) -> -769.81 | V46: =T46-U46 -> 8.0717655e-12 | W46: {=INDEX({"Volume","Mix","Price","Unit cost"},_xlfn.XMATCH(MAX(ABS(P46:S46)),ABS(P46:S46)))} -> Price
... B58: Cheese & Dairy | C58: Online Direct | D58: =SUMIFS(tbl_Budget[units],tbl_Budget[category],$B58,tbl_Budget[channel],$C58,tbl_Budget[month],">="&FYStart,tbl_Budget[month],"<="&AsOfMonth) -> 1887 | E58: =SUMIFS(tbl_Budget[revenue],tbl_Budget[category],$B58,tbl_Budget[channel],$C58,tbl_Budget[month],">="&FYStart,tbl_Budget[month],"<="&AsOfMonth) -> 288770.31 | F58: =SUMIFS(tbl_Budget[cogs],tbl_Budget[category],$B58,tbl_Budget[channel],$C58,tbl_Budget[month],">="&FYStart,tbl_Budget[month],"<="&AsOfMonth) -> 159072.83 | G58: =SUMIFS(tbl_Sales[units],tbl_Sales[category],$B58,tbl_Sales[channel],$C58,tbl_Sales[month],">="&FYStart,tbl_Sales[month],"<="&AsOfMonth) -> 1788 | H58: =SUMIFS(tbl_Sales[net_revenue],tbl_Sales[category],$B58,tbl_Sales[channel],$C58,tbl_Sales[month],">="&FYStart,tbl_Sales[month],"<="&AsOfMonth) -> 273813.31 | I58: =SUMIFS(tbl_Sales[cogs],tbl_Sales[category],$B58,tbl_Sales[channel],$C58,tbl_Sales[month],">="&FYStart,tbl_Sales[month],"<="&AsOfMonth) -> 150990.23 | J58: {=SAFEDIV(E58,D58)} -> 153.03143 | K58: {=SAFEDIV(H58,G58)} -> 153.13944 | L58: {=SAFEDIV(F58,D58)} -> 84.299327 | M58: {=SAFEDIV(I58,G58)} -> 84.446437 | N58: =J58-L58 -> 68.732104 | O58: {=SAFEDIV(G58,G$59)-SAFEDIV(D58,D$59)} -> -0.00076132363 | P58: =(G58-D58)*N$59 -> -3841.7198 | Q58: =(G58-D58)*(N58-N$59) -> -2962.7584 | R58: =G58*(K58-J58) -> 193.11165 | S58: =-G58*(M58-L58) -> -263.03337 | T58: =SUM(P58:S58) -> -6874.4 | U58: =(H58-I58)-(E58-F58) -> -6874.4 | V58: =T58-U58 -> 0 | W58: {=INDEX({"Volume","Mix","Price","Unit cost"},_xlfn.XMATCH(MAX(ABS(P58:S58)),ABS(P58:S58)))} -> Volume
B59: All segments | D59: =SUM(D35:D58) -> 210532 | E59: =SUM(E35:E58) -> 30423381 | F59: =SUM(F35:F58) -> 22253634 | G59: =SUM(G35:G58) -> 218004 | H59: =SUM(H35:H58) -> 31533631 | I59: =SUM(I35:I58) -> 23381163 | J59: {=SAFEDIV(E59,D59)} -> 144.50716 | K59: {=SAFEDIV(H59,G59)} -> 144.64703 | L59: {=SAFEDIV(F59,D59)} -> 105.70191 | M59: {=SAFEDIV(I59,G59)} -> 107.25107 | N59: =J59-L59 -> 38.805251 | O59: =SUM(O35:O58) -> 1.2143064e-17 | P59: =SUM(P35:P58) -> 289952.84 | Q59: =SUM(Q35:Q58) -> -173287.14 | R59: =SUM(R35:R58) -> 238025.89 | S59: =SUM(S35:S58) -> -371970.8 | T59: =SUM(P59:S59) -> -17279.22 | U59: =(H59-I59)-(E59-F59) -> -17279.22 | V59: =T59-U59 -> -9.95351e-09 | W59: {=INDEX({"Volume","Mix","Price","Unit cost"},_xlfn.XMATCH(MAX(ABS(P59:S59)),ABS(P59:S59)))} -> Unit cost
B62: YTD gross-margin bridge by category
B63: Category | C63: Volume | D63: Mix | E63: Price | F63: Unit cost | G63: Effects, total | H63: Budget GM | I63: Actual GM | J63: GM vs budget
B64: Beef | C64: =SUMIFS(P$35:P$58,$B$35:$B$58,$B64) -> 40085.824 | D64: =SUMIFS(Q$35:Q$58,$B$35:$B$58,$B64) -> -41929.15 | E64: =SUMIFS(R$35:R$58,$B$35:$B$58,$B64) -> 92468.853 | F64: =SUMIFS(S$35:S$58,$B$35:$B$58,$B64) -> -368914.72 | G64: =SUM(C64:F64) -> -278289.19 | H64: =SUMIFS($E$35:$E$58,$B$35:$B$58,$B64)-SUMIFS($F$35:$F$58,$B$35:$B$58,$B64) -> 2120199.4 | I64: =SUMIFS($H$35:$H$58,$B$35:$B$58,$B64)-SUMIFS($I$35:$I$58,$B$35:$B$58,$B64) -> 1841910.2 | J64: {=SAFEDIV(I64-H64,ABS(H64))} -> -0.13125614
B65: Pork | C65: =SUMIFS(P$35:P$58,$B$35:$B$58,$B65) -> 83741.732 | D65: =SUMIFS(Q$35:Q$58,$B$35:$B$58,$B65) -> -38130.102 | E65: =SUMIFS(R$35:R$58,$B$35:$B$58,$B65) -> -652.99818 | F65: =SUMIFS(S$35:S$58,$B$35:$B$58,$B65) -> 603.87856 | G65: =SUM(C65:F65) -> 45562.51 | H65: =SUMIFS($E$35:$E$58,$B$35:$B$58,$B65)-SUMIFS($F$35:$F$58,$B$35:$B$58,$B65) -> 1365177.8 | I65: =SUMIFS($H$35:$H$58,$B$35:$B$58,$B65)-SUMIFS($I$35:$I$58,$B$35:$B$58,$B65) -> 1410740.3 | J65: {=SAFEDIV(I65-H65,ABS(H65))} -> 0.033374781
B66: Poultry | C66: =SUMIFS(P$35:P$58,$B$35:$B$58,$B66) -> 108344.26 | D66: =SUMIFS(Q$35:Q$58,$B$35:$B$58,$B66) -> -63445.249 | E66: =SUMIFS(R$35:R$58,$B$35:$B$58,$B66) -> 3559.207 | F66: =SUMIFS(S$35:S$58,$B$35:$B$58,$B66) -> -2873.6493 | G66: =SUM(C66:F66) -> 45584.57 | H66: =SUMIFS($E$35:$E$58,$B$35:$B$58,$B66)-SUMIFS($F$35:$F$58,$B$35:$B$58,$B66) -> 1585581.8 | I66: =SUMIFS($H$35:$H$58,$B$35:$B$58,$B66)-SUMIFS($I$35:$I$58,$B$35:$B$58,$B66) -> 1631166.3 | J66: {=SAFEDIV(I66-H66,ABS(H66))} -> 0.028749429
B67: Seafood | C67: =SUMIFS(P$35:P$58,$B$35:$B$58,$B67) -> 35856.052 | D67: =SUMIFS(Q$35:Q$58,$B$35:$B$58,$B67) -> -18326.646 | E67: =SUMIFS(R$35:R$58,$B$35:$B$58,$B67) -> 137156.28 | F67: =SUMIFS(S$35:S$58,$B$35:$B$58,$B67) -> -1630.1055 | G67: =SUM(C67:F67) -> 153055.58 | H67: =SUMIFS($E$35:$E$58,$B$35:$B$58,$B67)-SUMIFS($F$35:$F$58,$B$35:$B$58,$B67) -> 946584.6 | I67: =SUMIFS($H$35:$H$58,$B$35:$B$58,$B67)-SUMIFS($I$35:$I$58,$B$35:$B$58,$B67) -> 1099640.2 | J67: {=SAFEDIV(I67-H67,ABS(H67))} -> 0.16169245
B68: Charcuterie | C68: =SUMIFS(P$35:P$58,$B$35:$B$58,$B68) -> 24447.308 | D68: =SUMIFS(Q$35:Q$58,$B$35:$B$58,$B68) -> 3771.9399 | E68: =SUMIFS(R$35:R$58,$B$35:$B$58,$B68) -> 3446.8365 | F68: =SUMIFS(S$35:S$58,$B$35:$B$58,$B68) -> -119.15448 | G68: =SUM(C68:F68) -> 31546.93 | H68: =SUMIFS($E$35:$E$58,$B$35:$B$58,$B68)-SUMIFS($F$35:$F$58,$B$35:$B$58,$B68) -> 1040113.9 | I68: =SUMIFS($H$35:$H$58,$B$35:$B$58,$B68)-SUMIFS($I$35:$I$58,$B$35:$B$58,$B68) -> 1071660.8 | J68: {=SAFEDIV(I68-H68,ABS(H68))} -> 0.030330265
B69: Cheese & Dairy | C69: =SUMIFS(P$35:P$58,$B$35:$B$58,$B69) -> -2522.3413 | D69: =SUMIFS(Q$35:Q$58,$B$35:$B$58,$B69) -> -15227.936 | E69: =SUMIFS(R$35:R$58,$B$35:$B$58,$B69) -> 2047.711 | F69: =SUMIFS(S$35:S$58,$B$35:$B$58,$B69) -> 962.94624 | G69: =SUM(C69:F69) -> -14739.62 | H69: =SUMIFS($E$35:$E$58,$B$35:$B$58,$B69)-SUMIFS($F$35:$F$58,$B$35:$B$58,$B69) -> 1112089.6 | I69: =SUMIFS($H$35:$H$58,$B$35:$B$58,$B69)-SUMIFS($I$35:$I$58,$B$35:$B$58,$B69) -> 1097350 | J69: {=SAFEDIV(I69-H69,ABS(H69))} -> -0.013253986
B70: Total | C70: =SUM(C64:C69) -> 289952.84 | D70: =SUM(D64:D69) -> -173287.14 | E70: =SUM(E64:E69) -> 238025.89 | F70: =SUM(F64:F69) -> -371970.8 | G70: =SUM(C70:F70) -> -17279.22 | H70: =SUM(H64:H69) -> 8169747.1 | I70: =SUM(I64:I69) -> 8152467.9 | J70: {=SAFEDIV(I70-H70,ABS(H70))} -> -0.0021150251
B73: YTD gross-margin bridge by channel
B74: Channel | C74: Volume | D74: Mix | E74: Price | F74: Unit cost | G74: Effects, total | H74: Budget GM | I74: Actual GM | J74: GM vs budget
B75: Restaurants | C75: =SUMIFS(P$35:P$58,$C$35:$C$58,$B75) -> -60264.555 | D75: =SUMIFS(Q$35:Q$58,$C$35:$C$58,$B75) -> -18899.721 | E75: =SUMIFS(R$35:R$58,$C$35:$C$58,$B75) -> 92226.806 | F75: =SUMIFS(S$35:S$58,$C$35:$C$58,$B75) -> -153861.64 | G75: =SUM(C75:F75) -> -140799.11 | H75: =SUMIFS($E$35:$E$58,$C$35:$C$58,$B75)-SUMIFS($F$35:$F$58,$C$35:$C$58,$B75) -> 4140177.1 | I75: =SUMIFS($H$35:$H$58,$C$35:$C$58,$B75)-SUMIFS($I$35:$I$58,$C$35:$C$58,$B75) -> 3999378 | J75: {=SAFEDIV(I75-H75,ABS(H75))} -> -0.034007992
B76: Grocery Retail | C76: =SUMIFS(P$35:P$58,$C$35:$C$58,$B76) -> 385142.12 | D76: =SUMIFS(Q$35:Q$58,$C$35:$C$58,$B76) -> -143753.2 | E76: =SUMIFS(R$35:R$58,$C$35:$C$58,$B76) -> 80161.636 | F76: =SUMIFS(S$35:S$58,$C$35:$C$58,$B76) -> -121669.28 | G76: =SUM(C76:F76) -> 199881.27 | H76: =SUMIFS($E$35:$E$58,$C$35:$C$58,$B76)-SUMIFS($F$35:$F$58,$C$35:$C$58,$B76) -> 1571695.7 | I76: =SUMIFS($H$35:$H$58,$C$35:$C$58,$B76)-SUMIFS($I$35:$I$58,$C$35:$C$58,$B76) -> 1771577 | J76: {=SAFEDIV(I76-H76,ABS(H76))} -> 0.12717555
B77: Hotels & Institutions | C77: =SUMIFS(P$35:P$58,$C$35:$C$58,$B77) -> -25339.829 | D77: =SUMIFS(Q$35:Q$58,$C$35:$C$58,$B77) -> -2538.439 | E77: =SUMIFS(R$35:R$58,$C$35:$C$58,$B77) -> 42544.975 | F77: =SUMIFS(S$35:S$58,$C$35:$C$58,$B77) -> -64036.157 | G77: =SUM(C77:F77) -> -49369.45 | H77: =SUMIFS($E$35:$E$58,$C$35:$C$58,$B77)-SUMIFS($F$35:$F$58,$C$35:$C$58,$B77) -> 1405293.7 | I77: =SUMIFS($H$35:$H$58,$C$35:$C$58,$B77)-SUMIFS($I$35:$I$58,$C$35:$C$58,$B77) -> 1355924.2 | J77: {=SAFEDIV(I77-H77,ABS(H77))} -> -0.035131055
B78: Online Direct | C78: =SUMIFS(P$35:P$58,$C$35:$C$58,$B78) -> -9584.897 | D78: =SUMIFS(Q$35:Q$58,$C$35:$C$58,$B78) -> -8095.7839 | E78: =SUMIFS(R$35:R$58,$C$35:$C$58,$B78) -> 23092.471 | F78: =SUMIFS(S$35:S$58,$C$35:$C$58,$B78) -> -32403.72 | G78: =SUM(C78:F78) -> -26991.93 | H78: =SUMIFS($E$35:$E$58,$C$35:$C$58,$B78)-SUMIFS($F$35:$F$58,$C$35:$C$58,$B78) -> 1052580.6 | I78: =SUMIFS($H$35:$H$58,$C$35:$C$58,$B78)-SUMIFS($I$35:$I$58,$C$35:$C$58,$B78) -> 1025588.7 | J78: {=SAFEDIV(I78-H78,ABS(H78))} -> -0.025643576
B79: Total | C79: =SUM(C75:C78) -> 289952.84 | D79: =SUM(D75:D78) -> -173287.14 | E79: =SUM(E75:E78) -> 238025.89 | F79: =SUM(F75:F78) -> -371970.8 | G79: =SUM(C79:F79) -> -17279.22 | H79: =SUM(H75:H78) -> 8169747.1 | I79: =SUM(I75:I78) -> 8152467.9 | J79: {=SAFEDIV(I79-H79,ABS(H79))} -> -0.0021150251
B82: Year-to-date bridges
B83: Gross margin | C83: $ | E83: EBITDA | F83: $
B84: Budget gross margin | C84: =E59-F59 -> 8169747.1 | E84: Budget EBITDA | F84: =PnL!X19 -> 1757686.4
B85: Volume | C85: =P59 -> 289952.84 | E85: Volume | F85: =P59 -> 289952.84
B86: Mix | C86: =Q59 -> -173287.14 | E86: Mix | F86: =Q59 -> -173287.14
B87: Price | C87: =R59 -> 238025.89 | E87: Price | F87: =R59 -> 238025.89
B88: Unit cost | C88: =S59 -> -371970.8 | E88: Unit cost | F88: =S59 -> -371970.8
B89: Actual gross margin | C89: =H59-I59 -> 8152467.9 | E89: Freight | F89: =PnL!Y12 -> -36270.05
E90: Operating expenses | F90: =PnL!Y18 -> -178186.57
E91: Actual EBITDA | F91: =PnL!W19 -> 1525950.5
B93: Bridge closes (zero) | C93: =C84+SUM(C85:C88)-C89 -> -1.0244548e-08 | E93: Bridge closes (zero) | F93: =F84+SUM(F85:F90)-F91 -> -8.3819032e-09

Sheet Forecast
B1: Rolling forecast by driver
B2: ="Actuals through "&TEXT(AsOfMonth,"mmmm yyyy")&"; the other "&(12-MonthsClosed)&" months are forecast from drivers. Scenario: "&ScenarioName&"." -> Actuals through August 2026; the other 4 months are forecast from drivers. Scenario: Base.
B4: Forecast basis by category: year-to-date run-rate and trailing unit economics
B5: Category | C5: YTD cases | D5: YTD budget cases | E5: Volume run-rate | F5: Trailing cases | G5: Trailing revenue | H5: Trailing COGS | I5: Trailing freight | J5: Price per case | K5: Cost per case | L5: Freight per case | M5: Margin per case, live drivers
B6: Beef | C6: =SUMIFS(tbl_Sales[units],tbl_Sales[category],$B6,tbl_Sales[month],">="&FYStart,tbl_Sales[month],"<="&AsOfMonth) -> 49644 | D6: =SUMIFS(tbl_Budget[units],tbl_Budget[category],$B6,tbl_Budget[month],">="&FYStart,tbl_Budget[month],"<="&AsOfMonth) -> 48611 | E6: {=SAFEDIV(C6,D6)} -> 1.0212503 | F6: =SUMIFS(tbl_Sales[units],tbl_Sales[category],$B6,tbl_Sales[month],">="&TrailStart,tbl_Sales[month],"<="&AsOfMonth) -> 21428 | G6: =SUMIFS(tbl_Sales[net_revenue],tbl_Sales[category],$B6,tbl_Sales[month],">="&TrailStart,tbl_Sales[month],"<="&AsOfMonth) -> 4076552 | H6: =SUMIFS(tbl_Sales[cogs],tbl_Sales[category],$B6,tbl_Sales[month],">="&TrailStart,tbl_Sales[month],"<="&AsOfMonth) -> 3337254.3 | I6: =SUMIFS(tbl_Sales[freight],tbl_Sales[category],$B6,tbl_Sales[month],">="&TrailStart,tbl_Sales[month],"<="&AsOfMonth) -> 70709.79 | J6: {=SAFEDIV(G6,$F6)} -> 190.24416 | K6: {=SAFEDIV(H6,$F6)} -> 155.74269 | L6: {=SAFEDIV(I6,$F6)} -> 3.2998782 | M6: =J6*(1+sel_price)-K6*(1+sel_cost)-L6*(1+sel_freight) -> 31.201599
B7: Pork | C7: =SUMIFS(tbl_Sales[units],tbl_Sales[category],$B7,tbl_Sales[month],">="&FYStart,tbl_Sales[month],"<="&AsOfMonth) -> 43450 | D7: =SUMIFS(tbl_Budget[units],tbl_Budget[category],$B7,tbl_Budget[month],">="&FYStart,tbl_Budget[month],"<="&AsOfMonth) -> 41292 | E7: {=SAFEDIV(C7,D7)} -> 1.0522619 | F7: =SUMIFS(tbl_Sales[units],tbl_Sales[category],$B7,tbl_Sales[month],">="&TrailStart,tbl_Sales[month],"<="&AsOfMonth) -> 17278 | G7: =SUMIFS(tbl_Sales[net_revenue],tbl_Sales[category],$B7,tbl_Sales[month],">="&TrailStart,tbl_Sales[month],"<="&AsOfMonth) -> 2059228.6 | H7: =SUMIFS(tbl_Sales[cogs],tbl_Sales[category],$B7,tbl_Sales[month],">="&TrailStart,tbl_Sales[month],"<="&AsOfMonth) -> 1503446.9 | I7: =SUMIFS(tbl_Sales[freight],tbl_Sales[category],$B7,tbl_Sales[month],">="&TrailStart,tbl_Sales[month],"<="&AsOfMonth) -> 56772.61 | J7: {=SAFEDIV(G7,$F7)} -> 119.18211 | K7: {=SAFEDIV(H7,$F7)} -> 87.015099 | L7: {=SAFEDIV(I7,$F7)} -> 3.2858323 | M7: =J7*(1+sel_price)-K7*(1+sel_cost)-L7*(1+sel_freight) -> 28.881184
B8: Poultry | C8: =SUMIFS(tbl_Sales[units],tbl_Sales[category],$B8,tbl_Sales[month],">="&FYStart,tbl_Sales[month],"<="&AsOfMonth) -> 61430 | D8: =SUMIFS(tbl_Budget[units],tbl_Budget[category],$B8,tbl_Budget[month],">="&FYStart,tbl_Budget[month],"<="&AsOfMonth) -> 58638 | E8: {=SAFEDIV(C8,D8)} -> 1.0476142 | F8: =SUMIFS(tbl_Sales[units],tbl_Sales[category],$B8,tbl_Sales[month],">="&TrailStart,tbl_Sales[month],"<="&AsOfMonth) -> 23646 | G8: =SUMIFS(tbl_Sales[net_revenue],tbl_Sales[category],$B8,tbl_Sales[month],">="&TrailStart,tbl_Sales[month],"<="&AsOfMonth) -> 2497557.6 | H8: =SUMIFS(tbl_Sales[cogs],tbl_Sales[category],$B8,tbl_Sales[month],">="&TrailStart,tbl_Sales[month],"<="&AsOfMonth) -> 1872935.5 | I8: =SUMIFS(tbl_Sales[freight],tbl_Sales[category],$B8,tbl_Sales[month],">="&TrailStart,tbl_Sales[month],"<="&AsOfMonth) -> 78113.31 | J8: {=SAFEDIV(G8,$F8)} -> 105.62284 | K8: {=SAFEDIV(H8,$F8)} -> 79.207286 | L8: {=SAFEDIV(I8,$F8)} -> 3.3034471 | M8: =J8*(1+sel_price)-K8*(1+sel_cost)-L8*(1+sel_freight) -> 23.112102
B9: Seafood | C9: =SUMIFS(tbl_Sales[units],tbl_Sales[category],$B9,tbl_Sales[month],">="&FYStart,tbl_Sales[month],"<="&AsOfMonth) -> 23025 | D9: =SUMIFS(tbl_Budget[units],tbl_Budget[category],$B9,tbl_Budget[month],">="&FYStart,tbl_Budget[month],"<="&AsOfMonth) -> 22101 | E9: {=SAFEDIV(C9,D9)} -> 1.0418081 | F9: =SUMIFS(tbl_Sales[units],tbl_Sales[category],$B9,tbl_Sales[month],">="&TrailStart,tbl_Sales[month],"<="&AsOfMonth) -> 9961 | G9: =SUMIFS(tbl_Sales[net_revenue],tbl_Sales[category],$B9,tbl_Sales[month],">="&TrailStart,tbl_Sales[month],"<="&AsOfMonth) -> 1986570.3 | H9: =SUMIFS(tbl_Sales[cogs],tbl_Sales[category],$B9,tbl_Sales[month],">="&TrailStart,tbl_Sales[month],"<="&AsOfMonth) -> 1511204.1 | I9: =SUMIFS(tbl_Sales[freight],tbl_Sales[category],$B9,tbl_Sales[month],">="&TrailStart,tbl_Sales[month],"<="&AsOfMonth) -> 32828.33 | J9: {=SAFEDIV(G9,$F9)} -> 199.43483 | K9: {=SAFEDIV(H9,$F9)} -> 151.71208 | L9: {=SAFEDIV(I9,$F9)} -> 3.2956862 | M9: =J9*(1+sel_price)-K9*(1+sel_cost)-L9*(1+sel_freight) -> 44.427057
B10: Charcuterie | C10: =SUMIFS(tbl_Sales[units],tbl_Sales[category],$B10,tbl_Sales[month],">="&FYStart,tbl_Sales[month],"<="&AsOfMonth) -> 16777 | D10: =SUMIFS(tbl_Budget[units],tbl_Budget[category],$B10,tbl_Budget[month],">="&FYStart,tbl_Budget[month],"<="&AsOfMonth) -> 16147 | E10: {=SAFEDIV(C10,D10)} -> 1.0390165 | F10: =SUMIFS(tbl_Sales[units],tbl_Sales[category],$B10,tbl_Sales[month],">="&TrailStart,tbl_Sales[month],"<="&AsOfMonth) -> 6526 | G10: =SUMIFS(tbl_Sales[net_revenue],tbl_Sales[category],$B10,tbl_Sales[month],">="&TrailStart,tbl_Sales[month],"<="&AsOfMonth) -> 1049823.5 | H10: =SUMIFS(tbl_Sales[cogs],tbl_Sales[category],$B10,tbl_Sales[month],">="&TrailStart,tbl_Sales[month],"<="&AsOfMonth) -> 633792.78 | I10: =SUMIFS(tbl_Sales[freight],tbl_Sales[category],$B10,tbl_Sales[month],">="&TrailStart,tbl_Sales[month],"<="&AsOfMonth) -> 21591.45 | J10: {=SAFEDIV(G10,$F10)} -> 160.86784 | K10: {=SAFEDIV(H10,$F10)} -> 97.118109 | L10: {=SAFEDIV(I10,$F10)} -> 3.3085274 | M10: =J10*(1+sel_price)-K10*(1+sel_cost)-L10*(1+sel_freight) -> 60.441207
B11: Cheese & Dairy | C11: =SUMIFS(tbl_Sales[units],tbl_Sales[category],$B11,tbl_Sales[month],">="&FYStart,tbl_Sales[month],"<="&AsOfMonth) -> 23678 | D11: =SUMIFS(tbl_Budget[units],tbl_Budget[category],$B11,tbl_Budget[month],">="&FYStart,tbl_Budget[month],"<="&AsOfMonth) -> 23743 | E11: {=SAFEDIV(C11,D11)} -> 0.99726235 | F11: =SUMIFS(tbl_Sales[units],tbl_Sales[category],$B11,tbl_Sales[month],">="&TrailStart,tbl_Sales[month],"<="&AsOfMonth) -> 9006 | G11: =SUMIFS(tbl_Sales[net_revenue],tbl_Sales[category],$B11,tbl_Sales[month],">="&TrailStart,tbl_Sales[month],"<="&AsOfMonth) -> 1178374.7 | H11: =SUMIFS(tbl_Sales[cogs],tbl_Sales[category],$B11,tbl_Sales[month],">="&TrailStart,tbl_Sales[month],"<="&AsOfMonth) -> 760237.34 | I11: =SUMIFS(tbl_Sales[freight],tbl_Sales[category],$B11,tbl_Sales[month],">="&TrailStart,tbl_Sales[month],"<="&AsOfMonth) -> 29716.25 | J11: {=SAFEDIV(G11,$F11)} -> 130.8433 | K11: {=SAFEDIV(H11,$F11)} -> 84.414539 | L11: {=SAFEDIV(I11,$F11)} -> 3.2996058 | M11: =J11*(1+sel_price)-K11*(1+sel_cost)-L11*(1+sel_freight) -> 43.129153
B12: All categories | C12: =SUM(C6:C11) -> 218004 | D12: =SUM(D6:D11) -> 210532 | E12: {=SAFEDIV(C12,D12)} -> 1.035491 | F12: =SUM(F6:F11) -> 87845 | G12: =SUM(G6:G11) -> 12848107 | H12: =SUM(H6:H11) -> 9618870.9 | I12: =SUM(I6:I11) -> 289731.74 | J12: {=SAFEDIV(G12,$F12)} -> 146.25883 | K12: {=SAFEDIV(H12,$F12)} -> 109.49822 | L12: {=SAFEDIV(I12,$F12)} -> 3.2982155 | M12: =J12*(1+sel_price)-K12*(1+sel_cost)-L12*(1+sel_freight) -> 33.462395
B14: Operating expense run-rate by department
B15: Department | C15: YTD actual | D15: YTD budget | E15: Run-rate
B16: Sales & Marketing | C16: =SUMIFS(tbl_Opex[amount],tbl_Opex[dept],$B16,tbl_Opex[scenario],"Actual",tbl_Opex[month],">="&FYStart,tbl_Opex[month],"<="&AsOfMonth) -> 1583082.2 | D16: =SUMIFS(tbl_Opex[amount],tbl_Opex[dept],$B16,tbl_Opex[scenario],"Budget",tbl_Opex[month],">="&FYStart,tbl_Opex[month],"<="&AsOfMonth) -> 1612971.1 | E16: {=SAFEDIV(C16,D16)} -> 0.98146966
B17: Warehouse & Logistics | C17: =SUMIFS(tbl_Opex[amount],tbl_Opex[dept],$B17,tbl_Opex[scenario],"Actual",tbl_Opex[month],">="&FYStart,tbl_Opex[month],"<="&AsOfMonth) -> 2387972.2 | D17: =SUMIFS(tbl_Opex[amount],tbl_Opex[dept],$B17,tbl_Opex[scenario],"Budget",tbl_Opex[month],">="&FYStart,tbl_Opex[month],"<="&AsOfMonth) -> 2207917.4 | E17: {=SAFEDIV(C17,D17)} -> 1.0815496
B18: General & Admin | C18: =SUMIFS(tbl_Opex[amount],tbl_Opex[dept],$B18,tbl_Opex[scenario],"Actual",tbl_Opex[month],">="&FYStart,tbl_Opex[month],"<="&AsOfMonth) -> 1468910.3 | D18: =SUMIFS(tbl_Opex[amount],tbl_Opex[dept],$B18,tbl_Opex[scenario],"Budget",tbl_Opex[month],">="&FYStart,tbl_Opex[month],"<="&AsOfMonth) -> 1440539.5 | E18: {=SAFEDIV(C18,D18)} -> 1.0196945
B19: Technology | C19: =SUMIFS(tbl_Opex[amount],tbl_Opex[dept],$B19,tbl_Opex[scenario],"Actual",tbl_Opex[month],">="&FYStart,tbl_Opex[month],"<="&AsOfMonth) -> 465862.39 | D19: =SUMIFS(tbl_Opex[amount],tbl_Opex[dept],$B19,tbl_Opex[scenario],"Budget",tbl_Opex[month],">="&FYStart,tbl_Opex[month],"<="&AsOfMonth) -> 466212.48 | E19: {=SAFEDIV(C19,D19)} -> 0.99924908
B20: All departments | C20: =SUM(C16:C19) -> 5905827 | D20: =SUM(D16:D19) -> 5727640.5 | E20: {=SAFEDIV(C20,D20)} -> 1.0311099
B21: Monthly forecast, category by month. Closed months are zero here: the P&L uses actuals for them
B23: Month | D23: =FYStart -> 46023 | E23: =EDATE(D23,1) -> 46054 | F23: =EDATE(E23,1) -> 46082 | G23: =EDATE(F23,1) -> 46113 | H23: =EDATE(G23,1) -> 46143 | I23: =EDATE(H23,1) -> 46174 | J23: =EDATE(I23,1) -> 46204 | K23: =EDATE(J23,1) -> 46235 | L23: =EDATE(K23,1) -> 46266 | ... O23: =EDATE(N23,1) -> 46357 | P23: Full year
D24: {=IF(ISCLOSED(D$23),"Actual","Forecast")} -> Actual | E24: {=IF(ISCLOSED(E$23),"Actual","Forecast")} -> Actual | F24: {=IF(ISCLOSED(F$23),"Actual","Forecast")} -> Actual | G24: {=IF(ISCLOSED(G$23),"Actual","Forecast")} -> Actual | H24: {=IF(ISCLOSED(H$23),"Actual","Forecast")} -> Actual | I24: {=IF(ISCLOSED(I$23),"Actual","Forecast")} -> Actual | J24: {=IF(ISCLOSED(J$23),"Actual","Forecast")} -> Actual | K24: {=IF(ISCLOSED(K$23),"Actual","Forecast")} -> Actual | ... O24: {=IF(ISCLOSED(O$23),"Actual","Forecast")} -> Forecast
B26: Baseline cases: budget cases × the category's YTD volume run-rate
B27: =$B6 -> Beef | D27: {=IF(ISCLOSED(D$23),0,SUMIFS(tbl_Budget[units],tbl_Budget[category],$B27,tbl_Budget[month],D$23)*_xlfn.XLOOKUP($B27,$B$6:$B$11,$E$6:$E$11))} -> 0 | E27: {=IF(ISCLOSED(E$23),0,SUMIFS(tbl_Budget[units],tbl_Budget[category],$B27,tbl_Budget[month],E$23)*_xlfn.XLOOKUP($B27,$B$6:$B$11,$E$6:$E$11))} -> 0 | F27: {=IF(ISCLOSED(F$23),0,SUMIFS(tbl_Budget[units],tbl_Budget[category],$B27,tbl_Budget[month],F$23)*_xlfn.XLOOKUP($B27,$B$6:$B$11,$E$6:$E$11))} -> 0 | G27: {=IF(ISCLOSED(G$23),0,SUMIFS(tbl_Budget[units],tbl_Budget[category],$B27,tbl_Budget[month],G$23)*_xlfn.XLOOKUP($B27,$B$6:$B$11,$E$6:$E$11))} -> 0 | H27: {=IF(ISCLOSED(H$23),0,SUMIFS(tbl_Budget[units],tbl_Budget[category],$B27,tbl_Budget[month],H$23)*_xlfn.XLOOKUP($B27,$B$6:$B$11,$E$6:$E$11))} -> 0 | I27: {=IF(ISCLOSED(I$23),0,SUMIFS(tbl_Budget[units],tbl_Budget[category],$B27,tbl_Budget[month],I$23)*_xlfn.XLOOKUP($B27,$B$6:$B$11,$E$6:$E$11))} -> 0 | J27: {=IF(ISCLOSED(J$23),0,SUMIFS(tbl_Budget[units],tbl_Budget[category],$B27,tbl_Budget[month],J$23)*_xlfn.XLOOKUP($B27,$B$6:$B$11,$E$6:$E$11))} -> 0 | K27: {=IF(ISCLOSED(K$23),0,SUMIFS(tbl_Budget[units],tbl_Budget[category],$B27,tbl_Budget[month],K$23)*_xlfn.XLOOKUP($B27,$B$6:$B$11,$E$6:$E$11))} -> 0 | ... O27: {=IF(ISCLOSED(O$23),0,SUMIFS(tbl_Budget[units],tbl_Budget[category],$B27,tbl_Budget[month],O$23)*_xlfn.XLOOKUP($B27,$B$6:$B$11,$E$6:$E$11))} -> 5662.8331 | P27: =SUM(D27:O27) -> 22805.541
B28: =$B7 -> Pork | D28: {=IF(ISCLOSED(D$23),0,SUMIFS(tbl_Budget[units],tbl_Budget[category],$B28,tbl_Budget[month],D$23)*_xlfn.XLOOKUP($B28,$B$6:$B$11,$E$6:$E$11))} -> 0 | E28: {=IF(ISCLOSED(E$23),0,SUMIFS(tbl_Budget[units],tbl_Budget[category],$B28,tbl_Budget[month],E$23)*_xlfn.XLOOKUP($B28,$B$6:$B$11,$E$6:$E$11))} -> 0 | F28: {=IF(ISCLOSED(F$23),0,SUMIFS(tbl_Budget[units],tbl_Budget[category],$B28,tbl_Budget[month],F$23)*_xlfn.XLOOKUP($B28,$B$6:$B$11,$E$6:$E$11))} -> 0 | G28: {=IF(ISCLOSED(G$23),0,SUMIFS(tbl_Budget[units],tbl_Budget[category],$B28,tbl_Budget[month],G$23)*_xlfn.XLOOKUP($B28,$B$6:$B$11,$E$6:$E$11))} -> 0 | H28: {=IF(ISCLOSED(H$23),0,SUMIFS(tbl_Budget[units],tbl_Budget[category],$B28,tbl_Budget[month],H$23)*_xlfn.XLOOKUP($B28,$B$6:$B$11,$E$6:$E$11))} -> 0 | I28: {=IF(ISCLOSED(I$23),0,SUMIFS(tbl_Budget[units],tbl_Budget[category],$B28,tbl_Budget[month],I$23)*_xlfn.XLOOKUP($B28,$B$6:$B$11,$E$6:$E$11))} -> 0 | J28: {=IF(ISCLOSED(J$23),0,SUMIFS(tbl_Budget[units],tbl_Budget[category],$B28,tbl_Budget[month],J$23)*_xlfn.XLOOKUP($B28,$B$6:$B$11,$E$6:$E$11))} -> 0 | K28: {=IF(ISCLOSED(K$23),0,SUMIFS(tbl_Budget[units],tbl_Budget[category],$B28,tbl_Budget[month],K$23)*_xlfn.XLOOKUP($B28,$B$6:$B$11,$E$6:$E$11))} -> 0 | ... O28: {=IF(ISCLOSED(O$23),0,SUMIFS(tbl_Budget[units],tbl_Budget[category],$B28,tbl_Budget[month],O$23)*_xlfn.XLOOKUP($B28,$B$6:$B$11,$E$6:$E$11))} -> 5978.9523 | P28: =SUM(D28:O28) -> 22075.403
B29: =$B8 -> Poultry | D29: {=IF(ISCLOSED(D$23),0,SUMIFS(tbl_Budget[units],tbl_Budget[category],$B29,tbl_Budget[month],D$23)*_xlfn.XLOOKUP($B29,$B$6:$B$11,$E$6:$E$11))} -> 0 | E29: {=IF(ISCLOSED(E$23),0,SUMIFS(tbl_Budget[units],tbl_Budget[category],$B29,tbl_Budget[month],E$23)*_xlfn.XLOOKUP($B29,$B$6:$B$11,$E$6:$E$11))} -> 0 | F29: {=IF(ISCLOSED(F$23),0,SUMIFS(tbl_Budget[units],tbl_Budget[category],$B29,tbl_Budget[month],F$23)*_xlfn.XLOOKUP($B29,$B$6:$B$11,$E$6:$E$11))} -> 0 | G29: {=IF(ISCLOSED(G$23),0,SUMIFS(tbl_Budget[units],tbl_Budget[category],$B29,tbl_Budget[month],G$23)*_xlfn.XLOOKUP($B29,$B$6:$B$11,$E$6:$E$11))} -> 0 | H29: {=IF(ISCLOSED(H$23),0,SUMIFS(tbl_Budget[units],tbl_Budget[category],$B29,tbl_Budget[month],H$23)*_xlfn.XLOOKUP($B29,$B$6:$B$11,$E$6:$E$11))} -> 0 | I29: {=IF(ISCLOSED(I$23),0,SUMIFS(tbl_Budget[units],tbl_Budget[category],$B29,tbl_Budget[month],I$23)*_xlfn.XLOOKUP($B29,$B$6:$B$11,$E$6:$E$11))} -> 0 | J29: {=IF(ISCLOSED(J$23),0,SUMIFS(tbl_Budget[units],tbl_Budget[category],$B29,tbl_Budget[month],J$23)*_xlfn.XLOOKUP($B29,$B$6:$B$11,$E$6:$E$11))} -> 0 | K29: {=IF(ISCLOSED(K$23),0,SUMIFS(tbl_Budget[units],tbl_Budget[category],$B29,tbl_Budget[month],K$23)*_xlfn.XLOOKUP($B29,$B$6:$B$11,$E$6:$E$11))} -> 0 | ... O29: {=IF(ISCLOSED(O$23),0,SUMIFS(tbl_Budget[units],tbl_Budget[category],$B29,tbl_Budget[month],O$23)*_xlfn.XLOOKUP($B29,$B$6:$B$11,$E$6:$E$11))} -> 8387.1991 | P29: =SUM(D29:O29) -> 31092.141
B30: =$B9 -> Seafood | D30: {=IF(ISCLOSED(D$23),0,SUMIFS(tbl_Budget[units],tbl_Budget[category],$B30,tbl_Budget[month],D$23)*_xlfn.XLOOKUP($B30,$B$6:$B$11,$E$6:$E$11))} -> 0 | E30: {=IF(ISCLOSED(E$23),0,SUMIFS(tbl_Budget[units],tbl_Budget[category],$B30,tbl_Budget[month],E$23)*_xlfn.XLOOKUP($B30,$B$6:$B$11,$E$6:$E$11))} -> 0 | F30: {=IF(ISCLOSED(F$23),0,SUMIFS(tbl_Budget[units],tbl_Budget[category],$B30,tbl_Budget[month],F$23)*_xlfn.XLOOKUP($B30,$B$6:$B$11,$E$6:$E$11))} -> 0 | G30: {=IF(ISCLOSED(G$23),0,SUMIFS(tbl_Budget[units],tbl_Budget[category],$B30,tbl_Budget[month],G$23)*_xlfn.XLOOKUP($B30,$B$6:$B$11,$E$6:$E$11))} -> 0 | H30: {=IF(ISCLOSED(H$23),0,SUMIFS(tbl_Budget[units],tbl_Budget[category],$B30,tbl_Budget[month],H$23)*_xlfn.XLOOKUP($B30,$B$6:$B$11,$E$6:$E$11))} -> 0 | I30: {=IF(ISCLOSED(I$23),0,SUMIFS(tbl_Budget[units],tbl_Budget[category],$B30,tbl_Budget[month],I$23)*_xlfn.XLOOKUP($B30,$B$6:$B$11,$E$6:$E$11))} -> 0 | J30: {=IF(ISCLOSED(J$23),0,SUMIFS(tbl_Budget[units],tbl_Budget[category],$B30,tbl_Budget[month],J$23)*_xlfn.XLOOKUP($B30,$B$6:$B$11,$E$6:$E$11))} -> 0 | K30: {=IF(ISCLOSED(K$23),0,SUMIFS(tbl_Budget[units],tbl_Budget[category],$B30,tbl_Budget[month],K$23)*_xlfn.XLOOKUP($B30,$B$6:$B$11,$E$6:$E$11))} -> 0 | ... O30: {=IF(ISCLOSED(O$23),0,SUMIFS(tbl_Budget[units],tbl_Budget[category],$B30,tbl_Budget[month],O$23)*_xlfn.XLOOKUP($B30,$B$6:$B$11,$E$6:$E$11))} -> 2651.4015 | P30: =SUM(D30:O30) -> 10235.764
B31: =$B10 -> Charcuterie | D31: {=IF(ISCLOSED(D$23),0,SUMIFS(tbl_Budget[units],tbl_Budget[category],$B31,tbl_Budget[month],D$23)*_xlfn.XLOOKUP($B31,$B$6:$B$11,$E$6:$E$11))} -> 0 | E31: {=IF(ISCLOSED(E$23),0,SUMIFS(tbl_Budget[units],tbl_Budget[category],$B31,tbl_Budget[month],E$23)*_xlfn.XLOOKUP($B31,$B$6:$B$11,$E$6:$E$11))} -> 0 | F31: {=IF(ISCLOSED(F$23),0,SUMIFS(tbl_Budget[units],tbl_Budget[category],$B31,tbl_Budget[month],F$23)*_xlfn.XLOOKUP($B31,$B$6:$B$11,$E$6:$E$11))} -> 0 | G31: {=IF(ISCLOSED(G$23),0,SUMIFS(tbl_Budget[units],tbl_Budget[category],$B31,tbl_Budget[month],G$23)*_xlfn.XLOOKUP($B31,$B$6:$B$11,$E$6:$E$11))} -> 0 | H31: {=IF(ISCLOSED(H$23),0,SUMIFS(tbl_Budget[units],tbl_Budget[category],$B31,tbl_Budget[month],H$23)*_xlfn.XLOOKUP($B31,$B$6:$B$11,$E$6:$E$11))} -> 0 | I31: {=IF(ISCLOSED(I$23),0,SUMIFS(tbl_Budget[units],tbl_Budget[category],$B31,tbl_Budget[month],I$23)*_xlfn.XLOOKUP($B31,$B$6:$B$11,$E$6:$E$11))} -> 0 | J31: {=IF(ISCLOSED(J$23),0,SUMIFS(tbl_Budget[units],tbl_Budget[category],$B31,tbl_Budget[month],J$23)*_xlfn.XLOOKUP($B31,$B$6:$B$11,$E$6:$E$11))} -> 0 | K31: {=IF(ISCLOSED(K$23),0,SUMIFS(tbl_Budget[units],tbl_Budget[category],$B31,tbl_Budget[month],K$23)*_xlfn.XLOOKUP($B31,$B$6:$B$11,$E$6:$E$11))} -> 0 | ... O31: {=IF(ISCLOSED(O$23),0,SUMIFS(tbl_Budget[units],tbl_Budget[category],$B31,tbl_Budget[month],O$23)*_xlfn.XLOOKUP($B31,$B$6:$B$11,$E$6:$E$11))} -> 3179.3906 | P31: =SUM(D31:O31) -> 10769.406
B32: =$B11 -> Cheese & Dairy | D32: {=IF(ISCLOSED(D$23),0,SUMIFS(tbl_Budget[units],tbl_Budget[category],$B32,tbl_Budget[month],D$23)*_xlfn.XLOOKUP($B32,$B$6:$B$11,$E$6:$E$11))} -> 0 | E32: {=IF(ISCLOSED(E$23),0,SUMIFS(tbl_Budget[units],tbl_Budget[category],$B32,tbl_Budget[month],E$23)*_xlfn.XLOOKUP($B32,$B$6:$B$11,$E$6:$E$11))} -> 0 | F32: {=IF(ISCLOSED(F$23),0,SUMIFS(tbl_Budget[units],tbl_Budget[category],$B32,tbl_Budget[month],F$23)*_xlfn.XLOOKUP($B32,$B$6:$B$11,$E$6:$E$11))} -> 0 | G32: {=IF(ISCLOSED(G$23),0,SUMIFS(tbl_Budget[units],tbl_Budget[category],$B32,tbl_Budget[month],G$23)*_xlfn.XLOOKUP($B32,$B$6:$B$11,$E$6:$E$11))} -> 0 | H32: {=IF(ISCLOSED(H$23),0,SUMIFS(tbl_Budget[units],tbl_Budget[category],$B32,tbl_Budget[month],H$23)*_xlfn.XLOOKUP($B32,$B$6:$B$11,$E$6:$E$11))} -> 0 | I32: {=IF(ISCLOSED(I$23),0,SUMIFS(tbl_Budget[units],tbl_Budget[category],$B32,tbl_Budget[month],I$23)*_xlfn.XLOOKUP($B32,$B$6:$B$11,$E$6:$E$11))} -> 0 | J32: {=IF(ISCLOSED(J$23),0,SUMIFS(tbl_Budget[units],tbl_Budget[category],$B32,tbl_Budget[month],J$23)*_xlfn.XLOOKUP($B32,$B$6:$B$11,$E$6:$E$11))} -> 0 | K32: {=IF(ISCLOSED(K$23),0,SUMIFS(tbl_Budget[units],tbl_Budget[category],$B32,tbl_Budget[month],K$23)*_xlfn.XLOOKUP($B32,$B$6:$B$11,$E$6:$E$11))} -> 0 | ... O32: {=IF(ISCLOSED(O$23),0,SUMIFS(tbl_Budget[units],tbl_Budget[category],$B32,tbl_Budget[month],O$23)*_xlfn.XLOOKUP($B32,$B$6:$B$11,$E$6:$E$11))} -> 4071.8222 | P32: =SUM(D32:O32) -> 14110.265
B33: Total | D33: =SUM(D27:D32) -> 0 | E33: =SUM(E27:E32) -> 0 | F33: =SUM(F27:F32) -> 0 | G33: =SUM(G27:G32) -> 0 | H33: =SUM(H27:H32) -> 0 | I33: =SUM(I27:I32) -> 0 | J33: =SUM(J27:J32) -> 0 | K33: =SUM(K27:K32) -> 0 | ... P33: =SUM(P27:P32) -> 111088.52
B36: Forecast cases: baseline × (1 + volume driver)
B37: =$B6 -> Beef | D37: =D27*(1+sel_volume) -> 0 | E37: =E27*(1+sel_volume) -> 0 | F37: =F27*(1+sel_volume) -> 0 | G37: =G27*(1+sel_volume) -> 0 | H37: =H27*(1+sel_volume) -> 0 | I37: =I27*(1+sel_volume) -> 0 | J37: =J27*(1+sel_volume) -> 0 | K37: =K27*(1+sel_volume) -> 0 | ... O37: =O27*(1+sel_volume) -> 5662.8331 | P37: =SUM(D37:O37) -> 22805.541
B38: =$B7 -> Pork | D38: =D28*(1+sel_volume) -> 0 | E38: =E28*(1+sel_volume) -> 0 | F38: =F28*(1+sel_volume) -> 0 | G38: =G28*(1+sel_volume) -> 0 | H38: =H28*(1+sel_volume) -> 0 | I38: =I28*(1+sel_volume) -> 0 | J38: =J28*(1+sel_volume) -> 0 | K38: =K28*(1+sel_volume) -> 0 | ... O38: =O28*(1+sel_volume) -> 5978.9523 | P38: =SUM(D38:O38) -> 22075.403
B39: =$B8 -> Poultry | D39: =D29*(1+sel_volume) -> 0 | E39: =E29*(1+sel_volume) -> 0 | F39: =F29*(1+sel_volume) -> 0 | G39: =G29*(1+sel_volume) -> 0 | H39: =H29*(1+sel_volume) -> 0 | I39: =I29*(1+sel_volume) -> 0 | J39: =J29*(1+sel_volume) -> 0 | K39: =K29*(1+sel_volume) -> 0 | ... O39: =O29*(1+sel_volume) -> 8387.1991 | P39: =SUM(D39:O39) -> 31092.141
B40: =$B9 -> Seafood | D40: =D30*(1+sel_volume) -> 0 | E40: =E30*(1+sel_volume) -> 0 | F40: =F30*(1+sel_volume) -> 0 | G40: =G30*(1+sel_volume) -> 0 | H40: =H30*(1+sel_volume) -> 0 | I40: =I30*(1+sel_volume) -> 0 | J40: =J30*(1+sel_volume) -> 0 | K40: =K30*(1+sel_volume) -> 0 | ... O40: =O30*(1+sel_volume) -> 2651.4015 | P40: =SUM(D40:O40) -> 10235.764
B41: =$B10 -> Charcuterie | D41: =D31*(1+sel_volume) -> 0 | E41: =E31*(1+sel_volume) -> 0 | F41: =F31*(1+sel_volume) -> 0 | G41: =G31*(1+sel_volume) -> 0 | H41: =H31*(1+sel_volume) -> 0 | I41: =I31*(1+sel_volume) -> 0 | J41: =J31*(1+sel_volume) -> 0 | K41: =K31*(1+sel_volume) -> 0 | ... O41: =O31*(1+sel_volume) -> 3179.3906 | P41: =SUM(D41:O41) -> 10769.406
B42: =$B11 -> Cheese & Dairy | D42: =D32*(1+sel_volume) -> 0 | E42: =E32*(1+sel_volume) -> 0 | F42: =F32*(1+sel_volume) -> 0 | G42: =G32*(1+sel_volume) -> 0 | H42: =H32*(1+sel_volume) -> 0 | I42: =I32*(1+sel_volume) -> 0 | J42: =J32*(1+sel_volume) -> 0 | K42: =K32*(1+sel_volume) -> 0 | ... O42: =O32*(1+sel_volume) -> 4071.8222 | P42: =SUM(D42:O42) -> 14110.265
B43: Total | D43: =SUM(D37:D42) -> 0 | E43: =SUM(E37:E42) -> 0 | F43: =SUM(F37:F42) -> 0 | G43: =SUM(G37:G42) -> 0 | H43: =SUM(H37:H42) -> 0 | I43: =SUM(I37:I42) -> 0 | J43: =SUM(J37:J42) -> 0 | K43: =SUM(K37:K42) -> 0 | ... P43: =SUM(P37:P42) -> 111088.52
B46: Forecast revenue: cases × trailing price per case × (1 + price driver)
B47: =$B6 -> Beef | D47: =D37*(_xlfn.XLOOKUP($B47,$B$6:$B$11,$J$6:$J$11)*(1+sel_price)) -> 0 | E47: =E37*(_xlfn.XLOOKUP($B47,$B$6:$B$11,$J$6:$J$11)*(1+sel_price)) -> 0 | F47: =F37*(_xlfn.XLOOKUP($B47,$B$6:$B$11,$J$6:$J$11)*(1+sel_price)) -> 0 | G47: =G37*(_xlfn.XLOOKUP($B47,$B$6:$B$11,$J$6:$J$11)*(1+sel_price)) -> 0 | H47: =H37*(_xlfn.XLOOKUP($B47,$B$6:$B$11,$J$6:$J$11)*(1+sel_price)) -> 0 | I47: =I37*(_xlfn.XLOOKUP($B47,$B$6:$B$11,$J$6:$J$11)*(1+sel_price)) -> 0 | J47: =J37*(_xlfn.XLOOKUP($B47,$B$6:$B$11,$J$6:$J$11)*(1+sel_price)) -> 0 | K47: =K37*(_xlfn.XLOOKUP($B47,$B$6:$B$11,$J$6:$J$11)*(1+sel_price)) -> 0 | ... O47: =O37*(_xlfn.XLOOKUP($B47,$B$6:$B$11,$J$6:$J$11)*(1+sel_price)) -> 1077321 | P47: =SUM(D47:O47) -> 4338621.1
B48: =$B7 -> Pork | D48: =D38*(_xlfn.XLOOKUP($B48,$B$6:$B$11,$J$6:$J$11)*(1+sel_price)) -> 0 | E48: =E38*(_xlfn.XLOOKUP($B48,$B$6:$B$11,$J$6:$J$11)*(1+sel_price)) -> 0 | F48: =F38*(_xlfn.XLOOKUP($B48,$B$6:$B$11,$J$6:$J$11)*(1+sel_price)) -> 0 | G48: =G38*(_xlfn.XLOOKUP($B48,$B$6:$B$11,$J$6:$J$11)*(1+sel_price)) -> 0 | H48: =H38*(_xlfn.XLOOKUP($B48,$B$6:$B$11,$J$6:$J$11)*(1+sel_price)) -> 0 | I48: =I38*(_xlfn.XLOOKUP($B48,$B$6:$B$11,$J$6:$J$11)*(1+sel_price)) -> 0 | J48: =J38*(_xlfn.XLOOKUP($B48,$B$6:$B$11,$J$6:$J$11)*(1+sel_price)) -> 0 | K48: =K38*(_xlfn.XLOOKUP($B48,$B$6:$B$11,$J$6:$J$11)*(1+sel_price)) -> 0 | ... O48: =O38*(_xlfn.XLOOKUP($B48,$B$6:$B$11,$J$6:$J$11)*(1+sel_price)) -> 712584.18 | P48: =SUM(D48:O48) -> 2630993.2
B49: =$B8 -> Poultry | D49: =D39*(_xlfn.XLOOKUP($B49,$B$6:$B$11,$J$6:$J$11)*(1+sel_price)) -> 0 | E49: =E39*(_xlfn.XLOOKUP($B49,$B$6:$B$11,$J$6:$J$11)*(1+sel_price)) -> 0 | F49: =F39*(_xlfn.XLOOKUP($B49,$B$6:$B$11,$J$6:$J$11)*(1+sel_price)) -> 0 | G49: =G39*(_xlfn.XLOOKUP($B49,$B$6:$B$11,$J$6:$J$11)*(1+sel_price)) -> 0 | H49: =H39*(_xlfn.XLOOKUP($B49,$B$6:$B$11,$J$6:$J$11)*(1+sel_price)) -> 0 | I49: =I39*(_xlfn.XLOOKUP($B49,$B$6:$B$11,$J$6:$J$11)*(1+sel_price)) -> 0 | J49: =J39*(_xlfn.XLOOKUP($B49,$B$6:$B$11,$J$6:$J$11)*(1+sel_price)) -> 0 | K49: =K39*(_xlfn.XLOOKUP($B49,$B$6:$B$11,$J$6:$J$11)*(1+sel_price)) -> 0 | ... O49: =O39*(_xlfn.XLOOKUP($B49,$B$6:$B$11,$J$6:$J$11)*(1+sel_price)) -> 885879.75 | P49: =SUM(D49:O49) -> 3284040.1
B50: =$B9 -> Seafood | D50: =D40*(_xlfn.XLOOKUP($B50,$B$6:$B$11,$J$6:$J$11)*(1+sel_price)) -> 0 | E50: =E40*(_xlfn.XLOOKUP($B50,$B$6:$B$11,$J$6:$J$11)*(1+sel_price)) -> 0 | F50: =F40*(_xlfn.XLOOKUP($B50,$B$6:$B$11,$J$6:$J$11)*(1+sel_price)) -> 0 | G50: =G40*(_xlfn.XLOOKUP($B50,$B$6:$B$11,$J$6:$J$11)*(1+sel_price)) -> 0 | H50: =H40*(_xlfn.XLOOKUP($B50,$B$6:$B$11,$J$6:$J$11)*(1+sel_price)) -> 0 | I50: =I40*(_xlfn.XLOOKUP($B50,$B$6:$B$11,$J$6:$J$11)*(1+sel_price)) -> 0 | J50: =J40*(_xlfn.XLOOKUP($B50,$B$6:$B$11,$J$6:$J$11)*(1+sel_price)) -> 0 | K50: =K40*(_xlfn.XLOOKUP($B50,$B$6:$B$11,$J$6:$J$11)*(1+sel_price)) -> 0 | ... O50: =O40*(_xlfn.XLOOKUP($B50,$B$6:$B$11,$J$6:$J$11)*(1+sel_price)) -> 528781.8 | P50: =SUM(D50:O50) -> 2041367.9
B51: =$B10 -> Charcuterie | D51: =D41*(_xlfn.XLOOKUP($B51,$B$6:$B$11,$J$6:$J$11)*(1+sel_price)) -> 0 | E51: =E41*(_xlfn.XLOOKUP($B51,$B$6:$B$11,$J$6:$J$11)*(1+sel_price)) -> 0 | F51: =F41*(_xlfn.XLOOKUP($B51,$B$6:$B$11,$J$6:$J$11)*(1+sel_price)) -> 0 | G51: =G41*(_xlfn.XLOOKUP($B51,$B$6:$B$11,$J$6:$J$11)*(1+sel_price)) -> 0 | H51: =H41*(_xlfn.XLOOKUP($B51,$B$6:$B$11,$J$6:$J$11)*(1+sel_price)) -> 0 | I51: =I41*(_xlfn.XLOOKUP($B51,$B$6:$B$11,$J$6:$J$11)*(1+sel_price)) -> 0 | J51: =J41*(_xlfn.XLOOKUP($B51,$B$6:$B$11,$J$6:$J$11)*(1+sel_price)) -> 0 | K51: =K41*(_xlfn.XLOOKUP($B51,$B$6:$B$11,$J$6:$J$11)*(1+sel_price)) -> 0 | ... O51: =O41*(_xlfn.XLOOKUP($B51,$B$6:$B$11,$J$6:$J$11)*(1+sel_price)) -> 511461.71 | P51: =SUM(D51:O51) -> 1732451.2
B52: =$B11 -> Cheese & Dairy | D52: =D42*(_xlfn.XLOOKUP($B52,$B$6:$B$11,$J$6:$J$11)*(1+sel_price)) -> 0 | E52: =E42*(_xlfn.XLOOKUP($B52,$B$6:$B$11,$J$6:$J$11)*(1+sel_price)) -> 0 | F52: =F42*(_xlfn.XLOOKUP($B52,$B$6:$B$11,$J$6:$J$11)*(1+sel_price)) -> 0 | G52: =G42*(_xlfn.XLOOKUP($B52,$B$6:$B$11,$J$6:$J$11)*(1+sel_price)) -> 0 | H52: =H42*(_xlfn.XLOOKUP($B52,$B$6:$B$11,$J$6:$J$11)*(1+sel_price)) -> 0 | I52: =I42*(_xlfn.XLOOKUP($B52,$B$6:$B$11,$J$6:$J$11)*(1+sel_price)) -> 0 | J52: =J42*(_xlfn.XLOOKUP($B52,$B$6:$B$11,$J$6:$J$11)*(1+sel_price)) -> 0 | K52: =K42*(_xlfn.XLOOKUP($B52,$B$6:$B$11,$J$6:$J$11)*(1+sel_price)) -> 0 | ... O52: =O42*(_xlfn.XLOOKUP($B52,$B$6:$B$11,$J$6:$J$11)*(1+sel_price)) -> 532770.64 | P52: =SUM(D52:O52) -> 1846233.6
B53: Total | D53: =SUM(D47:D52) -> 0 | E53: =SUM(E47:E52) -> 0 | F53: =SUM(F47:F52) -> 0 | G53: =SUM(G47:G52) -> 0 | H53: =SUM(H47:H52) -> 0 | I53: =SUM(I47:I52) -> 0 | J53: =SUM(J47:J52) -> 0 | K53: =SUM(K47:K52) -> 0 | ... P53: =SUM(P47:P52) -> 15873707
B56: Forecast cost of goods: cases × trailing cost per case × (1 + cost driver)
B57: =$B6 -> Beef | D57: =D37*(_xlfn.XLOOKUP($B57,$B$6:$B$11,$K$6:$K$11)*(1+sel_cost)) -> 0 | E57: =E37*(_xlfn.XLOOKUP($B57,$B$6:$B$11,$K$6:$K$11)*(1+sel_cost)) -> 0 | F57: =F37*(_xlfn.XLOOKUP($B57,$B$6:$B$11,$K$6:$K$11)*(1+sel_cost)) -> 0 | G57: =G37*(_xlfn.XLOOKUP($B57,$B$6:$B$11,$K$6:$K$11)*(1+sel_cost)) -> 0 | H57: =H37*(_xlfn.XLOOKUP($B57,$B$6:$B$11,$K$6:$K$11)*(1+sel_cost)) -> 0 | I57: =I37*(_xlfn.XLOOKUP($B57,$B$6:$B$11,$K$6:$K$11)*(1+sel_cost)) -> 0 | J57: =J37*(_xlfn.XLOOKUP($B57,$B$6:$B$11,$K$6:$K$11)*(1+sel_cost)) -> 0 | K57: =K37*(_xlfn.XLOOKUP($B57,$B$6:$B$11,$K$6:$K$11)*(1+sel_cost)) -> 0 | ... O57: =O37*(_xlfn.XLOOKUP($B57,$B$6:$B$11,$K$6:$K$11)*(1+sel_cost)) -> 881944.84 | P57: =SUM(D57:O57) -> 3551796.3
B58: =$B7 -> Pork | D58: =D38*(_xlfn.XLOOKUP($B58,$B$6:$B$11,$K$6:$K$11)*(1+sel_cost)) -> 0 | E58: =E38*(_xlfn.XLOOKUP($B58,$B$6:$B$11,$K$6:$K$11)*(1+sel_cost)) -> 0 | F58: =F38*(_xlfn.XLOOKUP($B58,$B$6:$B$11,$K$6:$K$11)*(1+sel_cost)) -> 0 | G58: =G38*(_xlfn.XLOOKUP($B58,$B$6:$B$11,$K$6:$K$11)*(1+sel_cost)) -> 0 | H58: =H38*(_xlfn.XLOOKUP($B58,$B$6:$B$11,$K$6:$K$11)*(1+sel_cost)) -> 0 | I58: =I38*(_xlfn.XLOOKUP($B58,$B$6:$B$11,$K$6:$K$11)*(1+sel_cost)) -> 0 | J58: =J38*(_xlfn.XLOOKUP($B58,$B$6:$B$11,$K$6:$K$11)*(1+sel_cost)) -> 0 | K58: =K38*(_xlfn.XLOOKUP($B58,$B$6:$B$11,$K$6:$K$11)*(1+sel_cost)) -> 0 | ... O58: =O38*(_xlfn.XLOOKUP($B58,$B$6:$B$11,$K$6:$K$11)*(1+sel_cost)) -> 520259.13 | P58: =SUM(D58:O58) -> 1920893.4
B59: =$B8 -> Poultry | D59: =D39*(_xlfn.XLOOKUP($B59,$B$6:$B$11,$K$6:$K$11)*(1+sel_cost)) -> 0 | E59: =E39*(_xlfn.XLOOKUP($B59,$B$6:$B$11,$K$6:$K$11)*(1+sel_cost)) -> 0 | F59: =F39*(_xlfn.XLOOKUP($B59,$B$6:$B$11,$K$6:$K$11)*(1+sel_cost)) -> 0 | G59: =G39*(_xlfn.XLOOKUP($B59,$B$6:$B$11,$K$6:$K$11)*(1+sel_cost)) -> 0 | H59: =H39*(_xlfn.XLOOKUP($B59,$B$6:$B$11,$K$6:$K$11)*(1+sel_cost)) -> 0 | I59: =I39*(_xlfn.XLOOKUP($B59,$B$6:$B$11,$K$6:$K$11)*(1+sel_cost)) -> 0 | J59: =J39*(_xlfn.XLOOKUP($B59,$B$6:$B$11,$K$6:$K$11)*(1+sel_cost)) -> 0 | K59: =K39*(_xlfn.XLOOKUP($B59,$B$6:$B$11,$K$6:$K$11)*(1+sel_cost)) -> 0 | ... O59: =O39*(_xlfn.XLOOKUP($B59,$B$6:$B$11,$K$6:$K$11)*(1+sel_cost)) -> 664327.28 | P59: =SUM(D59:O59) -> 2462724.1
B60: =$B9 -> Seafood | D60: =D40*(_xlfn.XLOOKUP($B60,$B$6:$B$11,$K$6:$K$11)*(1+sel_cost)) -> 0 | E60: =E40*(_xlfn.XLOOKUP($B60,$B$6:$B$11,$K$6:$K$11)*(1+sel_cost)) -> 0 | F60: =F40*(_xlfn.XLOOKUP($B60,$B$6:$B$11,$K$6:$K$11)*(1+sel_cost)) -> 0 | G60: =G40*(_xlfn.XLOOKUP($B60,$B$6:$B$11,$K$6:$K$11)*(1+sel_cost)) -> 0 | H60: =H40*(_xlfn.XLOOKUP($B60,$B$6:$B$11,$K$6:$K$11)*(1+sel_cost)) -> 0 | I60: =I40*(_xlfn.XLOOKUP($B60,$B$6:$B$11,$K$6:$K$11)*(1+sel_cost)) -> 0 | J60: =J40*(_xlfn.XLOOKUP($B60,$B$6:$B$11,$K$6:$K$11)*(1+sel_cost)) -> 0 | K60: =K40*(_xlfn.XLOOKUP($B60,$B$6:$B$11,$K$6:$K$11)*(1+sel_cost)) -> 0 | ... O60: =O40*(_xlfn.XLOOKUP($B60,$B$6:$B$11,$K$6:$K$11)*(1+sel_cost)) -> 402249.65 | P60: =SUM(D60:O60) -> 1552889.1
B61: =$B10 -> Charcuterie | D61: =D41*(_xlfn.XLOOKUP($B61,$B$6:$B$11,$K$6:$K$11)*(1+sel_cost)) -> 0 | E61: =E41*(_xlfn.XLOOKUP($B61,$B$6:$B$11,$K$6:$K$11)*(1+sel_cost)) -> 0 | F61: =F41*(_xlfn.XLOOKUP($B61,$B$6:$B$11,$K$6:$K$11)*(1+sel_cost)) -> 0 | G61: =G41*(_xlfn.XLOOKUP($B61,$B$6:$B$11,$K$6:$K$11)*(1+sel_cost)) -> 0 | H61: =H41*(_xlfn.XLOOKUP($B61,$B$6:$B$11,$K$6:$K$11)*(1+sel_cost)) -> 0 | I61: =I41*(_xlfn.XLOOKUP($B61,$B$6:$B$11,$K$6:$K$11)*(1+sel_cost)) -> 0 | J61: =J41*(_xlfn.XLOOKUP($B61,$B$6:$B$11,$K$6:$K$11)*(1+sel_cost)) -> 0 | K61: =K41*(_xlfn.XLOOKUP($B61,$B$6:$B$11,$K$6:$K$11)*(1+sel_cost)) -> 0 | ... O61: =O41*(_xlfn.XLOOKUP($B61,$B$6:$B$11,$K$6:$K$11)*(1+sel_cost)) -> 308776.4 | P61: =SUM(D61:O61) -> 1045904.4
B62: =$B11 -> Cheese & Dairy | D62: =D42*(_xlfn.XLOOKUP($B62,$B$6:$B$11,$K$6:$K$11)*(1+sel_cost)) -> 0 | E62: =E42*(_xlfn.XLOOKUP($B62,$B$6:$B$11,$K$6:$K$11)*(1+sel_cost)) -> 0 | F62: =F42*(_xlfn.XLOOKUP($B62,$B$6:$B$11,$K$6:$K$11)*(1+sel_cost)) -> 0 | G62: =G42*(_xlfn.XLOOKUP($B62,$B$6:$B$11,$K$6:$K$11)*(1+sel_cost)) -> 0 | H62: =H42*(_xlfn.XLOOKUP($B62,$B$6:$B$11,$K$6:$K$11)*(1+sel_cost)) -> 0 | I62: =I42*(_xlfn.XLOOKUP($B62,$B$6:$B$11,$K$6:$K$11)*(1+sel_cost)) -> 0 | J62: =J42*(_xlfn.XLOOKUP($B62,$B$6:$B$11,$K$6:$K$11)*(1+sel_cost)) -> 0 | K62: =K42*(_xlfn.XLOOKUP($B62,$B$6:$B$11,$K$6:$K$11)*(1+sel_cost)) -> 0 | ... O62: =O42*(_xlfn.XLOOKUP($B62,$B$6:$B$11,$K$6:$K$11)*(1+sel_cost)) -> 343720.99 | P62: =SUM(D62:O62) -> 1191111.5
B63: Total | D63: =SUM(D57:D62) -> 0 | E63: =SUM(E57:E62) -> 0 | F63: =SUM(F57:F62) -> 0 | G63: =SUM(G57:G62) -> 0 | H63: =SUM(H57:H62) -> 0 | I63: =SUM(I57:I62) -> 0 | J63: =SUM(J57:J62) -> 0 | K63: =SUM(K57:K62) -> 0 | ... P63: =SUM(P57:P62) -> 11725319
B66: Forecast freight: cases × trailing freight per case × (1 + freight driver)
B67: =$B6 -> Beef | D67: =D37*(_xlfn.XLOOKUP($B67,$B$6:$B$11,$L$6:$L$11)*(1+sel_freight)) -> 0 | E67: =E37*(_xlfn.XLOOKUP($B67,$B$6:$B$11,$L$6:$L$11)*(1+sel_freight)) -> 0 | F67: =F37*(_xlfn.XLOOKUP($B67,$B$6:$B$11,$L$6:$L$11)*(1+sel_freight)) -> 0 | G67: =G37*(_xlfn.XLOOKUP($B67,$B$6:$B$11,$L$6:$L$11)*(1+sel_freight)) -> 0 | H67: =H37*(_xlfn.XLOOKUP($B67,$B$6:$B$11,$L$6:$L$11)*(1+sel_freight)) -> 0 | I67: =I37*(_xlfn.XLOOKUP($B67,$B$6:$B$11,$L$6:$L$11)*(1+sel_freight)) -> 0 | J67: =J37*(_xlfn.XLOOKUP($B67,$B$6:$B$11,$L$6:$L$11)*(1+sel_freight)) -> 0 | K67: =K37*(_xlfn.XLOOKUP($B67,$B$6:$B$11,$L$6:$L$11)*(1+sel_freight)) -> 0 | ... O67: =O37*(_xlfn.XLOOKUP($B67,$B$6:$B$11,$L$6:$L$11)*(1+sel_freight)) -> 18686.659 | P67: =SUM(D67:O67) -> 75255.508
B68: =$B7 -> Pork | D68: =D38*(_xlfn.XLOOKUP($B68,$B$6:$B$11,$L$6:$L$11)*(1+sel_freight)) -> 0 | E68: =E38*(_xlfn.XLOOKUP($B68,$B$6:$B$11,$L$6:$L$11)*(1+sel_freight)) -> 0 | F68: =F38*(_xlfn.XLOOKUP($B68,$B$6:$B$11,$L$6:$L$11)*(1+sel_freight)) -> 0 | G68: =G38*(_xlfn.XLOOKUP($B68,$B$6:$B$11,$L$6:$L$11)*(1+sel_freight)) -> 0 | H68: =H38*(_xlfn.XLOOKUP($B68,$B$6:$B$11,$L$6:$L$11)*(1+sel_freight)) -> 0 | I68: =I38*(_xlfn.XLOOKUP($B68,$B$6:$B$11,$L$6:$L$11)*(1+sel_freight)) -> 0 | J68: =J38*(_xlfn.XLOOKUP($B68,$B$6:$B$11,$L$6:$L$11)*(1+sel_freight)) -> 0 | K68: =K38*(_xlfn.XLOOKUP($B68,$B$6:$B$11,$L$6:$L$11)*(1+sel_freight)) -> 0 | ... O68: =O38*(_xlfn.XLOOKUP($B68,$B$6:$B$11,$L$6:$L$11)*(1+sel_freight)) -> 19645.835 | P68: =SUM(D68:O68) -> 72536.072
B69: =$B8 -> Poultry | D69: =D39*(_xlfn.XLOOKUP($B69,$B$6:$B$11,$L$6:$L$11)*(1+sel_freight)) -> 0 | E69: =E39*(_xlfn.XLOOKUP($B69,$B$6:$B$11,$L$6:$L$11)*(1+sel_freight)) -> 0 | F69: =F39*(_xlfn.XLOOKUP($B69,$B$6:$B$11,$L$6:$L$11)*(1+sel_freight)) -> 0 | G69: =G39*(_xlfn.XLOOKUP($B69,$B$6:$B$11,$L$6:$L$11)*(1+sel_freight)) -> 0 | H69: =H39*(_xlfn.XLOOKUP($B69,$B$6:$B$11,$L$6:$L$11)*(1+sel_freight)) -> 0 | I69: =I39*(_xlfn.XLOOKUP($B69,$B$6:$B$11,$L$6:$L$11)*(1+sel_freight)) -> 0 | J69: =J39*(_xlfn.XLOOKUP($B69,$B$6:$B$11,$L$6:$L$11)*(1+sel_freight)) -> 0 | K69: =K39*(_xlfn.XLOOKUP($B69,$B$6:$B$11,$L$6:$L$11)*(1+sel_freight)) -> 0 | ... O69: =O39*(_xlfn.XLOOKUP($B69,$B$6:$B$11,$L$6:$L$11)*(1+sel_freight)) -> 27706.668 | P69: =SUM(D69:O69) -> 102711.24
B70: =$B9 -> Seafood | D70: =D40*(_xlfn.XLOOKUP($B70,$B$6:$B$11,$L$6:$L$11)*(1+sel_freight)) -> 0 | E70: =E40*(_xlfn.XLOOKUP($B70,$B$6:$B$11,$L$6:$L$11)*(1+sel_freight)) -> 0 | F70: =F40*(_xlfn.XLOOKUP($B70,$B$6:$B$11,$L$6:$L$11)*(1+sel_freight)) -> 0 | G70: =G40*(_xlfn.XLOOKUP($B70,$B$6:$B$11,$L$6:$L$11)*(1+sel_freight)) -> 0 | H70: =H40*(_xlfn.XLOOKUP($B70,$B$6:$B$11,$L$6:$L$11)*(1+sel_freight)) -> 0 | I70: =I40*(_xlfn.XLOOKUP($B70,$B$6:$B$11,$L$6:$L$11)*(1+sel_freight)) -> 0 | J70: =J40*(_xlfn.XLOOKUP($B70,$B$6:$B$11,$L$6:$L$11)*(1+sel_freight)) -> 0 | K70: =K40*(_xlfn.XLOOKUP($B70,$B$6:$B$11,$L$6:$L$11)*(1+sel_freight)) -> 0 | ... O70: =O40*(_xlfn.XLOOKUP($B70,$B$6:$B$11,$L$6:$L$11)*(1+sel_freight)) -> 8738.1873 | P70: =SUM(D70:O70) -> 33733.867
B71: =$B10 -> Charcuterie | D71: =D41*(_xlfn.XLOOKUP($B71,$B$6:$B$11,$L$6:$L$11)*(1+sel_freight)) -> 0 | E71: =E41*(_xlfn.XLOOKUP($B71,$B$6:$B$11,$L$6:$L$11)*(1+sel_freight)) -> 0 | F71: =F41*(_xlfn.XLOOKUP($B71,$B$6:$B$11,$L$6:$L$11)*(1+sel_freight)) -> 0 | G71: =G41*(_xlfn.XLOOKUP($B71,$B$6:$B$11,$L$6:$L$11)*(1+sel_freight)) -> 0 | H71: =H41*(_xlfn.XLOOKUP($B71,$B$6:$B$11,$L$6:$L$11)*(1+sel_freight)) -> 0 | I71: =I41*(_xlfn.XLOOKUP($B71,$B$6:$B$11,$L$6:$L$11)*(1+sel_freight)) -> 0 | J71: =J41*(_xlfn.XLOOKUP($B71,$B$6:$B$11,$L$6:$L$11)*(1+sel_freight)) -> 0 | K71: =K41*(_xlfn.XLOOKUP($B71,$B$6:$B$11,$L$6:$L$11)*(1+sel_freight)) -> 0 | ... O71: =O41*(_xlfn.XLOOKUP($B71,$B$6:$B$11,$L$6:$L$11)*(1+sel_freight)) -> 10519.101 | P71: =SUM(D71:O71) -> 35630.876
B72: =$B11 -> Cheese & Dairy | D72: =D42*(_xlfn.XLOOKUP($B72,$B$6:$B$11,$L$6:$L$11)*(1+sel_freight)) -> 0 | E72: =E42*(_xlfn.XLOOKUP($B72,$B$6:$B$11,$L$6:$L$11)*(1+sel_freight)) -> 0 | F72: =F42*(_xlfn.XLOOKUP($B72,$B$6:$B$11,$L$6:$L$11)*(1+sel_freight)) -> 0 | G72: =G42*(_xlfn.XLOOKUP($B72,$B$6:$B$11,$L$6:$L$11)*(1+sel_freight)) -> 0 | H72: =H42*(_xlfn.XLOOKUP($B72,$B$6:$B$11,$L$6:$L$11)*(1+sel_freight)) -> 0 | I72: =I42*(_xlfn.XLOOKUP($B72,$B$6:$B$11,$L$6:$L$11)*(1+sel_freight)) -> 0 | J72: =J42*(_xlfn.XLOOKUP($B72,$B$6:$B$11,$L$6:$L$11)*(1+sel_freight)) -> 0 | K72: =K42*(_xlfn.XLOOKUP($B72,$B$6:$B$11,$L$6:$L$11)*(1+sel_freight)) -> 0 | ... O72: =O42*(_xlfn.XLOOKUP($B72,$B$6:$B$11,$L$6:$L$11)*(1+sel_freight)) -> 13435.408 | P72: =SUM(D72:O72) -> 46558.313
B73: Total | D73: =SUM(D67:D72) -> 0 | E73: =SUM(E67:E72) -> 0 | F73: =SUM(F67:F72) -> 0 | G73: =SUM(G67:G72) -> 0 | H73: =SUM(H67:H72) -> 0 | I73: =SUM(I67:I72) -> 0 | J73: =SUM(J67:J72) -> 0 | K73: =SUM(K67:K72) -> 0 | ... P73: =SUM(P67:P72) -> 366425.88
B76: Baseline operating expenses: budget × the department's YTD run-rate
B77: =$B16 -> Sales & Marketing | D77: {=IF(ISCLOSED(D$23),0,SUMIFS(tbl_Opex[amount],tbl_Opex[dept],$B77,tbl_Opex[scenario],"Budget",tbl_Opex[month],D$23)*_xlfn.XLOOKUP($B77,$B$16:$B$19,$E$16:$E$19))} -> 0 | E77: {=IF(ISCLOSED(E$23),0,SUMIFS(tbl_Opex[amount],tbl_Opex[dept],$B77,tbl_Opex[scenario],"Budget",tbl_Opex[month],E$23)*_xlfn.XLOOKUP($B77,$B$16:$B$19,$E$16:$E$19))} -> 0 | F77: {=IF(ISCLOSED(F$23),0,SUMIFS(tbl_Opex[amount],tbl_Opex[dept],$B77,tbl_Opex[scenario],"Budget",tbl_Opex[month],F$23)*_xlfn.XLOOKUP($B77,$B$16:$B$19,$E$16:$E$19))} -> 0 | G77: {=IF(ISCLOSED(G$23),0,SUMIFS(tbl_Opex[amount],tbl_Opex[dept],$B77,tbl_Opex[scenario],"Budget",tbl_Opex[month],G$23)*_xlfn.XLOOKUP($B77,$B$16:$B$19,$E$16:$E$19))} -> 0 | H77: {=IF(ISCLOSED(H$23),0,SUMIFS(tbl_Opex[amount],tbl_Opex[dept],$B77,tbl_Opex[scenario],"Budget",tbl_Opex[month],H$23)*_xlfn.XLOOKUP($B77,$B$16:$B$19,$E$16:$E$19))} -> 0 | I77: {=IF(ISCLOSED(I$23),0,SUMIFS(tbl_Opex[amount],tbl_Opex[dept],$B77,tbl_Opex[scenario],"Budget",tbl_Opex[month],I$23)*_xlfn.XLOOKUP($B77,$B$16:$B$19,$E$16:$E$19))} -> 0 | J77: {=IF(ISCLOSED(J$23),0,SUMIFS(tbl_Opex[amount],tbl_Opex[dept],$B77,tbl_Opex[scenario],"Budget",tbl_Opex[month],J$23)*_xlfn.XLOOKUP($B77,$B$16:$B$19,$E$16:$E$19))} -> 0 | K77: {=IF(ISCLOSED(K$23),0,SUMIFS(tbl_Opex[amount],tbl_Opex[dept],$B77,tbl_Opex[scenario],"Budget",tbl_Opex[month],K$23)*_xlfn.XLOOKUP($B77,$B$16:$B$19,$E$16:$E$19))} -> 0 | ... O77: {=IF(ISCLOSED(O$23),0,SUMIFS(tbl_Opex[amount],tbl_Opex[dept],$B77,tbl_Opex[scenario],"Budget",tbl_Opex[month],O$23)*_xlfn.XLOOKUP($B77,$B$16:$B$19,$E$16:$E$19))} -> 197885.28 | P77: =SUM(D77:O77) -> 791541.11
B78: =$B17 -> Warehouse & Logistics | D78: {=IF(ISCLOSED(D$23),0,SUMIFS(tbl_Opex[amount],tbl_Opex[dept],$B78,tbl_Opex[scenario],"Budget",tbl_Opex[month],D$23)*_xlfn.XLOOKUP($B78,$B$16:$B$19,$E$16:$E$19))} -> 0 | E78: {=IF(ISCLOSED(E$23),0,SUMIFS(tbl_Opex[amount],tbl_Opex[dept],$B78,tbl_Opex[scenario],"Budget",tbl_Opex[month],E$23)*_xlfn.XLOOKUP($B78,$B$16:$B$19,$E$16:$E$19))} -> 0 | F78: {=IF(ISCLOSED(F$23),0,SUMIFS(tbl_Opex[amount],tbl_Opex[dept],$B78,tbl_Opex[scenario],"Budget",tbl_Opex[month],F$23)*_xlfn.XLOOKUP($B78,$B$16:$B$19,$E$16:$E$19))} -> 0 | G78: {=IF(ISCLOSED(G$23),0,SUMIFS(tbl_Opex[amount],tbl_Opex[dept],$B78,tbl_Opex[scenario],"Budget",tbl_Opex[month],G$23)*_xlfn.XLOOKUP($B78,$B$16:$B$19,$E$16:$E$19))} -> 0 | H78: {=IF(ISCLOSED(H$23),0,SUMIFS(tbl_Opex[amount],tbl_Opex[dept],$B78,tbl_Opex[scenario],"Budget",tbl_Opex[month],H$23)*_xlfn.XLOOKUP($B78,$B$16:$B$19,$E$16:$E$19))} -> 0 | I78: {=IF(ISCLOSED(I$23),0,SUMIFS(tbl_Opex[amount],tbl_Opex[dept],$B78,tbl_Opex[scenario],"Budget",tbl_Opex[month],I$23)*_xlfn.XLOOKUP($B78,$B$16:$B$19,$E$16:$E$19))} -> 0 | J78: {=IF(ISCLOSED(J$23),0,SUMIFS(tbl_Opex[amount],tbl_Opex[dept],$B78,tbl_Opex[scenario],"Budget",tbl_Opex[month],J$23)*_xlfn.XLOOKUP($B78,$B$16:$B$19,$E$16:$E$19))} -> 0 | K78: {=IF(ISCLOSED(K$23),0,SUMIFS(tbl_Opex[amount],tbl_Opex[dept],$B78,tbl_Opex[scenario],"Budget",tbl_Opex[month],K$23)*_xlfn.XLOOKUP($B78,$B$16:$B$19,$E$16:$E$19))} -> 0 | ... O78: {=IF(ISCLOSED(O$23),0,SUMIFS(tbl_Opex[amount],tbl_Opex[dept],$B78,tbl_Opex[scenario],"Budget",tbl_Opex[month],O$23)*_xlfn.XLOOKUP($B78,$B$16:$B$19,$E$16:$E$19))} -> 316406.31 | P78: =SUM(D78:O78) -> 1229805.7
B79: =$B18 -> General & Admin | D79: {=IF(ISCLOSED(D$23),0,SUMIFS(tbl_Opex[amount],tbl_Opex[dept],$B79,tbl_Opex[scenario],"Budget",tbl_Opex[month],D$23)*_xlfn.XLOOKUP($B79,$B$16:$B$19,$E$16:$E$19))} -> 0 | E79: {=IF(ISCLOSED(E$23),0,SUMIFS(tbl_Opex[amount],tbl_Opex[dept],$B79,tbl_Opex[scenario],"Budget",tbl_Opex[month],E$23)*_xlfn.XLOOKUP($B79,$B$16:$B$19,$E$16:$E$19))} -> 0 | F79: {=IF(ISCLOSED(F$23),0,SUMIFS(tbl_Opex[amount],tbl_Opex[dept],$B79,tbl_Opex[scenario],"Budget",tbl_Opex[month],F$23)*_xlfn.XLOOKUP($B79,$B$16:$B$19,$E$16:$E$19))} -> 0 | G79: {=IF(ISCLOSED(G$23),0,SUMIFS(tbl_Opex[amount],tbl_Opex[dept],$B79,tbl_Opex[scenario],"Budget",tbl_Opex[month],G$23)*_xlfn.XLOOKUP($B79,$B$16:$B$19,$E$16:$E$19))} -> 0 | H79: {=IF(ISCLOSED(H$23),0,SUMIFS(tbl_Opex[amount],tbl_Opex[dept],$B79,tbl_Opex[scenario],"Budget",tbl_Opex[month],H$23)*_xlfn.XLOOKUP($B79,$B$16:$B$19,$E$16:$E$19))} -> 0 | I79: {=IF(ISCLOSED(I$23),0,SUMIFS(tbl_Opex[amount],tbl_Opex[dept],$B79,tbl_Opex[scenario],"Budget",tbl_Opex[month],I$23)*_xlfn.XLOOKUP($B79,$B$16:$B$19,$E$16:$E$19))} -> 0 | J79: {=IF(ISCLOSED(J$23),0,SUMIFS(tbl_Opex[amount],tbl_Opex[dept],$B79,tbl_Opex[scenario],"Budget",tbl_Opex[month],J$23)*_xlfn.XLOOKUP($B79,$B$16:$B$19,$E$16:$E$19))} -> 0 | K79: {=IF(ISCLOSED(K$23),0,SUMIFS(tbl_Opex[amount],tbl_Opex[dept],$B79,tbl_Opex[scenario],"Budget",tbl_Opex[month],K$23)*_xlfn.XLOOKUP($B79,$B$16:$B$19,$E$16:$E$19))} -> 0 | ... O79: {=IF(ISCLOSED(O$23),0,SUMIFS(tbl_Opex[amount],tbl_Opex[dept],$B79,tbl_Opex[scenario],"Budget",tbl_Opex[month],O$23)*_xlfn.XLOOKUP($B79,$B$16:$B$19,$E$16:$E$19))} -> 183613.78 | P79: =SUM(D79:O79) -> 734455.14
B80: =$B19 -> Technology | D80: {=IF(ISCLOSED(D$23),0,SUMIFS(tbl_Opex[amount],tbl_Opex[dept],$B80,tbl_Opex[scenario],"Budget",tbl_Opex[month],D$23)*_xlfn.XLOOKUP($B80,$B$16:$B$19,$E$16:$E$19))} -> 0 | E80: {=IF(ISCLOSED(E$23),0,SUMIFS(tbl_Opex[amount],tbl_Opex[dept],$B80,tbl_Opex[scenario],"Budget",tbl_Opex[month],E$23)*_xlfn.XLOOKUP($B80,$B$16:$B$19,$E$16:$E$19))} -> 0 | F80: {=IF(ISCLOSED(F$23),0,SUMIFS(tbl_Opex[amount],tbl_Opex[dept],$B80,tbl_Opex[scenario],"Budget",tbl_Opex[month],F$23)*_xlfn.XLOOKUP($B80,$B$16:$B$19,$E$16:$E$19))} -> 0 | G80: {=IF(ISCLOSED(G$23),0,SUMIFS(tbl_Opex[amount],tbl_Opex[dept],$B80,tbl_Opex[scenario],"Budget",tbl_Opex[month],G$23)*_xlfn.XLOOKUP($B80,$B$16:$B$19,$E$16:$E$19))} -> 0 | H80: {=IF(ISCLOSED(H$23),0,SUMIFS(tbl_Opex[amount],tbl_Opex[dept],$B80,tbl_Opex[scenario],"Budget",tbl_Opex[month],H$23)*_xlfn.XLOOKUP($B80,$B$16:$B$19,$E$16:$E$19))} -> 0 | I80: {=IF(ISCLOSED(I$23),0,SUMIFS(tbl_Opex[amount],tbl_Opex[dept],$B80,tbl_Opex[scenario],"Budget",tbl_Opex[month],I$23)*_xlfn.XLOOKUP($B80,$B$16:$B$19,$E$16:$E$19))} -> 0 | J80: {=IF(ISCLOSED(J$23),0,SUMIFS(tbl_Opex[amount],tbl_Opex[dept],$B80,tbl_Opex[scenario],"Budget",tbl_Opex[month],J$23)*_xlfn.XLOOKUP($B80,$B$16:$B$19,$E$16:$E$19))} -> 0 | K80: {=IF(ISCLOSED(K$23),0,SUMIFS(tbl_Opex[amount],tbl_Opex[dept],$B80,tbl_Opex[scenario],"Budget",tbl_Opex[month],K$23)*_xlfn.XLOOKUP($B80,$B$16:$B$19,$E$16:$E$19))} -> 0 | ... O80: {=IF(ISCLOSED(O$23),0,SUMIFS(tbl_Opex[amount],tbl_Opex[dept],$B80,tbl_Opex[scenario],"Budget",tbl_Opex[month],O$23)*_xlfn.XLOOKUP($B80,$B$16:$B$19,$E$16:$E$19))} -> 58232.799 | P80: =SUM(D80:O80) -> 232931.2
B81: Total | D81: =SUM(D77:D80) -> 0 | E81: =SUM(E77:E80) -> 0 | F81: =SUM(F77:F80) -> 0 | G81: =SUM(G77:G80) -> 0 | H81: =SUM(H77:H80) -> 0 | I81: =SUM(I77:I80) -> 0 | J81: =SUM(J77:J80) -> 0 | K81: =SUM(K77:K80) -> 0 | ... P81: =SUM(P77:P80) -> 2988733.1
B84: Forecast operating expenses: baseline × (1 + opex driver)
B85: =$B16 -> Sales & Marketing | D85: =D77*(1+sel_opex) -> 0 | E85: =E77*(1+sel_opex) -> 0 | F85: =F77*(1+sel_opex) -> 0 | G85: =G77*(1+sel_opex) -> 0 | H85: =H77*(1+sel_opex) -> 0 | I85: =I77*(1+sel_opex) -> 0 | J85: =J77*(1+sel_opex) -> 0 | K85: =K77*(1+sel_opex) -> 0 | ... O85: =O77*(1+sel_opex) -> 197885.28 | P85: =SUM(D85:O85) -> 791541.11
B86: =$B17 -> Warehouse & Logistics | D86: =D78*(1+sel_opex) -> 0 | E86: =E78*(1+sel_opex) -> 0 | F86: =F78*(1+sel_opex) -> 0 | G86: =G78*(1+sel_opex) -> 0 | H86: =H78*(1+sel_opex) -> 0 | I86: =I78*(1+sel_opex) -> 0 | J86: =J78*(1+sel_opex) -> 0 | K86: =K78*(1+sel_opex) -> 0 | ... O86: =O78*(1+sel_opex) -> 316406.31 | P86: =SUM(D86:O86) -> 1229805.7
B87: =$B18 -> General & Admin | D87: =D79*(1+sel_opex) -> 0 | E87: =E79*(1+sel_opex) -> 0 | F87: =F79*(1+sel_opex) -> 0 | G87: =G79*(1+sel_opex) -> 0 | H87: =H79*(1+sel_opex) -> 0 | I87: =I79*(1+sel_opex) -> 0 | J87: =J79*(1+sel_opex) -> 0 | K87: =K79*(1+sel_opex) -> 0 | ... O87: =O79*(1+sel_opex) -> 183613.78 | P87: =SUM(D87:O87) -> 734455.14
B88: =$B19 -> Technology | D88: =D80*(1+sel_opex) -> 0 | E88: =E80*(1+sel_opex) -> 0 | F88: =F80*(1+sel_opex) -> 0 | G88: =G80*(1+sel_opex) -> 0 | H88: =H80*(1+sel_opex) -> 0 | I88: =I80*(1+sel_opex) -> 0 | J88: =J80*(1+sel_opex) -> 0 | K88: =K80*(1+sel_opex) -> 0 | ... O88: =O80*(1+sel_opex) -> 58232.799 | P88: =SUM(D88:O88) -> 232931.2
B89: Total | D89: =SUM(D85:D88) -> 0 | E89: =SUM(E85:E88) -> 0 | F89: =SUM(F85:F88) -> 0 | G89: =SUM(G85:G88) -> 0 | H89: =SUM(H85:H88) -> 0 | I89: =SUM(I85:I88) -> 0 | J89: =SUM(J85:J88) -> 0 | K89: =SUM(K85:K88) -> 0 | ... P89: =SUM(P85:P88) -> 2988733.1
B92: How well did the budget call volume? Category × closed month
B93: Actual cases | D93: =D$23 -> 46023 | E93: =E$23 -> 46054 | F93: =F$23 -> 46082 | G93: =G$23 -> 46113 | H93: =H$23 -> 46143 | I93: =I$23 -> 46174 | J93: =J$23 -> 46204 | K93: =K$23 -> 46235 | ... O93: =O$23 -> 46357 | P93: WAPE
B94: =$B6 -> Beef | D94: {=IF(ISCLOSED(D$23),SUMIFS(tbl_Sales[units],tbl_Sales[category],$B94,tbl_Sales[month],D$23),0)} -> 4893 | E94: {=IF(ISCLOSED(E$23),SUMIFS(tbl_Sales[units],tbl_Sales[category],$B94,tbl_Sales[month],E$23),0)} -> 5109 | F94: {=IF(ISCLOSED(F$23),SUMIFS(tbl_Sales[units],tbl_Sales[category],$B94,tbl_Sales[month],F$23),0)} -> 5581 | G94: {=IF(ISCLOSED(G$23),SUMIFS(tbl_Sales[units],tbl_Sales[category],$B94,tbl_Sales[month],G$23),0)} -> 6016 | H94: {=IF(ISCLOSED(H$23),SUMIFS(tbl_Sales[units],tbl_Sales[category],$B94,tbl_Sales[month],H$23),0)} -> 6617 | I94: {=IF(ISCLOSED(I$23),SUMIFS(tbl_Sales[units],tbl_Sales[category],$B94,tbl_Sales[month],I$23),0)} -> 7135 | J94: {=IF(ISCLOSED(J$23),SUMIFS(tbl_Sales[units],tbl_Sales[category],$B94,tbl_Sales[month],J$23),0)} -> 7317 | K94: {=IF(ISCLOSED(K$23),SUMIFS(tbl_Sales[units],tbl_Sales[category],$B94,tbl_Sales[month],K$23),0)} -> 6976 | ... O94: {=IF(ISCLOSED(O$23),SUMIFS(tbl_Sales[units],tbl_Sales[category],$B94,tbl_Sales[month],O$23),0)} -> 0 | P94: {=SAFEDIV(SUMPRODUCT(ABS(D94:O94-D102:O102)),SUM(D94:O94))} -> 0.026891467
B95: =$B7 -> Pork | D95: {=IF(ISCLOSED(D$23),SUMIFS(tbl_Sales[units],tbl_Sales[category],$B95,tbl_Sales[month],D$23),0)} -> 4891 | E95: {=IF(ISCLOSED(E$23),SUMIFS(tbl_Sales[units],tbl_Sales[category],$B95,tbl_Sales[month],E$23),0)} -> 4934 | F95: {=IF(ISCLOSED(F$23),SUMIFS(tbl_Sales[units],tbl_Sales[category],$B95,tbl_Sales[month],F$23),0)} -> 5181 | G95: {=IF(ISCLOSED(G$23),SUMIFS(tbl_Sales[units],tbl_Sales[category],$B95,tbl_Sales[month],G$23),0)} -> 5438 | H95: {=IF(ISCLOSED(H$23),SUMIFS(tbl_Sales[units],tbl_Sales[category],$B95,tbl_Sales[month],H$23),0)} -> 5728 | I95: {=IF(ISCLOSED(I$23),SUMIFS(tbl_Sales[units],tbl_Sales[category],$B95,tbl_Sales[month],I$23),0)} -> 5777 | J95: {=IF(ISCLOSED(J$23),SUMIFS(tbl_Sales[units],tbl_Sales[category],$B95,tbl_Sales[month],J$23),0)} -> 5758 | K95: {=IF(ISCLOSED(K$23),SUMIFS(tbl_Sales[units],tbl_Sales[category],$B95,tbl_Sales[month],K$23),0)} -> 5743 | ... O95: {=IF(ISCLOSED(O$23),SUMIFS(tbl_Sales[units],tbl_Sales[category],$B95,tbl_Sales[month],O$23),0)} -> 0 | P95: {=SAFEDIV(SUMPRODUCT(ABS(D95:O95-D103:O103)),SUM(D95:O95))} -> 0.052428078
B96: =$B8 -> Poultry | D96: {=IF(ISCLOSED(D$23),SUMIFS(tbl_Sales[units],tbl_Sales[category],$B96,tbl_Sales[month],D$23),0)} -> 7156 | E96: {=IF(ISCLOSED(E$23),SUMIFS(tbl_Sales[units],tbl_Sales[category],$B96,tbl_Sales[month],E$23),0)} -> 7480 | F96: {=IF(ISCLOSED(F$23),SUMIFS(tbl_Sales[units],tbl_Sales[category],$B96,tbl_Sales[month],F$23),0)} -> 7705 | G96: {=IF(ISCLOSED(G$23),SUMIFS(tbl_Sales[units],tbl_Sales[category],$B96,tbl_Sales[month],G$23),0)} -> 7693 | H96: {=IF(ISCLOSED(H$23),SUMIFS(tbl_Sales[units],tbl_Sales[category],$B96,tbl_Sales[month],H$23),0)} -> 7750 | I96: {=IF(ISCLOSED(I$23),SUMIFS(tbl_Sales[units],tbl_Sales[category],$B96,tbl_Sales[month],I$23),0)} -> 7870 | J96: {=IF(ISCLOSED(J$23),SUMIFS(tbl_Sales[units],tbl_Sales[category],$B96,tbl_Sales[month],J$23),0)} -> 7881 | K96: {=IF(ISCLOSED(K$23),SUMIFS(tbl_Sales[units],tbl_Sales[category],$B96,tbl_Sales[month],K$23),0)} -> 7895 | ... O96: {=IF(ISCLOSED(O$23),SUMIFS(tbl_Sales[units],tbl_Sales[category],$B96,tbl_Sales[month],O$23),0)} -> 0 | P96: {=SAFEDIV(SUMPRODUCT(ABS(D96:O96-D104:O104)),SUM(D96:O96))} -> 0.046947745
B97: =$B9 -> Seafood | D97: {=IF(ISCLOSED(D$23),SUMIFS(tbl_Sales[units],tbl_Sales[category],$B97,tbl_Sales[month],D$23),0)} -> 2102 | E97: {=IF(ISCLOSED(E$23),SUMIFS(tbl_Sales[units],tbl_Sales[category],$B97,tbl_Sales[month],E$23),0)} -> 2229 | F97: {=IF(ISCLOSED(F$23),SUMIFS(tbl_Sales[units],tbl_Sales[category],$B97,tbl_Sales[month],F$23),0)} -> 2503 | G97: {=IF(ISCLOSED(G$23),SUMIFS(tbl_Sales[units],tbl_Sales[category],$B97,tbl_Sales[month],G$23),0)} -> 2787 | H97: {=IF(ISCLOSED(H$23),SUMIFS(tbl_Sales[units],tbl_Sales[category],$B97,tbl_Sales[month],H$23),0)} -> 3443 | I97: {=IF(ISCLOSED(I$23),SUMIFS(tbl_Sales[units],tbl_Sales[category],$B97,tbl_Sales[month],I$23),0)} -> 3629 | J97: {=IF(ISCLOSED(J$23),SUMIFS(tbl_Sales[units],tbl_Sales[category],$B97,tbl_Sales[month],J$23),0)} -> 3302 | K97: {=IF(ISCLOSED(K$23),SUMIFS(tbl_Sales[units],tbl_Sales[category],$B97,tbl_Sales[month],K$23),0)} -> 3030 | ... O97: {=IF(ISCLOSED(O$23),SUMIFS(tbl_Sales[units],tbl_Sales[category],$B97,tbl_Sales[month],O$23),0)} -> 0 | P97: {=SAFEDIV(SUMPRODUCT(ABS(D97:O97-D105:O105)),SUM(D97:O97))} -> 0.042996743
B98: =$B10 -> Charcuterie | D98: {=IF(ISCLOSED(D$23),SUMIFS(tbl_Sales[units],tbl_Sales[category],$B98,tbl_Sales[month],D$23),0)} -> 1931 | E98: {=IF(ISCLOSED(E$23),SUMIFS(tbl_Sales[units],tbl_Sales[category],$B98,tbl_Sales[month],E$23),0)} -> 1942 | F98: {=IF(ISCLOSED(F$23),SUMIFS(tbl_Sales[units],tbl_Sales[category],$B98,tbl_Sales[month],F$23),0)} -> 2058 | G98: {=IF(ISCLOSED(G$23),SUMIFS(tbl_Sales[units],tbl_Sales[category],$B98,tbl_Sales[month],G$23),0)} -> 2165 | H98: {=IF(ISCLOSED(H$23),SUMIFS(tbl_Sales[units],tbl_Sales[category],$B98,tbl_Sales[month],H$23),0)} -> 2155 | I98: {=IF(ISCLOSED(I$23),SUMIFS(tbl_Sales[units],tbl_Sales[category],$B98,tbl_Sales[month],I$23),0)} -> 2187 | J98: {=IF(ISCLOSED(J$23),SUMIFS(tbl_Sales[units],tbl_Sales[category],$B98,tbl_Sales[month],J$23),0)} -> 2169 | K98: {=IF(ISCLOSED(K$23),SUMIFS(tbl_Sales[units],tbl_Sales[category],$B98,tbl_Sales[month],K$23),0)} -> 2170 | ... O98: {=IF(ISCLOSED(O$23),SUMIFS(tbl_Sales[units],tbl_Sales[category],$B98,tbl_Sales[month],O$23),0)} -> 0 | P98: {=SAFEDIV(SUMPRODUCT(ABS(D98:O98-D106:O106)),SUM(D98:O98))} -> 0.042319843
B99: =$B11 -> Cheese & Dairy | D99: {=IF(ISCLOSED(D$23),SUMIFS(tbl_Sales[units],tbl_Sales[category],$B99,tbl_Sales[month],D$23),0)} -> 2829 | E99: {=IF(ISCLOSED(E$23),SUMIFS(tbl_Sales[units],tbl_Sales[category],$B99,tbl_Sales[month],E$23),0)} -> 2839 | F99: {=IF(ISCLOSED(F$23),SUMIFS(tbl_Sales[units],tbl_Sales[category],$B99,tbl_Sales[month],F$23),0)} -> 3006 | G99: {=IF(ISCLOSED(G$23),SUMIFS(tbl_Sales[units],tbl_Sales[category],$B99,tbl_Sales[month],G$23),0)} -> 3000 | H99: {=IF(ISCLOSED(H$23),SUMIFS(tbl_Sales[units],tbl_Sales[category],$B99,tbl_Sales[month],H$23),0)} -> 2998 | I99: {=IF(ISCLOSED(I$23),SUMIFS(tbl_Sales[units],tbl_Sales[category],$B99,tbl_Sales[month],I$23),0)} -> 2999 | J99: {=IF(ISCLOSED(J$23),SUMIFS(tbl_Sales[units],tbl_Sales[category],$B99,tbl_Sales[month],J$23),0)} -> 3006 | K99: {=IF(ISCLOSED(K$23),SUMIFS(tbl_Sales[units],tbl_Sales[category],$B99,tbl_Sales[month],K$23),0)} -> 3001 | ... O99: {=IF(ISCLOSED(O$23),SUMIFS(tbl_Sales[units],tbl_Sales[category],$B99,tbl_Sales[month],O$23),0)} -> 0 | P99: {=SAFEDIV(SUMPRODUCT(ABS(D99:O99-D107:O107)),SUM(D99:O99))} -> 0.0093335586
B101: Budget cases | D101: =D$23 -> 46023 | E101: =E$23 -> 46054 | F101: =F$23 -> 46082 | G101: =G$23 -> 46113 | H101: =H$23 -> 46143 | I101: =I$23 -> 46174 | J101: =J$23 -> 46204 | K101: =K$23 -> 46235 | ... O101: =O$23 -> 46357
B102: =$B6 -> Beef | D102: {=IF(ISCLOSED(D$23),SUMIFS(tbl_Budget[units],tbl_Budget[category],$B102,tbl_Budget[month],D$23),0)} -> 5044 | E102: {=IF(ISCLOSED(E$23),SUMIFS(tbl_Budget[units],tbl_Budget[category],$B102,tbl_Budget[month],E$23),0)} -> 5063 | F102: {=IF(ISCLOSED(F$23),SUMIFS(tbl_Budget[units],tbl_Budget[category],$B102,tbl_Budget[month],F$23),0)} -> 5408 | G102: {=IF(ISCLOSED(G$23),SUMIFS(tbl_Budget[units],tbl_Budget[category],$B102,tbl_Budget[month],G$23),0)} -> 5883 | H102: {=IF(ISCLOSED(H$23),SUMIFS(tbl_Budget[units],tbl_Budget[category],$B102,tbl_Budget[month],H$23),0)} -> 6433 | I102: {=IF(ISCLOSED(I$23),SUMIFS(tbl_Budget[units],tbl_Budget[category],$B102,tbl_Budget[month],I$23),0)} -> 6989 | J102: {=IF(ISCLOSED(J$23),SUMIFS(tbl_Budget[units],tbl_Budget[category],$B102,tbl_Budget[month],J$23),0)} -> 7026 | K102: {=IF(ISCLOSED(K$23),SUMIFS(tbl_Budget[units],tbl_Budget[category],$B102,tbl_Budget[month],K$23),0)} -> 6765 | ... O102: {=IF(ISCLOSED(O$23),SUMIFS(tbl_Budget[units],tbl_Budget[category],$B102,tbl_Budget[month],O$23),0)} -> 0
B103: =$B7 -> Pork | D103: {=IF(ISCLOSED(D$23),SUMIFS(tbl_Budget[units],tbl_Budget[category],$B103,tbl_Budget[month],D$23),0)} -> 4951 | E103: {=IF(ISCLOSED(E$23),SUMIFS(tbl_Budget[units],tbl_Budget[category],$B103,tbl_Budget[month],E$23),0)} -> 4681 | F103: {=IF(ISCLOSED(F$23),SUMIFS(tbl_Budget[units],tbl_Budget[category],$B103,tbl_Budget[month],F$23),0)} -> 4910 | G103: {=IF(ISCLOSED(G$23),SUMIFS(tbl_Budget[units],tbl_Budget[category],$B103,tbl_Budget[month],G$23),0)} -> 5114 | H103: {=IF(ISCLOSED(H$23),SUMIFS(tbl_Budget[units],tbl_Budget[category],$B103,tbl_Budget[month],H$23),0)} -> 5450 | I103: {=IF(ISCLOSED(I$23),SUMIFS(tbl_Budget[units],tbl_Budget[category],$B103,tbl_Budget[month],I$23),0)} -> 5371 | J103: {=IF(ISCLOSED(J$23),SUMIFS(tbl_Budget[units],tbl_Budget[category],$B103,tbl_Budget[month],J$23),0)} -> 5402 | K103: {=IF(ISCLOSED(K$23),SUMIFS(tbl_Budget[units],tbl_Budget[category],$B103,tbl_Budget[month],K$23),0)} -> 5413 | ... O103: {=IF(ISCLOSED(O$23),SUMIFS(tbl_Budget[units],tbl_Budget[category],$B103,tbl_Budget[month],O$23),0)} -> 0
B104: =$B8 -> Poultry | D104: {=IF(ISCLOSED(D$23),SUMIFS(tbl_Budget[units],tbl_Budget[category],$B104,tbl_Budget[month],D$23),0)} -> 7202 | E104: {=IF(ISCLOSED(E$23),SUMIFS(tbl_Budget[units],tbl_Budget[category],$B104,tbl_Budget[month],E$23),0)} -> 7080 | F104: {=IF(ISCLOSED(F$23),SUMIFS(tbl_Budget[units],tbl_Budget[category],$B104,tbl_Budget[month],F$23),0)} -> 7288 | G104: {=IF(ISCLOSED(G$23),SUMIFS(tbl_Budget[units],tbl_Budget[category],$B104,tbl_Budget[month],G$23),0)} -> 7288 | H104: {=IF(ISCLOSED(H$23),SUMIFS(tbl_Budget[units],tbl_Budget[category],$B104,tbl_Budget[month],H$23),0)} -> 7413 | I104: {=IF(ISCLOSED(I$23),SUMIFS(tbl_Budget[units],tbl_Budget[category],$B104,tbl_Budget[month],I$23),0)} -> 7523 | J104: {=IF(ISCLOSED(J$23),SUMIFS(tbl_Budget[units],tbl_Budget[category],$B104,tbl_Budget[month],J$23),0)} -> 7478 | K104: {=IF(ISCLOSED(K$23),SUMIFS(tbl_Budget[units],tbl_Budget[category],$B104,tbl_Budget[month],K$23),0)} -> 7366 | ... O104: {=IF(ISCLOSED(O$23),SUMIFS(tbl_Budget[units],tbl_Budget[category],$B104,tbl_Budget[month],O$23),0)} -> 0
B105: =$B9 -> Seafood | D105: {=IF(ISCLOSED(D$23),SUMIFS(tbl_Budget[units],tbl_Budget[category],$B105,tbl_Budget[month],D$23),0)} -> 2135 | E105: {=IF(ISCLOSED(E$23),SUMIFS(tbl_Budget[units],tbl_Budget[category],$B105,tbl_Budget[month],E$23),0)} -> 2090 | F105: {=IF(ISCLOSED(F$23),SUMIFS(tbl_Budget[units],tbl_Budget[category],$B105,tbl_Budget[month],F$23),0)} -> 2404 | G105: {=IF(ISCLOSED(G$23),SUMIFS(tbl_Budget[units],tbl_Budget[category],$B105,tbl_Budget[month],G$23),0)} -> 2637 | H105: {=IF(ISCLOSED(H$23),SUMIFS(tbl_Budget[units],tbl_Budget[category],$B105,tbl_Budget[month],H$23),0)} -> 3292 | I105: {=IF(ISCLOSED(I$23),SUMIFS(tbl_Budget[units],tbl_Budget[category],$B105,tbl_Budget[month],I$23),0)} -> 3421 | J105: {=IF(ISCLOSED(J$23),SUMIFS(tbl_Budget[units],tbl_Budget[category],$B105,tbl_Budget[month],J$23),0)} -> 3195 | K105: {=IF(ISCLOSED(K$23),SUMIFS(tbl_Budget[units],tbl_Budget[category],$B105,tbl_Budget[month],K$23),0)} -> 2927 | ... O105: {=IF(ISCLOSED(O$23),SUMIFS(tbl_Budget[units],tbl_Budget[category],$B105,tbl_Budget[month],O$23),0)} -> 0
B106: =$B10 -> Charcuterie | D106: {=IF(ISCLOSED(D$23),SUMIFS(tbl_Budget[units],tbl_Budget[category],$B106,tbl_Budget[month],D$23),0)} -> 1971 | E106: {=IF(ISCLOSED(E$23),SUMIFS(tbl_Budget[units],tbl_Budget[category],$B106,tbl_Budget[month],E$23),0)} -> 1866 | F106: {=IF(ISCLOSED(F$23),SUMIFS(tbl_Budget[units],tbl_Budget[category],$B106,tbl_Budget[month],F$23),0)} -> 1951 | G106: {=IF(ISCLOSED(G$23),SUMIFS(tbl_Budget[units],tbl_Budget[category],$B106,tbl_Budget[month],G$23),0)} -> 2076 | H106: {=IF(ISCLOSED(H$23),SUMIFS(tbl_Budget[units],tbl_Budget[category],$B106,tbl_Budget[month],H$23),0)} -> 2080 | I106: {=IF(ISCLOSED(I$23),SUMIFS(tbl_Budget[units],tbl_Budget[category],$B106,tbl_Budget[month],I$23),0)} -> 2058 | J106: {=IF(ISCLOSED(J$23),SUMIFS(tbl_Budget[units],tbl_Budget[category],$B106,tbl_Budget[month],J$23),0)} -> 2061 | K106: {=IF(ISCLOSED(K$23),SUMIFS(tbl_Budget[units],tbl_Budget[category],$B106,tbl_Budget[month],K$23),0)} -> 2084 | ... O106: {=IF(ISCLOSED(O$23),SUMIFS(tbl_Budget[units],tbl_Budget[category],$B106,tbl_Budget[month],O$23),0)} -> 0
B107: =$B11 -> Cheese & Dairy | D107: {=IF(ISCLOSED(D$23),SUMIFS(tbl_Budget[units],tbl_Budget[category],$B107,tbl_Budget[month],D$23),0)} -> 2959 | E107: {=IF(ISCLOSED(E$23),SUMIFS(tbl_Budget[units],tbl_Budget[category],$B107,tbl_Budget[month],E$23),0)} -> 2820 | F107: {=IF(ISCLOSED(F$23),SUMIFS(tbl_Budget[units],tbl_Budget[category],$B107,tbl_Budget[month],F$23),0)} -> 2993 | G107: {=IF(ISCLOSED(G$23),SUMIFS(tbl_Budget[units],tbl_Budget[category],$B107,tbl_Budget[month],G$23),0)} -> 3012 | H107: {=IF(ISCLOSED(H$23),SUMIFS(tbl_Budget[units],tbl_Budget[category],$B107,tbl_Budget[month],H$23),0)} -> 2998 | I107: {=IF(ISCLOSED(I$23),SUMIFS(tbl_Budget[units],tbl_Budget[category],$B107,tbl_Budget[month],I$23),0)} -> 3000 | J107: {=IF(ISCLOSED(J$23),SUMIFS(tbl_Budget[units],tbl_Budget[category],$B107,tbl_Budget[month],J$23),0)} -> 2987 | K107: {=IF(ISCLOSED(K$23),SUMIFS(tbl_Budget[units],tbl_Budget[category],$B107,tbl_Budget[month],K$23),0)} -> 2974 | ... O107: {=IF(ISCLOSED(O$23),SUMIFS(tbl_Budget[units],tbl_Budget[category],$B107,tbl_Budget[month],O$23),0)} -> 0
B109: Budget accuracy, all categories: WAPE | D109: {=SAFEDIV(SUMPRODUCT(ABS(D94:O99-D102:O107)),SUM(D94:O99))} -> 0.03861397 | F109: Weighted absolute percentage error: the share of cases the budget placed in the wrong category-month.
B110: Bias: (budget − actual) ÷ actual | D110: {=SAFEDIV(SUM(D102:O107)-SUM(D94:O99),SUM(D94:O99))} -> -0.0342746 | F110: ="Below zero means the budget under-called volume"&IF(D110<0,": the year sold more cases than planned.",".") -> Below zero means the budget under-called volume: the year sold more cases than planned.
B113: Cross-check: a statistical forecast of total revenue (FORECAST.ETS, 12-month seasonality)
B114: Month | D114: =D$23 -> 46023 | E114: =E$23 -> 46054 | F114: =F$23 -> 46082 | G114: =G$23 -> 46113 | H114: =H$23 -> 46143 | I114: =I$23 -> 46174 | J114: =J$23 -> 46204 | K114: =K$23 -> 46235 | ... O114: =O$23 -> 46357 | P114: Open months
B115: Driver forecast | D115: {=IF(ISCLOSED(D$23),"",D$53)} | E115: {=IF(ISCLOSED(E$23),"",E$53)} | F115: {=IF(ISCLOSED(F$23),"",F$53)} | G115: {=IF(ISCLOSED(G$23),"",G$53)} | H115: {=IF(ISCLOSED(H$23),"",H$53)} | I115: {=IF(ISCLOSED(I$23),"",I$53)} | J115: {=IF(ISCLOSED(J$23),"",J$53)} | K115: {=IF(ISCLOSED(K$23),"",K$53)} | ... O115: {=IF(ISCLOSED(O$23),"",O$53)} -> 4248799 | P115: =SUM(D115:O115) -> 15873707
B116: FORECAST.ETS | D116: {=IF(ISCLOSED(D$23),"",_xlfn.FORECAST.ETS(MATCH(D$23,$B$123:$B$158,0),$D$123:INDEX($D$123:$D$158,MATCH(AsOfMonth,$B$123:$B$158,0)),$C$123:INDEX($C$123:$C$158,MATCH(AsOfMonth,$B$123:$B$158,0)),12))} | E116: {=IF(ISCLOSED(E$23),"",_xlfn.FORECAST.ETS(MATCH(E$23,$B$123:$B$158,0),$D$123:INDEX($D$123:$D$158,MATCH(AsOfMonth,$B$123:$B$158,0)),$C$123:INDEX($C$123:$C$158,MATCH(AsOfMonth,$B$123:$B$158,0)),12))} | F116: {=IF(ISCLOSED(F$23),"",_xlfn.FORECAST.ETS(MATCH(F$23,$B$123:$B$158,0),$D$123:INDEX($D$123:$D$158,MATCH(AsOfMonth,$B$123:$B$158,0)),$C$123:INDEX($C$123:$C$158,MATCH(AsOfMonth,$B$123:$B$158,0)),12))} | G116: {=IF(ISCLOSED(G$23),"",_xlfn.FORECAST.ETS(MATCH(G$23,$B$123:$B$158,0),$D$123:INDEX($D$123:$D$158,MATCH(AsOfMonth,$B$123:$B$158,0)),$C$123:INDEX($C$123:$C$158,MATCH(AsOfMonth,$B$123:$B$158,0)),12))} | H116: {=IF(ISCLOSED(H$23),"",_xlfn.FORECAST.ETS(MATCH(H$23,$B$123:$B$158,0),$D$123:INDEX($D$123:$D$158,MATCH(AsOfMonth,$B$123:$B$158,0)),$C$123:INDEX($C$123:$C$158,MATCH(AsOfMonth,$B$123:$B$158,0)),12))} | I116: {=IF(ISCLOSED(I$23),"",_xlfn.FORECAST.ETS(MATCH(I$23,$B$123:$B$158,0),$D$123:INDEX($D$123:$D$158,MATCH(AsOfMonth,$B$123:$B$158,0)),$C$123:INDEX($C$123:$C$158,MATCH(AsOfMonth,$B$123:$B$158,0)),12))} | J116: {=IF(ISCLOSED(J$23),"",_xlfn.FORECAST.ETS(MATCH(J$23,$B$123:$B$158,0),$D$123:INDEX($D$123:$D$158,MATCH(AsOfMonth,$B$123:$B$158,0)),$C$123:INDEX($C$123:$C$158,MATCH(AsOfMonth,$B$123:$B$158,0)),12))} | K116: {=IF(ISCLOSED(K$23),"",_xlfn.FORECAST.ETS(MATCH(K$23,$B$123:$B$158,0),$D$123:INDEX($D$123:$D$158,MATCH(AsOfMonth,$B$123:$B$158,0)),$C$123:INDEX($C$123:$C$158,MATCH(AsOfMonth,$B$123:$B$158,0)),12))} | ... O116: {=IF(ISCLOSED(O$23),"",_xlfn.FORECAST.ETS(MATCH(O$23,$B$123:$B$158,0),$D$123:INDEX($D$123:$D$158,MATCH(AsOfMonth,$B$123:$B$158,0)),$C$123:INDEX($C$123:$C$158,MATCH(AsOfMonth,$B$123:$B$158,0)),12))} -> 4296635.5 | P116: =SUM(D116:O116) -> 16155635
B117: Driver vs statistical | D117: {=IF(ISCLOSED(D$23),"",SAFEDIV(D115-D116,D116))} | E117: {=IF(ISCLOSED(E$23),"",SAFEDIV(E115-E116,E116))} | F117: {=IF(ISCLOSED(F$23),"",SAFEDIV(F115-F116,F116))} | G117: {=IF(ISCLOSED(G$23),"",SAFEDIV(G115-G116,G116))} | H117: {=IF(ISCLOSED(H$23),"",SAFEDIV(H115-H116,H116))} | I117: {=IF(ISCLOSED(I$23),"",SAFEDIV(I115-I116,I116))} | J117: {=IF(ISCLOSED(J$23),"",SAFEDIV(J115-J116,J116))} | K117: {=IF(ISCLOSED(K$23),"",SAFEDIV(K115-K116,K116))} | ... O117: {=IF(ISCLOSED(O$23),"",SAFEDIV(O115-O116,O116))} -> -0.011133463 | P117: {=SAFEDIV(P115-P116,P116)} -> -0.017450746
B118: ="Over the open months the driver forecast sits "&TEXT(ABS(P117),"0.0%")&IF(P117>=0," above"," below")&" a purely statistical projection of the same history. A gap this size says the drivers, not the trend, are doing the work: check them before trusting either." -> Over the open months the driver forecast sits 1.7% below a purely statistical projection of the same history. A gap this size says the drivers, not the trend, are doing the work: check them before trusting either.
B121: History feeding FORECAST.ETS: total revenue by month
B122: Month | C122: Index | D122: Revenue
B123: =EDATE(FYStart,-24) -> 45292 | C123: =ROWS($B$123:B123) -> 1 | D123: =IF(B123<=AsOfMonth,SUMIFS(tbl_Sales[net_revenue],tbl_Sales[month],B123),"") -> 3022888.2
B124: =EDATE(B123,1) -> 45323 | C124: =ROWS($B$123:B124) -> 2 | D124: =IF(B124<=AsOfMonth,SUMIFS(tbl_Sales[net_revenue],tbl_Sales[month],B124),"") -> 2945002.7
...

Sheet Scenarios
B1: Scenarios, sensitivities and the gap to budget
B2: Pick a scenario in C4 and every sheet follows. The tables below are Excel what-if data tables: they re-run the whole forecast for each scenario and for every price × volume pair.
B4: Scenario | C4: Base | D4: =MATCH(C4,ScenarioList,0) -> 1 | E4: Base, Upside or Downside: the driver sets are on Assumptions.
B5: Price overlay | C5: 0 | E5: Added to the scenario's price driver.
B6: Volume overlay | C6: 0 | E6: Added to the scenario's volume driver.
B8: Live outputs for the selected scenario, full year
B9: FY revenue | C9: =PnL!P8 -> 47407338
B10: FY gross margin | C10: =PnL!P10 -> 12300856
B11: FY EBITDA | C11: =PnL!P19 -> 2319179.9
B12: FY EBITDA margin | C12: =PnL!P20 -> 0.048920272
B13: FY EBITDA vs budget | C13: =PnL!R19 -> -412477.17
B15: Scenario comparison, full year: a one-variable data table on C4
B16: Scenario | C16: Revenue | D16: Gross margin | E16: EBITDA | F16: EBITDA margin | G16: EBITDA vs budget
B17: Live selection | C17: =C9 -> 47407338 | D17: =C10 -> 12300856 | E17: =C11 -> 2319179.9 | F17: =C12 -> 0.048920272 | G17: =C13 -> -412477.17
B18: Base | C18: 47407338 | D18: 12300856 | E18: 2319179.9 | F18: 0.048920272 | G18: -412477.17
B19: Upside | C19: 48128798 | D19: 12791327 | E19: 2836094 | F19: 0.058927173 | G19: 104436.97
B20: Downside | C20: 46620002 | D20: 11701125 | E20: 1656743 | F20: 0.035537171 | G20: -1074914
B21: Budget | C21: =PnL!Q8 -> 45768802 | D21: =PnL!Q10 -> 12389803 | E21: =PnL!Q19 -> 2731657 | F21: =PnL!Q20 -> 0.059683822
B23: FY EBITDA sensitivity: price change down the side, volume change across the top (two-variable data table on C5 and C6)
B24: Price ↓ Volume →
B25: =C11 -> 2319179.9 | C25: -0.06 | D25: -0.04 | E25: -0.02 | F25: 0 | G25: 0.02 | H25: 0.04 | I25: 0.06
B26: -0.03 | C26: 1644623.6 | D26: 1710738.6 | E26: 1776853.6 | F26: 1842968.6 | G26: 1909083.7 | H26: 1975198.7 | I26: 2041313.7
B27: -0.02 | C27: 1793836.4 | D27: 1863126.2 | E27: 1932416 | F27: 2001705.7 | G27: 2070995.5 | H27: 2140285.3 | I27: 2209575
B28: -0.01 | C28: 1943049.3 | D28: 2015513.8 | E28: 2087978.3 | F28: 2160442.8 | G28: 2232907.3 | H28: 2305371.8 | I28: 2377836.3
B29: 0 | C29: 2092262.1 | D29: 2167901.4 | E29: 2243540.6 | F29: 2319179.9 | G29: 2394819.1 | H29: 2470458.4 | I29: 2546097.6
B30: 0.01 | C30: 2241475 | D30: 2320289 | E30: 2399102.9 | F30: 2477916.9 | G30: 2556730.9 | H30: 2635544.9 | I30: 2714358.9
B31: 0.02 | C31: 2390687.8 | D31: 2472676.5 | E31: 2554665.3 | F31: 2636654 | G31: 2718642.7 | H31: 2800631.5 | I31: 2882620.2
B32: 0.03 | C32: 2539900.7 | D32: 2625064.1 | E32: 2710227.6 | F32: 2795391.1 | G32: 2880554.6 | H32: 2965718 | I32: 3050881.5
B34: Which driver matters most: full-year EBITDA impact of one step on each driver
B35: Step | C35: 0.01 | D35: Exact, not an estimate: the forecast is linear in each driver.
B36: Driver | C36: FY EBITDA impact | D36: Rank | S36: Chart data: drivers sorted by size (SORTBY + HSTACK)
B37: Volume | C37: {=SUMPRODUCT(Forecast!$P$27:$P$32,Forecast!$M$6:$M$11)*TornadoStep} -> 37819.624 | D37: {=SUMPRODUCT(--(ABS($C$37:$C$41)>ABS(C37)))+1} -> 3 | S37: {=_xlfn.SORTBY(_xlfn.HSTACK(B37:B41,C37:C41),ABS(C37:C41),1)} -> Freight per case | T37: -3664.2588
B38: Price | C38: {=SUMPRODUCT(Forecast!$P$37:$P$42,Forecast!$J$6:$J$11)*TornadoStep} -> 158737.07 | D38: {=SUMPRODUCT(--(ABS($C$37:$C$41)>ABS(C38)))+1} -> 1 | S38: Operating expenses | T38: -29887.331
B39: Unit cost | C39: {=-SUMPRODUCT(Forecast!$P$37:$P$42,Forecast!$K$6:$K$11)*TornadoStep} -> -117253.19 | D39: {=SUMPRODUCT(--(ABS($C$37:$C$41)>ABS(C39)))+1} -> 2 | S39: Volume | T39: 37819.624
B40: Freight per case | C40: {=-SUMPRODUCT(Forecast!$P$37:$P$42,Forecast!$L$6:$L$11)*TornadoStep} -> -3664.2588 | D40: {=SUMPRODUCT(--(ABS($C$37:$C$41)>ABS(C40)))+1} -> 5 | S40: Unit cost | T40: -117253.19
B41: Operating expenses | C41: {=-Forecast!$P$81*TornadoStep} -> -29887.331 | D41: {=SUMPRODUCT(--(ABS($C$37:$C$41)>ABS(C41)))+1} -> 4 | S41: Price | T41: 158737.07
B43: What would it take to hit budget?
B44: Full-year EBITDA gap to budget | C44: =PnL!Q19-PnL!P19 -> 412477.17
B45: Open-month revenue at trailing prices | C45: =SUMPRODUCT(Forecast!$P$37:$P$42,Forecast!$J$6:$J$11) -> 15873707
B46: Price rise needed on the open months | C46: {=SAFEDIV(MAX(C44,0),C45)} -> 0.02598493
B47: …or extra volume at today's margins | C47: {=SAFEDIV(MAX(C44,0),SUMPRODUCT(Forecast!$P$27:$P$32,Forecast!$M$6:$M$11))} -> 0.10906432
B48: {=IF(C44<=0,"The "&ScenarioName&" outlook already meets the budget's full-year EBITDA.","Budget needs "&MONEY(C44)&" more EBITDA than the "&ScenarioName&" outlook. That is a "&TEXT(C46,"0.0%")&" price rise on the "&(12-MonthsClosed)&" open months, or "&TEXT(C47,"0%")&" more volume at today's margins: price is the lever, volume is not.")} -> Budget needs $412K more EBITDA than the Base outlook. That is a 2.6% price rise on the 4 open months, or 11% more volume at today's margins: price is the lever, volume is not.

Sheet WorkingCapital
B1: Working capital: cash tied up, and stock close to its shelf life
B2: ="Days are balances over the trailing "&TrailMonths&" months of flow ("&WCDays&" days). Month-end balances from tbl_Balances; flows from tbl_Sales." -> Days are balances over the trailing 3 months of flow (91 days). Month-end balances from tbl_Balances; flows from tbl_Sales.
B4: Trend: thirteen month-ends to the as-of month
B5: Month-end | C5: =EDATE(AsOfMonth,-12) -> 45870 | D5: =EDATE(C5,1) -> 45901 | E5: =EDATE(D5,1) -> 45931 | F5: =EDATE(E5,1) -> 45962 | G5: =EDATE(F5,1) -> 45992 | H5: =EDATE(G5,1) -> 46023 | I5: =EDATE(H5,1) -> 46054 | J5: =EDATE(I5,1) -> 46082 | K5: =EDATE(J5,1) -> 46113 | ... O5: =EDATE(N5,1) -> 46235
B6: Accounts receivable | C6: =SUMIFS(tbl_Balances[balance],tbl_Balances[month],C$5,tbl_Balances[account],$B6) -> 3884003.3 | D6: =SUMIFS(tbl_Balances[balance],tbl_Balances[month],D$5,tbl_Balances[account],$B6) -> 3814133.4 | E6: =SUMIFS(tbl_Balances[balance],tbl_Balances[month],E$5,tbl_Balances[account],$B6) -> 3764948.1 | F6: =SUMIFS(tbl_Balances[balance],tbl_Balances[month],F$5,tbl_Balances[account],$B6) -> 3688045 | G6: =SUMIFS(tbl_Balances[balance],tbl_Balances[month],G$5,tbl_Balances[account],$B6) -> 4056966 | H6: =SUMIFS(tbl_Balances[balance],tbl_Balances[month],H$5,tbl_Balances[account],$B6) -> 3542836.9 | I6: =SUMIFS(tbl_Balances[balance],tbl_Balances[month],I$5,tbl_Balances[account],$B6) -> 3802872.7 | J6: =SUMIFS(tbl_Balances[balance],tbl_Balances[month],J$5,tbl_Balances[account],$B6) -> 3963240.3 | ... O6: =SUMIFS(tbl_Balances[balance],tbl_Balances[month],O$5,tbl_Balances[account],$B6) -> 4501878.4
B7: Inventory | C7: =SUMIFS(tbl_Balances[balance],tbl_Balances[month],C$5,tbl_Balances[account],$B7) -> 1398347.9 | D7: =SUMIFS(tbl_Balances[balance],tbl_Balances[month],D$5,tbl_Balances[account],$B7) -> 1346687.2 | E7: =SUMIFS(tbl_Balances[balance],tbl_Balances[month],E$5,tbl_Balances[account],$B7) -> 1363037.6 | F7: =SUMIFS(tbl_Balances[balance],tbl_Balances[month],F$5,tbl_Balances[account],$B7) -> 1438889.6 | G7: =SUMIFS(tbl_Balances[balance],tbl_Balances[month],G$5,tbl_Balances[account],$B7) -> 1552604.1 | H7: =SUMIFS(tbl_Balances[balance],tbl_Balances[month],H$5,tbl_Balances[account],$B7) -> 1290933.9 | I7: =SUMIFS(tbl_Balances[balance],tbl_Balances[month],I$5,tbl_Balances[account],$B7) -> 1337453.8 | J7: =SUMIFS(tbl_Balances[balance],tbl_Balances[month],J$5,tbl_Balances[account],$B7) -> 1446445 | ... O7: =SUMIFS(tbl_Balances[balance],tbl_Balances[month],O$5,tbl_Balances[account],$B7) -> 1715054.6
B8: Accounts payable | C8: =SUMIFS(tbl_Balances[balance],tbl_Balances[month],C$5,tbl_Balances[account],$B8) -> 2517050.6 | D8: =SUMIFS(tbl_Balances[balance],tbl_Balances[month],D$5,tbl_Balances[account],$B8) -> 2367141.5 | E8: =SUMIFS(tbl_Balances[balance],tbl_Balances[month],E$5,tbl_Balances[account],$B8) -> 2313271.6 | F8: =SUMIFS(tbl_Balances[balance],tbl_Balances[month],F$5,tbl_Balances[account],$B8) -> 2380026.2 | G8: =SUMIFS(tbl_Balances[balance],tbl_Balances[month],G$5,tbl_Balances[account],$B8) -> 2636317.3 | H8: =SUMIFS(tbl_Balances[balance],tbl_Balances[month],H$5,tbl_Balances[account],$B8) -> 2250848 | I8: =SUMIFS(tbl_Balances[balance],tbl_Balances[month],I$5,tbl_Balances[account],$B8) -> 2337128.3 | J8: =SUMIFS(tbl_Balances[balance],tbl_Balances[month],J$5,tbl_Balances[account],$B8) -> 2515054.6 | ... O8: =SUMIFS(tbl_Balances[balance],tbl_Balances[month],O$5,tbl_Balances[account],$B8) -> 2903700.3
B9: Net working capital | C9: =C6+C7-C8 -> 2765300.6 | D9: =D6+D7-D8 -> 2793679.1 | E9: =E6+E7-E8 -> 2814714.2 | F9: =F6+F7-F8 -> 2746908.4 | G9: =G6+G7-G8 -> 2973252.8 | H9: =H6+H7-H8 -> 2582922.8 | I9: =I6+I7-I8 -> 2803198.2 | J9: =J6+J7-J8 -> 2894630.7 | ... O9: =O6+O7-O8 -> 3313232.7
B10: Trailing revenue | C10: =SUMIFS(tbl_Sales[net_revenue],tbl_Sales[month],">="&EDATE(C$5,1-TrailMonths),tbl_Sales[month],"<="&C$5) -> 11488383 | D10: =SUMIFS(tbl_Sales[net_revenue],tbl_Sales[month],">="&EDATE(D$5,1-TrailMonths),tbl_Sales[month],"<="&D$5) -> 11124770 | E10: =SUMIFS(tbl_Sales[net_revenue],tbl_Sales[month],">="&EDATE(E$5,1-TrailMonths),tbl_Sales[month],"<="&E$5) -> 10741330 | F10: =SUMIFS(tbl_Sales[net_revenue],tbl_Sales[month],">="&EDATE(F$5,1-TrailMonths),tbl_Sales[month],"<="&F$5) -> 10507809 | G10: =SUMIFS(tbl_Sales[net_revenue],tbl_Sales[month],">="&EDATE(G$5,1-TrailMonths),tbl_Sales[month],"<="&G$5) -> 10822453 | H10: =SUMIFS(tbl_Sales[net_revenue],tbl_Sales[month],">="&EDATE(H$5,1-TrailMonths),tbl_Sales[month],"<="&H$5) -> 10743815 | I10: =SUMIFS(tbl_Sales[net_revenue],tbl_Sales[month],">="&EDATE(I$5,1-TrailMonths),tbl_Sales[month],"<="&I$5) -> 10713707 | J10: =SUMIFS(tbl_Sales[net_revenue],tbl_Sales[month],">="&EDATE(J$5,1-TrailMonths),tbl_Sales[month],"<="&J$5) -> 10598807 | ... O10: =SUMIFS(tbl_Sales[net_revenue],tbl_Sales[month],">="&EDATE(O$5,1-TrailMonths),tbl_Sales[month],"<="&O$5) -> 12848107
B11: Trailing COGS | C11: =SUMIFS(tbl_Sales[cogs],tbl_Sales[month],">="&EDATE(C$5,1-TrailMonths),tbl_Sales[month],"<="&C$5) -> 8510411 | D11: =SUMIFS(tbl_Sales[cogs],tbl_Sales[month],">="&EDATE(D$5,1-TrailMonths),tbl_Sales[month],"<="&D$5) -> 8224792.7 | E11: =SUMIFS(tbl_Sales[cogs],tbl_Sales[month],">="&EDATE(E$5,1-TrailMonths),tbl_Sales[month],"<="&E$5) -> 7912193 | F11: =SUMIFS(tbl_Sales[cogs],tbl_Sales[month],">="&EDATE(F$5,1-TrailMonths),tbl_Sales[month],"<="&F$5) -> 7704113.1 | G11: =SUMIFS(tbl_Sales[cogs],tbl_Sales[month],">="&EDATE(G$5,1-TrailMonths),tbl_Sales[month],"<="&G$5) -> 7908668.1 | H11: =SUMIFS(tbl_Sales[cogs],tbl_Sales[month],">="&EDATE(H$5,1-TrailMonths),tbl_Sales[month],"<="&H$5) -> 7832413.5 | I11: =SUMIFS(tbl_Sales[cogs],tbl_Sales[month],">="&EDATE(I$5,1-TrailMonths),tbl_Sales[month],"<="&I$5) -> 7824234.1 | J11: =SUMIFS(tbl_Sales[cogs],tbl_Sales[month],">="&EDATE(J$5,1-TrailMonths),tbl_Sales[month],"<="&J$5) -> 7759663.4 | ... O11: =SUMIFS(tbl_Sales[cogs],tbl_Sales[month],">="&EDATE(O$5,1-TrailMonths),tbl_Sales[month],"<="&O$5) -> 9618870.9
B12: DSO (days sales outstanding) | C12: {=DAYSOF(C6,C10,WCDays)} -> 30.765364 | D12: {=DAYSOF(D6,D10,WCDays)} -> 31.199398 | E12: {=DAYSOF(E6,E10,WCDays)} -> 31.896448 | F12: {=DAYSOF(F6,F10,WCDays)} -> 31.939301 | G12: {=DAYSOF(G6,G10,WCDays)} -> 34.112775 | H12: {=DAYSOF(H6,H10,WCDays)} -> 30.007792 | I12: {=DAYSOF(I6,I10,WCDays)} -> 32.30081 | J12: {=DAYSOF(J6,J10,WCDays)} -> 34.027873 | ... O12: {=DAYSOF(O6,O10,WCDays)} -> 31.885704
B13: DIO (days inventory outstanding) | C13: {=DAYSOF(C7,C11,WCDays)} -> 14.952234 | D13: {=DAYSOF(D7,D11,WCDays)} -> 14.899894 | E13: {=DAYSOF(E7,E11,WCDays)} -> 15.676618 | F13: {=DAYSOF(F7,F11,WCDays)} -> 16.99598 | G13: {=DAYSOF(G7,G11,WCDays)} -> 17.864826 | H13: {=DAYSOF(H7,H11,WCDays)} -> 14.998567 | I13: {=DAYSOF(I7,I11,WCDays)} -> 15.555298 | J13: {=DAYSOF(J7,J11,WCDays)} -> 16.962914 | ... O13: {=DAYSOF(O7,O11,WCDays)} -> 16.225394
B14: DPO (days payables outstanding) | C14: {=DAYSOF(C8,C11,WCDays)} -> 26.914282 | D14: {=DAYSOF(D8,D11,WCDays)} -> 26.190311 | E14: {=DAYSOF(E8,E11,WCDays)} -> 26.605483 | F14: {=DAYSOF(F8,F11,WCDays)} -> 28.112566 | G14: {=DAYSOF(G8,G11,WCDays)} -> 30.334422 | H14: {=DAYSOF(H8,H11,WCDays)} -> 26.151219 | I14: {=DAYSOF(I8,I11,WCDays)} -> 27.182044 | J14: {=DAYSOF(J8,J11,WCDays)} -> 29.494832 | ... O14: {=DAYSOF(O8,O11,WCDays)} -> 27.47066
B15: Cash conversion cycle (DSO + DIO − DPO) | C15: =C12+C13-C14 -> 18.803316 | D15: =D12+D13-D14 -> 19.90898 | E15: =E12+E13-E14 -> 20.967583 | F15: =F12+F13-F14 -> 20.822716 | G15: =G12+G13-G14 -> 21.643179 | H15: =H12+H13-H14 -> 18.85514 | I15: =I12+I13-I14 -> 20.674065 | J15: =J12+J13-J14 -> 21.495954 | ... O15: =O12+O13-O14 -> 20.640439
B17: Days of inventory by category
B18: Category | C18: =C$5 -> 45870 | D18: =D$5 -> 45901 | E18: =E$5 -> 45931 | F18: =F$5 -> 45962 | G18: =G$5 -> 45992 | H18: =H$5 -> 46023 | I18: =I$5 -> 46054 | J18: =J$5 -> 46082 | ... O18: =O$5 -> 46235
B19: Beef | C19: {=DAYSOF(SUMIFS(tbl_Balances[balance],tbl_Balances[month],C$18,tbl_Balances[account],"Inventory",tbl_Balances[category],$B19),SUMIFS(tbl_Sales[cogs],tbl_Sales[category],$B19,tbl_Sales[month],">="&EDATE(C$18,1-TrailMonths),tbl_Sales[month],"<="&C$18),WCDays)} -> 15.67239 | D19: {=DAYSOF(SUMIFS(tbl_Balances[balance],tbl_Balances[month],D$18,tbl_Balances[account],"Inventory",tbl_Balances[category],$B19),SUMIFS(tbl_Sales[cogs],tbl_Sales[category],$B19,tbl_Sales[month],">="&EDATE(D$18,1-TrailMonths),tbl_Sales[month],"<="&D$18),WCDays)} -> 14.281388 | E19: {=DAYSOF(SUMIFS(tbl_Balances[balance],tbl_Balances[month],E$18,tbl_Balances[account],"Inventory",tbl_Balances[category],$B19),SUMIFS(tbl_Sales[cogs],tbl_Sales[category],$B19,tbl_Sales[month],">="&EDATE(E$18,1-TrailMonths),tbl_Sales[month],"<="&E$18),WCDays)} -> 14.513319 | F19: {=DAYSOF(SUMIFS(tbl_Balances[balance],tbl_Balances[month],F$18,tbl_Balances[account],"Inventory",tbl_Balances[category],$B19),SUMIFS(tbl_Sales[cogs],tbl_Sales[category],$B19,tbl_Sales[month],">="&EDATE(F$18,1-TrailMonths),tbl_Sales[month],"<="&F$18),WCDays)} -> 15.212799 | G19: {=DAYSOF(SUMIFS(tbl_Balances[balance],tbl_Balances[month],G$18,tbl_Balances[account],"Inventory",tbl_Balances[category],$B19),SUMIFS(tbl_Sales[cogs],tbl_Sales[category],$B19,tbl_Sales[month],">="&EDATE(G$18,1-TrailMonths),tbl_Sales[month],"<="&G$18),WCDays)} -> 16.008753 | H19: {=DAYSOF(SUMIFS(tbl_Balances[balance],tbl_Balances[month],H$18,tbl_Balances[account],"Inventory",tbl_Balances[category],$B19),SUMIFS(tbl_Sales[cogs],tbl_Sales[category],$B19,tbl_Sales[month],">="&EDATE(H$18,1-TrailMonths),tbl_Sales[month],"<="&H$18),WCDays)} -> 15.373112 | I19: {=DAYSOF(SUMIFS(tbl_Balances[balance],tbl_Balances[month],I$18,tbl_Balances[account],"Inventory",tbl_Balances[category],$B19),SUMIFS(tbl_Sales[cogs],tbl_Sales[category],$B19,tbl_Sales[month],">="&EDATE(I$18,1-TrailMonths),tbl_Sales[month],"<="&I$18),WCDays)} -> 16.090292 | J19: {=DAYSOF(SUMIFS(tbl_Balances[balance],tbl_Balances[month],J$18,tbl_Balances[account],"Inventory",tbl_Balances[category],$B19),SUMIFS(tbl_Sales[cogs],tbl_Sales[category],$B19,tbl_Sales[month],">="&EDATE(J$18,1-TrailMonths),tbl_Sales[month],"<="&J$18),WCDays)} -> 17.225518 | ... O19: {=DAYSOF(SUMIFS(tbl_Balances[balance],tbl_Balances[month],O$18,tbl_Balances[account],"Inventory",tbl_Balances[category],$B19),SUMIFS(tbl_Sales[cogs],tbl_Sales[category],$B19,tbl_Sales[month],">="&EDATE(O$18,1-TrailMonths),tbl_Sales[month],"<="&O$18),WCDays)} -> 16.016824
B20: Pork | C20: {=DAYSOF(SUMIFS(tbl_Balances[balance],tbl_Balances[month],C$18,tbl_Balances[account],"Inventory",tbl_Balances[category],$B20),SUMIFS(tbl_Sales[cogs],tbl_Sales[category],$B20,tbl_Sales[month],">="&EDATE(C$18,1-TrailMonths),tbl_Sales[month],"<="&C$18),WCDays)} -> 12.860208 | D20: {=DAYSOF(SUMIFS(tbl_Balances[balance],tbl_Balances[month],D$18,tbl_Balances[account],"Inventory",tbl_Balances[category],$B20),SUMIFS(tbl_Sales[cogs],tbl_Sales[category],$B20,tbl_Sales[month],">="&EDATE(D$18,1-TrailMonths),tbl_Sales[month],"<="&D$18),WCDays)} -> 12.308688 | E20: {=DAYSOF(SUMIFS(tbl_Balances[balance],tbl_Balances[month],E$18,tbl_Balances[account],"Inventory",tbl_Balances[category],$B20),SUMIFS(tbl_Sales[cogs],tbl_Sales[category],$B20,tbl_Sales[month],">="&EDATE(E$18,1-TrailMonths),tbl_Sales[month],"<="&E$18),WCDays)} -> 12.369887 | F20: {=DAYSOF(SUMIFS(tbl_Balances[balance],tbl_Balances[month],F$18,tbl_Balances[account],"Inventory",tbl_Balances[category],$B20),SUMIFS(tbl_Sales[cogs],tbl_Sales[category],$B20,tbl_Sales[month],">="&EDATE(F$18,1-TrailMonths),tbl_Sales[month],"<="&F$18),WCDays)} -> 13.318679 | G20: {=DAYSOF(SUMIFS(tbl_Balances[balance],tbl_Balances[month],G$18,tbl_Balances[account],"Inventory",tbl_Balances[category],$B20),SUMIFS(tbl_Sales[cogs],tbl_Sales[category],$B20,tbl_Sales[month],">="&EDATE(G$18,1-TrailMonths),tbl_Sales[month],"<="&G$18),WCDays)} -> 13.996395 | H20: {=DAYSOF(SUMIFS(tbl_Balances[balance],tbl_Balances[month],H$18,tbl_Balances[account],"Inventory",tbl_Balances[category],$B20),SUMIFS(tbl_Sales[cogs],tbl_Sales[category],$B20,tbl_Sales[month],">="&EDATE(H$18,1-TrailMonths),tbl_Sales[month],"<="&H$18),WCDays)} -> 12.65712 | I20: {=DAYSOF(SUMIFS(tbl_Balances[balance],tbl_Balances[month],I$18,tbl_Balances[account],"Inventory",tbl_Balances[category],$B20),SUMIFS(tbl_Sales[cogs],tbl_Sales[category],$B20,tbl_Sales[month],">="&EDATE(I$18,1-TrailMonths),tbl_Sales[month],"<="&I$18),WCDays)} -> 12.413842 | J20: {=DAYSOF(SUMIFS(tbl_Balances[balance],tbl_Balances[month],J$18,tbl_Balances[account],"Inventory",tbl_Balances[category],$B20),SUMIFS(tbl_Sales[cogs],tbl_Sales[category],$B20,tbl_Sales[month],">="&EDATE(J$18,1-TrailMonths),tbl_Sales[month],"<="&J$18),WCDays)} -> 13.090591 | ... O20: {=DAYSOF(SUMIFS(tbl_Balances[balance],tbl_Balances[month],O$18,tbl_Balances[account],"Inventory",tbl_Balances[category],$B20),SUMIFS(tbl_Sales[cogs],tbl_Sales[category],$B20,tbl_Sales[month],">="&EDATE(O$18,1-TrailMonths),tbl_Sales[month],"<="&O$18),WCDays)} -> 12.751319
