Workbook
Name actual_cdd: Weather!$C$15:$N$15
Name actual_hdd: Weather!$C$14:$N$14
Name AsOfMonth: Assumptions!$C$6
Name backtest: Plan!$B$113:$H$116
Name BaseYear: Assumptions!$C$13
Name bridge_long: PVM!$C$34:$C$38
Name CddOverlay: Scenarios!$C$9
Name CddScale: INDEX(ScenarioCdd,ScenarioNo)*CddOverlay
Name checks_status: Checks!$H$6:$H$36
Name checks_summary: Checks!$B$2
Name coef_commercial: Weather!$C$7:$G$7
Name coef_residential: Weather!$C$6:$G$6
Name CompanyId: Assumptions!$C$12
Name cover_answers: Cover!$C$13:$C$17
Name CPK: _xlfn.LAMBDA(_xlpm.revenue,_xlpm.mwh,SAFEDIV(_xlpm.revenue,_xlpm.mwh)/10)
Name ctrl_eia_mwh: Checks!$D$42
Name ctrl_eia_revenue_k: Checks!$D$43
Name ctrl_eia_rows: Checks!$D$41
Name ctrl_ferc_rows: Checks!$D$44
Name ctrl_noaa_lines: Checks!$D$45
Name CustOverlay: Scenarios!$C$7
Name dash_commentary: Dashboard!$B$11:$B$15
Name dash_outlook_table: Dashboard!$K$57:$S$61
Name dash_plan_table: Dashboard!$B$57:$J$61
Name explore_cube: Explore!$C$28:$F$32
Name explore_yoy: Explore!$G$28:$I$32
Name ExtraMW: Scenarios!$C$6
Name fc_degree_days: Forecast!$C$13:$N$14
Name fc_drivers: Forecast!$D$6:$L$9
Name fc_long: Forecast!$B$19:$K$66
Name fc_months: Forecast!$B$80:$H$91
Name fc_months_total: Forecast!$C$92:$H$92
Name fc_outlook: Forecast!$D$71:$L$74
Name fc_outlook_total: Forecast!$D$75:$L$75
Name FercYear: Assumptions!$C$14
Name FiscalYear: Assumptions!$C$7
Name fit_months: Weather!$H$6:$H$7
Name FitStart: Assumptions!$C$10
Name fy_mwh: Forecast!$K$75
Name fy_revenue: Forecast!$F$75
Name FYStart: Assumptions!$C$8
Name h2_revenue: Forecast!$E$75
Name HddOverlay: Scenarios!$C$8
Name HddScale: INDEX(ScenarioHdd,ScenarioNo)*HddOverlay
Name ISCLOSED: _xlfn.LAMBDA(_xlpm.month,_xlpm.month<=AsOfMonth)
Name kpi_fy_revenue: Dashboard!$B$5
Name kpi_industrial_growth: Dashboard!$K$5
Name kpi_op_margin: Dashboard!$Q$5
Name kpi_price: Dashboard!$N$5
Name kpi_weather_gwh: Dashboard!$H$5
Name kpi_ytd_vs_plan: Dashboard!$E$5
Name MONEY: _xlfn.LAMBDA(_xlpm.x,IF(ABS(_xlpm.x)>=999500000,TEXT(_xlpm.x/1000000000,"$#,##0.00")&"B",IF(ABS(_xlpm.x)>=999500,TEXT(_xlpm.x/1000000,"$#,##0.0")&"M",TEXT(_xlpm.x/1000,"$#,##0")&"K")))
Name monthly_ytd: Monthly!$D$6:$Q$9
Name monthly_ytd_total: Monthly!$D$10:$Q$10
Name MonthsClosed: Assumptions!$C$9
Name normal_cdd: Weather!$C$13:$N$13
Name normal_hdd: Weather!$C$12:$N$12
Name NormalYears: Assumptions!$C$11
Name offset_loss: Scenarios!$C$46
Name offset_rate: Scenarios!$C$47

Sheet Cover
B2: Portland General Electric
B3: Utility FP&A model on public filings: FERC, EIA and NOAA
B4: Plan against actual · weather normalization · price-volume-mix · rolling forecast · scenarios · peers
B6: Every figure is a live formula, Power Query step or DAX measure over public regulatory data: PGE's monthly returns to the U.S. Energy Information Administration, its audited annual FERC Form 1 (processed by Catalyst Cooperative's PUDL project), and NOAA's degree days for the Willamette Valley.
B7: Independent analysis. Not affiliated with or endorsed by Portland General Electric.
B8: Built by Kush Patel · github.com/KushPatel29/excel-fpa-model
B10: Model status | C10: =checks_summary -> All 31 checks pass | D10: Open the checks →
B12: Five questions it answers, live from the model
B13: Is the year on plan, and if not, why? | C13: {="Year to date "&MONEY(ABS(INDEX(plan_bridge_total,7)))&IF(INDEX(plan_bridge_total,7)<0," under"," over")&" plan ("&TEXT(INDEX(plan_bridge_total,8),"+0.0%;-0.0%")&"): weather "&SIGNMONEY(INDEX(plan_bridge_total,3))&", price "&SIGNMONEY(INDEX(plan_bridge_total,5))&", usage "&SIGNMONEY(INDEX(plan_bridge_total,4))&"."} -> Year to date $100.9M under plan (-6.4%): weather −$40.4M, price −$42.3M, usage −$18.3M. | D13: Plan →
B14: How much of that is the weather? | C14: {="Weather against normal: "&TEXT(INDEX(weather_impact_total,11)/1000,"+#,##0;-#,##0")&" GWh and "&SIGNMONEY(INDEX(weather_impact_total,12))&" of revenue this year."} -> Weather against normal: -212 GWh and −$38.7M of revenue this year. | D14: Weather →
B15: Where did revenue growth come from? | C15: {="Since "&BaseYear&": price "&SIGNMONEY(PVM!L11)&", volume "&SIGNMONEY(PVM!J11)&", mix "&SIGNMONEY(PVM!K11)&"."} -> Since 2019: price +$993.6M, volume +$275.4M, mix −$89.0M. | D15: PVM →
B16: Where will the year land? | C16: {="Retail revenue "&MONEY(fy_revenue)&", "&TEXT(Forecast!H75,"+0.0%;-0.0%")&" on "&(FiscalYear-1)&"; a point of rate on the open months is worth "&MONEY(INDEX(tornado,1))&"."} -> Retail revenue $3.01B, +2.7% on 2025; a point of rate on the open months is worth $15.4M. | D16: Forecast →
B17: How does PGE compare with its neighbours? | C17: ="Industrial load growing "&TEXT(INDEX(peers_table,8,1),"0.0%")&" a year, rank "&INDEX(peers_rank,8)&" of 5; retail price "&TEXT(INDEX(peers_table,4,1),"0.0")&"¢/kWh, rank "&INDEX(peers_rank,4)&" of 5." -> Industrial load growing 10.9% a year, rank 1 of 5; retail price 14.9¢/kWh, rank 2 of 5. | D17: Peers →
B19: Sheets
B20: Sheet | C20: What it shows | D20: Excel on show
B21: Dashboard | C21: One page: plan against actual, weather, price mix, the outlook, and a summary written by formulas. | D21: Formula-driven commentary, waterfalls, combo chart, sparklines, LET
B22: PnL | C22: Twelve years of PGE's electric P&L from FERC Form 1, with unit economics. | D22: SUMIFS over a long table with array criteria, named LAMBDAs, CAGR
B23: PVM | C23: Where retail revenue growth came from: volume, mix and price by customer class. | D23: Exact three-effect decomposition, waterfall
B24: Monthly | C24: EIA's monthly survey by class, a revenue heat map, and the EIA-to-FERC tie-out. | D24: SUMIFS, colour scales, cross-source reconciliation
B25: Weather | C25: How much load follows the thermostat; this year's weather impact. | D25: LINEST on FILTER + HSTACK, normals with FILTER/AVERAGE
B26: Plan | C26: A plan built only from data before the year, against actuals, split four ways; backtested. | D26: Month-by-class model, what-if data table on the plan year
B27: Forecast | C27: The rest of the year from drivers and observed weather; a FORECAST.ETS cross-check. | D27: XLOOKUP with fallbacks, FORECAST.ETS
B28: Scenarios | C28: Weather, rates, data-center load: tables that re-run the model, and a tornado. | D28: One- and two-variable data tables, SORTBY + HSTACK
B29: Peers | C29: PGE against four Pacific Northwest utilities on price, growth and cost. | D29: SUMIFS by respondent, RANK.EQ
B30: Explore | C30: The same data as a Power Pivot model: PivotTable, slicers, CUBEVALUE. | D30: Power Pivot, DAX (TREATAS time intelligence), CUBEVALUE
B31: Checks | C31: 31 controls that prove the numbers, each with its own tolerance. | D31: Reconciliations
... B35: Data_EIA | C35: The public extracts, exactly as published. | D35: Excel tables, structured references
B37: How to use it
B38: 1 Move a lever | C38: Scenarios!C4:C9: weather, a rate change, new data-center load. Every sheet follows.
B39: 2 Re-run the plan as of another year | C39: Plan!C4. The backtest on the same sheet does it for four years.
B40: 3 Explore the data model | C40: The slicers on Explore filter a PivotTable built on DAX measures.
B41: 4 Refresh the data | C41: python pipeline/fetch_sources.py downloads the latest public releases; rebuild.
B43: Sources and conventions
B44: EIA-861M | C44: U.S. Energy Information Administration, monthly electric utility sales and revenue. Public domain.
B45: FERC Form 1 | C45: Federal Energy Regulatory Commission annual report, via Catalyst Cooperative's PUDL (CC BY 4.0).
B46: NOAA nClimDiv | C46: NOAA National Centers for Environmental Information, divisional degree days. Public domain.
B47: 0.01 | C47: Input: blue on yellow. Change these; everything else is calculated.
B48: +1,234 (1,234) | C48: Variances are signed so favourable is positive (green) and unfavourable is in brackets (red).

Sheet Dashboard
B1: ="Portland General Electric: "&FiscalYear&" retail revenue, plan and outlook" -> Portland General Electric: 2026 retail revenue, plan and outlook
B2: ="Actuals from EIA through "&TEXT(AsOfMonth,"mmmm yyyy")&" · FERC Form 1 through "&FercYear&" · weather: NOAA, Willamette Valley · scenario: "&WeatherScenario&" · "&checks_summary -> Actuals from EIA through June 2026 · FERC Form 1 through 2025 · weather: NOAA, Willamette Valley · scenario: Normal · All 31 checks pass
B4: =UPPER("Retail revenue, "&FiscalYear&" outlook") -> RETAIL REVENUE, 2026 OUTLOOK | E4: YEAR TO DATE AGAINST PLAN | H4: WEATHER AGAINST NORMAL, YTD | K4: INDUSTRIAL LOAD, YTD | N4: AVERAGE RETAIL PRICE, YTD | Q4: =UPPER("Operating margin, FERC "&FercYear) -> OPERATING MARGIN, FERC 2025
B5: =fy_revenue -> 3.0076648e+09 | E5: =INDEX(plan_bridge_total,7) -> -1.0094098e+08 | H5: =INDEX(weather_impact_total,11)/1000 -> -211.51445 | K5: =Monthly!I8 -> 0.12163369 | N5: =Monthly!J10 -> 14.75726 | Q5: =INDEX(pnl_op_margin,1,MATCH(FercYear,pnl_years,0)) -> 0.15287796
B6: =Forecast!H75 -> 0.027144809 | E6: =INDEX(plan_bridge_total,8) -> -0.064256653 | H6: =INDEX(weather_impact_total,12) -> -38674235 | K6: megawatt-hours, on last year | N6: =Monthly!L10 -> 0.0015430234 | Q6: =PnL!P33 -> -0.019790371
E7: {="weather "&SIGNMONEY(INDEX(plan_bridge_total,3))&" · price "&SIGNMONEY(INDEX(plan_bridge_total,5))} -> weather −$40.4M · price −$42.3M
B8: {="plan "&MONEY(Forecast!I75)&" · "&SIGNMONEY(Forecast!J75)} -> plan $3.19B · −$184.2M | E8: ="plan from data to Dec "&(PlanYear-1) -> plan from data to Dec 2025 | H8: {="heating degree days "&TEXT(SAFEDIV(INDEX(weather_impact_total,1),SUM(INDEX(normal_hdd,1,1):INDEX(normal_hdd,1,MonthsClosed))),"+0%;-0%")&" vs normal"} -> heating degree days -13% vs normal | K8: ="plan assumed "&TEXT(Plan!I11-1,"+0%;-0%") -> plan assumed +17% | N8: ="classes "&TEXT(MIN(Monthly!L6:L8),"+0.0%")&" to "&TEXT(MAX(Monthly!L6:L8),"+0.0%") -> classes +0.8% to +2.9% | Q8: ="before income tax, since "&BaseYear -> before income tax, since 2019
B10: What the numbers say
B11: {="Retail revenue for "&TEXT(FYStart,"mmm")&"–"&TEXT(AsOfMonth,"mmm")&" came in "&MONEY(ABS(INDEX(plan_bridge_total,7)))&" ("&TEXT(ABS(INDEX(plan_bridge_total,8)),"0.0%")&")"&IF(INDEX(plan_bridge_total,7)<0," under"," over")&" plan: weather "&SIGNMONEY(INDEX(plan_bridge_total,3))&", price "&SIGNMONEY(INDEX(plan_bridge_total,5))&", usage "&SIGNMONEY(INDEX(plan_bridge_total,4))&", customers "&SIGNMONEY(INDEX(plan_bridge_total,2))&"."} -> Retail revenue for Jan–Jun came in $100.9M (6.4%) under plan: weather −$40.4M, price −$42.3M, usage −$18.3M, customers +$79K.
B12: {=_xlfn.LET(_xlpm.dev,SAFEDIV(INDEX(weather_impact_total,1),SUM(INDEX(normal_hdd,1,1):INDEX(normal_hdd,1,MonthsClosed))),"Heating degree days ran "&TEXT(ABS(_xlpm.dev),"0%")&IF(_xlpm.dev<0," below"," above")&" normal: "&TEXT(ABS(INDEX(weather_impact_total,11))/1000,"#,##0")&" GWh of load and "&MONEY(ABS(INDEX(weather_impact_total,12)))&" of revenue"&IF(INDEX(weather_impact_total,12)<0," lost"," gained")&" to the thermostat, at actual prices.")} -> Heating degree days ran 13% below normal: 212 GWh of load and $38.7M of revenue lost to the thermostat, at actual prices.
B13: =_xlfn.LET(_xlpm.p,Monthly!L6:L8,"Every class paid more per kWh ("&TEXT(MIN(_xlpm.p),"+0.0%")&" to "&TEXT(MAX(_xlpm.p),"+0.0%")&"), yet the average rose "&TEXT(Monthly!L10,"+0.0%;-0.0%")&": the growth is industrial load ("&TEXT(Monthly!I8,"+0.0%")&" MWh), billed at "&TEXT(Monthly!J8,"0.0")&"¢ against "&TEXT(Monthly!J6,"0.0")&"¢ residential.") -> Every class paid more per kWh (+0.8% to +2.9%), yet the average rose +0.2%: the growth is industrial load (+12.2% MWh), billed at 9.4¢ against 18.9¢ residential.
B14: {="Since "&BaseYear&", retail revenue is up "&MONEY(PVM!N11)&": price "&SIGNMONEY(PVM!L11)&", volume "&SIGNMONEY(PVM!J11)&", mix "&SIGNMONEY(PVM!K11)&". Power cost rose faster than revenue, and operating margin fell "&TEXT(ABS(PnL!P33),"0.0%")&" points."} -> Since 2019, retail revenue is up $1.18B: price +$993.6M, volume +$275.4M, mix −$89.0M. Power cost rose faster than revenue, and operating margin fell 2.0% points.
B15: {="Full year "&FiscalYear&": "&MONEY(fy_revenue)&", "&TEXT(Forecast!H75,"+0.0%;-0.0%")&" on "&(FiscalYear-1)&IF(ISNUMBER(Forecast!J75),", "&MONEY(ABS(Forecast!J75))&IF(Forecast!J75<0," under"," over")&" plan","")&". A point of rate on the open months is worth "&MONEY(INDEX(tornado,1))&"; 50 MW of new data-center load, "&MONEY(INDEX(tornado,2))&"."} -> Full year 2026: $3.01B, +2.7% on 2025, $184.2M under plan. A point of rate on the open months is worth $15.4M; 50 MW of new data-center load, $21.1M.
B55: ="Plan against actual by class, "&TEXT(FYStart,"mmm")&"–"&TEXT(AsOfMonth,"mmm") -> Plan against actual by class, Jan–Jun | K55: ="Full-year outlook by class, "&FiscalYear -> Full-year outlook by class, 2026
B56: Class | E56: Plan | G56: Actual | I56: Variance | J56: % | K56: Class | M56: Actual YTD | O56: Forecast | Q56: Full year | S56: Growth
B57: =Plan!B80 -> Residential | E57: =Plan!D80 -> 7.6124929e+08 | G57: =Plan!I80 -> 695144762 | I57: =Plan!J80 -> -66104525 | J57: =Plan!K80 -> -0.086836896 | K57: =Forecast!B71 -> Residential | M57: =Forecast!D71 -> 695144762 | O57: =Forecast!E71 -> 7.1944283e+08 | Q57: =Forecast!F71 -> 1.4145876e+09 | S57: =Forecast!H71 -> -0.0091738536
B58: =Plan!B81 -> Commercial | E58: =Plan!D81 -> 4.8858664e+08 | G58: =Plan!I81 -> 474305106 | I58: =Plan!J81 -> -14281537 | J58: =Plan!K81 -> -0.029230306 | K58: =Forecast!B72 -> Commercial | M58: =Forecast!D72 -> 474305106 | O58: =Forecast!E72 -> 4.8063087e+08 | Q58: =Forecast!F72 -> 9.5493598e+08 | S58: =Forecast!H72 -> 0.010327589
B59: =Plan!B82 -> Industrial | E59: =Plan!D82 -> 3.2023868e+08 | G59: =Plan!I82 -> 299820792 | I59: =Plan!J82 -> -20417887 | J59: =Plan!K82 -> -0.063758342 | K59: =Forecast!B73 -> Industrial | M59: =Forecast!D73 -> 299820792 | O59: =Forecast!E73 -> 3.3699007e+08 | Q59: =Forecast!F73 -> 6.3681086e+08 | S59: =Forecast!H73 -> 0.14964437
B60: =Plan!B83 -> Transportation | E60: =Plan!D83 -> 828523.27 | G60: =Plan!I83 -> 691495 | I60: =Plan!J83 -> -137028.27 | J60: =Plan!K83 -> -0.16538856 | K60: =Forecast!B74 -> Transportation | M60: =Forecast!D74 -> 691495 | O60: =Forecast!E74 -> 638908.92 | Q60: =Forecast!F74 -> 1330403.9 | S60: =Forecast!H74 -> -0.0500555
B61: =Plan!B84 -> All classes | E61: =Plan!D84 -> 1.5709031e+09 | G61: =Plan!I84 -> 1469962155 | I61: =Plan!J84 -> -1.0094098e+08 | J61: =Plan!K84 -> -0.064256653 | K61: =Forecast!B75 -> All classes | M61: =Forecast!D75 -> 1469962155 | O61: =Forecast!E75 -> 1.5377027e+09 | Q61: =Forecast!F75 -> 3.0076648e+09 | S61: =Forecast!H75 -> 0.027144809
B62: Independent analysis of public regulatory filings (EIA-861M, FERC Form 1 via Catalyst Cooperative's PUDL, NOAA nClimDiv). Not affiliated with or endorsed by Portland General Electric. Built in Excel by Kush Patel: github.com/KushPatel29/excel-fpa-model
B68: Chart data: the charts above read these cells, which read the model.
B71: Month | C71: Actual | D71: Forecast | E71: Plan | F71: Prior year
B72: =TEXT(Forecast!B80,"mmm") -> Jan | C72: =Forecast!C80 -> 271495430 | D72: =Forecast!D80 | E72: =Forecast!E80 -> 2.8301338e+08 | F72: =Forecast!F80 -> 280461721
B73: =TEXT(Forecast!B81,"mmm") -> Feb | C73: =Forecast!C81 -> 236446919 | D73: =Forecast!D81 | E73: =Forecast!E81 -> 2.78332e+08 | F73: =Forecast!F81 -> 252288295
B74: =TEXT(Forecast!B82,"mmm") -> Mar | C74: =Forecast!C82 -> 241516825 | D74: =Forecast!D82 | E74: =Forecast!E82 -> 2.7853482e+08 | F74: =Forecast!F82 -> 247602397
B75: =TEXT(Forecast!B83,"mmm") -> Apr | C75: =Forecast!C83 -> 233585146 | D75: =Forecast!D83 | E75: =Forecast!E83 -> 2.5837732e+08 | F75: =Forecast!F83 -> 217637842
B76: =TEXT(Forecast!B84,"mmm") -> May | C76: =Forecast!C84 -> 239271154 | D76: =Forecast!D84 | E76: =Forecast!E84 -> 2.4114012e+08 | F76: =Forecast!F84 -> 216290531
B77: =TEXT(Forecast!B85,"mmm") -> Jun | C77: =Forecast!C85 -> 247646681 | D77: =Forecast!D85 | E77: =Forecast!E85 -> 2.3150549e+08 | F77: =Forecast!F85 -> 228083828
B78: =TEXT(Forecast!B86,"mmm") -> Jul | C78: =Forecast!C86 | D78: =Forecast!D86 -> 2.4976576e+08 | E78: =Forecast!E86 -> 2.7190595e+08 | F78: =Forecast!F86 -> 260233530
B79: =TEXT(Forecast!B87,"mmm") -> Aug | C79: =Forecast!C87 | D79: =Forecast!D87 -> 2.618713e+08 | E79: =Forecast!E87 -> 2.8285095e+08 | F79: =Forecast!F87 -> 268274378
B80: =TEXT(Forecast!B88,"mmm") -> Sep | C80: =Forecast!C88 | D80: =Forecast!D88 -> 2.3329519e+08 | E80: =Forecast!E88 -> 2.4272094e+08 | F80: =Forecast!F88 -> 230382555
B81: =TEXT(Forecast!B89,"mmm") -> Oct | C81: =Forecast!C89 | D81: =Forecast!D89 -> 2.4243137e+08 | E81: =Forecast!E89 -> 2.5203e+08 | F81: =Forecast!F89 -> 226390278
B82: =TEXT(Forecast!B90,"mmm") -> Nov | C82: =Forecast!C90 | D82: =Forecast!D90 -> 2.662898e+08 | E82: =Forecast!E90 -> 2.7651424e+08 | F82: =Forecast!F90 -> 236444019
B83: =TEXT(Forecast!B91,"mmm") -> Dec | C83: =Forecast!C91 | D83: =Forecast!D91 -> 2.8404926e+08 | E83: =Forecast!E91 -> 2.9498314e+08 | F83: =Forecast!F91 -> 264090576
B86: =Plan!N79 -> Plan 2026 | C86: =Plan!O79 -> 1.5709031e+09
B87: =Plan!N80 -> Customers | C87: =Plan!O80 -> 79021.507
B88: =Plan!N81 -> Weather | C88: =Plan!O81 -> -40425964
B89: =Plan!N82 -> Usage | C89: =Plan!O82 -> -18307381
B90: =Plan!N83 -> Price | C90: =Plan!O83 -> -42286654
B91: =Plan!N84 -> Actual | C91: =Plan!O84 -> 1469962155
B94: =PVM!B34 -> 2019 retail revenue | C94: =PVM!C34 -> 1789303774
B95: =PVM!B35 -> Volume | C95: =PVM!C35 -> 2.7540322e+08
B96: =PVM!B36 -> Mix | C96: =PVM!C36 -> -88952656
B97: =PVM!B37 -> Price | C97: =PVM!C37 -> 9.9359228e+08
B98: =PVM!B38 -> 2025 retail revenue | C98: =PVM!C38 -> 2969346620

Sheet PnL
B1: Profit and loss: Portland General Electric, electric utility (FERC Form 1)
B2: Audited annual figures as filed with FERC, via Catalyst Cooperative's PUDL, in $ millions. Column C names the FERC line each revenue row reads. Operating income is before income taxes and interest.
B4: Year | C4: FERC line | D4: =FercYear-11 -> 2014 | E4: =D4+1 -> 2015 | F4: =E4+1 -> 2016 | G4: =F4+1 -> 2017 | H4: =G4+1 -> 2018 | I4: =H4+1 -> 2019 | J4: =I4+1 -> 2020 | K4: =J4+1 -> 2021 | L4: =K4+1 -> 2022 | ... O4: =N4+1 -> 2025 | P4: ="CAGR "&BaseYear&"–"&RIGHT(FercYear,2) -> CAGR 2019–25 | Q4: ="Δ vs "&(FercYear-1) -> Δ vs 2024 | R4: % change
B5: Revenue
B6: Residential | C6: residential_sales | D6: =SUMIFS(tbl_FERC_Revenue[dollar_value],tbl_FERC_Revenue[utility_id_ferc1],CompanyId,tbl_FERC_Revenue[report_year],D$4,tbl_FERC_Revenue[revenue_type],"residential_sales") -> 848594155 | E6: =SUMIFS(tbl_FERC_Revenue[dollar_value],tbl_FERC_Revenue[utility_id_ferc1],CompanyId,tbl_FERC_Revenue[report_year],E$4,tbl_FERC_Revenue[revenue_type],"residential_sales") -> 845906182 | F6: =SUMIFS(tbl_FERC_Revenue[dollar_value],tbl_FERC_Revenue[utility_id_ferc1],CompanyId,tbl_FERC_Revenue[report_year],F$4,tbl_FERC_Revenue[revenue_type],"residential_sales") -> 837938465 | G6: =SUMIFS(tbl_FERC_Revenue[dollar_value],tbl_FERC_Revenue[utility_id_ferc1],CompanyId,tbl_FERC_Revenue[report_year],G$4,tbl_FERC_Revenue[revenue_type],"residential_sales") -> 900171801 | H6: =SUMIFS(tbl_FERC_Revenue[dollar_value],tbl_FERC_Revenue[utility_id_ferc1],CompanyId,tbl_FERC_Revenue[report_year],H$4,tbl_FERC_Revenue[revenue_type],"residential_sales") -> 890376597 | I6: =SUMIFS(tbl_FERC_Revenue[dollar_value],tbl_FERC_Revenue[utility_id_ferc1],CompanyId,tbl_FERC_Revenue[report_year],I$4,tbl_FERC_Revenue[revenue_type],"residential_sales") -> 917792335 | J6: =SUMIFS(tbl_FERC_Revenue[dollar_value],tbl_FERC_Revenue[utility_id_ferc1],CompanyId,tbl_FERC_Revenue[report_year],J$4,tbl_FERC_Revenue[revenue_type],"residential_sales") -> 969909454 | K6: =SUMIFS(tbl_FERC_Revenue[dollar_value],tbl_FERC_Revenue[utility_id_ferc1],CompanyId,tbl_FERC_Revenue[report_year],K$4,tbl_FERC_Revenue[revenue_type],"residential_sales") -> 1056368675 | ... O6: =SUMIFS(tbl_FERC_Revenue[dollar_value],tbl_FERC_Revenue[utility_id_ferc1],CompanyId,tbl_FERC_Revenue[report_year],O$4,tbl_FERC_Revenue[revenue_type],"residential_sales") -> 1427684968 | P6: =IFERROR((INDEX($D6:$O6,MATCH(FercYear,$D$4:$O$4,0))/INDEX($D6:$O6,MATCH(BaseYear,$D$4:$O$4,0)))^(1/(FercYear-BaseYear))-1,0) -> 0.07641893 | Q6: =INDEX($D6:$O6,MATCH(FercYear,$D$4:$O$4,0))-INDEX($D6:$O6,MATCH(FercYear-1,$D$4:$O$4,0)) -> 21314333 | R6: {=SAFEDIV(Q6,ABS(INDEX($D6:$O6,MATCH(FercYear-1,$D$4:$O$4,0))))} -> 0.015155559
B7: Commercial | C7: small_or_commercial | D7: =SUMIFS(tbl_FERC_Revenue[dollar_value],tbl_FERC_Revenue[utility_id_ferc1],CompanyId,tbl_FERC_Revenue[report_year],D$4,tbl_FERC_Revenue[revenue_type],"small_or_commercial") -> 633949689 | E7: =SUMIFS(tbl_FERC_Revenue[dollar_value],tbl_FERC_Revenue[utility_id_ferc1],CompanyId,tbl_FERC_Revenue[report_year],E$4,tbl_FERC_Revenue[revenue_type],"small_or_commercial") -> 646306478 | F7: =SUMIFS(tbl_FERC_Revenue[dollar_value],tbl_FERC_Revenue[utility_id_ferc1],CompanyId,tbl_FERC_Revenue[report_year],F$4,tbl_FERC_Revenue[revenue_type],"small_or_commercial") -> 645487072 | G7: =SUMIFS(tbl_FERC_Revenue[dollar_value],tbl_FERC_Revenue[utility_id_ferc1],CompanyId,tbl_FERC_Revenue[report_year],G$4,tbl_FERC_Revenue[revenue_type],"small_or_commercial") -> 650481084 | H7: =SUMIFS(tbl_FERC_Revenue[dollar_value],tbl_FERC_Revenue[utility_id_ferc1],CompanyId,tbl_FERC_Revenue[report_year],H$4,tbl_FERC_Revenue[revenue_type],"small_or_commercial") -> 648540186 | I7: =SUMIFS(tbl_FERC_Revenue[dollar_value],tbl_FERC_Revenue[utility_id_ferc1],CompanyId,tbl_FERC_Revenue[report_year],I$4,tbl_FERC_Revenue[revenue_type],"small_or_commercial") -> 638317031 | J7: =SUMIFS(tbl_FERC_Revenue[dollar_value],tbl_FERC_Revenue[utility_id_ferc1],CompanyId,tbl_FERC_Revenue[report_year],J$4,tbl_FERC_Revenue[revenue_type],"small_or_commercial") -> 619175770 | K7: =SUMIFS(tbl_FERC_Revenue[dollar_value],tbl_FERC_Revenue[utility_id_ferc1],CompanyId,tbl_FERC_Revenue[report_year],K$4,tbl_FERC_Revenue[revenue_type],"small_or_commercial") -> 691317312 | ... O7: =SUMIFS(tbl_FERC_Revenue[dollar_value],tbl_FERC_Revenue[utility_id_ferc1],CompanyId,tbl_FERC_Revenue[report_year],O$4,tbl_FERC_Revenue[revenue_type],"small_or_commercial") -> 966187754 | P7: =IFERROR((INDEX($D7:$O7,MATCH(FercYear,$D$4:$O$4,0))/INDEX($D7:$O7,MATCH(BaseYear,$D$4:$O$4,0)))^(1/(FercYear-BaseYear))-1,0) -> 0.071529625 | Q7: =INDEX($D7:$O7,MATCH(FercYear,$D$4:$O$4,0))-INDEX($D7:$O7,MATCH(FercYear-1,$D$4:$O$4,0)) -> 61289117 | R7: {=SAFEDIV(Q7,ABS(INDEX($D7:$O7,MATCH(FercYear-1,$D$4:$O$4,0))))} -> 0.067730367
B8: Industrial | C8: large_or_industrial | D8: =SUMIFS(tbl_FERC_Revenue[dollar_value],tbl_FERC_Revenue[utility_id_ferc1],CompanyId,tbl_FERC_Revenue[report_year],D$4,tbl_FERC_Revenue[revenue_type],"large_or_industrial") -> 221298764 | E8: =SUMIFS(tbl_FERC_Revenue[dollar_value],tbl_FERC_Revenue[utility_id_ferc1],CompanyId,tbl_FERC_Revenue[report_year],E$4,tbl_FERC_Revenue[revenue_type],"large_or_industrial") -> 227985121 | F8: =SUMIFS(tbl_FERC_Revenue[dollar_value],tbl_FERC_Revenue[utility_id_ferc1],CompanyId,tbl_FERC_Revenue[report_year],F$4,tbl_FERC_Revenue[revenue_type],"large_or_industrial") -> 207677973 | G8: =SUMIFS(tbl_FERC_Revenue[dollar_value],tbl_FERC_Revenue[utility_id_ferc1],CompanyId,tbl_FERC_Revenue[report_year],G$4,tbl_FERC_Revenue[revenue_type],"large_or_industrial") -> 211588342 | H8: =SUMIFS(tbl_FERC_Revenue[dollar_value],tbl_FERC_Revenue[utility_id_ferc1],CompanyId,tbl_FERC_Revenue[report_year],H$4,tbl_FERC_Revenue[revenue_type],"large_or_industrial") -> 209586172 | I8: =SUMIFS(tbl_FERC_Revenue[dollar_value],tbl_FERC_Revenue[utility_id_ferc1],CompanyId,tbl_FERC_Revenue[report_year],I$4,tbl_FERC_Revenue[revenue_type],"large_or_industrial") -> 221934941 | J8: =SUMIFS(tbl_FERC_Revenue[dollar_value],tbl_FERC_Revenue[utility_id_ferc1],CompanyId,tbl_FERC_Revenue[report_year],J$4,tbl_FERC_Revenue[revenue_type],"large_or_industrial") -> 246051284 | K8: =SUMIFS(tbl_FERC_Revenue[dollar_value],tbl_FERC_Revenue[utility_id_ferc1],CompanyId,tbl_FERC_Revenue[report_year],K$4,tbl_FERC_Revenue[revenue_type],"large_or_industrial") -> 279876046 | ... O8: =SUMIFS(tbl_FERC_Revenue[dollar_value],tbl_FERC_Revenue[utility_id_ferc1],CompanyId,tbl_FERC_Revenue[report_year],O$4,tbl_FERC_Revenue[revenue_type],"large_or_industrial") -> 560496980 | P8: =IFERROR((INDEX($D8:$O8,MATCH(FercYear,$D$4:$O$4,0))/INDEX($D8:$O8,MATCH(BaseYear,$D$4:$O$4,0)))^(1/(FercYear-BaseYear))-1,0) -> 0.16696527 | Q8: =INDEX($D8:$O8,MATCH(FercYear,$D$4:$O$4,0))-INDEX($D8:$O8,MATCH(FercYear-1,$D$4:$O$4,0)) -> 103041230 | R8: {=SAFEDIV(Q8,ABS(INDEX($D8:$O8,MATCH(FercYear-1,$D$4:$O$4,0))))} -> 0.22524852
B9: Street lighting | C9: public_street_and_highway_lighting | D9: =SUMIFS(tbl_FERC_Revenue[dollar_value],tbl_FERC_Revenue[utility_id_ferc1],CompanyId,tbl_FERC_Revenue[report_year],D$4,tbl_FERC_Revenue[revenue_type],"public_street_and_highway_lighting") -> 17151203 | E9: =SUMIFS(tbl_FERC_Revenue[dollar_value],tbl_FERC_Revenue[utility_id_ferc1],CompanyId,tbl_FERC_Revenue[report_year],E$4,tbl_FERC_Revenue[revenue_type],"public_street_and_highway_lighting") -> 15385088 | F9: =SUMIFS(tbl_FERC_Revenue[dollar_value],tbl_FERC_Revenue[utility_id_ferc1],CompanyId,tbl_FERC_Revenue[report_year],F$4,tbl_FERC_Revenue[revenue_type],"public_street_and_highway_lighting") -> 12824132 | G9: =SUMIFS(tbl_FERC_Revenue[dollar_value],tbl_FERC_Revenue[utility_id_ferc1],CompanyId,tbl_FERC_Revenue[report_year],G$4,tbl_FERC_Revenue[revenue_type],"public_street_and_highway_lighting") -> 11954183 | H9: =SUMIFS(tbl_FERC_Revenue[dollar_value],tbl_FERC_Revenue[utility_id_ferc1],CompanyId,tbl_FERC_Revenue[report_year],H$4,tbl_FERC_Revenue[revenue_type],"public_street_and_highway_lighting") -> 11648005 | I9: =SUMIFS(tbl_FERC_Revenue[dollar_value],tbl_FERC_Revenue[utility_id_ferc1],CompanyId,tbl_FERC_Revenue[report_year],I$4,tbl_FERC_Revenue[revenue_type],"public_street_and_highway_lighting") -> 11259467 | J9: =SUMIFS(tbl_FERC_Revenue[dollar_value],tbl_FERC_Revenue[utility_id_ferc1],CompanyId,tbl_FERC_Revenue[report_year],J$4,tbl_FERC_Revenue[revenue_type],"public_street_and_highway_lighting") -> 10945945 | K9: =SUMIFS(tbl_FERC_Revenue[dollar_value],tbl_FERC_Revenue[utility_id_ferc1],CompanyId,tbl_FERC_Revenue[report_year],K$4,tbl_FERC_Revenue[revenue_type],"public_street_and_highway_lighting") -> 11922891 | ... O9: =SUMIFS(tbl_FERC_Revenue[dollar_value],tbl_FERC_Revenue[utility_id_ferc1],CompanyId,tbl_FERC_Revenue[report_year],O$4,tbl_FERC_Revenue[revenue_type],"public_street_and_highway_lighting") -> 14976918 | P9: =IFERROR((INDEX($D9:$O9,MATCH(FercYear,$D$4:$O$4,0))/INDEX($D9:$O9,MATCH(BaseYear,$D$4:$O$4,0)))^(1/(FercYear-BaseYear))-1,0) -> 0.048698797 | Q9: =INDEX($D9:$O9,MATCH(FercYear,$D$4:$O$4,0))-INDEX($D9:$O9,MATCH(FercYear-1,$D$4:$O$4,0)) -> 672712 | R9: {=SAFEDIV(Q9,ABS(INDEX($D9:$O9,MATCH(FercYear-1,$D$4:$O$4,0))))} -> 0.047028965
B10: Public authorities | C10: other_sales_to_public_authorities | D10: =SUMIFS(tbl_FERC_Revenue[dollar_value],tbl_FERC_Revenue[utility_id_ferc1],CompanyId,tbl_FERC_Revenue[report_year],D$4,tbl_FERC_Revenue[revenue_type],"other_sales_to_public_authorities") -> 0 | E10: =SUMIFS(tbl_FERC_Revenue[dollar_value],tbl_FERC_Revenue[utility_id_ferc1],CompanyId,tbl_FERC_Revenue[report_year],E$4,tbl_FERC_Revenue[revenue_type],"other_sales_to_public_authorities") -> 0 | F10: =SUMIFS(tbl_FERC_Revenue[dollar_value],tbl_FERC_Revenue[utility_id_ferc1],CompanyId,tbl_FERC_Revenue[report_year],F$4,tbl_FERC_Revenue[revenue_type],"other_sales_to_public_authorities") -> 0 | G10: =SUMIFS(tbl_FERC_Revenue[dollar_value],tbl_FERC_Revenue[utility_id_ferc1],CompanyId,tbl_FERC_Revenue[report_year],G$4,tbl_FERC_Revenue[revenue_type],"other_sales_to_public_authorities") -> 0 | H10: =SUMIFS(tbl_FERC_Revenue[dollar_value],tbl_FERC_Revenue[utility_id_ferc1],CompanyId,tbl_FERC_Revenue[report_year],H$4,tbl_FERC_Revenue[revenue_type],"other_sales_to_public_authorities") -> 0 | I10: =SUMIFS(tbl_FERC_Revenue[dollar_value],tbl_FERC_Revenue[utility_id_ferc1],CompanyId,tbl_FERC_Revenue[report_year],I$4,tbl_FERC_Revenue[revenue_type],"other_sales_to_public_authorities") -> 0 | J10: =SUMIFS(tbl_FERC_Revenue[dollar_value],tbl_FERC_Revenue[utility_id_ferc1],CompanyId,tbl_FERC_Revenue[report_year],J$4,tbl_FERC_Revenue[revenue_type],"other_sales_to_public_authorities") -> 0 | K10: =SUMIFS(tbl_FERC_Revenue[dollar_value],tbl_FERC_Revenue[utility_id_ferc1],CompanyId,tbl_FERC_Revenue[report_year],K$4,tbl_FERC_Revenue[revenue_type],"other_sales_to_public_authorities") -> 0 | ... O10: =SUMIFS(tbl_FERC_Revenue[dollar_value],tbl_FERC_Revenue[utility_id_ferc1],CompanyId,tbl_FERC_Revenue[report_year],O$4,tbl_FERC_Revenue[revenue_type],"other_sales_to_public_authorities") -> 0 | P10: =IFERROR((INDEX($D10:$O10,MATCH(FercYear,$D$4:$O$4,0))/INDEX($D10:$O10,MATCH(BaseYear,$D$4:$O$4,0)))^(1/(FercYear-BaseYear))-1,0) -> 0 | Q10: =INDEX($D10:$O10,MATCH(FercYear,$D$4:$O$4,0))-INDEX($D10:$O10,MATCH(FercYear-1,$D$4:$O$4,0)) -> 0 | R10: {=SAFEDIV(Q10,ABS(INDEX($D10:$O10,MATCH(FercYear-1,$D$4:$O$4,0))))} -> 0
B11: Retail revenue | D11: =SUM(D6:D10) -> 1720993811 | E11: =SUM(E6:E10) -> 1735582869 | F11: =SUM(F6:F10) -> 1703927642 | G11: =SUM(G6:G10) -> 1774195410 | H11: =SUM(H6:H10) -> 1760150960 | I11: =SUM(I6:I10) -> 1789303774 | J11: =SUM(J6:J10) -> 1846082453 | K11: =SUM(K6:K10) -> 2039484924 | ... O11: =SUM(O6:O10) -> 2969346620 | P11: =IFERROR((INDEX($D11:$O11,MATCH(FercYear,$D$4:$O$4,0))/INDEX($D11:$O11,MATCH(BaseYear,$D$4:$O$4,0)))^(1/(FercYear-BaseYear))-1,0) -> 0.08808495 | Q11: =INDEX($D11:$O11,MATCH(FercYear,$D$4:$O$4,0))-INDEX($D11:$O11,MATCH(FercYear-1,$D$4:$O$4,0)) -> 186317392 | R11: {=SAFEDIV(Q11,ABS(INDEX($D11:$O11,MATCH(FercYear-1,$D$4:$O$4,0))))} -> 0.066947695
B12: Wholesale (sales for resale) | D12: =SUMIFS(tbl_FERC_Revenue[dollar_value],tbl_FERC_Revenue[utility_id_ferc1],CompanyId,tbl_FERC_Revenue[report_year],D$4,tbl_FERC_Revenue[revenue_type],"sales_for_resale") -> 130021814 | E12: =SUMIFS(tbl_FERC_Revenue[dollar_value],tbl_FERC_Revenue[utility_id_ferc1],CompanyId,tbl_FERC_Revenue[report_year],E$4,tbl_FERC_Revenue[revenue_type],"sales_for_resale") -> 109756221 | F12: =SUMIFS(tbl_FERC_Revenue[dollar_value],tbl_FERC_Revenue[utility_id_ferc1],CompanyId,tbl_FERC_Revenue[report_year],F$4,tbl_FERC_Revenue[revenue_type],"sales_for_resale") -> 123165759 | G12: =SUMIFS(tbl_FERC_Revenue[dollar_value],tbl_FERC_Revenue[utility_id_ferc1],CompanyId,tbl_FERC_Revenue[report_year],G$4,tbl_FERC_Revenue[revenue_type],"sales_for_resale") -> 122591295 | H12: =SUMIFS(tbl_FERC_Revenue[dollar_value],tbl_FERC_Revenue[utility_id_ferc1],CompanyId,tbl_FERC_Revenue[report_year],H$4,tbl_FERC_Revenue[revenue_type],"sales_for_resale") -> 177074310 | I12: =SUMIFS(tbl_FERC_Revenue[dollar_value],tbl_FERC_Revenue[utility_id_ferc1],CompanyId,tbl_FERC_Revenue[report_year],I$4,tbl_FERC_Revenue[revenue_type],"sales_for_resale") -> 203335776 | J12: =SUMIFS(tbl_FERC_Revenue[dollar_value],tbl_FERC_Revenue[utility_id_ferc1],CompanyId,tbl_FERC_Revenue[report_year],J$4,tbl_FERC_Revenue[revenue_type],"sales_for_resale") -> 184596850 | K12: =SUMIFS(tbl_FERC_Revenue[dollar_value],tbl_FERC_Revenue[utility_id_ferc1],CompanyId,tbl_FERC_Revenue[report_year],K$4,tbl_FERC_Revenue[revenue_type],"sales_for_resale") -> 287282619 | ... O12: =SUMIFS(tbl_FERC_Revenue[dollar_value],tbl_FERC_Revenue[utility_id_ferc1],CompanyId,tbl_FERC_Revenue[report_year],O$4,tbl_FERC_Revenue[revenue_type],"sales_for_resale") -> 406261710 | P12: =IFERROR((INDEX($D12:$O12,MATCH(FercYear,$D$4:$O$4,0))/INDEX($D12:$O12,MATCH(BaseYear,$D$4:$O$4,0)))^(1/(FercYear-BaseYear))-1,0) -> 0.12227343 | Q12: =INDEX($D12:$O12,MATCH(FercYear,$D$4:$O$4,0))-INDEX($D12:$O12,MATCH(FercYear-1,$D$4:$O$4,0)) -> -181832439 | R12: {=SAFEDIV(Q12,ABS(INDEX($D12:$O12,MATCH(FercYear-1,$D$4:$O$4,0))))} -> -0.30918934
B13: Refund provision | D13: =-SUMIFS(tbl_FERC_Revenue[dollar_value],tbl_FERC_Revenue[utility_id_ferc1],CompanyId,tbl_FERC_Revenue[report_year],D$4,tbl_FERC_Revenue[revenue_type],"provision_for_rate_refunds") -> -3398715 | E13: =-SUMIFS(tbl_FERC_Revenue[dollar_value],tbl_FERC_Revenue[utility_id_ferc1],CompanyId,tbl_FERC_Revenue[report_year],E$4,tbl_FERC_Revenue[revenue_type],"provision_for_rate_refunds") -> 1197209 | F13: =-SUMIFS(tbl_FERC_Revenue[dollar_value],tbl_FERC_Revenue[utility_id_ferc1],CompanyId,tbl_FERC_Revenue[report_year],F$4,tbl_FERC_Revenue[revenue_type],"provision_for_rate_refunds") -> 7913648 | G13: =-SUMIFS(tbl_FERC_Revenue[dollar_value],tbl_FERC_Revenue[utility_id_ferc1],CompanyId,tbl_FERC_Revenue[report_year],G$4,tbl_FERC_Revenue[revenue_type],"provision_for_rate_refunds") -> 10337496 | H13: =-SUMIFS(tbl_FERC_Revenue[dollar_value],tbl_FERC_Revenue[utility_id_ferc1],CompanyId,tbl_FERC_Revenue[report_year],H$4,tbl_FERC_Revenue[revenue_type],"provision_for_rate_refunds") -> -40343222 | I13: =-SUMIFS(tbl_FERC_Revenue[dollar_value],tbl_FERC_Revenue[utility_id_ferc1],CompanyId,tbl_FERC_Revenue[report_year],I$4,tbl_FERC_Revenue[revenue_type],"provision_for_rate_refunds") -> 24671723 | J13: =-SUMIFS(tbl_FERC_Revenue[dollar_value],tbl_FERC_Revenue[utility_id_ferc1],CompanyId,tbl_FERC_Revenue[report_year],J$4,tbl_FERC_Revenue[revenue_type],"provision_for_rate_refunds") -> 5767072 | K13: =-SUMIFS(tbl_FERC_Revenue[dollar_value],tbl_FERC_Revenue[utility_id_ferc1],CompanyId,tbl_FERC_Revenue[report_year],K$4,tbl_FERC_Revenue[revenue_type],"provision_for_rate_refunds") -> -17402956 | ... O13: =-SUMIFS(tbl_FERC_Revenue[dollar_value],tbl_FERC_Revenue[utility_id_ferc1],CompanyId,tbl_FERC_Revenue[report_year],O$4,tbl_FERC_Revenue[revenue_type],"provision_for_rate_refunds") -> 20225849 | P13: =IFERROR((INDEX($D13:$O13,MATCH(FercYear,$D$4:$O$4,0))/INDEX($D13:$O13,MATCH(BaseYear,$D$4:$O$4,0)))^(1/(FercYear-BaseYear))-1,0) -> -0.032573722 | Q13: =INDEX($D13:$O13,MATCH(FercYear,$D$4:$O$4,0))-INDEX($D13:$O13,MATCH(FercYear-1,$D$4:$O$4,0)) -> 57155467 | R13: {=SAFEDIV(Q13,ABS(INDEX($D13:$O13,MATCH(FercYear-1,$D$4:$O$4,0))))} -> 1.5476864
B14: Other operating revenue | D14: =SUMIFS(tbl_FERC_Revenue[dollar_value],tbl_FERC_Revenue[utility_id_ferc1],CompanyId,tbl_FERC_Revenue[report_year],D$4,tbl_FERC_Revenue[revenue_type],"other_operating_revenues") -> 78961758 | E14: =SUMIFS(tbl_FERC_Revenue[dollar_value],tbl_FERC_Revenue[utility_id_ferc1],CompanyId,tbl_FERC_Revenue[report_year],E$4,tbl_FERC_Revenue[revenue_type],"other_operating_revenues") -> 68384771 | F14: =SUMIFS(tbl_FERC_Revenue[dollar_value],tbl_FERC_Revenue[utility_id_ferc1],CompanyId,tbl_FERC_Revenue[report_year],F$4,tbl_FERC_Revenue[revenue_type],"other_operating_revenues") -> 104159765 | G14: =SUMIFS(tbl_FERC_Revenue[dollar_value],tbl_FERC_Revenue[utility_id_ferc1],CompanyId,tbl_FERC_Revenue[report_year],G$4,tbl_FERC_Revenue[revenue_type],"other_operating_revenues") -> 115569351 | H14: =SUMIFS(tbl_FERC_Revenue[dollar_value],tbl_FERC_Revenue[utility_id_ferc1],CompanyId,tbl_FERC_Revenue[report_year],H$4,tbl_FERC_Revenue[revenue_type],"other_operating_revenues") -> 108227995 | I14: =SUMIFS(tbl_FERC_Revenue[dollar_value],tbl_FERC_Revenue[utility_id_ferc1],CompanyId,tbl_FERC_Revenue[report_year],I$4,tbl_FERC_Revenue[revenue_type],"other_operating_revenues") -> 130671136 | J14: =SUMIFS(tbl_FERC_Revenue[dollar_value],tbl_FERC_Revenue[utility_id_ferc1],CompanyId,tbl_FERC_Revenue[report_year],J$4,tbl_FERC_Revenue[revenue_type],"other_operating_revenues") -> 120765993 | K14: =SUMIFS(tbl_FERC_Revenue[dollar_value],tbl_FERC_Revenue[utility_id_ferc1],CompanyId,tbl_FERC_Revenue[report_year],K$4,tbl_FERC_Revenue[revenue_type],"other_operating_revenues") -> 105789779 | ... O14: =SUMIFS(tbl_FERC_Revenue[dollar_value],tbl_FERC_Revenue[utility_id_ferc1],CompanyId,tbl_FERC_Revenue[report_year],O$4,tbl_FERC_Revenue[revenue_type],"other_operating_revenues") -> 152350066 | P14: =IFERROR((INDEX($D14:$O14,MATCH(FercYear,$D$4:$O$4,0))/INDEX($D14:$O14,MATCH(BaseYear,$D$4:$O$4,0)))^(1/(FercYear-BaseYear))-1,0) -> 0.025912914 | Q14: =INDEX($D14:$O14,MATCH(FercYear,$D$4:$O$4,0))-INDEX($D14:$O14,MATCH(FercYear-1,$D$4:$O$4,0)) -> 25829084 | R14: {=SAFEDIV(Q14,ABS(INDEX($D14:$O14,MATCH(FercYear-1,$D$4:$O$4,0))))} -> 0.20414862
B15: Total operating revenue | D15: =SUM(D11:D14) -> 1926578668 | E15: =SUM(E11:E14) -> 1914921070 | F15: =SUM(F11:F14) -> 1939166814 | G15: =SUM(G11:G14) -> 2022693552 | H15: =SUM(H11:H14) -> 2005110043 | I15: =SUM(I11:I14) -> 2147982409 | J15: =SUM(J11:J14) -> 2157212368 | K15: =SUM(K11:K14) -> 2415154366 | ... O15: =SUM(O11:O14) -> 3548184245 | P15: =IFERROR((INDEX($D15:$O15,MATCH(FercYear,$D$4:$O$4,0))/INDEX($D15:$O15,MATCH(BaseYear,$D$4:$O$4,0)))^(1/(FercYear-BaseYear))-1,0) -> 0.08724956 | Q15: =INDEX($D15:$O15,MATCH(FercYear,$D$4:$O$4,0))-INDEX($D15:$O15,MATCH(FercYear-1,$D$4:$O$4,0)) -> 87469504 | R15: {=SAFEDIV(Q15,ABS(INDEX($D15:$O15,MATCH(FercYear-1,$D$4:$O$4,0))))} -> 0.025274982
B16: Power supply
B17: Fuel | D17: {=SUM(SUMIFS(tbl_FERC_Expense[dollar_value],tbl_FERC_Expense[utility_id_ferc1],CompanyId,tbl_FERC_Expense[report_year],D$4,tbl_FERC_Expense[expense_type],{"fuel_steam_power_generation","nuclear_fuel_expense","fuel","fuel_other_renewable_generation"}))} -> 251136059 | E17: {=SUM(SUMIFS(tbl_FERC_Expense[dollar_value],tbl_FERC_Expense[utility_id_ferc1],CompanyId,tbl_FERC_Expense[report_year],E$4,tbl_FERC_Expense[expense_type],{"fuel_steam_power_generation","nuclear_fuel_expense","fuel","fuel_other_renewable_generation"}))} -> 275229785 | F17: {=SUM(SUMIFS(tbl_FERC_Expense[dollar_value],tbl_FERC_Expense[utility_id_ferc1],CompanyId,tbl_FERC_Expense[report_year],F$4,tbl_FERC_Expense[expense_type],{"fuel_steam_power_generation","nuclear_fuel_expense","fuel","fuel_other_renewable_generation"}))} -> 294823521 | G17: {=SUM(SUMIFS(tbl_FERC_Expense[dollar_value],tbl_FERC_Expense[utility_id_ferc1],CompanyId,tbl_FERC_Expense[report_year],G$4,tbl_FERC_Expense[expense_type],{"fuel_steam_power_generation","nuclear_fuel_expense","fuel","fuel_other_renewable_generation"}))} -> 280282013 | H17: {=SUM(SUMIFS(tbl_FERC_Expense[dollar_value],tbl_FERC_Expense[utility_id_ferc1],CompanyId,tbl_FERC_Expense[report_year],H$4,tbl_FERC_Expense[expense_type],{"fuel_steam_power_generation","nuclear_fuel_expense","fuel","fuel_other_renewable_generation"}))} -> 250256859 | I17: {=SUM(SUMIFS(tbl_FERC_Expense[dollar_value],tbl_FERC_Expense[utility_id_ferc1],CompanyId,tbl_FERC_Expense[report_year],I$4,tbl_FERC_Expense[expense_type],{"fuel_steam_power_generation","nuclear_fuel_expense","fuel","fuel_other_renewable_generation"}))} -> 287914148 | J17: {=SUM(SUMIFS(tbl_FERC_Expense[dollar_value],tbl_FERC_Expense[utility_id_ferc1],CompanyId,tbl_FERC_Expense[report_year],J$4,tbl_FERC_Expense[expense_type],{"fuel_steam_power_generation","nuclear_fuel_expense","fuel","fuel_other_renewable_generation"}))} -> 241441550 | K17: {=SUM(SUMIFS(tbl_FERC_Expense[dollar_value],tbl_FERC_Expense[utility_id_ferc1],CompanyId,tbl_FERC_Expense[report_year],K$4,tbl_FERC_Expense[expense_type],{"fuel_steam_power_generation","nuclear_fuel_expense","fuel","fuel_other_renewable_generation"}))} -> 236524037 | ... O17: {=SUM(SUMIFS(tbl_FERC_Expense[dollar_value],tbl_FERC_Expense[utility_id_ferc1],CompanyId,tbl_FERC_Expense[report_year],O$4,tbl_FERC_Expense[expense_type],{"fuel_steam_power_generation","nuclear_fuel_expense","fuel","fuel_other_renewable_generation"}))} -> 475759791 | P17: =IFERROR((INDEX($D17:$O17,MATCH(FercYear,$D$4:$O$4,0))/INDEX($D17:$O17,MATCH(BaseYear,$D$4:$O$4,0)))^(1/(FercYear-BaseYear))-1,0) -> 0.08731185 | Q17: =INDEX($D17:$O17,MATCH(FercYear,$D$4:$O$4,0))-INDEX($D17:$O17,MATCH(FercYear-1,$D$4:$O$4,0)) -> 17994661 | R17: {=SAFEDIV(Q17,ABS(INDEX($D17:$O17,MATCH(FercYear-1,$D$4:$O$4,0))))} -> 0.039309812
B18: Purchased power | D18: {=SUM(SUMIFS(tbl_FERC_Expense[dollar_value],tbl_FERC_Expense[utility_id_ferc1],CompanyId,tbl_FERC_Expense[report_year],D$4,tbl_FERC_Expense[expense_type],{"purchased_power","power_purchased_for_storage_operations","storage_fuel_energy_storage_expense"}))} -> 414524300 | E18: {=SUM(SUMIFS(tbl_FERC_Expense[dollar_value],tbl_FERC_Expense[utility_id_ferc1],CompanyId,tbl_FERC_Expense[report_year],E$4,tbl_FERC_Expense[expense_type],{"purchased_power","power_purchased_for_storage_operations","storage_fuel_energy_storage_expense"}))} -> 325139822 | F18: {=SUM(SUMIFS(tbl_FERC_Expense[dollar_value],tbl_FERC_Expense[utility_id_ferc1],CompanyId,tbl_FERC_Expense[report_year],F$4,tbl_FERC_Expense[expense_type],{"purchased_power","power_purchased_for_storage_operations","storage_fuel_energy_storage_expense"}))} -> 264106264 | G18: {=SUM(SUMIFS(tbl_FERC_Expense[dollar_value],tbl_FERC_Expense[utility_id_ferc1],CompanyId,tbl_FERC_Expense[report_year],G$4,tbl_FERC_Expense[expense_type],{"purchased_power","power_purchased_for_storage_operations","storage_fuel_energy_storage_expense"}))} -> 244313723 | H18: {=SUM(SUMIFS(tbl_FERC_Expense[dollar_value],tbl_FERC_Expense[utility_id_ferc1],CompanyId,tbl_FERC_Expense[report_year],H$4,tbl_FERC_Expense[expense_type],{"purchased_power","power_purchased_for_storage_operations","storage_fuel_energy_storage_expense"}))} -> 257926636 | I18: {=SUM(SUMIFS(tbl_FERC_Expense[dollar_value],tbl_FERC_Expense[utility_id_ferc1],CompanyId,tbl_FERC_Expense[report_year],I$4,tbl_FERC_Expense[expense_type],{"purchased_power","power_purchased_for_storage_operations","storage_fuel_energy_storage_expense"}))} -> 281457582 | J18: {=SUM(SUMIFS(tbl_FERC_Expense[dollar_value],tbl_FERC_Expense[utility_id_ferc1],CompanyId,tbl_FERC_Expense[report_year],J$4,tbl_FERC_Expense[expense_type],{"purchased_power","power_purchased_for_storage_operations","storage_fuel_energy_storage_expense"}))} -> 418799466 | K18: {=SUM(SUMIFS(tbl_FERC_Expense[dollar_value],tbl_FERC_Expense[utility_id_ferc1],CompanyId,tbl_FERC_Expense[report_year],K$4,tbl_FERC_Expense[expense_type],{"purchased_power","power_purchased_for_storage_operations","storage_fuel_energy_storage_expense"}))} -> 530010343 | ... O18: {=SUM(SUMIFS(tbl_FERC_Expense[dollar_value],tbl_FERC_Expense[utility_id_ferc1],CompanyId,tbl_FERC_Expense[report_year],O$4,tbl_FERC_Expense[expense_type],{"purchased_power","power_purchased_for_storage_operations","storage_fuel_energy_storage_expense"}))} -> 845996268 | P18: =IFERROR((INDEX($D18:$O18,MATCH(FercYear,$D$4:$O$4,0))/INDEX($D18:$O18,MATCH(BaseYear,$D$4:$O$4,0)))^(1/(FercYear-BaseYear))-1,0) -> 0.2013215 | Q18: =INDEX($D18:$O18,MATCH(FercYear,$D$4:$O$4,0))-INDEX($D18:$O18,MATCH(FercYear-1,$D$4:$O$4,0)) -> -33863493 | R18: {=SAFEDIV(Q18,ABS(INDEX($D18:$O18,MATCH(FercYear-1,$D$4:$O$4,0))))} -> -0.038487375
B19: Power cost | D19: =D17+D18 -> 665660359 | E19: =E17+E18 -> 600369607 | F19: =F17+F18 -> 558929785 | G19: =G17+G18 -> 524595736 | H19: =H17+H18 -> 508183495 | I19: =I17+I18 -> 569371730 | J19: =J17+J18 -> 660241016 | K19: =K17+K18 -> 766534380 | ... O19: =O17+O18 -> 1321756059 | P19: =IFERROR((INDEX($D19:$O19,MATCH(FercYear,$D$4:$O$4,0))/INDEX($D19:$O19,MATCH(BaseYear,$D$4:$O$4,0)))^(1/(FercYear-BaseYear))-1,0) -> 0.15069237 | Q19: =INDEX($D19:$O19,MATCH(FercYear,$D$4:$O$4,0))-INDEX($D19:$O19,MATCH(FercYear-1,$D$4:$O$4,0)) -> -15868832 | R19: {=SAFEDIV(Q19,ABS(INDEX($D19:$O19,MATCH(FercYear-1,$D$4:$O$4,0))))} -> -0.01186344
B20: Gross margin | D20: =D15-D19 -> 1260918309 | E20: =E15-E19 -> 1314551463 | F20: =F15-F19 -> 1380237029 | G20: =G15-G19 -> 1498097816 | H20: =H15-H19 -> 1496926548 | I20: =I15-I19 -> 1578610679 | J20: =J15-J19 -> 1496971352 | K20: =K15-K19 -> 1648619986 | ... O20: =O15-O19 -> 2226428186 | P20: =IFERROR((INDEX($D20:$O20,MATCH(FercYear,$D$4:$O$4,0))/INDEX($D20:$O20,MATCH(BaseYear,$D$4:$O$4,0)))^(1/(FercYear-BaseYear))-1,0) -> 0.058982888 | Q20: =INDEX($D20:$O20,MATCH(FercYear,$D$4:$O$4,0))-INDEX($D20:$O20,MATCH(FercYear-1,$D$4:$O$4,0)) -> 103338336 | R20: {=SAFEDIV(Q20,ABS(INDEX($D20:$O20,MATCH(FercYear-1,$D$4:$O$4,0))))} -> 0.048673558
B21: Gross margin % | D21: {=SAFEDIV(D20,D15)} -> 0.65448576 | E21: {=SAFEDIV(E20,E15)} -> 0.68647814 | F21: {=SAFEDIV(F20,F15)} -> 0.71176807 | G21: {=SAFEDIV(G20,G15)} -> 0.74064498 | H21: {=SAFEDIV(H20,H15)} -> 0.74655581 | I21: {=SAFEDIV(I20,I15)} -> 0.73492719 | J21: {=SAFEDIV(J20,J15)} -> 0.69393787 | K21: {=SAFEDIV(K20,K15)} -> 0.68261475 | ... O21: {=SAFEDIV(O20,O15)} -> 0.62748381 | P21: =INDEX($D21:$O21,MATCH(FercYear,$D$4:$O$4,0))-INDEX($D21:$O21,MATCH(BaseYear,$D$4:$O$4,0)) -> -0.10744338 | Q21: =INDEX($D21:$O21,MATCH(FercYear,$D$4:$O$4,0))-INDEX($D21:$O21,MATCH(FercYear-1,$D$4:$O$4,0)) -> 0.01400076
B22: Operating expenses, excluding power
B23: Production, excluding fuel and purchased power | D23: =SUMIFS(tbl_FERC_Expense[dollar_value],tbl_FERC_Expense[utility_id_ferc1],CompanyId,tbl_FERC_Expense[report_year],D$4,tbl_FERC_Expense[expense_type],"power_production_expenses")-D19 -> 132400112 | E23: =SUMIFS(tbl_FERC_Expense[dollar_value],tbl_FERC_Expense[utility_id_ferc1],CompanyId,tbl_FERC_Expense[report_year],E$4,tbl_FERC_Expense[expense_type],"power_production_expenses")-E19 -> 140808746 | F23: =SUMIFS(tbl_FERC_Expense[dollar_value],tbl_FERC_Expense[utility_id_ferc1],CompanyId,tbl_FERC_Expense[report_year],F$4,tbl_FERC_Expense[expense_type],"power_production_expenses")-F19 -> 146447063 | G23: =SUMIFS(tbl_FERC_Expense[dollar_value],tbl_FERC_Expense[utility_id_ferc1],CompanyId,tbl_FERC_Expense[report_year],G$4,tbl_FERC_Expense[expense_type],"power_production_expenses")-G19 -> 154358468 | H23: =SUMIFS(tbl_FERC_Expense[dollar_value],tbl_FERC_Expense[utility_id_ferc1],CompanyId,tbl_FERC_Expense[report_year],H$4,tbl_FERC_Expense[expense_type],"power_production_expenses")-H19 -> 151929566 | I23: =SUMIFS(tbl_FERC_Expense[dollar_value],tbl_FERC_Expense[utility_id_ferc1],CompanyId,tbl_FERC_Expense[report_year],I$4,tbl_FERC_Expense[expense_type],"power_production_expenses")-I19 -> 162912941 | J23: =SUMIFS(tbl_FERC_Expense[dollar_value],tbl_FERC_Expense[utility_id_ferc1],CompanyId,tbl_FERC_Expense[report_year],J$4,tbl_FERC_Expense[expense_type],"power_production_expenses")-J19 -> 141931061 | K23: =SUMIFS(tbl_FERC_Expense[dollar_value],tbl_FERC_Expense[utility_id_ferc1],CompanyId,tbl_FERC_Expense[report_year],K$4,tbl_FERC_Expense[expense_type],"power_production_expenses")-K19 -> 131395452 | ... O23: =SUMIFS(tbl_FERC_Expense[dollar_value],tbl_FERC_Expense[utility_id_ferc1],CompanyId,tbl_FERC_Expense[report_year],O$4,tbl_FERC_Expense[expense_type],"power_production_expenses")-O19 -> 181565942 | P23: =IFERROR((INDEX($D23:$O23,MATCH(FercYear,$D$4:$O$4,0))/INDEX($D23:$O23,MATCH(BaseYear,$D$4:$O$4,0)))^(1/(FercYear-BaseYear))-1,0) -> 0.018231357 | Q23: =INDEX($D23:$O23,MATCH(FercYear,$D$4:$O$4,0))-INDEX($D23:$O23,MATCH(FercYear-1,$D$4:$O$4,0)) -> 5313745 | R23: {=SAFEDIV(Q23,ABS(INDEX($D23:$O23,MATCH(FercYear-1,$D$4:$O$4,0))))} -> 0.030148532
B24: Transmission | D24: =SUMIFS(tbl_FERC_Expense[dollar_value],tbl_FERC_Expense[utility_id_ferc1],CompanyId,tbl_FERC_Expense[report_year],D$4,tbl_FERC_Expense[expense_type],"transmission_expenses") -> 96567225 | E24: =SUMIFS(tbl_FERC_Expense[dollar_value],tbl_FERC_Expense[utility_id_ferc1],CompanyId,tbl_FERC_Expense[report_year],E$4,tbl_FERC_Expense[expense_type],"transmission_expenses") -> 98091925 | F24: =SUMIFS(tbl_FERC_Expense[dollar_value],tbl_FERC_Expense[utility_id_ferc1],CompanyId,tbl_FERC_Expense[report_year],F$4,tbl_FERC_Expense[expense_type],"transmission_expenses") -> 95364654 | G24: =SUMIFS(tbl_FERC_Expense[dollar_value],tbl_FERC_Expense[utility_id_ferc1],CompanyId,tbl_FERC_Expense[report_year],G$4,tbl_FERC_Expense[expense_type],"transmission_expenses") -> 104281769 | H24: =SUMIFS(tbl_FERC_Expense[dollar_value],tbl_FERC_Expense[utility_id_ferc1],CompanyId,tbl_FERC_Expense[report_year],H$4,tbl_FERC_Expense[expense_type],"transmission_expenses") -> 103337318 | I24: =SUMIFS(tbl_FERC_Expense[dollar_value],tbl_FERC_Expense[utility_id_ferc1],CompanyId,tbl_FERC_Expense[report_year],I$4,tbl_FERC_Expense[expense_type],"transmission_expenses") -> 108556686 | J24: =SUMIFS(tbl_FERC_Expense[dollar_value],tbl_FERC_Expense[utility_id_ferc1],CompanyId,tbl_FERC_Expense[report_year],J$4,tbl_FERC_Expense[expense_type],"transmission_expenses") -> 101525817 | K24: =SUMIFS(tbl_FERC_Expense[dollar_value],tbl_FERC_Expense[utility_id_ferc1],CompanyId,tbl_FERC_Expense[report_year],K$4,tbl_FERC_Expense[expense_type],"transmission_expenses") -> 111907966 | ... O24: =SUMIFS(tbl_FERC_Expense[dollar_value],tbl_FERC_Expense[utility_id_ferc1],CompanyId,tbl_FERC_Expense[report_year],O$4,tbl_FERC_Expense[expense_type],"transmission_expenses") -> 166944422 | P24: =IFERROR((INDEX($D24:$O24,MATCH(FercYear,$D$4:$O$4,0))/INDEX($D24:$O24,MATCH(BaseYear,$D$4:$O$4,0)))^(1/(FercYear-BaseYear))-1,0) -> 0.074366742 | Q24: =INDEX($D24:$O24,MATCH(FercYear,$D$4:$O$4,0))-INDEX($D24:$O24,MATCH(FercYear-1,$D$4:$O$4,0)) -> 8139744 | R24: {=SAFEDIV(Q24,ABS(INDEX($D24:$O24,MATCH(FercYear-1,$D$4:$O$4,0))))} -> 0.051256324
B25: Distribution | D25: =SUMIFS(tbl_FERC_Expense[dollar_value],tbl_FERC_Expense[utility_id_ferc1],CompanyId,tbl_FERC_Expense[report_year],D$4,tbl_FERC_Expense[expense_type],"distribution_expenses") -> 99839203 | E25: =SUMIFS(tbl_FERC_Expense[dollar_value],tbl_FERC_Expense[utility_id_ferc1],CompanyId,tbl_FERC_Expense[report_year],E$4,tbl_FERC_Expense[expense_type],"distribution_expenses") -> 101417432 | F25: =SUMIFS(tbl_FERC_Expense[dollar_value],tbl_FERC_Expense[utility_id_ferc1],CompanyId,tbl_FERC_Expense[report_year],F$4,tbl_FERC_Expense[expense_type],"distribution_expenses") -> 116611492 | G25: =SUMIFS(tbl_FERC_Expense[dollar_value],tbl_FERC_Expense[utility_id_ferc1],CompanyId,tbl_FERC_Expense[report_year],G$4,tbl_FERC_Expense[expense_type],"distribution_expenses") -> 127636822 | H25: =SUMIFS(tbl_FERC_Expense[dollar_value],tbl_FERC_Expense[utility_id_ferc1],CompanyId,tbl_FERC_Expense[report_year],H$4,tbl_FERC_Expense[expense_type],"distribution_expenses") -> 113588197 | I25: =SUMIFS(tbl_FERC_Expense[dollar_value],tbl_FERC_Expense[utility_id_ferc1],CompanyId,tbl_FERC_Expense[report_year],I$4,tbl_FERC_Expense[expense_type],"distribution_expenses") -> 134617893 | J25: =SUMIFS(tbl_FERC_Expense[dollar_value],tbl_FERC_Expense[utility_id_ferc1],CompanyId,tbl_FERC_Expense[report_year],J$4,tbl_FERC_Expense[expense_type],"distribution_expenses") -> 124006010 | K25: =SUMIFS(tbl_FERC_Expense[dollar_value],tbl_FERC_Expense[utility_id_ferc1],CompanyId,tbl_FERC_Expense[report_year],K$4,tbl_FERC_Expense[expense_type],"distribution_expenses") -> 159848932 | ... O25: =SUMIFS(tbl_FERC_Expense[dollar_value],tbl_FERC_Expense[utility_id_ferc1],CompanyId,tbl_FERC_Expense[report_year],O$4,tbl_FERC_Expense[expense_type],"distribution_expenses") -> 246386322 | P25: =IFERROR((INDEX($D25:$O25,MATCH(FercYear,$D$4:$O$4,0))/INDEX($D25:$O25,MATCH(BaseYear,$D$4:$O$4,0)))^(1/(FercYear-BaseYear))-1,0) -> 0.1059928 | Q25: =INDEX($D25:$O25,MATCH(FercYear,$D$4:$O$4,0))-INDEX($D25:$O25,MATCH(FercYear-1,$D$4:$O$4,0)) -> 18058364 | R25: {=SAFEDIV(Q25,ABS(INDEX($D25:$O25,MATCH(FercYear-1,$D$4:$O$4,0))))} -> 0.079089587
B26: Customer accounts, service and sales | D26: {=SUM(SUMIFS(tbl_FERC_Expense[dollar_value],tbl_FERC_Expense[utility_id_ferc1],CompanyId,tbl_FERC_Expense[report_year],D$4,tbl_FERC_Expense[expense_type],{"customer_account_expenses","customer_service_and_information_expenses","sales_expenses"}))} -> 66009525 | E26: {=SUM(SUMIFS(tbl_FERC_Expense[dollar_value],tbl_FERC_Expense[utility_id_ferc1],CompanyId,tbl_FERC_Expense[report_year],E$4,tbl_FERC_Expense[expense_type],{"customer_account_expenses","customer_service_and_information_expenses","sales_expenses"}))} -> 69758456 | F26: {=SUM(SUMIFS(tbl_FERC_Expense[dollar_value],tbl_FERC_Expense[utility_id_ferc1],CompanyId,tbl_FERC_Expense[report_year],F$4,tbl_FERC_Expense[expense_type],{"customer_account_expenses","customer_service_and_information_expenses","sales_expenses"}))} -> 70626752 | G26: {=SUM(SUMIFS(tbl_FERC_Expense[dollar_value],tbl_FERC_Expense[utility_id_ferc1],CompanyId,tbl_FERC_Expense[report_year],G$4,tbl_FERC_Expense[expense_type],{"customer_account_expenses","customer_service_and_information_expenses","sales_expenses"}))} -> 74189210 | H26: {=SUM(SUMIFS(tbl_FERC_Expense[dollar_value],tbl_FERC_Expense[utility_id_ferc1],CompanyId,tbl_FERC_Expense[report_year],H$4,tbl_FERC_Expense[expense_type],{"customer_account_expenses","customer_service_and_information_expenses","sales_expenses"}))} -> 86086288 | I26: {=SUM(SUMIFS(tbl_FERC_Expense[dollar_value],tbl_FERC_Expense[utility_id_ferc1],CompanyId,tbl_FERC_Expense[report_year],I$4,tbl_FERC_Expense[expense_type],{"customer_account_expenses","customer_service_and_information_expenses","sales_expenses"}))} -> 79987880 | J26: {=SUM(SUMIFS(tbl_FERC_Expense[dollar_value],tbl_FERC_Expense[utility_id_ferc1],CompanyId,tbl_FERC_Expense[report_year],J$4,tbl_FERC_Expense[expense_type],{"customer_account_expenses","customer_service_and_information_expenses","sales_expenses"}))} -> 80061690 | K26: {=SUM(SUMIFS(tbl_FERC_Expense[dollar_value],tbl_FERC_Expense[utility_id_ferc1],CompanyId,tbl_FERC_Expense[report_year],K$4,tbl_FERC_Expense[expense_type],{"customer_account_expenses","customer_service_and_information_expenses","sales_expenses"}))} -> 89416307 | ... O26: {=SUM(SUMIFS(tbl_FERC_Expense[dollar_value],tbl_FERC_Expense[utility_id_ferc1],CompanyId,tbl_FERC_Expense[report_year],O$4,tbl_FERC_Expense[expense_type],{"customer_account_expenses","customer_service_and_information_expenses","sales_expenses"}))} -> 82694489 | P26: =IFERROR((INDEX($D26:$O26,MATCH(FercYear,$D$4:$O$4,0))/INDEX($D26:$O26,MATCH(BaseYear,$D$4:$O$4,0)))^(1/(FercYear-BaseYear))-1,0) -> 0.0055617156 | Q26: =INDEX($D26:$O26,MATCH(FercYear,$D$4:$O$4,0))-INDEX($D26:$O26,MATCH(FercYear-1,$D$4:$O$4,0)) -> -31152394 | R26: {=SAFEDIV(Q26,ABS(INDEX($D26:$O26,MATCH(FercYear-1,$D$4:$O$4,0))))} -> -0.27363414
B27: Administrative and general | D27: =SUMIFS(tbl_FERC_Expense[dollar_value],tbl_FERC_Expense[utility_id_ferc1],CompanyId,tbl_FERC_Expense[report_year],D$4,tbl_FERC_Expense[expense_type],"administrative_and_general_expenses") -> 161772278 | E27: =SUMIFS(tbl_FERC_Expense[dollar_value],tbl_FERC_Expense[utility_id_ferc1],CompanyId,tbl_FERC_Expense[report_year],E$4,tbl_FERC_Expense[expense_type],"administrative_and_general_expenses") -> 171798280 | F27: =SUMIFS(tbl_FERC_Expense[dollar_value],tbl_FERC_Expense[utility_id_ferc1],CompanyId,tbl_FERC_Expense[report_year],F$4,tbl_FERC_Expense[expense_type],"administrative_and_general_expenses") -> 176470725 | G27: =SUMIFS(tbl_FERC_Expense[dollar_value],tbl_FERC_Expense[utility_id_ferc1],CompanyId,tbl_FERC_Expense[report_year],G$4,tbl_FERC_Expense[expense_type],"administrative_and_general_expenses") -> 190762897 | H27: =SUMIFS(tbl_FERC_Expense[dollar_value],tbl_FERC_Expense[utility_id_ferc1],CompanyId,tbl_FERC_Expense[report_year],H$4,tbl_FERC_Expense[expense_type],"administrative_and_general_expenses") -> 190551981 | I27: =SUMIFS(tbl_FERC_Expense[dollar_value],tbl_FERC_Expense[utility_id_ferc1],CompanyId,tbl_FERC_Expense[report_year],I$4,tbl_FERC_Expense[expense_type],"administrative_and_general_expenses") -> 210248968 | J27: =SUMIFS(tbl_FERC_Expense[dollar_value],tbl_FERC_Expense[utility_id_ferc1],CompanyId,tbl_FERC_Expense[report_year],J$4,tbl_FERC_Expense[expense_type],"administrative_and_general_expenses") -> 204695622 | K27: =SUMIFS(tbl_FERC_Expense[dollar_value],tbl_FERC_Expense[utility_id_ferc1],CompanyId,tbl_FERC_Expense[report_year],K$4,tbl_FERC_Expense[expense_type],"administrative_and_general_expenses") -> 242114888 | ... O27: =SUMIFS(tbl_FERC_Expense[dollar_value],tbl_FERC_Expense[utility_id_ferc1],CompanyId,tbl_FERC_Expense[report_year],O$4,tbl_FERC_Expense[expense_type],"administrative_and_general_expenses") -> 283831875 | P27: =IFERROR((INDEX($D27:$O27,MATCH(FercYear,$D$4:$O$4,0))/INDEX($D27:$O27,MATCH(BaseYear,$D$4:$O$4,0)))^(1/(FercYear-BaseYear))-1,0) -> 0.05128681 | Q27: =INDEX($D27:$O27,MATCH(FercYear,$D$4:$O$4,0))-INDEX($D27:$O27,MATCH(FercYear-1,$D$4:$O$4,0)) -> 20434095 | R27: {=SAFEDIV(Q27,ABS(INDEX($D27:$O27,MATCH(FercYear-1,$D$4:$O$4,0))))} -> 0.077578843
B28: Regional market and other | D28: =D29-SUM(D23:D27) -> 0 | E28: =E29-SUM(E23:E27) -> 0 | F28: =F29-SUM(F23:F27) -> 0 | G28: =G29-SUM(G23:G27) -> 0 | H28: =H29-SUM(H23:H27) -> 0 | I28: =I29-SUM(I23:I27) -> 0 | J28: =J29-SUM(J23:J27) -> 0 | K28: =K29-SUM(K23:K27) -> 0 | ... O28: =O29-SUM(O23:O27) -> 4183939 | P28: =IFERROR((INDEX($D28:$O28,MATCH(FercYear,$D$4:$O$4,0))/INDEX($D28:$O28,MATCH(BaseYear,$D$4:$O$4,0)))^(1/(FercYear-BaseYear))-1,0) -> 0 | Q28: =INDEX($D28:$O28,MATCH(FercYear,$D$4:$O$4,0))-INDEX($D28:$O28,MATCH(FercYear-1,$D$4:$O$4,0)) -> 4183939 | R28: {=SAFEDIV(Q28,ABS(INDEX($D28:$O28,MATCH(FercYear-1,$D$4:$O$4,0))))} -> 0
B29: Other O&M | D29: =SUMIFS(tbl_FERC_Expense[dollar_value],tbl_FERC_Expense[utility_id_ferc1],CompanyId,tbl_FERC_Expense[report_year],D$4,tbl_FERC_Expense[expense_type],"operations_and_maintenance_expenses_electric")-D19 -> 556588343 | E29: =SUMIFS(tbl_FERC_Expense[dollar_value],tbl_FERC_Expense[utility_id_ferc1],CompanyId,tbl_FERC_Expense[report_year],E$4,tbl_FERC_Expense[expense_type],"operations_and_maintenance_expenses_electric")-E19 -> 581874839 | F29: =SUMIFS(tbl_FERC_Expense[dollar_value],tbl_FERC_Expense[utility_id_ferc1],CompanyId,tbl_FERC_Expense[report_year],F$4,tbl_FERC_Expense[expense_type],"operations_and_maintenance_expenses_electric")-F19 -> 605520686 | G29: =SUMIFS(tbl_FERC_Expense[dollar_value],tbl_FERC_Expense[utility_id_ferc1],CompanyId,tbl_FERC_Expense[report_year],G$4,tbl_FERC_Expense[expense_type],"operations_and_maintenance_expenses_electric")-G19 -> 651229166 | H29: =SUMIFS(tbl_FERC_Expense[dollar_value],tbl_FERC_Expense[utility_id_ferc1],CompanyId,tbl_FERC_Expense[report_year],H$4,tbl_FERC_Expense[expense_type],"operations_and_maintenance_expenses_electric")-H19 -> 645493350 | I29: =SUMIFS(tbl_FERC_Expense[dollar_value],tbl_FERC_Expense[utility_id_ferc1],CompanyId,tbl_FERC_Expense[report_year],I$4,tbl_FERC_Expense[expense_type],"operations_and_maintenance_expenses_electric")-I19 -> 696324368 | J29: =SUMIFS(tbl_FERC_Expense[dollar_value],tbl_FERC_Expense[utility_id_ferc1],CompanyId,tbl_FERC_Expense[report_year],J$4,tbl_FERC_Expense[expense_type],"operations_and_maintenance_expenses_electric")-J19 -> 652220200 | K29: =SUMIFS(tbl_FERC_Expense[dollar_value],tbl_FERC_Expense[utility_id_ferc1],CompanyId,tbl_FERC_Expense[report_year],K$4,tbl_FERC_Expense[expense_type],"operations_and_maintenance_expenses_electric")-K19 -> 734683545 | ... O29: =SUMIFS(tbl_FERC_Expense[dollar_value],tbl_FERC_Expense[utility_id_ferc1],CompanyId,tbl_FERC_Expense[report_year],O$4,tbl_FERC_Expense[expense_type],"operations_and_maintenance_expenses_electric")-O19 -> 965606989 | P29: =IFERROR((INDEX($D29:$O29,MATCH(FercYear,$D$4:$O$4,0))/INDEX($D29:$O29,MATCH(BaseYear,$D$4:$O$4,0)))^(1/(FercYear-BaseYear))-1,0) -> 0.056002147 | Q29: =INDEX($D29:$O29,MATCH(FercYear,$D$4:$O$4,0))-INDEX($D29:$O29,MATCH(FercYear-1,$D$4:$O$4,0)) -> 24977493 | R29: {=SAFEDIV(Q29,ABS(INDEX($D29:$O29,MATCH(FercYear-1,$D$4:$O$4,0))))} -> 0.026554018
B30: Depreciation and amortization | D30: {=SUM(SUMIFS(tbl_FERC_Income[dollar_value],tbl_FERC_Income[utility_id_ferc1],CompanyId,tbl_FERC_Income[report_year],D$4,tbl_FERC_Income[income_type],{"depreciation_expense","depreciation_expense_for_asset_retirement_costs","amortization_and_depletion_of_utility_plant","amortization_of_other_utility_plant"}))} -> 270700548 | E30: {=SUM(SUMIFS(tbl_FERC_Income[dollar_value],tbl_FERC_Income[utility_id_ferc1],CompanyId,tbl_FERC_Income[report_year],E$4,tbl_FERC_Income[income_type],{"depreciation_expense","depreciation_expense_for_asset_retirement_costs","amortization_and_depletion_of_utility_plant","amortization_of_other_utility_plant"}))} -> 295789259 | F30: {=SUM(SUMIFS(tbl_FERC_Income[dollar_value],tbl_FERC_Income[utility_id_ferc1],CompanyId,tbl_FERC_Income[report_year],F$4,tbl_FERC_Income[income_type],{"depreciation_expense","depreciation_expense_for_asset_retirement_costs","amortization_and_depletion_of_utility_plant","amortization_of_other_utility_plant"}))} -> 317600678 | G30: {=SUM(SUMIFS(tbl_FERC_Income[dollar_value],tbl_FERC_Income[utility_id_ferc1],CompanyId,tbl_FERC_Income[report_year],G$4,tbl_FERC_Income[income_type],{"depreciation_expense","depreciation_expense_for_asset_retirement_costs","amortization_and_depletion_of_utility_plant","amortization_of_other_utility_plant"}))} -> 343699429 | H30: {=SUM(SUMIFS(tbl_FERC_Income[dollar_value],tbl_FERC_Income[utility_id_ferc1],CompanyId,tbl_FERC_Income[report_year],H$4,tbl_FERC_Income[income_type],{"depreciation_expense","depreciation_expense_for_asset_retirement_costs","amortization_and_depletion_of_utility_plant","amortization_of_other_utility_plant"}))} -> 361731511 | I30: {=SUM(SUMIFS(tbl_FERC_Income[dollar_value],tbl_FERC_Income[utility_id_ferc1],CompanyId,tbl_FERC_Income[report_year],I$4,tbl_FERC_Income[income_type],{"depreciation_expense","depreciation_expense_for_asset_retirement_costs","amortization_and_depletion_of_utility_plant","amortization_of_other_utility_plant"}))} -> 378993196 | J30: {=SUM(SUMIFS(tbl_FERC_Income[dollar_value],tbl_FERC_Income[utility_id_ferc1],CompanyId,tbl_FERC_Income[report_year],J$4,tbl_FERC_Income[income_type],{"depreciation_expense","depreciation_expense_for_asset_retirement_costs","amortization_and_depletion_of_utility_plant","amortization_of_other_utility_plant"}))} -> 375712084 | K30: {=SUM(SUMIFS(tbl_FERC_Income[dollar_value],tbl_FERC_Income[utility_id_ferc1],CompanyId,tbl_FERC_Income[report_year],K$4,tbl_FERC_Income[income_type],{"depreciation_expense","depreciation_expense_for_asset_retirement_costs","amortization_and_depletion_of_utility_plant","amortization_of_other_utility_plant"}))} -> 379591275 | ... O30: {=SUM(SUMIFS(tbl_FERC_Income[dollar_value],tbl_FERC_Income[utility_id_ferc1],CompanyId,tbl_FERC_Income[report_year],O$4,tbl_FERC_Income[income_type],{"depreciation_expense","depreciation_expense_for_asset_retirement_costs","amortization_and_depletion_of_utility_plant","amortization_of_other_utility_plant"}))} -> 530444462 | P30: =IFERROR((INDEX($D30:$O30,MATCH(FercYear,$D$4:$O$4,0))/INDEX($D30:$O30,MATCH(BaseYear,$D$4:$O$4,0)))^(1/(FercYear-BaseYear))-1,0) -> 0.057632411 | Q30: =INDEX($D30:$O30,MATCH(FercYear,$D$4:$O$4,0))-INDEX($D30:$O30,MATCH(FercYear-1,$D$4:$O$4,0)) -> 44988218 | R30: {=SAFEDIV(Q30,ABS(INDEX($D30:$O30,MATCH(FercYear-1,$D$4:$O$4,0))))} -> 0.092672035
B31: Taxes other than income | D31: =SUMIFS(tbl_FERC_Income[dollar_value],tbl_FERC_Income[utility_id_ferc1],CompanyId,tbl_FERC_Income[report_year],D$4,tbl_FERC_Income[income_type],"taxes_other_than_income_taxes_utility_operating_income") -> 106846515 | E31: =SUMIFS(tbl_FERC_Income[dollar_value],tbl_FERC_Income[utility_id_ferc1],CompanyId,tbl_FERC_Income[report_year],E$4,tbl_FERC_Income[income_type],"taxes_other_than_income_taxes_utility_operating_income") -> 114643947 | F31: =SUMIFS(tbl_FERC_Income[dollar_value],tbl_FERC_Income[utility_id_ferc1],CompanyId,tbl_FERC_Income[report_year],F$4,tbl_FERC_Income[income_type],"taxes_other_than_income_taxes_utility_operating_income") -> 117893057 | G31: =SUMIFS(tbl_FERC_Income[dollar_value],tbl_FERC_Income[utility_id_ferc1],CompanyId,tbl_FERC_Income[report_year],G$4,tbl_FERC_Income[income_type],"taxes_other_than_income_taxes_utility_operating_income") -> 121629678 | H31: =SUMIFS(tbl_FERC_Income[dollar_value],tbl_FERC_Income[utility_id_ferc1],CompanyId,tbl_FERC_Income[report_year],H$4,tbl_FERC_Income[income_type],"taxes_other_than_income_taxes_utility_operating_income") -> 126448833 | I31: =SUMIFS(tbl_FERC_Income[dollar_value],tbl_FERC_Income[utility_id_ferc1],CompanyId,tbl_FERC_Income[report_year],I$4,tbl_FERC_Income[income_type],"taxes_other_than_income_taxes_utility_operating_income") -> 132404584 | J31: =SUMIFS(tbl_FERC_Income[dollar_value],tbl_FERC_Income[utility_id_ferc1],CompanyId,tbl_FERC_Income[report_year],J$4,tbl_FERC_Income[income_type],"taxes_other_than_income_taxes_utility_operating_income") -> 136443033 | K31: =SUMIFS(tbl_FERC_Income[dollar_value],tbl_FERC_Income[utility_id_ferc1],CompanyId,tbl_FERC_Income[report_year],K$4,tbl_FERC_Income[income_type],"taxes_other_than_income_taxes_utility_operating_income") -> 143889438 | ... O31: =SUMIFS(tbl_FERC_Income[dollar_value],tbl_FERC_Income[utility_id_ferc1],CompanyId,tbl_FERC_Income[report_year],O$4,tbl_FERC_Income[income_type],"taxes_other_than_income_taxes_utility_operating_income") -> 187937578 | P31: =IFERROR((INDEX($D31:$O31,MATCH(FercYear,$D$4:$O$4,0))/INDEX($D31:$O31,MATCH(BaseYear,$D$4:$O$4,0)))^(1/(FercYear-BaseYear))-1,0) -> 0.060112041 | Q31: =INDEX($D31:$O31,MATCH(FercYear,$D$4:$O$4,0))-INDEX($D31:$O31,MATCH(FercYear-1,$D$4:$O$4,0)) -> 14707427 | R31: {=SAFEDIV(Q31,ABS(INDEX($D31:$O31,MATCH(FercYear-1,$D$4:$O$4,0))))} -> 0.084901081
B32: Operating income before income taxes | D32: =D20-D29-D30-D31 -> 326782903 | E32: =E20-E29-E30-E31 -> 322243418 | F32: =F20-F29-F30-F31 -> 339222608 | G32: =G20-G29-G30-G31 -> 381539543 | H32: =H20-H29-H30-H31 -> 363252854 | I32: =I20-I29-I30-I31 -> 370888531 | J32: =J20-J29-J30-J31 -> 332596035 | K32: =K20-K29-K30-K31 -> 390455728 | ... O32: =O20-O29-O30-O31 -> 542439157 | P32: =IFERROR((INDEX($D32:$O32,MATCH(FercYear,$D$4:$O$4,0))/INDEX($D32:$O32,MATCH(BaseYear,$D$4:$O$4,0)))^(1/(FercYear-BaseYear))-1,0) -> 0.065412869 | Q32: =INDEX($D32:$O32,MATCH(FercYear,$D$4:$O$4,0))-INDEX($D32:$O32,MATCH(FercYear-1,$D$4:$O$4,0)) -> 18665198 | R32: {=SAFEDIV(Q32,ABS(INDEX($D32:$O32,MATCH(FercYear-1,$D$4:$O$4,0))))} -> 0.035635979
B33: Operating margin % | D33: {=SAFEDIV(D32,D15)} -> 0.16961825 | E33: {=SAFEDIV(E32,E15)} -> 0.16828026 | F33: {=SAFEDIV(F32,F15)} -> 0.17493214 | G33: {=SAFEDIV(G32,G15)} -> 0.18862944 | H33: {=SAFEDIV(H32,H15)} -> 0.18116355 | I33: {=SAFEDIV(I32,I15)} -> 0.17266833 | J33: {=SAFEDIV(J32,J15)} -> 0.15417862 | K33: {=SAFEDIV(K32,K15)} -> 0.16166906 | ... O33: {=SAFEDIV(O32,O15)} -> 0.15287796 | P33: =INDEX($D33:$O33,MATCH(FercYear,$D$4:$O$4,0))-INDEX($D33:$O33,MATCH(BaseYear,$D$4:$O$4,0)) -> -0.019790371 | Q33: =INDEX($D33:$O33,MATCH(FercYear,$D$4:$O$4,0))-INDEX($D33:$O33,MATCH(FercYear-1,$D$4:$O$4,0)) -> 0.0015294641
B34: Volumes and unit economics
B35: Retail MWh | D35: =SUMIFS(tbl_FERC_Revenue[sales_mwh],tbl_FERC_Revenue[utility_id_ferc1],CompanyId,tbl_FERC_Revenue[report_year],D$4,tbl_FERC_Revenue[revenue_type],"sales_to_ultimate_consumers") -> 17603187 | E35: =SUMIFS(tbl_FERC_Revenue[sales_mwh],tbl_FERC_Revenue[utility_id_ferc1],CompanyId,tbl_FERC_Revenue[report_year],E$4,tbl_FERC_Revenue[revenue_type],"sales_to_ultimate_consumers") -> 17696386 | F35: =SUMIFS(tbl_FERC_Revenue[sales_mwh],tbl_FERC_Revenue[utility_id_ferc1],CompanyId,tbl_FERC_Revenue[report_year],F$4,tbl_FERC_Revenue[revenue_type],"sales_to_ultimate_consumers") -> 17248173 | G35: =SUMIFS(tbl_FERC_Revenue[sales_mwh],tbl_FERC_Revenue[utility_id_ferc1],CompanyId,tbl_FERC_Revenue[report_year],G$4,tbl_FERC_Revenue[revenue_type],"sales_to_ultimate_consumers") -> 17754280 | H35: =SUMIFS(tbl_FERC_Revenue[sales_mwh],tbl_FERC_Revenue[utility_id_ferc1],CompanyId,tbl_FERC_Revenue[report_year],H$4,tbl_FERC_Revenue[revenue_type],"sales_to_ultimate_consumers") -> 17186002 | I35: =SUMIFS(tbl_FERC_Revenue[sales_mwh],tbl_FERC_Revenue[utility_id_ferc1],CompanyId,tbl_FERC_Revenue[report_year],I$4,tbl_FERC_Revenue[revenue_type],"sales_to_ultimate_consumers") -> 17304691 | J35: =SUMIFS(tbl_FERC_Revenue[sales_mwh],tbl_FERC_Revenue[utility_id_ferc1],CompanyId,tbl_FERC_Revenue[report_year],J$4,tbl_FERC_Revenue[revenue_type],"sales_to_ultimate_consumers") -> 17423803 | K35: =SUMIFS(tbl_FERC_Revenue[sales_mwh],tbl_FERC_Revenue[utility_id_ferc1],CompanyId,tbl_FERC_Revenue[report_year],K$4,tbl_FERC_Revenue[revenue_type],"sales_to_ultimate_consumers") -> 18296054 | ... O35: =SUMIFS(tbl_FERC_Revenue[sales_mwh],tbl_FERC_Revenue[utility_id_ferc1],CompanyId,tbl_FERC_Revenue[report_year],O$4,tbl_FERC_Revenue[revenue_type],"sales_to_ultimate_consumers") -> 19968167 | P35: =IFERROR((INDEX($D35:$O35,MATCH(FercYear,$D$4:$O$4,0))/INDEX($D35:$O35,MATCH(BaseYear,$D$4:$O$4,0)))^(1/(FercYear-BaseYear))-1,0) -> 0.024147223 | Q35: =INDEX($D35:$O35,MATCH(FercYear,$D$4:$O$4,0))-INDEX($D35:$O35,MATCH(FercYear-1,$D$4:$O$4,0)) -> 695545 | R35: {=SAFEDIV(Q35,ABS(INDEX($D35:$O35,MATCH(FercYear-1,$D$4:$O$4,0))))} -> 0.036089796
B36: Residential MWh | D36: =SUMIFS(tbl_FERC_Revenue[sales_mwh],tbl_FERC_Revenue[utility_id_ferc1],CompanyId,tbl_FERC_Revenue[report_year],D$4,tbl_FERC_Revenue[revenue_type],"residential_sales") -> 7461863 | E36: =SUMIFS(tbl_FERC_Revenue[sales_mwh],tbl_FERC_Revenue[utility_id_ferc1],CompanyId,tbl_FERC_Revenue[report_year],E$4,tbl_FERC_Revenue[revenue_type],"residential_sales") -> 7325314 | F36: =SUMIFS(tbl_FERC_Revenue[sales_mwh],tbl_FERC_Revenue[utility_id_ferc1],CompanyId,tbl_FERC_Revenue[report_year],F$4,tbl_FERC_Revenue[revenue_type],"residential_sales") -> 7347750 | G36: =SUMIFS(tbl_FERC_Revenue[sales_mwh],tbl_FERC_Revenue[utility_id_ferc1],CompanyId,tbl_FERC_Revenue[report_year],G$4,tbl_FERC_Revenue[revenue_type],"residential_sales") -> 7879585 | H36: =SUMIFS(tbl_FERC_Revenue[sales_mwh],tbl_FERC_Revenue[utility_id_ferc1],CompanyId,tbl_FERC_Revenue[report_year],H$4,tbl_FERC_Revenue[revenue_type],"residential_sales") -> 7415759 | I36: =SUMIFS(tbl_FERC_Revenue[sales_mwh],tbl_FERC_Revenue[utility_id_ferc1],CompanyId,tbl_FERC_Revenue[report_year],I$4,tbl_FERC_Revenue[revenue_type],"residential_sales") -> 7471069 | J36: =SUMIFS(tbl_FERC_Revenue[sales_mwh],tbl_FERC_Revenue[utility_id_ferc1],CompanyId,tbl_FERC_Revenue[report_year],J$4,tbl_FERC_Revenue[revenue_type],"residential_sales") -> 7756251 | K36: =SUMIFS(tbl_FERC_Revenue[sales_mwh],tbl_FERC_Revenue[utility_id_ferc1],CompanyId,tbl_FERC_Revenue[report_year],K$4,tbl_FERC_Revenue[revenue_type],"residential_sales") -> 7978099 | ... O36: =SUMIFS(tbl_FERC_Revenue[sales_mwh],tbl_FERC_Revenue[utility_id_ferc1],CompanyId,tbl_FERC_Revenue[report_year],O$4,tbl_FERC_Revenue[revenue_type],"residential_sales") -> 7596298 | P36: =IFERROR((INDEX($D36:$O36,MATCH(FercYear,$D$4:$O$4,0))/INDEX($D36:$O36,MATCH(BaseYear,$D$4:$O$4,0)))^(1/(FercYear-BaseYear))-1,0) -> 0.0027743295 | Q36: =INDEX($D36:$O36,MATCH(FercYear,$D$4:$O$4,0))-INDEX($D36:$O36,MATCH(FercYear-1,$D$4:$O$4,0)) -> -135296 | R36: {=SAFEDIV(Q36,ABS(INDEX($D36:$O36,MATCH(FercYear-1,$D$4:$O$4,0))))} -> -0.017499108
B37: Industrial MWh | D37: =SUMIFS(tbl_FERC_Revenue[sales_mwh],tbl_FERC_Revenue[utility_id_ferc1],CompanyId,tbl_FERC_Revenue[report_year],D$4,tbl_FERC_Revenue[revenue_type],"large_or_industrial") -> 3210619 | E37: =SUMIFS(tbl_FERC_Revenue[sales_mwh],tbl_FERC_Revenue[utility_id_ferc1],CompanyId,tbl_FERC_Revenue[report_year],E$4,tbl_FERC_Revenue[revenue_type],"large_or_industrial") -> 3369215 | F37: =SUMIFS(tbl_FERC_Revenue[sales_mwh],tbl_FERC_Revenue[utility_id_ferc1],CompanyId,tbl_FERC_Revenue[report_year],F$4,tbl_FERC_Revenue[revenue_type],"large_or_industrial") -> 2968238 | G37: =SUMIFS(tbl_FERC_Revenue[sales_mwh],tbl_FERC_Revenue[utility_id_ferc1],CompanyId,tbl_FERC_Revenue[report_year],G$4,tbl_FERC_Revenue[revenue_type],"large_or_industrial") -> 2942938 | H37: =SUMIFS(tbl_FERC_Revenue[sales_mwh],tbl_FERC_Revenue[utility_id_ferc1],CompanyId,tbl_FERC_Revenue[report_year],H$4,tbl_FERC_Revenue[revenue_type],"large_or_industrial") -> 2987403 | I37: =SUMIFS(tbl_FERC_Revenue[sales_mwh],tbl_FERC_Revenue[utility_id_ferc1],CompanyId,tbl_FERC_Revenue[report_year],I$4,tbl_FERC_Revenue[revenue_type],"large_or_industrial") -> 3180993 | J37: =SUMIFS(tbl_FERC_Revenue[sales_mwh],tbl_FERC_Revenue[utility_id_ferc1],CompanyId,tbl_FERC_Revenue[report_year],J$4,tbl_FERC_Revenue[revenue_type],"large_or_industrial") -> 3445801 | K37: =SUMIFS(tbl_FERC_Revenue[sales_mwh],tbl_FERC_Revenue[utility_id_ferc1],CompanyId,tbl_FERC_Revenue[report_year],K$4,tbl_FERC_Revenue[revenue_type],"large_or_industrial") -> 3713680 | ... O37: =SUMIFS(tbl_FERC_Revenue[sales_mwh],tbl_FERC_Revenue[utility_id_ferc1],CompanyId,tbl_FERC_Revenue[report_year],O$4,tbl_FERC_Revenue[revenue_type],"large_or_industrial") -> 5904529 | P37: =IFERROR((INDEX($D37:$O37,MATCH(FercYear,$D$4:$O$4,0))/INDEX($D37:$O37,MATCH(BaseYear,$D$4:$O$4,0)))^(1/(FercYear-BaseYear))-1,0) -> 0.10858864 | Q37: =INDEX($D37:$O37,MATCH(FercYear,$D$4:$O$4,0))-INDEX($D37:$O37,MATCH(FercYear-1,$D$4:$O$4,0)) -> 872144 | R37: {=SAFEDIV(Q37,ABS(INDEX($D37:$O37,MATCH(FercYear-1,$D$4:$O$4,0))))} -> 0.1733063
B38: Total MWh sold, including wholesale | D38: =SUMIFS(tbl_FERC_Revenue[sales_mwh],tbl_FERC_Revenue[utility_id_ferc1],CompanyId,tbl_FERC_Revenue[report_year],D$4,tbl_FERC_Revenue[revenue_type],"sales_of_electricity") -> 21080082 | E38: =SUMIFS(tbl_FERC_Revenue[sales_mwh],tbl_FERC_Revenue[utility_id_ferc1],CompanyId,tbl_FERC_Revenue[report_year],E$4,tbl_FERC_Revenue[revenue_type],"sales_of_electricity") -> 20859230 | F38: =SUMIFS(tbl_FERC_Revenue[sales_mwh],tbl_FERC_Revenue[utility_id_ferc1],CompanyId,tbl_FERC_Revenue[report_year],F$4,tbl_FERC_Revenue[revenue_type],"sales_of_electricity") -> 21247271 | G38: =SUMIFS(tbl_FERC_Revenue[sales_mwh],tbl_FERC_Revenue[utility_id_ferc1],CompanyId,tbl_FERC_Revenue[report_year],G$4,tbl_FERC_Revenue[revenue_type],"sales_of_electricity") -> 21328945 | H38: =SUMIFS(tbl_FERC_Revenue[sales_mwh],tbl_FERC_Revenue[utility_id_ferc1],CompanyId,tbl_FERC_Revenue[report_year],H$4,tbl_FERC_Revenue[revenue_type],"sales_of_electricity") -> 21876992 | I38: =SUMIFS(tbl_FERC_Revenue[sales_mwh],tbl_FERC_Revenue[utility_id_ferc1],CompanyId,tbl_FERC_Revenue[report_year],I$4,tbl_FERC_Revenue[revenue_type],"sales_of_electricity") -> 22572002 | J38: =SUMIFS(tbl_FERC_Revenue[sales_mwh],tbl_FERC_Revenue[utility_id_ferc1],CompanyId,tbl_FERC_Revenue[report_year],J$4,tbl_FERC_Revenue[revenue_type],"sales_of_electricity") -> 23866383 | K38: =SUMIFS(tbl_FERC_Revenue[sales_mwh],tbl_FERC_Revenue[utility_id_ferc1],CompanyId,tbl_FERC_Revenue[report_year],K$4,tbl_FERC_Revenue[revenue_type],"sales_of_electricity") -> 24780030 | ... O38: =SUMIFS(tbl_FERC_Revenue[sales_mwh],tbl_FERC_Revenue[utility_id_ferc1],CompanyId,tbl_FERC_Revenue[report_year],O$4,tbl_FERC_Revenue[revenue_type],"sales_of_electricity") -> 29824518 | P38: =IFERROR((INDEX($D38:$O38,MATCH(FercYear,$D$4:$O$4,0))/INDEX($D38:$O38,MATCH(BaseYear,$D$4:$O$4,0)))^(1/(FercYear-BaseYear))-1,0) -> 0.047531824 | Q38: =INDEX($D38:$O38,MATCH(FercYear,$D$4:$O$4,0))-INDEX($D38:$O38,MATCH(FercYear-1,$D$4:$O$4,0)) -> 246857 | R38: {=SAFEDIV(Q38,ABS(INDEX($D38:$O38,MATCH(FercYear-1,$D$4:$O$4,0))))} -> 0.0083460623
B39: Retail customers (average) | D39: =SUMIFS(tbl_FERC_Revenue[avg_customers_per_month],tbl_FERC_Revenue[utility_id_ferc1],CompanyId,tbl_FERC_Revenue[report_year],D$4,tbl_FERC_Revenue[revenue_type],"sales_to_ultimate_consumers") -> 840993 | E39: =SUMIFS(tbl_FERC_Revenue[avg_customers_per_month],tbl_FERC_Revenue[utility_id_ferc1],CompanyId,tbl_FERC_Revenue[report_year],E$4,tbl_FERC_Revenue[revenue_type],"sales_to_ultimate_consumers") -> 848524 | F39: =SUMIFS(tbl_FERC_Revenue[avg_customers_per_month],tbl_FERC_Revenue[utility_id_ferc1],CompanyId,tbl_FERC_Revenue[report_year],F$4,tbl_FERC_Revenue[revenue_type],"sales_to_ultimate_consumers") -> 859396 | G39: =SUMIFS(tbl_FERC_Revenue[avg_customers_per_month],tbl_FERC_Revenue[utility_id_ferc1],CompanyId,tbl_FERC_Revenue[report_year],G$4,tbl_FERC_Revenue[revenue_type],"sales_to_ultimate_consumers") -> 870333 | H39: =SUMIFS(tbl_FERC_Revenue[avg_customers_per_month],tbl_FERC_Revenue[utility_id_ferc1],CompanyId,tbl_FERC_Revenue[report_year],H$4,tbl_FERC_Revenue[revenue_type],"sales_to_ultimate_consumers") -> 881766 | I39: =SUMIFS(tbl_FERC_Revenue[avg_customers_per_month],tbl_FERC_Revenue[utility_id_ferc1],CompanyId,tbl_FERC_Revenue[report_year],I$4,tbl_FERC_Revenue[revenue_type],"sales_to_ultimate_consumers") -> 890019 | J39: =SUMIFS(tbl_FERC_Revenue[avg_customers_per_month],tbl_FERC_Revenue[utility_id_ferc1],CompanyId,tbl_FERC_Revenue[report_year],J$4,tbl_FERC_Revenue[revenue_type],"sales_to_ultimate_consumers") -> 902237 | K39: =SUMIFS(tbl_FERC_Revenue[avg_customers_per_month],tbl_FERC_Revenue[utility_id_ferc1],CompanyId,tbl_FERC_Revenue[report_year],K$4,tbl_FERC_Revenue[revenue_type],"sales_to_ultimate_consumers") -> 912209 | ... O39: =SUMIFS(tbl_FERC_Revenue[avg_customers_per_month],tbl_FERC_Revenue[utility_id_ferc1],CompanyId,tbl_FERC_Revenue[report_year],O$4,tbl_FERC_Revenue[revenue_type],"sales_to_ultimate_consumers") -> 955654 | P39: =IFERROR((INDEX($D39:$O39,MATCH(FercYear,$D$4:$O$4,0))/INDEX($D39:$O39,MATCH(BaseYear,$D$4:$O$4,0)))^(1/(FercYear-BaseYear))-1,0) -> 0.011929447 | Q39: =INDEX($D39:$O39,MATCH(FercYear,$D$4:$O$4,0))-INDEX($D39:$O39,MATCH(FercYear-1,$D$4:$O$4,0)) -> 11710 | R39: {=SAFEDIV(Q39,ABS(INDEX($D39:$O39,MATCH(FercYear-1,$D$4:$O$4,0))))} -> 0.012405397
B40: Retail price, ¢/kWh | D40: {=CPK(D11,D35)} -> 9.7766036 | E40: {=CPK(E11,E35)} -> 9.8075554 | F40: {=CPK(F11,F35)} -> 9.8788877 | G40: {=CPK(G11,G35)} -> 9.9930575 | H40: {=CPK(H11,H35)} -> 10.241771 | I40: {=CPK(I11,I35)} -> 10.339993 | J40: {=CPK(J11,J35)} -> 10.595175 | K40: {=CPK(K11,K35)} -> 11.14713 | ... O40: {=CPK(O11,O35)} -> 14.870402 | P40: =IFERROR((INDEX($D40:$O40,MATCH(FercYear,$D$4:$O$4,0))/INDEX($D40:$O40,MATCH(BaseYear,$D$4:$O$4,0)))^(1/(FercYear-BaseYear))-1,0) -> 0.06243021 | Q40: =INDEX($D40:$O40,MATCH(FercYear,$D$4:$O$4,0))-INDEX($D40:$O40,MATCH(FercYear-1,$D$4:$O$4,0)) -> 0.4300767 | R40: {=SAFEDIV(Q40,ABS(INDEX($D40:$O40,MATCH(FercYear-1,$D$4:$O$4,0))))} -> 0.029783035
B41: Residential price, ¢/kWh | D41: {=CPK(D6,D36)} -> 11.372417 | E41: {=CPK(E6,E36)} -> 11.547712 | F41: {=CPK(F6,F36)} -> 11.404014 | G41: {=CPK(G6,G36)} -> 11.424102 | H41: {=CPK(H6,H36)} -> 12.006547 | I41: {=CPK(I6,I36)} -> 12.284619 | J41: {=CPK(J6,J36)} -> 12.504875 | K41: {=CPK(K6,K36)} -> 13.240857 | ... O41: {=CPK(O6,O36)} -> 18.794483 | P41: =IFERROR((INDEX($D41:$O41,MATCH(FercYear,$D$4:$O$4,0))/INDEX($D41:$O41,MATCH(BaseYear,$D$4:$O$4,0)))^(1/(FercYear-BaseYear))-1,0) -> 0.073440852 | Q41: =INDEX($D41:$O41,MATCH(FercYear,$D$4:$O$4,0))-INDEX($D41:$O41,MATCH(FercYear-1,$D$4:$O$4,0)) -> 0.60456508 | R41: {=SAFEDIV(Q41,ABS(INDEX($D41:$O41,MATCH(FercYear-1,$D$4:$O$4,0))))} -> 0.033236272
B42: Industrial price, ¢/kWh | D42: {=CPK(D8,D37)} -> 6.8927133 | E42: {=CPK(E8,E37)} -> 6.7667133 | F42: {=CPK(F8,F37)} -> 6.9966752 | G42: {=CPK(G8,G37)} -> 7.1896976 | H42: {=CPK(H8,H37)} -> 7.0156645 | I42: {=CPK(I8,I37)} -> 6.9769076 | J42: {=CPK(J8,J37)} -> 7.1406121 | K42: {=CPK(K8,K37)} -> 7.5363533 | ... O42: {=CPK(O8,O37)} -> 9.492662 | P42: =IFERROR((INDEX($D42:$O42,MATCH(FercYear,$D$4:$O$4,0))/INDEX($D42:$O42,MATCH(BaseYear,$D$4:$O$4,0)))^(1/(FercYear-BaseYear))-1,0) -> 0.052658516 | Q42: =INDEX($D42:$O42,MATCH(FercYear,$D$4:$O$4,0))-INDEX($D42:$O42,MATCH(FercYear-1,$D$4:$O$4,0)) -> 0.40242446 | R42: {=SAFEDIV(Q42,ABS(INDEX($D42:$O42,MATCH(FercYear-1,$D$4:$O$4,0))))} -> 0.044269961
B43: Power cost per MWh sold, $ | D43: {=SAFEDIV(D19,D38)} -> 31.577693 | E43: {=SAFEDIV(E19,E38)} -> 28.781964 | F43: {=SAFEDIV(F19,F38)} -> 26.305956 | G43: {=SAFEDIV(G19,G38)} -> 24.595484 | H43: {=SAFEDIV(H19,H38)} -> 23.22913 | I43: {=SAFEDIV(I19,I38)} -> 25.224689 | J43: {=SAFEDIV(J19,J38)} -> 27.664059 | K43: {=SAFEDIV(K19,K38)} -> 30.933553 | ... O43: {=SAFEDIV(O19,O38)} -> 44.317768 | P43: =IFERROR((INDEX($D43:$O43,MATCH(FercYear,$D$4:$O$4,0))/INDEX($D43:$O43,MATCH(BaseYear,$D$4:$O$4,0)))^(1/(FercYear-BaseYear))-1,0) -> 0.098479634 | Q43: =INDEX($D43:$O43,MATCH(FercYear,$D$4:$O$4,0))-INDEX($D43:$O43,MATCH(FercYear-1,$D$4:$O$4,0)) -> -0.90639294 | R43: {=SAFEDIV(Q43,ABS(INDEX($D43:$O43,MATCH(FercYear-1,$D$4:$O$4,0))))} -> -0.020042228
B44: Other O&M per customer, $ | D44: {=SAFEDIV(D29,D39)} -> 661.8228 | E44: {=SAFEDIV(E29,E39)} -> 685.74942 | F44: {=SAFEDIV(F29,F39)} -> 704.58867 | G44: {=SAFEDIV(G29,G39)} -> 748.25287 | H44: {=SAFEDIV(H29,H39)} -> 732.04609 | I44: {=SAFEDIV(I29,I39)} -> 782.37023 | J44: {=SAFEDIV(J29,J39)} -> 722.89232 | K44: {=SAFEDIV(K29,K39)} -> 805.38949 | ... O44: {=SAFEDIV(O29,O39)} -> 1010.4148 | P44: =IFERROR((INDEX($D44:$O44,MATCH(FercYear,$D$4:$O$4,0))/INDEX($D44:$O44,MATCH(BaseYear,$D$4:$O$4,0)))^(1/(FercYear-BaseYear))-1,0) -> 0.043553135 | Q44: =INDEX($D44:$O44,MATCH(FercYear,$D$4:$O$4,0))-INDEX($D44:$O44,MATCH(FercYear-1,$D$4:$O$4,0)) -> 13.926181 | R44: {=SAFEDIV(Q44,ABS(INDEX($D44:$O44,MATCH(FercYear-1,$D$4:$O$4,0))))} -> 0.013975253
B45: Industrial share of retail MWh | D45: {=SAFEDIV(D37,D35)} -> 0.18238851 | E45: {=SAFEDIV(E37,E35)} -> 0.19039 | F45: {=SAFEDIV(F37,F35)} -> 0.17208999 | G45: {=SAFEDIV(G37,G35)} -> 0.16575935 | H45: {=SAFEDIV(H37,H35)} -> 0.17382769 | I45: {=SAFEDIV(I37,I35)} -> 0.18382258 | J45: {=SAFEDIV(J37,J35)} -> 0.197764 | K45: {=SAFEDIV(K37,K35)} -> 0.2029771 | ... O45: {=SAFEDIV(O37,O35)} -> 0.2956971 | P45: =INDEX($D45:$O45,MATCH(FercYear,$D$4:$O$4,0))-INDEX($D45:$O45,MATCH(BaseYear,$D$4:$O$4,0)) -> 0.11187451 | Q45: =INDEX($D45:$O45,MATCH(FercYear,$D$4:$O$4,0))-INDEX($D45:$O45,MATCH(FercYear-1,$D$4:$O$4,0)) -> 0.034581354

Sheet PVM
B1: Price, volume and mix: where retail revenue growth came from
B2: Each class's change in MWh is valued at the earlier period's average price (volume) and at its own price's distance from that average (mix); price is the change in $/MWh on the later period's MWh. The three effects add up to every class's revenue change: column O is zero.
B4: ="Long view: "&BaseYear&" to "&FercYear&", FERC Form 1" -> Long view: 2019 to 2025, FERC Form 1
B5: Class | C5: Source line | D5: MWh before | E5: Revenue before | F5: MWh after | G5: Revenue after | H5: $/MWh before | I5: $/MWh after | J5: Volume | K5: Mix | L5: Price | M5: Effects, total | N5: Revenue change | O5: Unexplained
B6: Residential | C6: residential_sales | D6: =SUMIFS(tbl_FERC_Revenue[sales_mwh],tbl_FERC_Revenue[utility_id_ferc1],CompanyId,tbl_FERC_Revenue[report_year],BaseYear,tbl_FERC_Revenue[revenue_type],$C6) -> 7471069 | E6: =SUMIFS(tbl_FERC_Revenue[dollar_value],tbl_FERC_Revenue[utility_id_ferc1],CompanyId,tbl_FERC_Revenue[report_year],BaseYear,tbl_FERC_Revenue[revenue_type],$C6) -> 917792335 | F6: =SUMIFS(tbl_FERC_Revenue[sales_mwh],tbl_FERC_Revenue[utility_id_ferc1],CompanyId,tbl_FERC_Revenue[report_year],FercYear,tbl_FERC_Revenue[revenue_type],$C6) -> 7596298 | G6: =SUMIFS(tbl_FERC_Revenue[dollar_value],tbl_FERC_Revenue[utility_id_ferc1],CompanyId,tbl_FERC_Revenue[report_year],FercYear,tbl_FERC_Revenue[revenue_type],$C6) -> 1427684968 | H6: {=SAFEDIV(E6,D6)} -> 122.84619 | I6: {=SAFEDIV(G6,F6)} -> 187.94483 | J6: =(F6-D6)*$H$11 -> 12948669 | K6: =(F6-D6)*(H6-$H$11) -> 2435235.7 | L6: =F6*(I6-H6) -> 4.9450873e+08 | M6: =SUM(J6:L6) -> 509892633 | N6: =G6-E6 -> 509892633 | O6: =M6-N6 -> 0
B7: Commercial | C7: small_or_commercial | D7: =SUMIFS(tbl_FERC_Revenue[sales_mwh],tbl_FERC_Revenue[utility_id_ferc1],CompanyId,tbl_FERC_Revenue[report_year],BaseYear,tbl_FERC_Revenue[revenue_type],$C7) -> 6603269 | E7: =SUMIFS(tbl_FERC_Revenue[dollar_value],tbl_FERC_Revenue[utility_id_ferc1],CompanyId,tbl_FERC_Revenue[report_year],BaseYear,tbl_FERC_Revenue[revenue_type],$C7) -> 638317031 | F7: =SUMIFS(tbl_FERC_Revenue[sales_mwh],tbl_FERC_Revenue[utility_id_ferc1],CompanyId,tbl_FERC_Revenue[report_year],FercYear,tbl_FERC_Revenue[revenue_type],$C7) -> 6425897 | G7: =SUMIFS(tbl_FERC_Revenue[dollar_value],tbl_FERC_Revenue[utility_id_ferc1],CompanyId,tbl_FERC_Revenue[report_year],FercYear,tbl_FERC_Revenue[revenue_type],$C7) -> 966187754 | H7: {=SAFEDIV(E7,D7)} -> 96.666822 | I7: {=SAFEDIV(G7,F7)} -> 150.35843 | J7: =(F7-D7)*$H$11 -> -18340252 | K7: =(F7-D7)*(H7-$H$11) -> 1194264.1 | L7: =F7*(I7-H7) -> 3.4501671e+08 | M7: =SUM(J7:L7) -> 3.2787072e+08 | N7: =G7-E7 -> 327870723 | O7: =M7-N7 -> 0
B8: Industrial | C8: large_or_industrial | D8: =SUMIFS(tbl_FERC_Revenue[sales_mwh],tbl_FERC_Revenue[utility_id_ferc1],CompanyId,tbl_FERC_Revenue[report_year],BaseYear,tbl_FERC_Revenue[revenue_type],$C8) -> 3180993 | E8: =SUMIFS(tbl_FERC_Revenue[dollar_value],tbl_FERC_Revenue[utility_id_ferc1],CompanyId,tbl_FERC_Revenue[report_year],BaseYear,tbl_FERC_Revenue[revenue_type],$C8) -> 221934941 | F8: =SUMIFS(tbl_FERC_Revenue[sales_mwh],tbl_FERC_Revenue[utility_id_ferc1],CompanyId,tbl_FERC_Revenue[report_year],FercYear,tbl_FERC_Revenue[revenue_type],$C8) -> 5904529 | G8: =SUMIFS(tbl_FERC_Revenue[dollar_value],tbl_FERC_Revenue[utility_id_ferc1],CompanyId,tbl_FERC_Revenue[report_year],FercYear,tbl_FERC_Revenue[revenue_type],$C8) -> 560496980 | H8: {=SAFEDIV(E8,D8)} -> 69.769076 | I8: {=SAFEDIV(G8,F8)} -> 94.92662 | J8: =(F8-D8)*$H$11 -> 2.8161342e+08 | K8: =(F8-D8)*(H8-$H$11) -> -91594833 | L8: =F8*(I8-H8) -> 1.4854345e+08 | M8: =SUM(J8:L8) -> 338562039 | N8: =G8-E8 -> 338562039 | O8: =M8-N8 -> 0
B9: Street lighting | C9: public_street_and_highway_lighting | D9: =SUMIFS(tbl_FERC_Revenue[sales_mwh],tbl_FERC_Revenue[utility_id_ferc1],CompanyId,tbl_FERC_Revenue[report_year],BaseYear,tbl_FERC_Revenue[revenue_type],$C9) -> 49360 | E9: =SUMIFS(tbl_FERC_Revenue[dollar_value],tbl_FERC_Revenue[utility_id_ferc1],CompanyId,tbl_FERC_Revenue[report_year],BaseYear,tbl_FERC_Revenue[revenue_type],$C9) -> 11259467 | F9: =SUMIFS(tbl_FERC_Revenue[sales_mwh],tbl_FERC_Revenue[utility_id_ferc1],CompanyId,tbl_FERC_Revenue[report_year],FercYear,tbl_FERC_Revenue[revenue_type],$C9) -> 41443 | G9: =SUMIFS(tbl_FERC_Revenue[dollar_value],tbl_FERC_Revenue[utility_id_ferc1],CompanyId,tbl_FERC_Revenue[report_year],FercYear,tbl_FERC_Revenue[revenue_type],$C9) -> 14976918 | H9: {=SAFEDIV(E9,D9)} -> 228.10914 | I9: {=SAFEDIV(G9,F9)} -> 361.38595 | J9: =(F9-D9)*$H$11 -> -818617.22 | K9: =(F9-D9)*(H9-$H$11) -> -987322.82 | L9: =F9*(I9-H9) -> 5523391 | M9: =SUM(J9:L9) -> 3717451 | N9: =G9-E9 -> 3717451 | O9: =M9-N9 -> 0
B10: Public authorities | C10: other_sales_to_public_authorities | D10: =SUMIFS(tbl_FERC_Revenue[sales_mwh],tbl_FERC_Revenue[utility_id_ferc1],CompanyId,tbl_FERC_Revenue[report_year],BaseYear,tbl_FERC_Revenue[revenue_type],$C10) -> 0 | E10: =SUMIFS(tbl_FERC_Revenue[dollar_value],tbl_FERC_Revenue[utility_id_ferc1],CompanyId,tbl_FERC_Revenue[report_year],BaseYear,tbl_FERC_Revenue[revenue_type],$C10) -> 0 | F10: =SUMIFS(tbl_FERC_Revenue[sales_mwh],tbl_FERC_Revenue[utility_id_ferc1],CompanyId,tbl_FERC_Revenue[report_year],FercYear,tbl_FERC_Revenue[revenue_type],$C10) -> 0 | G10: =SUMIFS(tbl_FERC_Revenue[dollar_value],tbl_FERC_Revenue[utility_id_ferc1],CompanyId,tbl_FERC_Revenue[report_year],FercYear,tbl_FERC_Revenue[revenue_type],$C10) -> 0 | H10: {=SAFEDIV(E10,D10)} -> 0 | I10: {=SAFEDIV(G10,F10)} -> 0 | J10: =(F10-D10)*$H$11 -> 0 | K10: =(F10-D10)*(H10-$H$11) -> 0 | L10: =F10*(I10-H10) -> 0 | M10: =SUM(J10:L10) -> 0 | N10: =G10-E10 -> 0 | O10: =M10-N10 -> 0
B11: All classes | D11: =SUM(D6:D10) -> 17304691 | E11: =SUM(E6:E10) -> 1789303774 | F11: =SUM(F6:F10) -> 19968167 | G11: =SUM(G6:G10) -> 2969346620 | H11: {=SAFEDIV(E11,D11)} -> 103.39993 | I11: {=SAFEDIV(G11,F11)} -> 148.70402 | J11: =SUM(J6:J10) -> 2.7540322e+08 | K11: =SUM(K6:K10) -> -88952656 | L11: =SUM(L6:L10) -> 9.9359228e+08 | M11: =SUM(J11:L11) -> 1180042846 | N11: =G11-E11 -> 1180042846 | O11: =M11-N11 -> 0
B14: ="Last year: "&(FercYear-1)&" to "&FercYear&", FERC Form 1" -> Last year: 2024 to 2025, FERC Form 1
B15: Class | C15: Source line | D15: MWh before | E15: Revenue before | F15: MWh after | G15: Revenue after | H15: $/MWh before | I15: $/MWh after | J15: Volume | K15: Mix | L15: Price | M15: Effects, total | N15: Revenue change | O15: Unexplained
B16: Residential | C16: residential_sales | D16: =SUMIFS(tbl_FERC_Revenue[sales_mwh],tbl_FERC_Revenue[utility_id_ferc1],CompanyId,tbl_FERC_Revenue[report_year],FercYear-1,tbl_FERC_Revenue[revenue_type],$C16) -> 7731594 | E16: =SUMIFS(tbl_FERC_Revenue[dollar_value],tbl_FERC_Revenue[utility_id_ferc1],CompanyId,tbl_FERC_Revenue[report_year],FercYear-1,tbl_FERC_Revenue[revenue_type],$C16) -> 1406370635 | F16: =SUMIFS(tbl_FERC_Revenue[sales_mwh],tbl_FERC_Revenue[utility_id_ferc1],CompanyId,tbl_FERC_Revenue[report_year],FercYear,tbl_FERC_Revenue[revenue_type],$C16) -> 7596298 | G16: =SUMIFS(tbl_FERC_Revenue[dollar_value],tbl_FERC_Revenue[utility_id_ferc1],CompanyId,tbl_FERC_Revenue[report_year],FercYear,tbl_FERC_Revenue[revenue_type],$C16) -> 1427684968 | H16: {=SAFEDIV(E16,D16)} -> 181.89918 | I16: {=SAFEDIV(G16,F16)} -> 187.94483 | J16: =(F16-D16)*$H$21 -> -19537182 | K16: =(F16-D16)*(H16-$H$21) -> -5073050 | L16: =F16*(I16-H16) -> 45924565 | M16: =SUM(J16:L16) -> 21314333 | N16: =G16-E16 -> 21314333 | O16: =M16-N16 -> 2.9802322e-08
B17: Commercial | C17: small_or_commercial | D17: =SUMIFS(tbl_FERC_Revenue[sales_mwh],tbl_FERC_Revenue[utility_id_ferc1],CompanyId,tbl_FERC_Revenue[report_year],FercYear-1,tbl_FERC_Revenue[revenue_type],$C17) -> 6466018 | E17: =SUMIFS(tbl_FERC_Revenue[dollar_value],tbl_FERC_Revenue[utility_id_ferc1],CompanyId,tbl_FERC_Revenue[report_year],FercYear-1,tbl_FERC_Revenue[revenue_type],$C17) -> 904898637 | F17: =SUMIFS(tbl_FERC_Revenue[sales_mwh],tbl_FERC_Revenue[utility_id_ferc1],CompanyId,tbl_FERC_Revenue[report_year],FercYear,tbl_FERC_Revenue[revenue_type],$C17) -> 6425897 | G17: =SUMIFS(tbl_FERC_Revenue[dollar_value],tbl_FERC_Revenue[utility_id_ferc1],CompanyId,tbl_FERC_Revenue[report_year],FercYear,tbl_FERC_Revenue[revenue_type],$C17) -> 966187754 | H17: {=SAFEDIV(E17,D17)} -> 139.94682 | I17: {=SAFEDIV(G17,F17)} -> 150.35843 | J17: =(F17-D17)*$H$21 -> -5793602.7 | K17: =(F17-D17)*(H17-$H$21) -> 178796.5 | L17: =F17*(I17-H17) -> 66903923 | M17: =SUM(J17:L17) -> 61289117 | N17: =G17-E17 -> 61289117 | O17: =M17-N17 -> -8.1956387e-08
B18: Industrial | C18: large_or_industrial | D18: =SUMIFS(tbl_FERC_Revenue[sales_mwh],tbl_FERC_Revenue[utility_id_ferc1],CompanyId,tbl_FERC_Revenue[report_year],FercYear-1,tbl_FERC_Revenue[revenue_type],$C18) -> 5032385 | E18: =SUMIFS(tbl_FERC_Revenue[dollar_value],tbl_FERC_Revenue[utility_id_ferc1],CompanyId,tbl_FERC_Revenue[report_year],FercYear-1,tbl_FERC_Revenue[revenue_type],$C18) -> 457455750 | F18: =SUMIFS(tbl_FERC_Revenue[sales_mwh],tbl_FERC_Revenue[utility_id_ferc1],CompanyId,tbl_FERC_Revenue[report_year],FercYear,tbl_FERC_Revenue[revenue_type],$C18) -> 5904529 | G18: =SUMIFS(tbl_FERC_Revenue[dollar_value],tbl_FERC_Revenue[utility_id_ferc1],CompanyId,tbl_FERC_Revenue[report_year],FercYear,tbl_FERC_Revenue[revenue_type],$C18) -> 560496980 | H18: {=SAFEDIV(E18,D18)} -> 90.902375 | I18: {=SAFEDIV(G18,F18)} -> 94.92662 | J18: =(F18-D18)*$H$21 -> 1.2594043e+08 | K18: =(F18-D18)*(H18-$H$21) -> -46660466 | L18: =F18*(I18-H18) -> 23761269 | M18: =SUM(J18:L18) -> 103041230 | N18: =G18-E18 -> 103041230 | O18: =M18-N18 -> 0
B19: Street lighting | C19: public_street_and_highway_lighting | D19: =SUMIFS(tbl_FERC_Revenue[sales_mwh],tbl_FERC_Revenue[utility_id_ferc1],CompanyId,tbl_FERC_Revenue[report_year],FercYear-1,tbl_FERC_Revenue[revenue_type],$C19) -> 42625 | E19: =SUMIFS(tbl_FERC_Revenue[dollar_value],tbl_FERC_Revenue[utility_id_ferc1],CompanyId,tbl_FERC_Revenue[report_year],FercYear-1,tbl_FERC_Revenue[revenue_type],$C19) -> 14304206 | F19: =SUMIFS(tbl_FERC_Revenue[sales_mwh],tbl_FERC_Revenue[utility_id_ferc1],CompanyId,tbl_FERC_Revenue[report_year],FercYear,tbl_FERC_Revenue[revenue_type],$C19) -> 41443 | G19: =SUMIFS(tbl_FERC_Revenue[dollar_value],tbl_FERC_Revenue[utility_id_ferc1],CompanyId,tbl_FERC_Revenue[report_year],FercYear,tbl_FERC_Revenue[revenue_type],$C19) -> 14976918 | H19: {=SAFEDIV(E19,D19)} -> 335.58255 | I19: {=SAFEDIV(G19,F19)} -> 361.38595 | J19: =(F19-D19)*$H$21 -> -170684.64 | K19: =(F19-D19)*(H19-$H$21) -> -225973.93 | L19: =F19*(I19-H19) -> 1069370.6 | M19: =SUM(J19:L19) -> 672712 | N19: =G19-E19 -> 672712 | O19: =M19-N19 -> -9.3132257e-10
B20: Public authorities | C20: other_sales_to_public_authorities | D20: =SUMIFS(tbl_FERC_Revenue[sales_mwh],tbl_FERC_Revenue[utility_id_ferc1],CompanyId,tbl_FERC_Revenue[report_year],FercYear-1,tbl_FERC_Revenue[revenue_type],$C20) -> 0 | E20: =SUMIFS(tbl_FERC_Revenue[dollar_value],tbl_FERC_Revenue[utility_id_ferc1],CompanyId,tbl_FERC_Revenue[report_year],FercYear-1,tbl_FERC_Revenue[revenue_type],$C20) -> 0 | F20: =SUMIFS(tbl_FERC_Revenue[sales_mwh],tbl_FERC_Revenue[utility_id_ferc1],CompanyId,tbl_FERC_Revenue[report_year],FercYear,tbl_FERC_Revenue[revenue_type],$C20) -> 0 | G20: =SUMIFS(tbl_FERC_Revenue[dollar_value],tbl_FERC_Revenue[utility_id_ferc1],CompanyId,tbl_FERC_Revenue[report_year],FercYear,tbl_FERC_Revenue[revenue_type],$C20) -> 0 | H20: {=SAFEDIV(E20,D20)} -> 0 | I20: {=SAFEDIV(G20,F20)} -> 0 | J20: =(F20-D20)*$H$21 -> 0 | K20: =(F20-D20)*(H20-$H$21) -> 0 | L20: =F20*(I20-H20) -> 0 | M20: =SUM(J20:L20) -> 0 | N20: =G20-E20 -> 0 | O20: =M20-N20 -> 0
B21: All classes | D21: =SUM(D16:D20) -> 19272622 | E21: =SUM(E16:E20) -> 2783029228 | F21: =SUM(F16:F20) -> 19968167 | G21: =SUM(G16:G20) -> 2969346620 | H21: {=SAFEDIV(E21,D21)} -> 144.40325 | I21: {=SAFEDIV(G21,F21)} -> 148.70402 | J21: =SUM(J16:J20) -> 1.0043896e+08 | K21: =SUM(K16:K20) -> -51780693 | L21: =SUM(L16:L20) -> 1.3765913e+08 | M21: =SUM(J21:L21) -> 186317392 | N21: =G21-E21 -> 186317392 | O21: =M21-N21 -> 0
B24: ="Year to date: "&TEXT(FYStart,"mmm")&"–"&TEXT(AsOfMonth,"mmm yyyy")&" against the same months of "&(FiscalYear-1)&", EIA-861M" -> Year to date: Jan–Jun 2026 against the same months of 2025, EIA-861M
B25: Class | C25: Source line | D25: MWh before | E25: Revenue before | F25: MWh after | G25: Revenue after | H25: $/MWh before | I25: $/MWh after | J25: Volume | K25: Mix | L25: Price | M25: Effects, total | N25: Revenue change | O25: Unexplained
B26: Residential | C26: residential | D26: =SUMIFS(tbl_Monthly[mwh],tbl_Monthly[class],$C26,tbl_Monthly[month],">="&EDATE(FYStart,-12),tbl_Monthly[month],"<="&EDATE(AsOfMonth,-12)) -> 3797252.5 | E26: =SUMIFS(tbl_Monthly[revenue],tbl_Monthly[class],$C26,tbl_Monthly[month],">="&EDATE(FYStart,-12),tbl_Monthly[month],"<="&EDATE(AsOfMonth,-12)) -> 712293444 | F26: =SUMIFS(tbl_Monthly[mwh],tbl_Monthly[class],$C26,tbl_Monthly[month],">="&FYStart,tbl_Monthly[month],"<="&AsOfMonth) -> 3677698.2 | G26: =SUMIFS(tbl_Monthly[revenue],tbl_Monthly[class],$C26,tbl_Monthly[month],">="&FYStart,tbl_Monthly[month],"<="&AsOfMonth) -> 695144762 | H26: {=SAFEDIV(E26,D26)} -> 187.58127 | I26: {=SAFEDIV(G26,F26)} -> 189.01626 | J26: =(F26-D26)*$H$30 -> -17615752 | K26: =(F26-D26)*(H26-$H$30) -> -4810389.3 | L26: =F26*(I26-H26) -> 5277459.6 | M26: =SUM(J26:L26) -> -17148682 | N26: =G26-E26 -> -17148682 | O26: =M26-N26 -> 0
B27: Commercial | C27: commercial | D27: =SUMIFS(tbl_Monthly[mwh],tbl_Monthly[class],$C27,tbl_Monthly[month],">="&EDATE(FYStart,-12),tbl_Monthly[month],"<="&EDATE(AsOfMonth,-12)) -> 3153190.5 | E27: =SUMIFS(tbl_Monthly[revenue],tbl_Monthly[class],$C27,tbl_Monthly[month],">="&EDATE(FYStart,-12),tbl_Monthly[month],"<="&EDATE(AsOfMonth,-12)) -> 468548856 | F27: =SUMIFS(tbl_Monthly[mwh],tbl_Monthly[class],$C27,tbl_Monthly[month],">="&FYStart,tbl_Monthly[month],"<="&AsOfMonth) -> 3100530.5 | G27: =SUMIFS(tbl_Monthly[revenue],tbl_Monthly[class],$C27,tbl_Monthly[month],">="&FYStart,tbl_Monthly[month],"<="&AsOfMonth) -> 474305106 | H27: {=SAFEDIV(E27,D27)} -> 148.59516 | I27: {=SAFEDIV(G27,F27)} -> 152.97547 | J27: =(F27-D27)*$H$30 -> -7759197.8 | K27: =(F27-D27)*(H27-$H$30) -> -65821.055 | L27: =F27*(I27-H27) -> 13581269 | M27: =SUM(J27:L27) -> 5756250 | N27: =G27-E27 -> 5756250 | O27: =M27-N27 -> 5.1222742e-08
B28: Industrial | C28: industrial | D28: =SUMIFS(tbl_Monthly[mwh],tbl_Monthly[class],$C28,tbl_Monthly[month],">="&EDATE(FYStart,-12),tbl_Monthly[month],"<="&EDATE(AsOfMonth,-12)) -> 2832897.3 | E28: =SUMIFS(tbl_Monthly[revenue],tbl_Monthly[class],$C28,tbl_Monthly[month],">="&EDATE(FYStart,-12),tbl_Monthly[month],"<="&EDATE(AsOfMonth,-12)) -> 260794382 | F28: =SUMIFS(tbl_Monthly[mwh],tbl_Monthly[class],$C28,tbl_Monthly[month],">="&FYStart,tbl_Monthly[month],"<="&AsOfMonth) -> 3177473.1 | G28: =SUMIFS(tbl_Monthly[revenue],tbl_Monthly[class],$C28,tbl_Monthly[month],">="&FYStart,tbl_Monthly[month],"<="&AsOfMonth) -> 299820792 | H28: {=SAFEDIV(E28,D28)} -> 92.059242 | I28: {=SAFEDIV(G28,F28)} -> 94.358247 | J28: =(F28-D28)*$H$30 -> 50771596 | K28: =(F28-D28)*(H28-$H$30) -> -19050214 | L28: =F28*(I28-H28) -> 7305027.5 | M28: =SUM(J28:L28) -> 39026410 | N28: =G28-E28 -> 39026410 | O28: =M28-N28 -> 0
B29: Transportation | C29: transportation | D29: =SUMIFS(tbl_Monthly[mwh],tbl_Monthly[class],$C29,tbl_Monthly[month],">="&EDATE(FYStart,-12),tbl_Monthly[month],"<="&EDATE(AsOfMonth,-12)) -> 5673.751 | E29: =SUMIFS(tbl_Monthly[revenue],tbl_Monthly[class],$C29,tbl_Monthly[month],">="&EDATE(FYStart,-12),tbl_Monthly[month],"<="&EDATE(AsOfMonth,-12)) -> 727932 | F29: =SUMIFS(tbl_Monthly[mwh],tbl_Monthly[class],$C29,tbl_Monthly[month],">="&FYStart,tbl_Monthly[month],"<="&AsOfMonth) -> 5240.776 | G29: =SUMIFS(tbl_Monthly[revenue],tbl_Monthly[class],$C29,tbl_Monthly[month],">="&FYStart,tbl_Monthly[month],"<="&AsOfMonth) -> 691495 | H29: {=SAFEDIV(E29,D29)} -> 128.29819 | I29: {=SAFEDIV(G29,F29)} -> 131.94515 | J29: =(F29-D29)*$H$30 -> -63796.805 | K29: =(F29-D29)*(H29-$H$30) -> 8246.8948 | L29: =F29*(I29-H29) -> 19112.91 | M29: =SUM(J29:L29) -> -36437 | N29: =G29-E29 -> -36437 | O29: =M29-N29 -> 0
B30: All classes | D30: =SUM(D26:D29) -> 9789014 | E30: =SUM(E26:E29) -> 1442364614 | F30: =SUM(F26:F29) -> 9960942.6 | G30: =SUM(G26:G29) -> 1469962155 | H30: {=SAFEDIV(E30,D30)} -> 147.34524 | I30: {=SAFEDIV(G30,F30)} -> 147.5726 | J30: =SUM(J26:J29) -> 25332849 | K30: =SUM(K26:K29) -> -23918177 | L30: =SUM(L26:L29) -> 26182869 | M30: =SUM(J30:L30) -> 27597541 | N30: =G30-E30 -> 27597541 | O30: =M30-N30 -> 0
B33: Bridge for the chart: long view
B34: =BaseYear&" retail revenue" -> 2019 retail revenue | C34: =E11 -> 1789303774
B35: Volume | C35: =J11 -> 2.7540322e+08
B36: Mix | C36: =K11 -> -88952656
B37: Price | C37: =L11 -> 9.9359228e+08
B38: =FercYear&" retail revenue" -> 2025 retail revenue | C38: =G11 -> 2969346620

Sheet Monthly
B1: Monthly retail sales: EIA-861M, and how it ties to the FERC filing
B2: ="PGE's monthly returns to EIA, "&TEXT(FitStart,"mmm yyyy")&" to "&TEXT(AsOfMonth,"mmm yyyy")&". EIA marks the latest months Preliminary and revises them." -> PGE's monthly returns to EIA, Jan 2017 to Jun 2026. EIA marks the latest months Preliminary and revises them.
B4: ="Year to date by class: "&TEXT(FYStart,"mmm")&"–"&TEXT(AsOfMonth,"mmm yyyy")&" against "&(FiscalYear-1) -> Year to date by class: Jan–Jun 2026 against 2025
B5: Class | C5: Key | D5: Revenue | E5: Prior year | F5: Change | G5: MWh | H5: Prior year | I5: Change | J5: ¢/kWh | K5: Prior year | L5: Change | M5: Customers, latest | N5: A year earlier | O5: Change | P5: MWh per customer | Q5: Prior year
B6: Residential | C6: residential | D6: =SUMIFS(tbl_Monthly[revenue],tbl_Monthly[class],$C6,tbl_Monthly[month],">="&FYStart,tbl_Monthly[month],"<="&AsOfMonth) -> 695144762 | E6: =SUMIFS(tbl_Monthly[revenue],tbl_Monthly[class],$C6,tbl_Monthly[month],">="&EDATE(FYStart,-12),tbl_Monthly[month],"<="&EDATE(AsOfMonth,-12)) -> 712293444 | F6: {=SAFEDIV(D6-E6,E6)} -> -0.024075305 | G6: =SUMIFS(tbl_Monthly[mwh],tbl_Monthly[class],$C6,tbl_Monthly[month],">="&FYStart,tbl_Monthly[month],"<="&AsOfMonth) -> 3677698.2 | H6: =SUMIFS(tbl_Monthly[mwh],tbl_Monthly[class],$C6,tbl_Monthly[month],">="&EDATE(FYStart,-12),tbl_Monthly[month],"<="&EDATE(AsOfMonth,-12)) -> 3797252.5 | I6: {=SAFEDIV(G6-H6,H6)} -> -0.031484414 | J6: {=CPK(D6,G6)} -> 18.901626 | K6: {=CPK(E6,H6)} -> 18.758127 | L6: {=SAFEDIV(J6-K6,K6)} -> 0.0076499634 | M6: =SUMIFS(tbl_Monthly[customers],tbl_Monthly[class],$C6,tbl_Monthly[month],AsOfMonth) -> 846477 | N6: =SUMIFS(tbl_Monthly[customers],tbl_Monthly[class],$C6,tbl_Monthly[month],EDATE(AsOfMonth,-12)) -> 840422 | O6: {=SAFEDIV(M6-N6,N6)} -> 0.0072047138 | P6: {=SAFEDIV(G6,M6)} -> 4.3447113 | Q6: {=SAFEDIV(H6,N6)} -> 4.5182688
B7: Commercial | C7: commercial | D7: =SUMIFS(tbl_Monthly[revenue],tbl_Monthly[class],$C7,tbl_Monthly[month],">="&FYStart,tbl_Monthly[month],"<="&AsOfMonth) -> 474305106 | E7: =SUMIFS(tbl_Monthly[revenue],tbl_Monthly[class],$C7,tbl_Monthly[month],">="&EDATE(FYStart,-12),tbl_Monthly[month],"<="&EDATE(AsOfMonth,-12)) -> 468548856 | F7: {=SAFEDIV(D7-E7,E7)} -> 0.012285272 | G7: =SUMIFS(tbl_Monthly[mwh],tbl_Monthly[class],$C7,tbl_Monthly[month],">="&FYStart,tbl_Monthly[month],"<="&AsOfMonth) -> 3100530.5 | H7: =SUMIFS(tbl_Monthly[mwh],tbl_Monthly[class],$C7,tbl_Monthly[month],">="&EDATE(FYStart,-12),tbl_Monthly[month],"<="&EDATE(AsOfMonth,-12)) -> 3153190.5 | I7: {=SAFEDIV(G7-H7,H7)} -> -0.01670054 | J7: {=CPK(D7,G7)} -> 15.297547 | K7: {=CPK(E7,H7)} -> 14.859516 | L7: {=SAFEDIV(J7-K7,K7)} -> 0.029478112 | M7: =SUMIFS(tbl_Monthly[customers],tbl_Monthly[class],$C7,tbl_Monthly[month],AsOfMonth) -> 110492 | N7: =SUMIFS(tbl_Monthly[customers],tbl_Monthly[class],$C7,tbl_Monthly[month],EDATE(AsOfMonth,-12)) -> 110061 | O7: {=SAFEDIV(M7-N7,N7)} -> 0.0039160102 | P7: {=SAFEDIV(G7,M7)} -> 28.061131 | Q7: {=SAFEDIV(H7,N7)} -> 28.64948
B8: Industrial | C8: industrial | D8: =SUMIFS(tbl_Monthly[revenue],tbl_Monthly[class],$C8,tbl_Monthly[month],">="&FYStart,tbl_Monthly[month],"<="&AsOfMonth) -> 299820792 | E8: =SUMIFS(tbl_Monthly[revenue],tbl_Monthly[class],$C8,tbl_Monthly[month],">="&EDATE(FYStart,-12),tbl_Monthly[month],"<="&EDATE(AsOfMonth,-12)) -> 260794382 | F8: {=SAFEDIV(D8-E8,E8)} -> 0.14964437 | G8: =SUMIFS(tbl_Monthly[mwh],tbl_Monthly[class],$C8,tbl_Monthly[month],">="&FYStart,tbl_Monthly[month],"<="&AsOfMonth) -> 3177473.1 | H8: =SUMIFS(tbl_Monthly[mwh],tbl_Monthly[class],$C8,tbl_Monthly[month],">="&EDATE(FYStart,-12),tbl_Monthly[month],"<="&EDATE(AsOfMonth,-12)) -> 2832897.3 | I8: {=SAFEDIV(G8-H8,H8)} -> 0.12163369 | J8: {=CPK(D8,G8)} -> 9.4358247 | K8: {=CPK(E8,H8)} -> 9.2059242 | L8: {=SAFEDIV(J8-K8,K8)} -> 0.024973107 | M8: =SUMIFS(tbl_Monthly[customers],tbl_Monthly[class],$C8,tbl_Monthly[month],AsOfMonth) -> 4318 | N8: =SUMIFS(tbl_Monthly[customers],tbl_Monthly[class],$C8,tbl_Monthly[month],EDATE(AsOfMonth,-12)) -> 4362 | O8: {=SAFEDIV(M8-N8,N8)} -> -0.010087116 | P8: {=SAFEDIV(G8,M8)} -> 735.86686 | Q8: {=SAFEDIV(H8,N8)} -> 649.44918
B9: Transportation | C9: transportation | D9: =SUMIFS(tbl_Monthly[revenue],tbl_Monthly[class],$C9,tbl_Monthly[month],">="&FYStart,tbl_Monthly[month],"<="&AsOfMonth) -> 691495 | E9: =SUMIFS(tbl_Monthly[revenue],tbl_Monthly[class],$C9,tbl_Monthly[month],">="&EDATE(FYStart,-12),tbl_Monthly[month],"<="&EDATE(AsOfMonth,-12)) -> 727932 | F9: {=SAFEDIV(D9-E9,E9)} -> -0.0500555 | G9: =SUMIFS(tbl_Monthly[mwh],tbl_Monthly[class],$C9,tbl_Monthly[month],">="&FYStart,tbl_Monthly[month],"<="&AsOfMonth) -> 5240.776 | H9: =SUMIFS(tbl_Monthly[mwh],tbl_Monthly[class],$C9,tbl_Monthly[month],">="&EDATE(FYStart,-12),tbl_Monthly[month],"<="&EDATE(AsOfMonth,-12)) -> 5673.751 | I9: {=SAFEDIV(G9-H9,H9)} -> -0.07631195 | J9: {=CPK(D9,G9)} -> 13.194515 | K9: {=CPK(E9,H9)} -> 12.829819 | L9: {=SAFEDIV(J9-K9,K9)} -> 0.028425668 | M9: =SUMIFS(tbl_Monthly[customers],tbl_Monthly[class],$C9,tbl_Monthly[month],AsOfMonth) -> 1 | N9: =SUMIFS(tbl_Monthly[customers],tbl_Monthly[class],$C9,tbl_Monthly[month],EDATE(AsOfMonth,-12)) -> 1 | O9: {=SAFEDIV(M9-N9,N9)} -> 0 | P9: {=SAFEDIV(G9,M9)} -> 5240.776 | Q9: {=SAFEDIV(H9,N9)} -> 5673.751
B10: All classes | D10: =SUM(D6:D9) -> 1469962155 | E10: =SUM(E6:E9) -> 1442364614 | F10: {=SAFEDIV(D10-E10,E10)} -> 0.01913354 | G10: =SUM(G6:G9) -> 9960942.6 | H10: =SUM(H6:H9) -> 9789014 | I10: {=SAFEDIV(G10-H10,H10)} -> 0.017563416 | J10: {=CPK(D10,G10)} -> 14.75726 | K10: {=CPK(E10,H10)} -> 14.734524 | L10: {=SAFEDIV(J10-K10,K10)} -> 0.0015430234 | M10: =SUM(M6:M9) -> 961288 | N10: =SUM(N6:N9) -> 954846 | O10: {=SAFEDIV(M10-N10,N10)} -> 0.0067466377 | P10: {=SAFEDIV(G10,M10)} -> 10.362079 | Q10: {=SAFEDIV(H10,N10)} -> 10.25193
B13: Retail revenue by month, all classes ($M)
B14: Year | C14: =TEXT(DATE(2000,COLUMN()-2,1),"mmm") -> Jan | D14: =TEXT(DATE(2000,COLUMN()-2,1),"mmm") -> Feb | E14: =TEXT(DATE(2000,COLUMN()-2,1),"mmm") -> Mar | F14: =TEXT(DATE(2000,COLUMN()-2,1),"mmm") -> Apr | G14: =TEXT(DATE(2000,COLUMN()-2,1),"mmm") -> May | H14: =TEXT(DATE(2000,COLUMN()-2,1),"mmm") -> Jun | I14: =TEXT(DATE(2000,COLUMN()-2,1),"mmm") -> Jul | J14: =TEXT(DATE(2000,COLUMN()-2,1),"mmm") -> Aug | ... N14: =TEXT(DATE(2000,COLUMN()-2,1),"mmm") -> Dec | O14: Year
B15: =YEAR(FitStart)+ROWS($B$15:B15)-1 -> 2017 | C15: =SUMIFS(tbl_Monthly[revenue],tbl_Monthly[month],DATE($B15,COLUMN()-2,1))/1000000 -> 178.42218 | D15: =SUMIFS(tbl_Monthly[revenue],tbl_Monthly[month],DATE($B15,COLUMN()-2,1))/1000000 -> 145.794 | E15: =SUMIFS(tbl_Monthly[revenue],tbl_Monthly[month],DATE($B15,COLUMN()-2,1))/1000000 -> 145.63287 | F15: =SUMIFS(tbl_Monthly[revenue],tbl_Monthly[month],DATE($B15,COLUMN()-2,1))/1000000 -> 130.33468 | G15: =SUMIFS(tbl_Monthly[revenue],tbl_Monthly[month],DATE($B15,COLUMN()-2,1))/1000000 -> 133.13686 | H15: =SUMIFS(tbl_Monthly[revenue],tbl_Monthly[month],DATE($B15,COLUMN()-2,1))/1000000 -> 128.56027 | I15: =SUMIFS(tbl_Monthly[revenue],tbl_Monthly[month],DATE($B15,COLUMN()-2,1))/1000000 -> 141.08893 | J15: =SUMIFS(tbl_Monthly[revenue],tbl_Monthly[month],DATE($B15,COLUMN()-2,1))/1000000 -> 158.94714 | ... N15: =SUMIFS(tbl_Monthly[revenue],tbl_Monthly[month],DATE($B15,COLUMN()-2,1))/1000000 -> 170.91504 | O15: =SUM(C15:N15) -> 1737.6067
B16: =YEAR(FitStart)+ROWS($B$15:B16)-1 -> 2018 | C16: =SUMIFS(tbl_Monthly[revenue],tbl_Monthly[month],DATE($B16,COLUMN()-2,1))/1000000 -> 152.23351 | D16: =SUMIFS(tbl_Monthly[revenue],tbl_Monthly[month],DATE($B16,COLUMN()-2,1))/1000000 -> 148.13551 | E16: =SUMIFS(tbl_Monthly[revenue],tbl_Monthly[month],DATE($B16,COLUMN()-2,1))/1000000 -> 144.76078 | F16: =SUMIFS(tbl_Monthly[revenue],tbl_Monthly[month],DATE($B16,COLUMN()-2,1))/1000000 -> 139.2836 | G16: =SUMIFS(tbl_Monthly[revenue],tbl_Monthly[month],DATE($B16,COLUMN()-2,1))/1000000 -> 129.63942 | H16: =SUMIFS(tbl_Monthly[revenue],tbl_Monthly[month],DATE($B16,COLUMN()-2,1))/1000000 -> 127.11055 | I16: =SUMIFS(tbl_Monthly[revenue],tbl_Monthly[month],DATE($B16,COLUMN()-2,1))/1000000 -> 151.67827 | J16: =SUMIFS(tbl_Monthly[revenue],tbl_Monthly[month],DATE($B16,COLUMN()-2,1))/1000000 -> 152.60959 | ... N16: =SUMIFS(tbl_Monthly[revenue],tbl_Monthly[month],DATE($B16,COLUMN()-2,1))/1000000 -> 164.75734 | O16: =SUM(C16:N16) -> 1717.5017
B17: =YEAR(FitStart)+ROWS($B$15:B17)-1 -> 2019 | C17: =SUMIFS(tbl_Monthly[revenue],tbl_Monthly[month],DATE($B17,COLUMN()-2,1))/1000000 -> 157.83686 | D17: =SUMIFS(tbl_Monthly[revenue],tbl_Monthly[month],DATE($B17,COLUMN()-2,1))/1000000 -> 162.68925 | E17: =SUMIFS(tbl_Monthly[revenue],tbl_Monthly[month],DATE($B17,COLUMN()-2,1))/1000000 -> 148.83769 | F17: =SUMIFS(tbl_Monthly[revenue],tbl_Monthly[month],DATE($B17,COLUMN()-2,1))/1000000 -> 134.15942 | G17: =SUMIFS(tbl_Monthly[revenue],tbl_Monthly[month],DATE($B17,COLUMN()-2,1))/1000000 -> 132.22681 | H17: =SUMIFS(tbl_Monthly[revenue],tbl_Monthly[month],DATE($B17,COLUMN()-2,1))/1000000 -> 131.874 | I17: =SUMIFS(tbl_Monthly[revenue],tbl_Monthly[month],DATE($B17,COLUMN()-2,1))/1000000 -> 142.4941 | J17: =SUMIFS(tbl_Monthly[revenue],tbl_Monthly[month],DATE($B17,COLUMN()-2,1))/1000000 -> 149.20084 | ... N17: =SUMIFS(tbl_Monthly[revenue],tbl_Monthly[month],DATE($B17,COLUMN()-2,1))/1000000 -> 165.51654 | O17: =SUM(C17:N17) -> 1745.7516
B18: =YEAR(FitStart)+ROWS($B$15:B18)-1 -> 2020 | C18: =SUMIFS(tbl_Monthly[revenue],tbl_Monthly[month],DATE($B18,COLUMN()-2,1))/1000000 -> 161.60308 | D18: =SUMIFS(tbl_Monthly[revenue],tbl_Monthly[month],DATE($B18,COLUMN()-2,1))/1000000 -> 155.07724 | E18: =SUMIFS(tbl_Monthly[revenue],tbl_Monthly[month],DATE($B18,COLUMN()-2,1))/1000000 -> 155.85651 | F18: =SUMIFS(tbl_Monthly[revenue],tbl_Monthly[month],DATE($B18,COLUMN()-2,1))/1000000 -> 132.59429 | G18: =SUMIFS(tbl_Monthly[revenue],tbl_Monthly[month],DATE($B18,COLUMN()-2,1))/1000000 -> 138.23522 | H18: =SUMIFS(tbl_Monthly[revenue],tbl_Monthly[month],DATE($B18,COLUMN()-2,1))/1000000 -> 131.37244 | I18: =SUMIFS(tbl_Monthly[revenue],tbl_Monthly[month],DATE($B18,COLUMN()-2,1))/1000000 -> 154.09748 | J18: =SUMIFS(tbl_Monthly[revenue],tbl_Monthly[month],DATE($B18,COLUMN()-2,1))/1000000 -> 159.56197 | ... N18: =SUMIFS(tbl_Monthly[revenue],tbl_Monthly[month],DATE($B18,COLUMN()-2,1))/1000000 -> 173.58307 | O18: =SUM(C18:N18) -> 1800.1133
B19: =YEAR(FitStart)+ROWS($B$15:B19)-1 -> 2021 | C19: =SUMIFS(tbl_Monthly[revenue],tbl_Monthly[month],DATE($B19,COLUMN()-2,1))/1000000 -> 176.2144 | D19: =SUMIFS(tbl_Monthly[revenue],tbl_Monthly[month],DATE($B19,COLUMN()-2,1))/1000000 -> 165.30814 | E19: =SUMIFS(tbl_Monthly[revenue],tbl_Monthly[month],DATE($B19,COLUMN()-2,1))/1000000 -> 172.69677 | F19: =SUMIFS(tbl_Monthly[revenue],tbl_Monthly[month],DATE($B19,COLUMN()-2,1))/1000000 -> 148.39559 | G19: =SUMIFS(tbl_Monthly[revenue],tbl_Monthly[month],DATE($B19,COLUMN()-2,1))/1000000 -> 151.3187 | H19: =SUMIFS(tbl_Monthly[revenue],tbl_Monthly[month],DATE($B19,COLUMN()-2,1))/1000000 -> 166.44079 | I19: =SUMIFS(tbl_Monthly[revenue],tbl_Monthly[month],DATE($B19,COLUMN()-2,1))/1000000 -> 175.86591 | J19: =SUMIFS(tbl_Monthly[revenue],tbl_Monthly[month],DATE($B19,COLUMN()-2,1))/1000000 -> 175.41912 | ... N19: =SUMIFS(tbl_Monthly[revenue],tbl_Monthly[month],DATE($B19,COLUMN()-2,1))/1000000 -> 202.72782 | O19: =SUM(C19:N19) -> 1992.166
B20: =YEAR(FitStart)+ROWS($B$15:B20)-1 -> 2022 | C20: =SUMIFS(tbl_Monthly[revenue],tbl_Monthly[month],DATE($B20,COLUMN()-2,1))/1000000 -> 193.18141 | D20: =SUMIFS(tbl_Monthly[revenue],tbl_Monthly[month],DATE($B20,COLUMN()-2,1))/1000000 -> 169.31434 | E20: =SUMIFS(tbl_Monthly[revenue],tbl_Monthly[month],DATE($B20,COLUMN()-2,1))/1000000 -> 175.66606 | F20: =SUMIFS(tbl_Monthly[revenue],tbl_Monthly[month],DATE($B20,COLUMN()-2,1))/1000000 -> 165.60545 | G20: =SUMIFS(tbl_Monthly[revenue],tbl_Monthly[month],DATE($B20,COLUMN()-2,1))/1000000 -> 160.30869 | H20: =SUMIFS(tbl_Monthly[revenue],tbl_Monthly[month],DATE($B20,COLUMN()-2,1))/1000000 -> 153.24457 | I20: =SUMIFS(tbl_Monthly[revenue],tbl_Monthly[month],DATE($B20,COLUMN()-2,1))/1000000 -> 186.06807 | J20: =SUMIFS(tbl_Monthly[revenue],tbl_Monthly[month],DATE($B20,COLUMN()-2,1))/1000000 -> 192.57307 | ... N20: =SUMIFS(tbl_Monthly[revenue],tbl_Monthly[month],DATE($B20,COLUMN()-2,1))/1000000 -> 209.16121 | O20: =SUM(C20:N20) -> 2110.9841
B21: =YEAR(FitStart)+ROWS($B$15:B21)-1 -> 2023 | C21: =SUMIFS(tbl_Monthly[revenue],tbl_Monthly[month],DATE($B21,COLUMN()-2,1))/1000000 -> 211.43024 | D21: =SUMIFS(tbl_Monthly[revenue],tbl_Monthly[month],DATE($B21,COLUMN()-2,1))/1000000 -> 202.89346 | E21: =SUMIFS(tbl_Monthly[revenue],tbl_Monthly[month],DATE($B21,COLUMN()-2,1))/1000000 -> 209.38596 | F21: =SUMIFS(tbl_Monthly[revenue],tbl_Monthly[month],DATE($B21,COLUMN()-2,1))/1000000 -> 191.70715 | G21: =SUMIFS(tbl_Monthly[revenue],tbl_Monthly[month],DATE($B21,COLUMN()-2,1))/1000000 -> 180.91381 | H21: =SUMIFS(tbl_Monthly[revenue],tbl_Monthly[month],DATE($B21,COLUMN()-2,1))/1000000 -> 176.73344 | I21: =SUMIFS(tbl_Monthly[revenue],tbl_Monthly[month],DATE($B21,COLUMN()-2,1))/1000000 -> 204.96873 | J21: =SUMIFS(tbl_Monthly[revenue],tbl_Monthly[month],DATE($B21,COLUMN()-2,1))/1000000 -> 211.01881 | ... N21: =SUMIFS(tbl_Monthly[revenue],tbl_Monthly[month],DATE($B21,COLUMN()-2,1))/1000000 -> 212.02617 | O21: =SUM(C21:N21) -> 2353.8297
B22: =YEAR(FitStart)+ROWS($B$15:B22)-1 -> 2024 | C22: =SUMIFS(tbl_Monthly[revenue],tbl_Monthly[month],DATE($B22,COLUMN()-2,1))/1000000 -> 264.74354 | D22: =SUMIFS(tbl_Monthly[revenue],tbl_Monthly[month],DATE($B22,COLUMN()-2,1))/1000000 -> 230.98386 | E22: =SUMIFS(tbl_Monthly[revenue],tbl_Monthly[month],DATE($B22,COLUMN()-2,1))/1000000 -> 232.4794 | F22: =SUMIFS(tbl_Monthly[revenue],tbl_Monthly[month],DATE($B22,COLUMN()-2,1))/1000000 -> 205.41081 | G22: =SUMIFS(tbl_Monthly[revenue],tbl_Monthly[month],DATE($B22,COLUMN()-2,1))/1000000 -> 208.81291 | H22: =SUMIFS(tbl_Monthly[revenue],tbl_Monthly[month],DATE($B22,COLUMN()-2,1))/1000000 -> 204.83244 | I22: =SUMIFS(tbl_Monthly[revenue],tbl_Monthly[month],DATE($B22,COLUMN()-2,1))/1000000 -> 251.60974 | J22: =SUMIFS(tbl_Monthly[revenue],tbl_Monthly[month],DATE($B22,COLUMN()-2,1))/1000000 -> 235.6834 | ... N22: =SUMIFS(tbl_Monthly[revenue],tbl_Monthly[month],DATE($B22,COLUMN()-2,1))/1000000 -> 257.81973 | O22: =SUM(C22:N22) -> 2751.0819
B23: =YEAR(FitStart)+ROWS($B$15:B23)-1 -> 2025 | C23: =SUMIFS(tbl_Monthly[revenue],tbl_Monthly[month],DATE($B23,COLUMN()-2,1))/1000000 -> 280.46172 | D23: =SUMIFS(tbl_Monthly[revenue],tbl_Monthly[month],DATE($B23,COLUMN()-2,1))/1000000 -> 252.2883 | E23: =SUMIFS(tbl_Monthly[revenue],tbl_Monthly[month],DATE($B23,COLUMN()-2,1))/1000000 -> 247.6024 | F23: =SUMIFS(tbl_Monthly[revenue],tbl_Monthly[month],DATE($B23,COLUMN()-2,1))/1000000 -> 217.63784 | G23: =SUMIFS(tbl_Monthly[revenue],tbl_Monthly[month],DATE($B23,COLUMN()-2,1))/1000000 -> 216.29053 | H23: =SUMIFS(tbl_Monthly[revenue],tbl_Monthly[month],DATE($B23,COLUMN()-2,1))/1000000 -> 228.08383 | I23: =SUMIFS(tbl_Monthly[revenue],tbl_Monthly[month],DATE($B23,COLUMN()-2,1))/1000000 -> 260.23353 | J23: =SUMIFS(tbl_Monthly[revenue],tbl_Monthly[month],DATE($B23,COLUMN()-2,1))/1000000 -> 268.27438 | ... N23: =SUMIFS(tbl_Monthly[revenue],tbl_Monthly[month],DATE($B23,COLUMN()-2,1))/1000000 -> 264.09058 | O23: =SUM(C23:N23) -> 2928.1799
B24: =YEAR(FitStart)+ROWS($B$15:B24)-1 -> 2026 | C24: =SUMIFS(tbl_Monthly[revenue],tbl_Monthly[month],DATE($B24,COLUMN()-2,1))/1000000 -> 271.49543 | D24: =SUMIFS(tbl_Monthly[revenue],tbl_Monthly[month],DATE($B24,COLUMN()-2,1))/1000000 -> 236.44692 | E24: =SUMIFS(tbl_Monthly[revenue],tbl_Monthly[month],DATE($B24,COLUMN()-2,1))/1000000 -> 241.51683 | F24: =SUMIFS(tbl_Monthly[revenue],tbl_Monthly[month],DATE($B24,COLUMN()-2,1))/1000000 -> 233.58515 | G24: =SUMIFS(tbl_Monthly[revenue],tbl_Monthly[month],DATE($B24,COLUMN()-2,1))/1000000 -> 239.27115 | H24: =SUMIFS(tbl_Monthly[revenue],tbl_Monthly[month],DATE($B24,COLUMN()-2,1))/1000000 -> 247.64668 | I24: =SUMIFS(tbl_Monthly[revenue],tbl_Monthly[month],DATE($B24,COLUMN()-2,1))/1000000 -> 0 | J24: =SUMIFS(tbl_Monthly[revenue],tbl_Monthly[month],DATE($B24,COLUMN()-2,1))/1000000 -> 0 | ... N24: =SUMIFS(tbl_Monthly[revenue],tbl_Monthly[month],DATE($B24,COLUMN()-2,1))/1000000 -> 0 | O24: =SUM(C24:N24) -> 1469.9622
B27: Two regulators, one utility: EIA's monthly survey summed to a year, against the FERC filing
B28: Year | C28: EIA MWh | D28: FERC MWh | E28: Difference | F28: EIA revenue | G28: FERC retail revenue | H28: Gap | I28: Gap %
B29: =YEAR(FitStart) -> 2017 | C29: =SUMIFS(tbl_Monthly[mwh],tbl_Monthly[month],">="&DATE($B29,1,1),tbl_Monthly[month],"<="&DATE($B29,12,1)) -> 17754280 | D29: =SUMIFS(tbl_FERC_Revenue[sales_mwh],tbl_FERC_Revenue[utility_id_ferc1],CompanyId,tbl_FERC_Revenue[report_year],$B29,tbl_FERC_Revenue[revenue_type],"sales_to_ultimate_consumers") -> 17754280 | E29: =C29-D29 -> -0.039999999 | F29: =SUMIFS(tbl_Monthly[revenue],tbl_Monthly[month],">="&DATE($B29,1,1),tbl_Monthly[month],"<="&DATE($B29,12,1)) -> 1737606737 | G29: =SUMIFS(tbl_FERC_Revenue[dollar_value],tbl_FERC_Revenue[utility_id_ferc1],CompanyId,tbl_FERC_Revenue[report_year],$B29,tbl_FERC_Revenue[revenue_type],"sales_to_ultimate_consumers") -> 1774195410 | H29: =F29-G29 -> -36588673 | I29: {=SAFEDIV(H29,G29)} -> -0.020622685
B30: =B29+1 -> 2018 | C30: =SUMIFS(tbl_Monthly[mwh],tbl_Monthly[month],">="&DATE($B30,1,1),tbl_Monthly[month],"<="&DATE($B30,12,1)) -> 17197022 | D30: =SUMIFS(tbl_FERC_Revenue[sales_mwh],tbl_FERC_Revenue[utility_id_ferc1],CompanyId,tbl_FERC_Revenue[report_year],$B30,tbl_FERC_Revenue[revenue_type],"sales_to_ultimate_consumers") -> 17186002 | E30: =C30-D30 -> 11019.535 | F30: =SUMIFS(tbl_Monthly[revenue],tbl_Monthly[month],">="&DATE($B30,1,1),tbl_Monthly[month],"<="&DATE($B30,12,1)) -> 1717501735 | G30: =SUMIFS(tbl_FERC_Revenue[dollar_value],tbl_FERC_Revenue[utility_id_ferc1],CompanyId,tbl_FERC_Revenue[report_year],$B30,tbl_FERC_Revenue[revenue_type],"sales_to_ultimate_consumers") -> 1760150960 | H30: =F30-G30 -> -42649225 | I30: {=SAFEDIV(H30,G30)} -> -0.024230436
B31: =B30+1 -> 2019 | C31: =SUMIFS(tbl_Monthly[mwh],tbl_Monthly[month],">="&DATE($B31,1,1),tbl_Monthly[month],"<="&DATE($B31,12,1)) -> 17304690 | D31: =SUMIFS(tbl_FERC_Revenue[sales_mwh],tbl_FERC_Revenue[utility_id_ferc1],CompanyId,tbl_FERC_Revenue[report_year],$B31,tbl_FERC_Revenue[revenue_type],"sales_to_ultimate_consumers") -> 17304691 | E31: =C31-D31 -> -0.885 | F31: =SUMIFS(tbl_Monthly[revenue],tbl_Monthly[month],">="&DATE($B31,1,1),tbl_Monthly[month],"<="&DATE($B31,12,1)) -> 1745751557 | G31: =SUMIFS(tbl_FERC_Revenue[dollar_value],tbl_FERC_Revenue[utility_id_ferc1],CompanyId,tbl_FERC_Revenue[report_year],$B31,tbl_FERC_Revenue[revenue_type],"sales_to_ultimate_consumers") -> 1789303774 | H31: =F31-G31 -> -43552217 | I31: {=SAFEDIV(H31,G31)} -> -0.024340315
B32: =B31+1 -> 2020 | C32: =SUMIFS(tbl_Monthly[mwh],tbl_Monthly[month],">="&DATE($B32,1,1),tbl_Monthly[month],"<="&DATE($B32,12,1)) -> 17423803 | D32: =SUMIFS(tbl_FERC_Revenue[sales_mwh],tbl_FERC_Revenue[utility_id_ferc1],CompanyId,tbl_FERC_Revenue[report_year],$B32,tbl_FERC_Revenue[revenue_type],"sales_to_ultimate_consumers") -> 17423803 | E32: =C32-D32 -> -0.22299999 | F32: =SUMIFS(tbl_Monthly[revenue],tbl_Monthly[month],">="&DATE($B32,1,1),tbl_Monthly[month],"<="&DATE($B32,12,1)) -> 1800113311 | G32: =SUMIFS(tbl_FERC_Revenue[dollar_value],tbl_FERC_Revenue[utility_id_ferc1],CompanyId,tbl_FERC_Revenue[report_year],$B32,tbl_FERC_Revenue[revenue_type],"sales_to_ultimate_consumers") -> 1846082453 | H32: =F32-G32 -> -45969142 | I32: {=SAFEDIV(H32,G32)} -> -0.024900915
B33: =B32+1 -> 2021 | C33: =SUMIFS(tbl_Monthly[mwh],tbl_Monthly[month],">="&DATE($B33,1,1),tbl_Monthly[month],"<="&DATE($B33,12,1)) -> 18296055 | D33: =SUMIFS(tbl_FERC_Revenue[sales_mwh],tbl_FERC_Revenue[utility_id_ferc1],CompanyId,tbl_FERC_Revenue[report_year],$B33,tbl_FERC_Revenue[revenue_type],"sales_to_ultimate_consumers") -> 18296054 | E33: =C33-D33 -> 0.53300001 | F33: =SUMIFS(tbl_Monthly[revenue],tbl_Monthly[month],">="&DATE($B33,1,1),tbl_Monthly[month],"<="&DATE($B33,12,1)) -> 1992166000 | G33: =SUMIFS(tbl_FERC_Revenue[dollar_value],tbl_FERC_Revenue[utility_id_ferc1],CompanyId,tbl_FERC_Revenue[report_year],$B33,tbl_FERC_Revenue[revenue_type],"sales_to_ultimate_consumers") -> 2039484924 | H33: =F33-G33 -> -47318924 | I33: {=SAFEDIV(H33,G33)} -> -0.023201409
B34: =B33+1 -> 2022 | C34: =SUMIFS(tbl_Monthly[mwh],tbl_Monthly[month],">="&DATE($B34,1,1),tbl_Monthly[month],"<="&DATE($B34,12,1)) -> 18905062 | D34: =SUMIFS(tbl_FERC_Revenue[sales_mwh],tbl_FERC_Revenue[utility_id_ferc1],CompanyId,tbl_FERC_Revenue[report_year],$B34,tbl_FERC_Revenue[revenue_type],"sales_to_ultimate_consumers") -> 18905061 | E34: =C34-D34 -> 0.51399999 | F34: =SUMIFS(tbl_Monthly[revenue],tbl_Monthly[month],">="&DATE($B34,1,1),tbl_Monthly[month],"<="&DATE($B34,12,1)) -> 2110984054 | G34: =SUMIFS(tbl_FERC_Revenue[dollar_value],tbl_FERC_Revenue[utility_id_ferc1],CompanyId,tbl_FERC_Revenue[report_year],$B34,tbl_FERC_Revenue[revenue_type],"sales_to_ultimate_consumers") -> 2145143572 | H34: =F34-G34 -> -34159518 | I34: {=SAFEDIV(H34,G34)} -> -0.015924117
B35: =B34+1 -> 2023 | C35: =SUMIFS(tbl_Monthly[mwh],tbl_Monthly[month],">="&DATE($B35,1,1),tbl_Monthly[month],"<="&DATE($B35,12,1)) -> 19131729 | D35: =SUMIFS(tbl_FERC_Revenue[sales_mwh],tbl_FERC_Revenue[utility_id_ferc1],CompanyId,tbl_FERC_Revenue[report_year],$B35,tbl_FERC_Revenue[revenue_type],"sales_to_ultimate_consumers") -> 19131728 | E35: =C35-D35 -> 0.501 | F35: =SUMIFS(tbl_Monthly[revenue],tbl_Monthly[month],">="&DATE($B35,1,1),tbl_Monthly[month],"<="&DATE($B35,12,1)) -> 2353829725 | G35: =SUMIFS(tbl_FERC_Revenue[dollar_value],tbl_FERC_Revenue[utility_id_ferc1],CompanyId,tbl_FERC_Revenue[report_year],$B35,tbl_FERC_Revenue[revenue_type],"sales_to_ultimate_consumers") -> 2379994297 | H35: =F35-G35 -> -26164572 | I35: {=SAFEDIV(H35,G35)} -> -0.010993544
B36: =B35+1 -> 2024 | C36: =SUMIFS(tbl_Monthly[mwh],tbl_Monthly[month],">="&DATE($B36,1,1),tbl_Monthly[month],"<="&DATE($B36,12,1)) -> 19272621 | D36: =SUMIFS(tbl_FERC_Revenue[sales_mwh],tbl_FERC_Revenue[utility_id_ferc1],CompanyId,tbl_FERC_Revenue[report_year],$B36,tbl_FERC_Revenue[revenue_type],"sales_to_ultimate_consumers") -> 19272622 | E36: =C36-D36 -> -0.555 | F36: =SUMIFS(tbl_Monthly[revenue],tbl_Monthly[month],">="&DATE($B36,1,1),tbl_Monthly[month],"<="&DATE($B36,12,1)) -> 2751081902 | G36: =SUMIFS(tbl_FERC_Revenue[dollar_value],tbl_FERC_Revenue[utility_id_ferc1],CompanyId,tbl_FERC_Revenue[report_year],$B36,tbl_FERC_Revenue[revenue_type],"sales_to_ultimate_consumers") -> 2783029228 | H36: =F36-G36 -> -31947326 | I36: {=SAFEDIV(H36,G36)} -> -0.011479335
B37: =B36+1 -> 2025 | C37: =SUMIFS(tbl_Monthly[mwh],tbl_Monthly[month],">="&DATE($B37,1,1),tbl_Monthly[month],"<="&DATE($B37,12,1)) -> 19968295 | D37: =SUMIFS(tbl_FERC_Revenue[sales_mwh],tbl_FERC_Revenue[utility_id_ferc1],CompanyId,tbl_FERC_Revenue[report_year],$B37,tbl_FERC_Revenue[revenue_type],"sales_to_ultimate_consumers") -> 19968167 | E37: =C37-D37 -> 128.413 | F37: =SUMIFS(tbl_Monthly[revenue],tbl_Monthly[month],">="&DATE($B37,1,1),tbl_Monthly[month],"<="&DATE($B37,12,1)) -> 2928179950 | G37: =SUMIFS(tbl_FERC_Revenue[dollar_value],tbl_FERC_Revenue[utility_id_ferc1],CompanyId,tbl_FERC_Revenue[report_year],$B37,tbl_FERC_Revenue[revenue_type],"sales_to_ultimate_consumers") -> 2969346620 | H37: =F37-G37 -> -41166670 | I37: {=SAFEDIV(H37,G37)} -> -0.013863882
B38: Volumes agree to within a few MWh a year. EIA's revenue runs 1–2.5% under FERC's: the monthly survey reports billed sales, the annual filing books accounting revenue (unbilled accruals, deferral amortization and other adjustments).

Sheet Weather
B1: Weather: how much of the load is the thermostat
B2: Monthly MWh per customer regressed with LINEST on heating and cooling degree days (Willamette Valley, base 65°F) and a time trend, fitted from the fit start to the December before the fiscal year.
B4: ="Weather model, fitted "&TEXT(FitStart,"mmm yyyy")&" to Dec "&(FiscalYear-1) -> Weather model, fitted Jan 2017 to Dec 2025
B5: Class | C5: Intercept | D5: Per HDD | E5: Per CDD | F5: Trend per year | G5: R² | H5: Months | I5: Key
B6: Residential | C6: {=_xlfn.LET(_xlpm.s,LINEST(_xlfn._xlws.FILTER(F$62:F$181,$J$62:$J$181),_xlfn.HSTACK(_xlfn._xlws.FILTER(D$62:D$181,$J$62:$J$181),_xlfn._xlws.FILTER(E$62:E$181,$J$62:$J$181),_xlfn._xlws.FILTER(C$62:C$181,$J$62:$J$181)),TRUE,TRUE),_xlfn.HSTACK(INDEX(_xlpm.s,1,4),INDEX(_xlpm.s,1,3),INDEX(_xlpm.s,1,2),INDEX(_xlpm.s,1,1),INDEX(_xlpm.s,3,1)))} -> 0.49596644 | D6: 0.00067761678 | E6: 0.0026779198 | F6: -0.0075184518 | G6: 0.83811812 | H6: =ROWS(_xlfn._xlws.FILTER(F$62:F$181,$J$62:$J$181)) -> 108 | I6: residential
B7: Commercial | C7: {=_xlfn.LET(_xlpm.s,LINEST(_xlfn._xlws.FILTER(G$62:G$181,$J$62:$J$181),_xlfn.HSTACK(_xlfn._xlws.FILTER(D$62:D$181,$J$62:$J$181),_xlfn._xlws.FILTER(E$62:E$181,$J$62:$J$181),_xlfn._xlws.FILTER(C$62:C$181,$J$62:$J$181)),TRUE,TRUE),_xlfn.HSTACK(INDEX(_xlpm.s,1,4),INDEX(_xlpm.s,1,3),INDEX(_xlpm.s,1,2),INDEX(_xlpm.s,1,1),INDEX(_xlpm.s,3,1)))} -> 4.9058294 | D7: 0.00062824613 | E7: 0.0073712067 | F7: -0.065020003 | G7: 0.58282378 | H7: =ROWS(_xlfn._xlws.FILTER(G$62:G$181,$J$62:$J$181)) -> 108 | I7: commercial
B8: MWh per customer per month: per degree day, and per year of trend. LINEST returns the coefficients last variable first; the formula puts them back in reading order.
B10: ="Normal weather: the average of "&(FiscalYear-NormalYears)&"–"&(FiscalYear-1)&", by month" -> Normal weather: the average of 2016–2025, by month
B11: Month | C11: =TEXT(DATE(2000,COLUMN()-2,1),"mmm") -> Jan | D11: =TEXT(DATE(2000,COLUMN()-2,1),"mmm") -> Feb | E11: =TEXT(DATE(2000,COLUMN()-2,1),"mmm") -> Mar | F11: =TEXT(DATE(2000,COLUMN()-2,1),"mmm") -> Apr | G11: =TEXT(DATE(2000,COLUMN()-2,1),"mmm") -> May | H11: =TEXT(DATE(2000,COLUMN()-2,1),"mmm") -> Jun | I11: =TEXT(DATE(2000,COLUMN()-2,1),"mmm") -> Jul | J11: =TEXT(DATE(2000,COLUMN()-2,1),"mmm") -> Aug | ... N11: =TEXT(DATE(2000,COLUMN()-2,1),"mmm") -> Dec | O11: Year
B12: Normal HDD | C12: {=AVERAGE(_xlfn._xlws.FILTER(tbl_Weather[hdd],(YEAR(tbl_Weather[month])>=FiscalYear-NormalYears)*(YEAR(tbl_Weather[month])<FiscalYear)*(MONTH(tbl_Weather[month])=COLUMN()-2)))} -> 748 | D12: {=AVERAGE(_xlfn._xlws.FILTER(tbl_Weather[hdd],(YEAR(tbl_Weather[month])>=FiscalYear-NormalYears)*(YEAR(tbl_Weather[month])<FiscalYear)*(MONTH(tbl_Weather[month])=COLUMN()-2)))} -> 679.3 | E12: {=AVERAGE(_xlfn._xlws.FILTER(tbl_Weather[hdd],(YEAR(tbl_Weather[month])>=FiscalYear-NormalYears)*(YEAR(tbl_Weather[month])<FiscalYear)*(MONTH(tbl_Weather[month])=COLUMN()-2)))} -> 640.8 | F12: {=AVERAGE(_xlfn._xlws.FILTER(tbl_Weather[hdd],(YEAR(tbl_Weather[month])>=FiscalYear-NormalYears)*(YEAR(tbl_Weather[month])<FiscalYear)*(MONTH(tbl_Weather[month])=COLUMN()-2)))} -> 467.4 | G12: {=AVERAGE(_xlfn._xlws.FILTER(tbl_Weather[hdd],(YEAR(tbl_Weather[month])>=FiscalYear-NormalYears)*(YEAR(tbl_Weather[month])<FiscalYear)*(MONTH(tbl_Weather[month])=COLUMN()-2)))} -> 287.4 | H12: {=AVERAGE(_xlfn._xlws.FILTER(tbl_Weather[hdd],(YEAR(tbl_Weather[month])>=FiscalYear-NormalYears)*(YEAR(tbl_Weather[month])<FiscalYear)*(MONTH(tbl_Weather[month])=COLUMN()-2)))} -> 129.5 | I12: {=AVERAGE(_xlfn._xlws.FILTER(tbl_Weather[hdd],(YEAR(tbl_Weather[month])>=FiscalYear-NormalYears)*(YEAR(tbl_Weather[month])<FiscalYear)*(MONTH(tbl_Weather[month])=COLUMN()-2)))} -> 32.6 | J12: {=AVERAGE(_xlfn._xlws.FILTER(tbl_Weather[hdd],(YEAR(tbl_Weather[month])>=FiscalYear-NormalYears)*(YEAR(tbl_Weather[month])<FiscalYear)*(MONTH(tbl_Weather[month])=COLUMN()-2)))} -> 22.4 | ... N12: {=AVERAGE(_xlfn._xlws.FILTER(tbl_Weather[hdd],(YEAR(tbl_Weather[month])>=FiscalYear-NormalYears)*(YEAR(tbl_Weather[month])<FiscalYear)*(MONTH(tbl_Weather[month])=COLUMN()-2)))} -> 753.3 | O12: =SUM(C12:N12) -> 4848
B13: Normal CDD | C13: {=AVERAGE(_xlfn._xlws.FILTER(tbl_Weather[cdd],(YEAR(tbl_Weather[month])>=FiscalYear-NormalYears)*(YEAR(tbl_Weather[month])<FiscalYear)*(MONTH(tbl_Weather[month])=COLUMN()-2)))} -> 0 | D13: {=AVERAGE(_xlfn._xlws.FILTER(tbl_Weather[cdd],(YEAR(tbl_Weather[month])>=FiscalYear-NormalYears)*(YEAR(tbl_Weather[month])<FiscalYear)*(MONTH(tbl_Weather[month])=COLUMN()-2)))} -> 0 | E13: {=AVERAGE(_xlfn._xlws.FILTER(tbl_Weather[cdd],(YEAR(tbl_Weather[month])>=FiscalYear-NormalYears)*(YEAR(tbl_Weather[month])<FiscalYear)*(MONTH(tbl_Weather[month])=COLUMN()-2)))} -> 0 | F13: {=AVERAGE(_xlfn._xlws.FILTER(tbl_Weather[cdd],(YEAR(tbl_Weather[month])>=FiscalYear-NormalYears)*(YEAR(tbl_Weather[month])<FiscalYear)*(MONTH(tbl_Weather[month])=COLUMN()-2)))} -> 0 | G13: {=AVERAGE(_xlfn._xlws.FILTER(tbl_Weather[cdd],(YEAR(tbl_Weather[month])>=FiscalYear-NormalYears)*(YEAR(tbl_Weather[month])<FiscalYear)*(MONTH(tbl_Weather[month])=COLUMN()-2)))} -> 4.1 | H13: {=AVERAGE(_xlfn._xlws.FILTER(tbl_Weather[cdd],(YEAR(tbl_Weather[month])>=FiscalYear-NormalYears)*(YEAR(tbl_Weather[month])<FiscalYear)*(MONTH(tbl_Weather[month])=COLUMN()-2)))} -> 23.3 | I13: {=AVERAGE(_xlfn._xlws.FILTER(tbl_Weather[cdd],(YEAR(tbl_Weather[month])>=FiscalYear-NormalYears)*(YEAR(tbl_Weather[month])<FiscalYear)*(MONTH(tbl_Weather[month])=COLUMN()-2)))} -> 114.6 | J13: {=AVERAGE(_xlfn._xlws.FILTER(tbl_Weather[cdd],(YEAR(tbl_Weather[month])>=FiscalYear-NormalYears)*(YEAR(tbl_Weather[month])<FiscalYear)*(MONTH(tbl_Weather[month])=COLUMN()-2)))} -> 130.8 | ... N13: {=AVERAGE(_xlfn._xlws.FILTER(tbl_Weather[cdd],(YEAR(tbl_Weather[month])>=FiscalYear-NormalYears)*(YEAR(tbl_Weather[month])<FiscalYear)*(MONTH(tbl_Weather[month])=COLUMN()-2)))} -> 0 | O13: =SUM(C13:N13) -> 308.6
B14: ="Actual HDD, "&FiscalYear -> Actual HDD, 2026 | C14: =_xlfn.XLOOKUP(DATE(FiscalYear,COLUMN()-2,1),tbl_Weather[month],tbl_Weather[hdd],"") -> 701 | D14: =_xlfn.XLOOKUP(DATE(FiscalYear,COLUMN()-2,1),tbl_Weather[month],tbl_Weather[hdd],"") -> 599 | E14: =_xlfn.XLOOKUP(DATE(FiscalYear,COLUMN()-2,1),tbl_Weather[month],tbl_Weather[hdd],"") -> 524 | F14: =_xlfn.XLOOKUP(DATE(FiscalYear,COLUMN()-2,1),tbl_Weather[month],tbl_Weather[hdd],"") -> 408 | G14: =_xlfn.XLOOKUP(DATE(FiscalYear,COLUMN()-2,1),tbl_Weather[month],tbl_Weather[hdd],"") -> 241 | H14: =_xlfn.XLOOKUP(DATE(FiscalYear,COLUMN()-2,1),tbl_Weather[month],tbl_Weather[hdd],"") -> 109 | I14: =_xlfn.XLOOKUP(DATE(FiscalYear,COLUMN()-2,1),tbl_Weather[month],tbl_Weather[hdd],"") -> 41 | J14: =_xlfn.XLOOKUP(DATE(FiscalYear,COLUMN()-2,1),tbl_Weather[month],tbl_Weather[hdd],"") -> 27 | ... N14: =_xlfn.XLOOKUP(DATE(FiscalYear,COLUMN()-2,1),tbl_Weather[month],tbl_Weather[hdd],"") | O14: =SUM(C14:N14) -> 2650
B15: ="Actual CDD, "&FiscalYear -> Actual CDD, 2026 | C15: =_xlfn.XLOOKUP(DATE(FiscalYear,COLUMN()-2,1),tbl_Weather[month],tbl_Weather[cdd],"") -> 0 | D15: =_xlfn.XLOOKUP(DATE(FiscalYear,COLUMN()-2,1),tbl_Weather[month],tbl_Weather[cdd],"") -> 0 | E15: =_xlfn.XLOOKUP(DATE(FiscalYear,COLUMN()-2,1),tbl_Weather[month],tbl_Weather[cdd],"") -> 0 | F15: =_xlfn.XLOOKUP(DATE(FiscalYear,COLUMN()-2,1),tbl_Weather[month],tbl_Weather[cdd],"") -> 0 | G15: =_xlfn.XLOOKUP(DATE(FiscalYear,COLUMN()-2,1),tbl_Weather[month],tbl_Weather[cdd],"") -> 8 | H15: =_xlfn.XLOOKUP(DATE(FiscalYear,COLUMN()-2,1),tbl_Weather[month],tbl_Weather[cdd],"") -> 28 | I15: =_xlfn.XLOOKUP(DATE(FiscalYear,COLUMN()-2,1),tbl_Weather[month],tbl_Weather[cdd],"") -> 91 | J15: =_xlfn.XLOOKUP(DATE(FiscalYear,COLUMN()-2,1),tbl_Weather[month],tbl_Weather[cdd],"") -> 111 | ... N15: =_xlfn.XLOOKUP(DATE(FiscalYear,COLUMN()-2,1),tbl_Weather[month],tbl_Weather[cdd],"") | O15: =SUM(C15:N15) -> 238
B17: ="Weather impact, "&TEXT(FYStart,"mmm")&"–"&TEXT(AsOfMonth,"mmm yyyy")&": actual against normal" -> Weather impact, Jan–Jun 2026: actual against normal
B18: Month | C18: HDD vs normal | D18: CDD vs normal | E18: Residential MWh per customer | F18: Residential customers | G18: Residential MWh | H18: Residential $ | I18: Commercial MWh per customer | J18: Commercial customers | K18: Commercial MWh | L18: Commercial $ | M18: Weather MWh | N18: Weather $
B19: =DATE(FiscalYear,ROWS($B$19:B19),1) -> 46023 | C19: {=IF(ISCLOSED(B19),INDEX(actual_hdd,MONTH(B19))-INDEX(normal_hdd,MONTH(B19)),"")} -> -47 | D19: {=IF(ISCLOSED(B19),INDEX(actual_cdd,MONTH(B19))-INDEX(normal_cdd,MONTH(B19)),"")} -> 0 | E19: {=IF(ISCLOSED(B19),$D$6*C19+$E$6*D19,"")} -> -0.031847988 | F19: {=IF(ISCLOSED(B19),SUMIFS(tbl_Monthly[customers],tbl_Monthly[class],"residential",tbl_Monthly[month],B19),"")} -> 845079 | G19: {=IF(ISCLOSED(B19),E19*F19,"")} -> -26914.066 | H19: {=IF(ISCLOSED(B19),G19*SAFEDIV(SUMIFS(tbl_Monthly[revenue],tbl_Monthly[class],"residential",tbl_Monthly[month],B19),SUMIFS(tbl_Monthly[mwh],tbl_Monthly[class],"residential",tbl_Monthly[month],B19)),"")} -> -4847316.3 | I19: {=IF(ISCLOSED(B19),$D$7*C19+$E$7*D19,"")} -> -0.029527568 | J19: {=IF(ISCLOSED(B19),SUMIFS(tbl_Monthly[customers],tbl_Monthly[class],"commercial",tbl_Monthly[month],B19),"")} -> 110273 | K19: {=IF(ISCLOSED(B19),I19*J19,"")} -> -3256.0935 | L19: {=IF(ISCLOSED(B19),K19*SAFEDIV(SUMIFS(tbl_Monthly[revenue],tbl_Monthly[class],"commercial",tbl_Monthly[month],B19),SUMIFS(tbl_Monthly[mwh],tbl_Monthly[class],"commercial",tbl_Monthly[month],B19)),"")} -> -468064.05 | M19: {=IF(ISCLOSED(B19),G19+K19,"")} -> -30170.16 | N19: {=IF(ISCLOSED(B19),H19+L19,"")} -> -5315380.3
B20: =DATE(FiscalYear,ROWS($B$19:B20),1) -> 46054 | C20: {=IF(ISCLOSED(B20),INDEX(actual_hdd,MONTH(B20))-INDEX(normal_hdd,MONTH(B20)),"")} -> -80.3 | D20: {=IF(ISCLOSED(B20),INDEX(actual_cdd,MONTH(B20))-INDEX(normal_cdd,MONTH(B20)),"")} -> 0 | E20: {=IF(ISCLOSED(B20),$D$6*C20+$E$6*D20,"")} -> -0.054412627 | F20: {=IF(ISCLOSED(B20),SUMIFS(tbl_Monthly[customers],tbl_Monthly[class],"residential",tbl_Monthly[month],B20),"")} -> 845421 | G20: {=IF(ISCLOSED(B20),E20*F20,"")} -> -46001.578 | H20: {=IF(ISCLOSED(B20),G20*SAFEDIV(SUMIFS(tbl_Monthly[revenue],tbl_Monthly[class],"residential",tbl_Monthly[month],B20),SUMIFS(tbl_Monthly[mwh],tbl_Monthly[class],"residential",tbl_Monthly[month],B20)),"")} -> -8345857.2 | I20: {=IF(ISCLOSED(B20),$D$7*C20+$E$7*D20,"")} -> -0.050448164 | J20: {=IF(ISCLOSED(B20),SUMIFS(tbl_Monthly[customers],tbl_Monthly[class],"commercial",tbl_Monthly[month],B20),"")} -> 110510 | K20: {=IF(ISCLOSED(B20),I20*J20,"")} -> -5575.0266 | L20: {=IF(ISCLOSED(B20),K20*SAFEDIV(SUMIFS(tbl_Monthly[revenue],tbl_Monthly[class],"commercial",tbl_Monthly[month],B20),SUMIFS(tbl_Monthly[mwh],tbl_Monthly[class],"commercial",tbl_Monthly[month],B20)),"")} -> -813691.91 | M20: {=IF(ISCLOSED(B20),G20+K20,"")} -> -51576.604 | N20: {=IF(ISCLOSED(B20),H20+L20,"")} -> -9159549.2
B21: =DATE(FiscalYear,ROWS($B$19:B21),1) -> 46082 | C21: {=IF(ISCLOSED(B21),INDEX(actual_hdd,MONTH(B21))-INDEX(normal_hdd,MONTH(B21)),"")} -> -116.8 | D21: {=IF(ISCLOSED(B21),INDEX(actual_cdd,MONTH(B21))-INDEX(normal_cdd,MONTH(B21)),"")} -> 0 | E21: {=IF(ISCLOSED(B21),$D$6*C21+$E$6*D21,"")} -> -0.079145639 | F21: {=IF(ISCLOSED(B21),SUMIFS(tbl_Monthly[customers],tbl_Monthly[class],"residential",tbl_Monthly[month],B21),"")} -> 845954 | G21: {=IF(ISCLOSED(B21),E21*F21,"")} -> -66953.57 | H21: {=IF(ISCLOSED(B21),G21*SAFEDIV(SUMIFS(tbl_Monthly[revenue],tbl_Monthly[class],"residential",tbl_Monthly[month],B21),SUMIFS(tbl_Monthly[mwh],tbl_Monthly[class],"residential",tbl_Monthly[month],B21)),"")} -> -12129612 | I21: {=IF(ISCLOSED(B21),$D$7*C21+$E$7*D21,"")} -> -0.073379148 | J21: {=IF(ISCLOSED(B21),SUMIFS(tbl_Monthly[customers],tbl_Monthly[class],"commercial",tbl_Monthly[month],B21),"")} -> 110584 | K21: {=IF(ISCLOSED(B21),I21*J21,"")} -> -8114.5597 | L21: {=IF(ISCLOSED(B21),K21*SAFEDIV(SUMIFS(tbl_Monthly[revenue],tbl_Monthly[class],"commercial",tbl_Monthly[month],B21),SUMIFS(tbl_Monthly[mwh],tbl_Monthly[class],"commercial",tbl_Monthly[month],B21)),"")} -> -1212989 | M21: {=IF(ISCLOSED(B21),G21+K21,"")} -> -75068.13 | N21: {=IF(ISCLOSED(B21),H21+L21,"")} -> -13342601
B22: =DATE(FiscalYear,ROWS($B$19:B22),1) -> 46113 | C22: {=IF(ISCLOSED(B22),INDEX(actual_hdd,MONTH(B22))-INDEX(normal_hdd,MONTH(B22)),"")} -> -59.4 | D22: {=IF(ISCLOSED(B22),INDEX(actual_cdd,MONTH(B22))-INDEX(normal_cdd,MONTH(B22)),"")} -> 0 | E22: {=IF(ISCLOSED(B22),$D$6*C22+$E$6*D22,"")} -> -0.040250437 | F22: {=IF(ISCLOSED(B22),SUMIFS(tbl_Monthly[customers],tbl_Monthly[class],"residential",tbl_Monthly[month],B22),"")} -> 846300 | G22: {=IF(ISCLOSED(B22),E22*F22,"")} -> -34063.944 | H22: {=IF(ISCLOSED(B22),G22*SAFEDIV(SUMIFS(tbl_Monthly[revenue],tbl_Monthly[class],"residential",tbl_Monthly[month],B22),SUMIFS(tbl_Monthly[mwh],tbl_Monthly[class],"residential",tbl_Monthly[month],B22)),"")} -> -6751636.6 | I22: {=IF(ISCLOSED(B22),$D$7*C22+$E$7*D22,"")} -> -0.03731782 | J22: {=IF(ISCLOSED(B22),SUMIFS(tbl_Monthly[customers],tbl_Monthly[class],"commercial",tbl_Monthly[month],B22),"")} -> 110424 | K22: {=IF(ISCLOSED(B22),I22*J22,"")} -> -4120.783 | L22: {=IF(ISCLOSED(B22),K22*SAFEDIV(SUMIFS(tbl_Monthly[revenue],tbl_Monthly[class],"commercial",tbl_Monthly[month],B22),SUMIFS(tbl_Monthly[mwh],tbl_Monthly[class],"commercial",tbl_Monthly[month],B22)),"")} -> -667758.13 | M22: {=IF(ISCLOSED(B22),G22+K22,"")} -> -38184.727 | N22: {=IF(ISCLOSED(B22),H22+L22,"")} -> -7419394.7
B23: =DATE(FiscalYear,ROWS($B$19:B23),1) -> 46143 | C23: {=IF(ISCLOSED(B23),INDEX(actual_hdd,MONTH(B23))-INDEX(normal_hdd,MONTH(B23)),"")} -> -46.4 | D23: {=IF(ISCLOSED(B23),INDEX(actual_cdd,MONTH(B23))-INDEX(normal_cdd,MONTH(B23)),"")} -> 3.9 | E23: {=IF(ISCLOSED(B23),$D$6*C23+$E$6*D23,"")} -> -0.020997531 | F23: {=IF(ISCLOSED(B23),SUMIFS(tbl_Monthly[customers],tbl_Monthly[class],"residential",tbl_Monthly[month],B23),"")} -> 846323 | G23: {=IF(ISCLOSED(B23),E23*F23,"")} -> -17770.694 | H23: {=IF(ISCLOSED(B23),G23*SAFEDIV(SUMIFS(tbl_Monthly[revenue],tbl_Monthly[class],"residential",tbl_Monthly[month],B23),SUMIFS(tbl_Monthly[mwh],tbl_Monthly[class],"residential",tbl_Monthly[month],B23)),"")} -> -3588677.5 | I23: {=IF(ISCLOSED(B23),$D$7*C23+$E$7*D23,"")} -> -0.00040291413 | J23: {=IF(ISCLOSED(B23),SUMIFS(tbl_Monthly[customers],tbl_Monthly[class],"commercial",tbl_Monthly[month],B23),"")} -> 110377 | K23: {=IF(ISCLOSED(B23),I23*J23,"")} -> -44.472452 | L23: {=IF(ISCLOSED(B23),K23*SAFEDIV(SUMIFS(tbl_Monthly[revenue],tbl_Monthly[class],"commercial",tbl_Monthly[month],B23),SUMIFS(tbl_Monthly[mwh],tbl_Monthly[class],"commercial",tbl_Monthly[month],B23)),"")} -> -7142.7811 | M23: {=IF(ISCLOSED(B23),G23+K23,"")} -> -17815.166 | N23: {=IF(ISCLOSED(B23),H23+L23,"")} -> -3595820.3
B24: =DATE(FiscalYear,ROWS($B$19:B24),1) -> 46174 | C24: {=IF(ISCLOSED(B24),INDEX(actual_hdd,MONTH(B24))-INDEX(normal_hdd,MONTH(B24)),"")} -> -20.5 | D24: {=IF(ISCLOSED(B24),INDEX(actual_cdd,MONTH(B24))-INDEX(normal_cdd,MONTH(B24)),"")} -> 4.7 | E24: {=IF(ISCLOSED(B24),$D$6*C24+$E$6*D24,"")} -> -0.0013049211 | F24: {=IF(ISCLOSED(B24),SUMIFS(tbl_Monthly[customers],tbl_Monthly[class],"residential",tbl_Monthly[month],B24),"")} -> 846477 | G24: {=IF(ISCLOSED(B24),E24*F24,"")} -> -1104.5857 | H24: {=IF(ISCLOSED(B24),G24*SAFEDIV(SUMIFS(tbl_Monthly[revenue],tbl_Monthly[class],"residential",tbl_Monthly[month],B24),SUMIFS(tbl_Monthly[mwh],tbl_Monthly[class],"residential",tbl_Monthly[month],B24)),"")} -> -220033.28 | I24: {=IF(ISCLOSED(B24),$D$7*C24+$E$7*D24,"")} -> 0.021765626 | J24: {=IF(ISCLOSED(B24),SUMIFS(tbl_Monthly[customers],tbl_Monthly[class],"commercial",tbl_Monthly[month],B24),"")} -> 110492 | K24: {=IF(ISCLOSED(B24),I24*J24,"")} -> 2404.9275 | L24: {=IF(ISCLOSED(B24),K24*SAFEDIV(SUMIFS(tbl_Monthly[revenue],tbl_Monthly[class],"commercial",tbl_Monthly[month],B24),SUMIFS(tbl_Monthly[mwh],tbl_Monthly[class],"commercial",tbl_Monthly[month],B24)),"")} -> 378543.83 | M24: {=IF(ISCLOSED(B24),G24+K24,"")} -> 1300.3419 | N24: {=IF(ISCLOSED(B24),H24+L24,"")} -> 158510.54
B25: =DATE(FiscalYear,ROWS($B$19:B25),1) -> 46204 | C25: {=IF(ISCLOSED(B25),INDEX(actual_hdd,MONTH(B25))-INDEX(normal_hdd,MONTH(B25)),"")} | D25: {=IF(ISCLOSED(B25),INDEX(actual_cdd,MONTH(B25))-INDEX(normal_cdd,MONTH(B25)),"")} | E25: {=IF(ISCLOSED(B25),$D$6*C25+$E$6*D25,"")} | F25: {=IF(ISCLOSED(B25),SUMIFS(tbl_Monthly[customers],tbl_Monthly[class],"residential",tbl_Monthly[month],B25),"")} | G25: {=IF(ISCLOSED(B25),E25*F25,"")} | H25: {=IF(ISCLOSED(B25),G25*SAFEDIV(SUMIFS(tbl_Monthly[revenue],tbl_Monthly[class],"residential",tbl_Monthly[month],B25),SUMIFS(tbl_Monthly[mwh],tbl_Monthly[class],"residential",tbl_Monthly[month],B25)),"")} | I25: {=IF(ISCLOSED(B25),$D$7*C25+$E$7*D25,"")} | J25: {=IF(ISCLOSED(B25),SUMIFS(tbl_Monthly[customers],tbl_Monthly[class],"commercial",tbl_Monthly[month],B25),"")} | K25: {=IF(ISCLOSED(B25),I25*J25,"")} | L25: {=IF(ISCLOSED(B25),K25*SAFEDIV(SUMIFS(tbl_Monthly[revenue],tbl_Monthly[class],"commercial",tbl_Monthly[month],B25),SUMIFS(tbl_Monthly[mwh],tbl_Monthly[class],"commercial",tbl_Monthly[month],B25)),"")} | M25: {=IF(ISCLOSED(B25),G25+K25,"")} | N25: {=IF(ISCLOSED(B25),H25+L25,"")}
B26: =DATE(FiscalYear,ROWS($B$19:B26),1) -> 46235 | C26: {=IF(ISCLOSED(B26),INDEX(actual_hdd,MONTH(B26))-INDEX(normal_hdd,MONTH(B26)),"")} | D26: {=IF(ISCLOSED(B26),INDEX(actual_cdd,MONTH(B26))-INDEX(normal_cdd,MONTH(B26)),"")} | E26: {=IF(ISCLOSED(B26),$D$6*C26+$E$6*D26,"")} | F26: {=IF(ISCLOSED(B26),SUMIFS(tbl_Monthly[customers],tbl_Monthly[class],"residential",tbl_Monthly[month],B26),"")} | G26: {=IF(ISCLOSED(B26),E26*F26,"")} | H26: {=IF(ISCLOSED(B26),G26*SAFEDIV(SUMIFS(tbl_Monthly[revenue],tbl_Monthly[class],"residential",tbl_Monthly[month],B26),SUMIFS(tbl_Monthly[mwh],tbl_Monthly[class],"residential",tbl_Monthly[month],B26)),"")} | I26: {=IF(ISCLOSED(B26),$D$7*C26+$E$7*D26,"")} | J26: {=IF(ISCLOSED(B26),SUMIFS(tbl_Monthly[customers],tbl_Monthly[class],"commercial",tbl_Monthly[month],B26),"")} | K26: {=IF(ISCLOSED(B26),I26*J26,"")} | L26: {=IF(ISCLOSED(B26),K26*SAFEDIV(SUMIFS(tbl_Monthly[revenue],tbl_Monthly[class],"commercial",tbl_Monthly[month],B26),SUMIFS(tbl_Monthly[mwh],tbl_Monthly[class],"commercial",tbl_Monthly[month],B26)),"")} | M26: {=IF(ISCLOSED(B26),G26+K26,"")} | N26: {=IF(ISCLOSED(B26),H26+L26,"")}
B27: =DATE(FiscalYear,ROWS($B$19:B27),1) -> 46266 | C27: {=IF(ISCLOSED(B27),INDEX(actual_hdd,MONTH(B27))-INDEX(normal_hdd,MONTH(B27)),"")} | D27: {=IF(ISCLOSED(B27),INDEX(actual_cdd,MONTH(B27))-INDEX(normal_cdd,MONTH(B27)),"")} | E27: {=IF(ISCLOSED(B27),$D$6*C27+$E$6*D27,"")} | F27: {=IF(ISCLOSED(B27),SUMIFS(tbl_Monthly[customers],tbl_Monthly[class],"residential",tbl_Monthly[month],B27),"")} | G27: {=IF(ISCLOSED(B27),E27*F27,"")} | H27: {=IF(ISCLOSED(B27),G27*SAFEDIV(SUMIFS(tbl_Monthly[revenue],tbl_Monthly[class],"residential",tbl_Monthly[month],B27),SUMIFS(tbl_Monthly[mwh],tbl_Monthly[class],"residential",tbl_Monthly[month],B27)),"")} | I27: {=IF(ISCLOSED(B27),$D$7*C27+$E$7*D27,"")} | J27: {=IF(ISCLOSED(B27),SUMIFS(tbl_Monthly[customers],tbl_Monthly[class],"commercial",tbl_Monthly[month],B27),"")} | K27: {=IF(ISCLOSED(B27),I27*J27,"")} | L27: {=IF(ISCLOSED(B27),K27*SAFEDIV(SUMIFS(tbl_Monthly[revenue],tbl_Monthly[class],"commercial",tbl_Monthly[month],B27),SUMIFS(tbl_Monthly[mwh],tbl_Monthly[class],"commercial",tbl_Monthly[month],B27)),"")} | M27: {=IF(ISCLOSED(B27),G27+K27,"")} | N27: {=IF(ISCLOSED(B27),H27+L27,"")}
B28: =DATE(FiscalYear,ROWS($B$19:B28),1) -> 46296 | C28: {=IF(ISCLOSED(B28),INDEX(actual_hdd,MONTH(B28))-INDEX(normal_hdd,MONTH(B28)),"")} | D28: {=IF(ISCLOSED(B28),INDEX(actual_cdd,MONTH(B28))-INDEX(normal_cdd,MONTH(B28)),"")} | E28: {=IF(ISCLOSED(B28),$D$6*C28+$E$6*D28,"")} | F28: {=IF(ISCLOSED(B28),SUMIFS(tbl_Monthly[customers],tbl_Monthly[class],"residential",tbl_Monthly[month],B28),"")} | G28: {=IF(ISCLOSED(B28),E28*F28,"")} | H28: {=IF(ISCLOSED(B28),G28*SAFEDIV(SUMIFS(tbl_Monthly[revenue],tbl_Monthly[class],"residential",tbl_Monthly[month],B28),SUMIFS(tbl_Monthly[mwh],tbl_Monthly[class],"residential",tbl_Monthly[month],B28)),"")} | I28: {=IF(ISCLOSED(B28),$D$7*C28+$E$7*D28,"")} | J28: {=IF(ISCLOSED(B28),SUMIFS(tbl_Monthly[customers],tbl_Monthly[class],"commercial",tbl_Monthly[month],B28),"")} | K28: {=IF(ISCLOSED(B28),I28*J28,"")} | L28: {=IF(ISCLOSED(B28),K28*SAFEDIV(SUMIFS(tbl_Monthly[revenue],tbl_Monthly[class],"commercial",tbl_Monthly[month],B28),SUMIFS(tbl_Monthly[mwh],tbl_Monthly[class],"commercial",tbl_Monthly[month],B28)),"")} | M28: {=IF(ISCLOSED(B28),G28+K28,"")} | N28: {=IF(ISCLOSED(B28),H28+L28,"")}
B29: =DATE(FiscalYear,ROWS($B$19:B29),1) -> 46327 | C29: {=IF(ISCLOSED(B29),INDEX(actual_hdd,MONTH(B29))-INDEX(normal_hdd,MONTH(B29)),"")} | D29: {=IF(ISCLOSED(B29),INDEX(actual_cdd,MONTH(B29))-INDEX(normal_cdd,MONTH(B29)),"")} | E29: {=IF(ISCLOSED(B29),$D$6*C29+$E$6*D29,"")} | F29: {=IF(ISCLOSED(B29),SUMIFS(tbl_Monthly[customers],tbl_Monthly[class],"residential",tbl_Monthly[month],B29),"")} | G29: {=IF(ISCLOSED(B29),E29*F29,"")} | H29: {=IF(ISCLOSED(B29),G29*SAFEDIV(SUMIFS(tbl_Monthly[revenue],tbl_Monthly[class],"residential",tbl_Monthly[month],B29),SUMIFS(tbl_Monthly[mwh],tbl_Monthly[class],"residential",tbl_Monthly[month],B29)),"")} | I29: {=IF(ISCLOSED(B29),$D$7*C29+$E$7*D29,"")} | J29: {=IF(ISCLOSED(B29),SUMIFS(tbl_Monthly[customers],tbl_Monthly[class],"commercial",tbl_Monthly[month],B29),"")} | K29: {=IF(ISCLOSED(B29),I29*J29,"")} | L29: {=IF(ISCLOSED(B29),K29*SAFEDIV(SUMIFS(tbl_Monthly[revenue],tbl_Monthly[class],"commercial",tbl_Monthly[month],B29),SUMIFS(tbl_Monthly[mwh],tbl_Monthly[class],"commercial",tbl_Monthly[month],B29)),"")} | M29: {=IF(ISCLOSED(B29),G29+K29,"")} | N29: {=IF(ISCLOSED(B29),H29+L29,"")}
B30: =DATE(FiscalYear,ROWS($B$19:B30),1) -> 46357 | C30: {=IF(ISCLOSED(B30),INDEX(actual_hdd,MONTH(B30))-INDEX(normal_hdd,MONTH(B30)),"")} | D30: {=IF(ISCLOSED(B30),INDEX(actual_cdd,MONTH(B30))-INDEX(normal_cdd,MONTH(B30)),"")} | E30: {=IF(ISCLOSED(B30),$D$6*C30+$E$6*D30,"")} | F30: {=IF(ISCLOSED(B30),SUMIFS(tbl_Monthly[customers],tbl_Monthly[class],"residential",tbl_Monthly[month],B30),"")} | G30: {=IF(ISCLOSED(B30),E30*F30,"")} | H30: {=IF(ISCLOSED(B30),G30*SAFEDIV(SUMIFS(tbl_Monthly[revenue],tbl_Monthly[class],"residential",tbl_Monthly[month],B30),SUMIFS(tbl_Monthly[mwh],tbl_Monthly[class],"residential",tbl_Monthly[month],B30)),"")} | I30: {=IF(ISCLOSED(B30),$D$7*C30+$E$7*D30,"")} | J30: {=IF(ISCLOSED(B30),SUMIFS(tbl_Monthly[customers],tbl_Monthly[class],"commercial",tbl_Monthly[month],B30),"")} | K30: {=IF(ISCLOSED(B30),I30*J30,"")} | L30: {=IF(ISCLOSED(B30),K30*SAFEDIV(SUMIFS(tbl_Monthly[revenue],tbl_Monthly[class],"commercial",tbl_Monthly[month],B30),SUMIFS(tbl_Monthly[mwh],tbl_Monthly[class],"commercial",tbl_Monthly[month],B30)),"")} | M30: {=IF(ISCLOSED(B30),G30+K30,"")} | N30: {=IF(ISCLOSED(B30),H30+L30,"")}
B31: Year to date | C31: =SUM(C19:C30) -> -370.4 | D31: =SUM(D19:D30) -> 8.6 | G31: =SUM(G19:G30) -> -192808.44 | H31: =SUM(H19:H30) -> -35883133 | K31: =SUM(K19:K30) -> -18706.008 | L31: =SUM(L19:L30) -> -2791102 | M31: =SUM(M19:M30) -> -211514.45 | N31: =SUM(N19:N30) -> -38674235
B32: {=IF(N31<0,"Weather took ","Weather added ")&TEXT(ABS(M31)/1000,"#,##0")&" GWh and "&MONEY(ABS(N31))&IF(N31<0," off"," to")&" retail revenue this year, valued at each month's actual price."} -> Weather took 212 GWh and $38.7M off retail revenue this year, valued at each month's actual price.
B60: Regression data: one row per month
B61: Month | C61: Trend (years) | D61: HDD | E61: CDD | F61: Residential MWh/customer | G61: Commercial MWh/customer | H61: Residential fitted | I61: Commercial fitted | J61: In fit window
B62: =FitStart -> 42736 | C62: {=TRENDYEARS(B62)} -> 0 | D62: =_xlfn.XLOOKUP(B62,tbl_Weather[month],tbl_Weather[hdd],"") -> 924 | E62: =_xlfn.XLOOKUP(B62,tbl_Weather[month],tbl_Weather[cdd],"") -> 0 | F62: {=IF(ISCLOSED(B62),SAFEDIV(SUMIFS(tbl_Monthly[mwh],tbl_Monthly[class],"residential",tbl_Monthly[month],B62),SUMIFS(tbl_Monthly[customers],tbl_Monthly[class],"residential",tbl_Monthly[month],B62)),"")} -> 1.3082339 | G62: {=IF(ISCLOSED(B62),SAFEDIV(SUMIFS(tbl_Monthly[mwh],tbl_Monthly[class],"commercial",tbl_Monthly[month],B62),SUMIFS(tbl_Monthly[customers],tbl_Monthly[class],"commercial",tbl_Monthly[month],B62)),"")} -> 5.4353454 | H62: =IF(ISNUMBER(D62),$C$6+$D$6*D62+$E$6*E62+$F$6*C62,"") -> 1.1220843 | I62: =IF(ISNUMBER(D62),$C$7+$D$7*D62+$E$7*E62+$F$7*C62,"") -> 5.4863288 | J62: =AND(ISCLOSED(B62),YEAR(B62)<FiscalYear) -> TRUE
B63: =EDATE(B62,1) -> 42767 | C63: {=TRENDYEARS(B63)} -> 0.083333333 | D63: =_xlfn.XLOOKUP(B63,tbl_Weather[month],tbl_Weather[hdd],"") -> 680 | E63: =_xlfn.XLOOKUP(B63,tbl_Weather[month],tbl_Weather[cdd],"") -> 0 | F63: {=IF(ISCLOSED(B63),SAFEDIV(SUMIFS(tbl_Monthly[mwh],tbl_Monthly[class],"residential",tbl_Monthly[month],B63),SUMIFS(tbl_Monthly[customers],tbl_Monthly[class],"residential",tbl_Monthly[month],B63)),"")} -> 0.93255016 | G63: {=IF(ISCLOSED(B63),SAFEDIV(SUMIFS(tbl_Monthly[mwh],tbl_Monthly[class],"commercial",tbl_Monthly[month],B63),SUMIFS(tbl_Monthly[customers],tbl_Monthly[class],"commercial",tbl_Monthly[month],B63)),"")} -> 5.2324099 | H63: =IF(ISNUMBER(D63),$C$6+$D$6*D63+$E$6*E63+$F$6*C63,"") -> 0.95611931 | I63: =IF(ISNUMBER(D63),$C$7+$D$7*D63+$E$7*E63+$F$7*C63,"") -> 5.3276184 | J63: =AND(ISCLOSED(B63),YEAR(B63)<FiscalYear) -> TRUE
B64: =EDATE(B63,1) -> 42795 | C64: {=TRENDYEARS(B64)} -> 0.16666667 | D64: =_xlfn.XLOOKUP(B64,tbl_Weather[month],tbl_Weather[hdd],"") -> 617 | E64: =_xlfn.XLOOKUP(B64,tbl_Weather[month],tbl_Weather[cdd],"") -> 0 | F64: {=IF(ISCLOSED(B64),SAFEDIV(SUMIFS(tbl_Monthly[mwh],tbl_Monthly[class],"residential",tbl_Monthly[month],B64),SUMIFS(tbl_Monthly[customers],tbl_Monthly[class],"residential",tbl_Monthly[month],B64)),"")} -> 0.90375568 | G64: {=IF(ISCLOSED(B64),SAFEDIV(SUMIFS(tbl_Monthly[mwh],tbl_Monthly[class],"commercial",tbl_Monthly[month],B64),SUMIFS(tbl_Monthly[customers],tbl_Monthly[class],"commercial",tbl_Monthly[month],B64)),"")} -> 5.5228368 | H64: =IF(ISNUMBER(D64),$C$6+$D$6*D64+$E$6*E64+$F$6*C64,"") -> 0.91280292 | I64: =IF(ISNUMBER(D64),$C$7+$D$7*D64+$E$7*E64+$F$7*C64,"") -> 5.2826206 | J64: =AND(ISCLOSED(B64),YEAR(B64)<FiscalYear) -> TRUE
B65: =EDATE(B64,1) -> 42826 | C65: {=TRENDYEARS(B65)} -> 0.25 | D65: =_xlfn.XLOOKUP(B65,tbl_Weather[month],tbl_Weather[hdd],"") -> 531 | E65: =_xlfn.XLOOKUP(B65,tbl_Weather[month],tbl_Weather[cdd],"") -> 0 | F65: {=IF(ISCLOSED(B65),SAFEDIV(SUMIFS(tbl_Monthly[mwh],tbl_Monthly[class],"residential",tbl_Monthly[month],B65),SUMIFS(tbl_Monthly[customers],tbl_Monthly[class],"residential",tbl_Monthly[month],B65)),"")} -> 0.7377436 | G65: {=IF(ISCLOSED(B65),SAFEDIV(SUMIFS(tbl_Monthly[mwh],tbl_Monthly[class],"commercial",tbl_Monthly[month],B65),SUMIFS(tbl_Monthly[customers],tbl_Monthly[class],"commercial",tbl_Monthly[month],B65)),"")} -> 5.0677497 | H65: =IF(ISNUMBER(D65),$C$6+$D$6*D65+$E$6*E65+$F$6*C65,"") -> 0.85390134 | I65: =IF(ISNUMBER(D65),$C$7+$D$7*D65+$E$7*E65+$F$7*C65,"") -> 5.2231731 | J65: =AND(ISCLOSED(B65),YEAR(B65)<FiscalYear) -> TRUE
B66: =EDATE(B65,1) -> 42856 | C66: {=TRENDYEARS(B66)} -> 0.33333333 | D66: =_xlfn.XLOOKUP(B66,tbl_Weather[month],tbl_Weather[hdd],"") -> 275 | E66: =_xlfn.XLOOKUP(B66,tbl_Weather[month],tbl_Weather[cdd],"") -> 5 | F66: {=IF(ISCLOSED(B66),SAFEDIV(SUMIFS(tbl_Monthly[mwh],tbl_Monthly[class],"residential",tbl_Monthly[month],B66),SUMIFS(tbl_Monthly[customers],tbl_Monthly[class],"residential",tbl_Monthly[month],B66)),"")} -> 0.72638642 | G66: {=IF(ISCLOSED(B66),SAFEDIV(SUMIFS(tbl_Monthly[mwh],tbl_Monthly[class],"commercial",tbl_Monthly[month],B66),SUMIFS(tbl_Monthly[customers],tbl_Monthly[class],"commercial",tbl_Monthly[month],B66)),"")} -> 5.2761626 | H66: =IF(ISNUMBER(D66),$C$6+$D$6*D66+$E$6*E66+$F$6*C66,"") -> 0.6931945 | I66: =IF(ISNUMBER(D66),$C$7+$D$7*D66+$E$7*E66+$F$7*C66,"") -> 5.0937798 | J66: =AND(ISCLOSED(B66),YEAR(B66)<FiscalYear) -> TRUE
B67: =EDATE(B66,1) -> 42887 | C67: {=TRENDYEARS(B67)} -> 0.41666667 | D67: =_xlfn.XLOOKUP(B67,tbl_Weather[month],tbl_Weather[hdd],"") -> 133 | E67: =_xlfn.XLOOKUP(B67,tbl_Weather[month],tbl_Weather[cdd],"") -> 19 | F67: {=IF(ISCLOSED(B67),SAFEDIV(SUMIFS(tbl_Monthly[mwh],tbl_Monthly[class],"residential",tbl_Monthly[month],B67),SUMIFS(tbl_Monthly[customers],tbl_Monthly[class],"residential",tbl_Monthly[month],B67)),"")} -> 0.67114025 | G67: {=IF(ISCLOSED(B67),SAFEDIV(SUMIFS(tbl_Monthly[mwh],tbl_Monthly[class],"commercial",tbl_Monthly[month],B67),SUMIFS(tbl_Monthly[customers],tbl_Monthly[class],"commercial",tbl_Monthly[month],B67)),"")} -> 5.4361453 | H67: =IF(ISNUMBER(D67),$C$6+$D$6*D67+$E$6*E67+$F$6*C67,"") -> 0.63383726 | I67: =IF(ISNUMBER(D67),$C$7+$D$7*D67+$E$7*E67+$F$7*C67,"") -> 5.1023474 | J67: =AND(ISCLOSED(B67),YEAR(B67)<FiscalYear) -> TRUE
B68: =EDATE(B67,1) -> 42917 | C68: {=TRENDYEARS(B68)} -> 0.5 | D68: =_xlfn.XLOOKUP(B68,tbl_Weather[month],tbl_Weather[hdd],"") -> 37 | E68: =_xlfn.XLOOKUP(B68,tbl_Weather[month],tbl_Weather[cdd],"") -> 96 | F68: {=IF(ISCLOSED(B68),SAFEDIV(SUMIFS(tbl_Monthly[mwh],tbl_Monthly[class],"residential",tbl_Monthly[month],B68),SUMIFS(tbl_Monthly[customers],tbl_Monthly[class],"residential",tbl_Monthly[month],B68)),"")} -> 0.77283545 | G68: {=IF(ISCLOSED(B68),SAFEDIV(SUMIFS(tbl_Monthly[mwh],tbl_Monthly[class],"commercial",tbl_Monthly[month],B68),SUMIFS(tbl_Monthly[customers],tbl_Monthly[class],"commercial",tbl_Monthly[month],B68)),"")} -> 5.7332837 | H68: =IF(ISNUMBER(D68),$C$6+$D$6*D68+$E$6*E68+$F$6*C68,"") -> 0.77435933 | I68: =IF(ISNUMBER(D68),$C$7+$D$7*D68+$E$7*E68+$F$7*C68,"") -> 5.6042003 | J68: =AND(ISCLOSED(B68),YEAR(B68)<FiscalYear) -> TRUE
B69: =EDATE(B68,1) -> 42948 | C69: {=TRENDYEARS(B69)} -> 0.58333333 | D69: =_xlfn.XLOOKUP(B69,tbl_Weather[month],tbl_Weather[hdd],"") -> 9 | E69: =_xlfn.XLOOKUP(B69,tbl_Weather[month],tbl_Weather[cdd],"") -> 177 | F69: {=IF(ISCLOSED(B69),SAFEDIV(SUMIFS(tbl_Monthly[mwh],tbl_Monthly[class],"residential",tbl_Monthly[month],B69),SUMIFS(tbl_Monthly[customers],tbl_Monthly[class],"residential",tbl_Monthly[month],B69)),"")} -> 0.89887262 | G69: {=IF(ISCLOSED(B69),SAFEDIV(SUMIFS(tbl_Monthly[mwh],tbl_Monthly[class],"commercial",tbl_Monthly[month],B69),SUMIFS(tbl_Monthly[customers],tbl_Monthly[class],"commercial",tbl_Monthly[month],B69)),"")} -> 6.2639553 | H69: =IF(ISNUMBER(D69),$C$6+$D$6*D69+$E$6*E69+$F$6*C69,"") -> 0.97167103 | I69: =IF(ISNUMBER(D69),$C$7+$D$7*D69+$E$7*E69+$F$7*C69,"") -> 6.1782589 | J69: =AND(ISCLOSED(B69),YEAR(B69)<FiscalYear) -> TRUE
B70: =EDATE(B69,1) -> 42979 | C70: {=TRENDYEARS(B70)} -> 0.66666667 | D70: =_xlfn.XLOOKUP(B70,tbl_Weather[month],tbl_Weather[hdd],"") -> 91 | E70: =_xlfn.XLOOKUP(B70,tbl_Weather[month],tbl_Weather[cdd],"") -> 46 | F70: {=IF(ISCLOSED(B70),SAFEDIV(SUMIFS(tbl_Monthly[mwh],tbl_Monthly[class],"residential",tbl_Monthly[month],B70),SUMIFS(tbl_Monthly[customers],tbl_Monthly[class],"residential",tbl_Monthly[month],B70)),"")} -> 0.70813211 | G70: {=IF(ISCLOSED(B70),SAFEDIV(SUMIFS(tbl_Monthly[mwh],tbl_Monthly[class],"commercial",tbl_Monthly[month],B70),SUMIFS(tbl_Monthly[customers],tbl_Monthly[class],"commercial",tbl_Monthly[month],B70)),"")} -> 5.3074119 | H70: =IF(ISNUMBER(D70),$C$6+$D$6*D70+$E$6*E70+$F$6*C70,"") -> 0.67580158 | I70: =IF(ISNUMBER(D70),$C$7+$D$7*D70+$E$7*E70+$F$7*C70,"") -> 5.2587286 | J70: =AND(ISCLOSED(B70),YEAR(B70)<FiscalYear) -> TRUE
B71: =EDATE(B70,1) -> 43009 | C71: {=TRENDYEARS(B71)} -> 0.75 | D71: =_xlfn.XLOOKUP(B71,tbl_Weather[month],tbl_Weather[hdd],"") -> 403 | E71: =_xlfn.XLOOKUP(B71,tbl_Weather[month],tbl_Weather[cdd],"") -> 0 | F71: {=IF(ISCLOSED(B71),SAFEDIV(SUMIFS(tbl_Monthly[mwh],tbl_Monthly[class],"residential",tbl_Monthly[month],B71),SUMIFS(tbl_Monthly[customers],tbl_Monthly[class],"residential",tbl_Monthly[month],B71)),"")} -> 0.6685348 | G71: {=IF(ISCLOSED(B71),SAFEDIV(SUMIFS(tbl_Monthly[mwh],tbl_Monthly[class],"commercial",tbl_Monthly[month],B71),SUMIFS(tbl_Monthly[customers],tbl_Monthly[class],"commercial",tbl_Monthly[month],B71)),"")} -> 5.3499351 | H71: =IF(ISNUMBER(D71),$C$6+$D$6*D71+$E$6*E71+$F$6*C71,"") -> 0.76340716 | I71: =IF(ISNUMBER(D71),$C$7+$D$7*D71+$E$7*E71+$F$7*C71,"") -> 5.1102476 | J71: =AND(ISCLOSED(B71),YEAR(B71)<FiscalYear) -> TRUE
B72: =EDATE(B71,1) -> 43040 | C72: {=TRENDYEARS(B72)} -> 0.83333333 | D72: =_xlfn.XLOOKUP(B72,tbl_Weather[month],tbl_Weather[hdd],"") -> 609 | E72: =_xlfn.XLOOKUP(B72,tbl_Weather[month],tbl_Weather[cdd],"") -> 0 | F72: {=IF(ISCLOSED(B72),SAFEDIV(SUMIFS(tbl_Monthly[mwh],tbl_Monthly[class],"residential",tbl_Monthly[month],B72),SUMIFS(tbl_Monthly[customers],tbl_Monthly[class],"residential",tbl_Monthly[month],B72)),"")} -> 0.86222176 | G72: {=IF(ISCLOSED(B72),SAFEDIV(SUMIFS(tbl_Monthly[mwh],tbl_Monthly[class],"commercial",tbl_Monthly[month],B72),SUMIFS(tbl_Monthly[customers],tbl_Monthly[class],"commercial",tbl_Monthly[month],B72)),"")} -> 5.3578264 | H72: =IF(ISNUMBER(D72),$C$6+$D$6*D72+$E$6*E72+$F$6*C72,"") -> 0.90236968 | I72: =IF(ISNUMBER(D72),$C$7+$D$7*D72+$E$7*E72+$F$7*C72,"") -> 5.2342479 | J72: =AND(ISCLOSED(B72),YEAR(B72)<FiscalYear) -> TRUE
B73: =EDATE(B72,1) -> 43070 | C73: {=TRENDYEARS(B73)} -> 0.91666667 | D73: =_xlfn.XLOOKUP(B73,tbl_Weather[month],tbl_Weather[hdd],"") -> 797 | E73: =_xlfn.XLOOKUP(B73,tbl_Weather[month],tbl_Weather[cdd],"") -> 0 | F73: {=IF(ISCLOSED(B73),SAFEDIV(SUMIFS(tbl_Monthly[mwh],tbl_Monthly[class],"residential",tbl_Monthly[month],B73),SUMIFS(tbl_Monthly[customers],tbl_Monthly[class],"residential",tbl_Monthly[month],B73)),"")} -> 1.1497488 | G73: {=IF(ISCLOSED(B73),SAFEDIV(SUMIFS(tbl_Monthly[mwh],tbl_Monthly[class],"commercial",tbl_Monthly[month],B73),SUMIFS(tbl_Monthly[customers],tbl_Monthly[class],"commercial",tbl_Monthly[month],B73)),"")} -> 5.7969934 | H73: =IF(ISNUMBER(D73),$C$6+$D$6*D73+$E$6*E73+$F$6*C73,"") -> 1.0291351 | I73: =IF(ISNUMBER(D73),$C$7+$D$7*D73+$E$7*E73+$F$7*C73,"") -> 5.3469399 | J73: =AND(ISCLOSED(B73),YEAR(B73)<FiscalYear) -> TRUE
B74: =EDATE(B73,1) -> 43101 | C74: {=TRENDYEARS(B74)} -> 1 | D74: =_xlfn.XLOOKUP(B74,tbl_Weather[month],tbl_Weather[hdd],"") -> 670 | E74: =_xlfn.XLOOKUP(B74,tbl_Weather[month],tbl_Weather[cdd],"") -> 0 | F74: {=IF(ISCLOSED(B74),SAFEDIV(SUMIFS(tbl_Monthly[mwh],tbl_Monthly[class],"residential",tbl_Monthly[month],B74),SUMIFS(tbl_Monthly[customers],tbl_Monthly[class],"residential",tbl_Monthly[month],B74)),"")} -> 1.0189859 | G74: {=IF(ISCLOSED(B74),SAFEDIV(SUMIFS(tbl_Monthly[mwh],tbl_Monthly[class],"commercial",tbl_Monthly[month],B74),SUMIFS(tbl_Monthly[customers],tbl_Monthly[class],"commercial",tbl_Monthly[month],B74)),"")} -> 4.7515756 | H74: =IF(ISNUMBER(D74),$C$6+$D$6*D74+$E$6*E74+$F$6*C74,"") -> 0.94245123 | I74: =IF(ISNUMBER(D74),$C$7+$D$7*D74+$E$7*E74+$F$7*C74,"") -> 5.2617343 | J74: =AND(ISCLOSED(B74),YEAR(B74)<FiscalYear) -> TRUE
... B181: =EDATE(B180,1) -> 46357 | C181: {=TRENDYEARS(B181)} -> 9.9166667 | D181: =_xlfn.XLOOKUP(B181,tbl_Weather[month],tbl_Weather[hdd],"") | E181: =_xlfn.XLOOKUP(B181,tbl_Weather[month],tbl_Weather[cdd],"") | F181: {=IF(ISCLOSED(B181),SAFEDIV(SUMIFS(tbl_Monthly[mwh],tbl_Monthly[class],"residential",tbl_Monthly[month],B181),SUMIFS(tbl_Monthly[customers],tbl_Monthly[class],"residential",tbl_Monthly[month],B181)),"")} | G181: {=IF(ISCLOSED(B181),SAFEDIV(SUMIFS(tbl_Monthly[mwh],tbl_Monthly[class],"commercial",tbl_Monthly[month],B181),SUMIFS(tbl_Monthly[customers],tbl_Monthly[class],"commercial",tbl_Monthly[month],B181)),"")} | H181: =IF(ISNUMBER(D181),$C$6+$D$6*D181+$E$6*E181+$F$6*C181,"") | I181: =IF(ISNUMBER(D181),$C$7+$D$7*D181+$E$7*E181+$F$7*C181,"") | J181: =AND(ISCLOSED(B181),YEAR(B181)<FiscalYear) -> FALSE

Sheet Plan
B1: {="Plan against actual: the "&PlanYear&" plan, built only from data through December "&(PlanYear-1)} -> Plan against actual: the 2026 plan, built only from data through December 2025
B2: Customers grow at last year's rate; residential and commercial use comes from the weather model at normal weather; industrial volume and every class's price grow at last year's rate. The bridge splits actual minus plan into customers, weather, usage and price, exactly.
B4: Plan year | C4: 2026 | D4: Change it to re-run the plan as of an earlier year-end; the backtest below does exactly that.
B5: Months closed | C5: =IF(PlanYear<FiscalYear,12,IF(PlanYear=FiscalYear,MonthsClosed,0)) -> 6
B7: ="Drivers, from "&(PlanYear-2)&" and "&(PlanYear-1) -> Drivers, from 2024 and 2025
B8: Class | C8: Key | D8: Customers, Dec before | E8: Dec two before | F8: Customer growth | G8: MWh, year before | H8: Two before | I8: Volume growth | J8: $/MWh, year before | K8: Two before | L8: Price growth
B9: Residential | C9: residential | D9: =SUMIFS(tbl_Monthly[customers],tbl_Monthly[class],$C9,tbl_Monthly[month],DATE(PlanYear-1,12,1)) -> 844308 | E9: =SUMIFS(tbl_Monthly[customers],tbl_Monthly[class],$C9,tbl_Monthly[month],DATE(PlanYear-2,12,1)) -> 835058 | F9: {=SAFEDIV(D9,E9)} -> 1.0110771 | G9: =SUMIFS(tbl_Monthly[mwh],tbl_Monthly[class],$C9,tbl_Monthly[month],">="&DATE(PlanYear-1,1,1),tbl_Monthly[month],"<="&DATE(PlanYear-1,12,1)) -> 7596297.6 | H9: =SUMIFS(tbl_Monthly[mwh],tbl_Monthly[class],$C9,tbl_Monthly[month],">="&DATE(PlanYear-2,1,1),tbl_Monthly[month],"<="&DATE(PlanYear-2,12,1)) -> 7731593.7 | I9: {=SAFEDIV(G9,H9)} -> 0.98250088 | J9: {=SAFEDIV(SUMIFS(tbl_Monthly[revenue],tbl_Monthly[class],$C9,tbl_Monthly[month],">="&DATE(PlanYear-1,1,1),tbl_Monthly[month],"<="&DATE(PlanYear-1,12,1)),G9)} -> 187.94484 | K9: {=SAFEDIV(SUMIFS(tbl_Monthly[revenue],tbl_Monthly[class],$C9,tbl_Monthly[month],">="&DATE(PlanYear-2,1,1),tbl_Monthly[month],"<="&DATE(PlanYear-2,12,1)),H9)} -> 181.89919 | L9: {=SAFEDIV(J9,K9)} -> 1.0332363
B10: Commercial | C10: commercial | D10: =SUMIFS(tbl_Monthly[customers],tbl_Monthly[class],$C10,tbl_Monthly[month],DATE(PlanYear-1,12,1)) -> 110212 | E10: =SUMIFS(tbl_Monthly[customers],tbl_Monthly[class],$C10,tbl_Monthly[month],DATE(PlanYear-2,12,1)) -> 110145 | F10: {=SAFEDIV(D10,E10)} -> 1.0006083 | G10: =SUMIFS(tbl_Monthly[mwh],tbl_Monthly[class],$C10,tbl_Monthly[month],">="&DATE(PlanYear-1,1,1),tbl_Monthly[month],"<="&DATE(PlanYear-1,12,1)) -> 6385089.5 | H10: =SUMIFS(tbl_Monthly[mwh],tbl_Monthly[class],$C10,tbl_Monthly[month],">="&DATE(PlanYear-2,1,1),tbl_Monthly[month],"<="&DATE(PlanYear-2,12,1)) -> 6433391 | I10: {=SAFEDIV(G10,H10)} -> 0.99249206 | J10: {=SAFEDIV(SUMIFS(tbl_Monthly[revenue],tbl_Monthly[class],$C10,tbl_Monthly[month],">="&DATE(PlanYear-1,1,1),tbl_Monthly[month],"<="&DATE(PlanYear-1,12,1)),G10)} -> 148.0284 | K10: {=SAFEDIV(SUMIFS(tbl_Monthly[revenue],tbl_Monthly[class],$C10,tbl_Monthly[month],">="&DATE(PlanYear-2,1,1),tbl_Monthly[month],"<="&DATE(PlanYear-2,12,1)),H10)} -> 138.71103 | L10: {=SAFEDIV(J10,K10)} -> 1.0671711
B11: Industrial | C11: industrial | D11: =SUMIFS(tbl_Monthly[customers],tbl_Monthly[class],$C11,tbl_Monthly[month],DATE(PlanYear-1,12,1)) -> 4312 | E11: =SUMIFS(tbl_Monthly[customers],tbl_Monthly[class],$C11,tbl_Monthly[month],DATE(PlanYear-2,12,1)) -> 4196 | F11: {=SAFEDIV(D11,E11)} -> 1.0276454 | G11: =SUMIFS(tbl_Monthly[mwh],tbl_Monthly[class],$C11,tbl_Monthly[month],">="&DATE(PlanYear-1,1,1),tbl_Monthly[month],"<="&DATE(PlanYear-1,12,1)) -> 5975991.5 | H11: =SUMIFS(tbl_Monthly[mwh],tbl_Monthly[class],$C11,tbl_Monthly[month],">="&DATE(PlanYear-2,1,1),tbl_Monthly[month],"<="&DATE(PlanYear-2,12,1)) -> 5097435.2 | I11: {=SAFEDIV(G11,H11)} -> 1.1723526 | J11: {=SAFEDIV(SUMIFS(tbl_Monthly[revenue],tbl_Monthly[class],$C11,tbl_Monthly[month],">="&DATE(PlanYear-1,1,1),tbl_Monthly[month],"<="&DATE(PlanYear-1,12,1)),G11)} -> 92.690873 | K11: {=SAFEDIV(SUMIFS(tbl_Monthly[revenue],tbl_Monthly[class],$C11,tbl_Monthly[month],">="&DATE(PlanYear-2,1,1),tbl_Monthly[month],"<="&DATE(PlanYear-2,12,1)),H11)} -> 88.495192 | L11: {=SAFEDIV(J11,K11)} -> 1.0474114
B12: Transportation | C12: transportation | D12: =SUMIFS(tbl_Monthly[customers],tbl_Monthly[class],$C12,tbl_Monthly[month],DATE(PlanYear-1,12,1)) -> 1 | E12: =SUMIFS(tbl_Monthly[customers],tbl_Monthly[class],$C12,tbl_Monthly[month],DATE(PlanYear-2,12,1)) -> 1 | F12: {=SAFEDIV(D12,E12)} -> 1 | G12: =SUMIFS(tbl_Monthly[mwh],tbl_Monthly[class],$C12,tbl_Monthly[month],">="&DATE(PlanYear-1,1,1),tbl_Monthly[month],"<="&DATE(PlanYear-1,12,1)) -> 10916.789 | H12: =SUMIFS(tbl_Monthly[mwh],tbl_Monthly[class],$C12,tbl_Monthly[month],">="&DATE(PlanYear-2,1,1),tbl_Monthly[month],"<="&DATE(PlanYear-2,12,1)) -> 10201.48 | I12: {=SAFEDIV(G12,H12)} -> 1.0701182 | J12: {=SAFEDIV(SUMIFS(tbl_Monthly[revenue],tbl_Monthly[class],$C12,tbl_Monthly[month],">="&DATE(PlanYear-1,1,1),tbl_Monthly[month],"<="&DATE(PlanYear-1,12,1)),G12)} -> 128.28928 | K12: {=SAFEDIV(SUMIFS(tbl_Monthly[revenue],tbl_Monthly[class],$C12,tbl_Monthly[month],">="&DATE(PlanYear-2,1,1),tbl_Monthly[month],"<="&DATE(PlanYear-2,12,1)),H12)} -> 120.61691 | L12: {=SAFEDIV(J12,K12)} -> 1.0636094
B14: ="Weather model for the plan, fitted to Dec "&(PlanYear-1) -> Weather model for the plan, fitted to Dec 2025
B15: Class | C15: Key | D15: Intercept | E15: Per HDD | F15: Per CDD | G15: Trend per year | H15: R² | I15: Months
B16: Residential | C16: residential | D16: {=_xlfn.LET(_xlpm.s,LINEST(_xlfn._xlws.FILTER(Weather!$F$62:$F$181,(Weather!$B$62:$B$181<=AsOfMonth)*(YEAR(Weather!$B$62:$B$181)<PlanYear)*(Weather!$B$62:$B$181>=FitStart)),_xlfn.HSTACK(_xlfn._xlws.FILTER(Weather!$D$62:$D$181,(Weather!$B$62:$B$181<=AsOfMonth)*(YEAR(Weather!$B$62:$B$181)<PlanYear)*(Weather!$B$62:$B$181>=FitStart)),_xlfn._xlws.FILTER(Weather!$E$62:$E$181,(Weather!$B$62:$B$181<=AsOfMonth)*(YEAR(Weather!$B$62:$B$181)<PlanYear)*(Weather!$B$62:$B$181>=FitStart)),_xlfn._xlws.FILTER(Weather!$C$62:$C$181,(Weather!$B$62:$B$181<=AsOfMonth)*(YEAR(Weather!$B$62:$B$181)<PlanYear)*(Weather!$B$62:$B$181>=FitStart))),TRUE,TRUE),_xlfn.HSTACK(INDEX(_xlpm.s,1,4),INDEX(_xlpm.s,1,3),INDEX(_xlpm.s,1,2),INDEX(_xlpm.s,1,1),INDEX(_xlpm.s,3,1)))} -> 0.49596644 | E16: 0.00067761678 | F16: 0.0026779198 | G16: -0.0075184518 | H16: 0.83811812 | I16: {=ROWS(_xlfn._xlws.FILTER(Weather!$F$62:$F$181,(Weather!$B$62:$B$181<=AsOfMonth)*(YEAR(Weather!$B$62:$B$181)<PlanYear)*(Weather!$B$62:$B$181>=FitStart)))} -> 108
B17: Commercial | C17: commercial | D17: {=_xlfn.LET(_xlpm.s,LINEST(_xlfn._xlws.FILTER(Weather!$G$62:$G$181,(Weather!$B$62:$B$181<=AsOfMonth)*(YEAR(Weather!$B$62:$B$181)<PlanYear)*(Weather!$B$62:$B$181>=FitStart)),_xlfn.HSTACK(_xlfn._xlws.FILTER(Weather!$D$62:$D$181,(Weather!$B$62:$B$181<=AsOfMonth)*(YEAR(Weather!$B$62:$B$181)<PlanYear)*(Weather!$B$62:$B$181>=FitStart)),_xlfn._xlws.FILTER(Weather!$E$62:$E$181,(Weather!$B$62:$B$181<=AsOfMonth)*(YEAR(Weather!$B$62:$B$181)<PlanYear)*(Weather!$B$62:$B$181>=FitStart)),_xlfn._xlws.FILTER(Weather!$C$62:$C$181,(Weather!$B$62:$B$181<=AsOfMonth)*(YEAR(Weather!$B$62:$B$181)<PlanYear)*(Weather!$B$62:$B$181>=FitStart))),TRUE,TRUE),_xlfn.HSTACK(INDEX(_xlpm.s,1,4),INDEX(_xlpm.s,1,3),INDEX(_xlpm.s,1,2),INDEX(_xlpm.s,1,1),INDEX(_xlpm.s,3,1)))} -> 4.9058294 | E17: 0.00062824613 | F17: 0.0073712067 | G17: -0.065020003 | H17: 0.58282378 | I17: {=ROWS(_xlfn._xlws.FILTER(Weather!$G$62:$G$181,(Weather!$B$62:$B$181<=AsOfMonth)*(YEAR(Weather!$B$62:$B$181)<PlanYear)*(Weather!$B$62:$B$181>=FitStart)))} -> 108
B19: ="Normal weather for "&PlanYear&" ("&(PlanYear-NormalYears)&"–"&(PlanYear-1)&") and what happened" -> Normal weather for 2026 (2016–2025) and what happened
B20: Month | C20: =TEXT(DATE(2000,COLUMN()-2,1),"mmm") -> Jan | D20: =TEXT(DATE(2000,COLUMN()-2,1),"mmm") -> Feb | E20: =TEXT(DATE(2000,COLUMN()-2,1),"mmm") -> Mar | F20: =TEXT(DATE(2000,COLUMN()-2,1),"mmm") -> Apr | G20: =TEXT(DATE(2000,COLUMN()-2,1),"mmm") -> May | H20: =TEXT(DATE(2000,COLUMN()-2,1),"mmm") -> Jun | I20: =TEXT(DATE(2000,COLUMN()-2,1),"mmm") -> Jul | J20: =TEXT(DATE(2000,COLUMN()-2,1),"mmm") -> Aug | ... N20: =TEXT(DATE(2000,COLUMN()-2,1),"mmm") -> Dec
B21: Normal HDD | C21: {=AVERAGE(_xlfn._xlws.FILTER(tbl_Weather[hdd],(YEAR(tbl_Weather[month])>=PlanYear-NormalYears)*(YEAR(tbl_Weather[month])<PlanYear)*(MONTH(tbl_Weather[month])=COLUMN()-2)))} -> 748 | D21: {=AVERAGE(_xlfn._xlws.FILTER(tbl_Weather[hdd],(YEAR(tbl_Weather[month])>=PlanYear-NormalYears)*(YEAR(tbl_Weather[month])<PlanYear)*(MONTH(tbl_Weather[month])=COLUMN()-2)))} -> 679.3 | E21: {=AVERAGE(_xlfn._xlws.FILTER(tbl_Weather[hdd],(YEAR(tbl_Weather[month])>=PlanYear-NormalYears)*(YEAR(tbl_Weather[month])<PlanYear)*(MONTH(tbl_Weather[month])=COLUMN()-2)))} -> 640.8 | F21: {=AVERAGE(_xlfn._xlws.FILTER(tbl_Weather[hdd],(YEAR(tbl_Weather[month])>=PlanYear-NormalYears)*(YEAR(tbl_Weather[month])<PlanYear)*(MONTH(tbl_Weather[month])=COLUMN()-2)))} -> 467.4 | G21: {=AVERAGE(_xlfn._xlws.FILTER(tbl_Weather[hdd],(YEAR(tbl_Weather[month])>=PlanYear-NormalYears)*(YEAR(tbl_Weather[month])<PlanYear)*(MONTH(tbl_Weather[month])=COLUMN()-2)))} -> 287.4 | H21: {=AVERAGE(_xlfn._xlws.FILTER(tbl_Weather[hdd],(YEAR(tbl_Weather[month])>=PlanYear-NormalYears)*(YEAR(tbl_Weather[month])<PlanYear)*(MONTH(tbl_Weather[month])=COLUMN()-2)))} -> 129.5 | I21: {=AVERAGE(_xlfn._xlws.FILTER(tbl_Weather[hdd],(YEAR(tbl_Weather[month])>=PlanYear-NormalYears)*(YEAR(tbl_Weather[month])<PlanYear)*(MONTH(tbl_Weather[month])=COLUMN()-2)))} -> 32.6 | J21: {=AVERAGE(_xlfn._xlws.FILTER(tbl_Weather[hdd],(YEAR(tbl_Weather[month])>=PlanYear-NormalYears)*(YEAR(tbl_Weather[month])<PlanYear)*(MONTH(tbl_Weather[month])=COLUMN()-2)))} -> 22.4 | ... N21: {=AVERAGE(_xlfn._xlws.FILTER(tbl_Weather[hdd],(YEAR(tbl_Weather[month])>=PlanYear-NormalYears)*(YEAR(tbl_Weather[month])<PlanYear)*(MONTH(tbl_Weather[month])=COLUMN()-2)))} -> 753.3
B22: Normal CDD | C22: {=AVERAGE(_xlfn._xlws.FILTER(tbl_Weather[cdd],(YEAR(tbl_Weather[month])>=PlanYear-NormalYears)*(YEAR(tbl_Weather[month])<PlanYear)*(MONTH(tbl_Weather[month])=COLUMN()-2)))} -> 0 | D22: {=AVERAGE(_xlfn._xlws.FILTER(tbl_Weather[cdd],(YEAR(tbl_Weather[month])>=PlanYear-NormalYears)*(YEAR(tbl_Weather[month])<PlanYear)*(MONTH(tbl_Weather[month])=COLUMN()-2)))} -> 0 | E22: {=AVERAGE(_xlfn._xlws.FILTER(tbl_Weather[cdd],(YEAR(tbl_Weather[month])>=PlanYear-NormalYears)*(YEAR(tbl_Weather[month])<PlanYear)*(MONTH(tbl_Weather[month])=COLUMN()-2)))} -> 0 | F22: {=AVERAGE(_xlfn._xlws.FILTER(tbl_Weather[cdd],(YEAR(tbl_Weather[month])>=PlanYear-NormalYears)*(YEAR(tbl_Weather[month])<PlanYear)*(MONTH(tbl_Weather[month])=COLUMN()-2)))} -> 0 | G22: {=AVERAGE(_xlfn._xlws.FILTER(tbl_Weather[cdd],(YEAR(tbl_Weather[month])>=PlanYear-NormalYears)*(YEAR(tbl_Weather[month])<PlanYear)*(MONTH(tbl_Weather[month])=COLUMN()-2)))} -> 4.1 | H22: {=AVERAGE(_xlfn._xlws.FILTER(tbl_Weather[cdd],(YEAR(tbl_Weather[month])>=PlanYear-NormalYears)*(YEAR(tbl_Weather[month])<PlanYear)*(MONTH(tbl_Weather[month])=COLUMN()-2)))} -> 23.3 | I22: {=AVERAGE(_xlfn._xlws.FILTER(tbl_Weather[cdd],(YEAR(tbl_Weather[month])>=PlanYear-NormalYears)*(YEAR(tbl_Weather[month])<PlanYear)*(MONTH(tbl_Weather[month])=COLUMN()-2)))} -> 114.6 | J22: {=AVERAGE(_xlfn._xlws.FILTER(tbl_Weather[cdd],(YEAR(tbl_Weather[month])>=PlanYear-NormalYears)*(YEAR(tbl_Weather[month])<PlanYear)*(MONTH(tbl_Weather[month])=COLUMN()-2)))} -> 130.8 | ... N22: {=AVERAGE(_xlfn._xlws.FILTER(tbl_Weather[cdd],(YEAR(tbl_Weather[month])>=PlanYear-NormalYears)*(YEAR(tbl_Weather[month])<PlanYear)*(MONTH(tbl_Weather[month])=COLUMN()-2)))} -> 0
B23: Actual HDD | C23: =_xlfn.XLOOKUP(DATE(PlanYear,COLUMN()-2,1),tbl_Weather[month],tbl_Weather[hdd],"") -> 701 | D23: =_xlfn.XLOOKUP(DATE(PlanYear,COLUMN()-2,1),tbl_Weather[month],tbl_Weather[hdd],"") -> 599 | E23: =_xlfn.XLOOKUP(DATE(PlanYear,COLUMN()-2,1),tbl_Weather[month],tbl_Weather[hdd],"") -> 524 | F23: =_xlfn.XLOOKUP(DATE(PlanYear,COLUMN()-2,1),tbl_Weather[month],tbl_Weather[hdd],"") -> 408 | G23: =_xlfn.XLOOKUP(DATE(PlanYear,COLUMN()-2,1),tbl_Weather[month],tbl_Weather[hdd],"") -> 241 | H23: =_xlfn.XLOOKUP(DATE(PlanYear,COLUMN()-2,1),tbl_Weather[month],tbl_Weather[hdd],"") -> 109 | I23: =_xlfn.XLOOKUP(DATE(PlanYear,COLUMN()-2,1),tbl_Weather[month],tbl_Weather[hdd],"") -> 41 | J23: =_xlfn.XLOOKUP(DATE(PlanYear,COLUMN()-2,1),tbl_Weather[month],tbl_Weather[hdd],"") -> 27 | ... N23: =_xlfn.XLOOKUP(DATE(PlanYear,COLUMN()-2,1),tbl_Weather[month],tbl_Weather[hdd],"")
B24: Actual CDD | C24: =_xlfn.XLOOKUP(DATE(PlanYear,COLUMN()-2,1),tbl_Weather[month],tbl_Weather[cdd],"") -> 0 | D24: =_xlfn.XLOOKUP(DATE(PlanYear,COLUMN()-2,1),tbl_Weather[month],tbl_Weather[cdd],"") -> 0 | E24: =_xlfn.XLOOKUP(DATE(PlanYear,COLUMN()-2,1),tbl_Weather[month],tbl_Weather[cdd],"") -> 0 | F24: =_xlfn.XLOOKUP(DATE(PlanYear,COLUMN()-2,1),tbl_Weather[month],tbl_Weather[cdd],"") -> 0 | G24: =_xlfn.XLOOKUP(DATE(PlanYear,COLUMN()-2,1),tbl_Weather[month],tbl_Weather[cdd],"") -> 8 | H24: =_xlfn.XLOOKUP(DATE(PlanYear,COLUMN()-2,1),tbl_Weather[month],tbl_Weather[cdd],"") -> 28 | I24: =_xlfn.XLOOKUP(DATE(PlanYear,COLUMN()-2,1),tbl_Weather[month],tbl_Weather[cdd],"") -> 91 | J24: =_xlfn.XLOOKUP(DATE(PlanYear,COLUMN()-2,1),tbl_Weather[month],tbl_Weather[cdd],"") -> 111 | ... N24: =_xlfn.XLOOKUP(DATE(PlanYear,COLUMN()-2,1),tbl_Weather[month],tbl_Weather[cdd],"")
B26: Plan and actual, month by class
B27: Month | C27: Class | D27: Has actuals | E27: Plan customers | F27: Model MWh per customer | G27: Plan MWh | H27: Plan MWh per customer | I27: Plan $/MWh | J27: Plan revenue | K27: Actual customers | L27: Actual MWh | M27: Actual revenue | N27: Actual $/MWh | O27: Weather effect per customer | P27: Customers | Q27: Weather | R27: Usage | S27: Price | T27: Check
B28: =DATE(PlanYear,MOD(ROWS($B$28:B28)-1,12)+1,1) -> 46023 | C28: residential | D28: =MONTH($B28)<=PlanClosed -> TRUE | E28: =_xlfn.XLOOKUP($C28,$C$9:$C$12,$D$9:$D$12)*_xlfn.XLOOKUP($C28,$C$9:$C$12,$F$9:$F$12)^(MONTH($B28)/12) -> 845083.44 | F28: {=IF(_xlfn.XLOOKUP($C28,tbl_Class[class],tbl_Class[weather_model])="yes",_xlfn.XLOOKUP($C28,$C$16:$C$17,$D$16:$D$17)+_xlfn.XLOOKUP($C28,$C$16:$C$17,$E$16:$E$17)*INDEX($C$21:$N$21,MONTH($B28))+_xlfn.XLOOKUP($C28,$C$16:$C$17,$F$16:$F$17)*INDEX($C$22:$N$22,MONTH($B28))+_xlfn.XLOOKUP($C28,$C$16:$C$17,$G$16:$G$17)*TRENDYEARS($B28),"")} -> 0.93515772 | G28: =IF(_xlfn.XLOOKUP($C28,tbl_Class[class],tbl_Class[weather_model])="yes",E28*F28,SUMIFS(tbl_Monthly[mwh],tbl_Monthly[class],$C28,tbl_Monthly[month],EDATE($B28,-12))*_xlfn.XLOOKUP($C28,$C$9:$C$12,$I$9:$I$12)) -> 790286.31 | H28: {=SAFEDIV(G28,E28)} -> 0.93515772 | I28: {=SAFEDIV(SUMIFS(tbl_Monthly[revenue],tbl_Monthly[class],$C28,tbl_Monthly[month],EDATE($B28,-12)),SUMIFS(tbl_Monthly[mwh],tbl_Monthly[class],$C28,tbl_Monthly[month],EDATE($B28,-12)))*_xlfn.XLOOKUP($C28,$C$9:$C$12,$L$9:$L$12)} -> 188.2844 | J28: =G28*I28 -> 1.4879859e+08 | K28: =IF($D28,SUMIFS(tbl_Monthly[customers],tbl_Monthly[class],$C28,tbl_Monthly[month],$B28),"") -> 845079 | L28: =IF($D28,SUMIFS(tbl_Monthly[mwh],tbl_Monthly[class],$C28,tbl_Monthly[month],$B28),"") -> 801286.41 | M28: =IF($D28,SUMIFS(tbl_Monthly[revenue],tbl_Monthly[class],$C28,tbl_Monthly[month],$B28),"") -> 144314450 | N28: {=IF($D28,SAFEDIV(M28,L28),"")} -> 180.10345 | O28: {=IF(AND($D28,_xlfn.XLOOKUP($C28,tbl_Class[class],tbl_Class[weather_model])="yes"),_xlfn.XLOOKUP($C28,$C$16:$C$17,$E$16:$E$17)*(INDEX($C$23:$N$23,MONTH($B28))-INDEX($C$21:$N$21,MONTH($B28)))+_xlfn.XLOOKUP($C28,$C$16:$C$17,$F$16:$F$17)*(INDEX($C$24:$N$24,MONTH($B28))-INDEX($C$22:$N$22,MONTH($B28))),IF($D28,0,""))} -> -0.031847988 | P28: =IF($D28,IF(_xlfn.XLOOKUP($C28,tbl_Class[class],tbl_Class[weather_model])="yes",(K28-E28)*H28*I28,0),"") -> -782.27314 | Q28: =IF($D28,IF(_xlfn.XLOOKUP($C28,tbl_Class[class],tbl_Class[weather_model])="yes",K28*O28*I28,0),"") -> -5067498.9 | R28: {=IF($D28,IF(_xlfn.XLOOKUP($C28,tbl_Class[class],tbl_Class[weather_model])="yes",K28*(SAFEDIV(L28,K28)-H28-O28)*I28,(L28-G28)*I28),"")} -> 7139429 | S28: =IF($D28,L28*(N28-I28),"") -> -6555283.9 | T28: =IF($D28,P28+Q28+R28+S28-(M28-J28),"") -> -1.1175871e-08
B29: =DATE(PlanYear,MOD(ROWS($B$28:B29)-1,12)+1,1) -> 46054 | C29: residential | D29: =MONTH($B29)<=PlanClosed -> TRUE | E29: =_xlfn.XLOOKUP($C29,$C$9:$C$12,$D$9:$D$12)*_xlfn.XLOOKUP($C29,$C$9:$C$12,$F$9:$F$12)^(MONTH($B29)/12) -> 845859.6 | F29: {=IF(_xlfn.XLOOKUP($C29,tbl_Class[class],tbl_Class[weather_model])="yes",_xlfn.XLOOKUP($C29,$C$16:$C$17,$D$16:$D$17)+_xlfn.XLOOKUP($C29,$C$16:$C$17,$E$16:$E$17)*INDEX($C$21:$N$21,MONTH($B29))+_xlfn.XLOOKUP($C29,$C$16:$C$17,$F$16:$F$17)*INDEX($C$22:$N$22,MONTH($B29))+_xlfn.XLOOKUP($C29,$C$16:$C$17,$G$16:$G$17)*TRENDYEARS($B29),"")} -> 0.88797891 | G29: =IF(_xlfn.XLOOKUP($C29,tbl_Class[class],tbl_Class[weather_model])="yes",E29*F29,SUMIFS(tbl_Monthly[mwh],tbl_Monthly[class],$C29,tbl_Monthly[month],EDATE($B29,-12))*_xlfn.XLOOKUP($C29,$C$9:$C$12,$I$9:$I$12)) -> 751105.49 | H29: {=SAFEDIV(G29,E29)} -> 0.88797891 | I29: {=SAFEDIV(SUMIFS(tbl_Monthly[revenue],tbl_Monthly[class],$C29,tbl_Monthly[month],EDATE($B29,-12)),SUMIFS(tbl_Monthly[mwh],tbl_Monthly[class],$C29,tbl_Monthly[month],EDATE($B29,-12)))*_xlfn.XLOOKUP($C29,$C$9:$C$12,$L$9:$L$12)} -> 191.84683 | J29: =G29*I29 -> 1.4409721e+08 | K29: =IF($D29,SUMIFS(tbl_Monthly[customers],tbl_Monthly[class],$C29,tbl_Monthly[month],$B29),"") -> 845421 | L29: =IF($D29,SUMIFS(tbl_Monthly[mwh],tbl_Monthly[class],$C29,tbl_Monthly[month],$B29),"") -> 658313.46 | M29: =IF($D29,SUMIFS(tbl_Monthly[revenue],tbl_Monthly[class],$C29,tbl_Monthly[month],$B29),"") -> 119434821 | N29: {=IF($D29,SAFEDIV(M29,L29),"")} -> 181.42546 | O29: {=IF(AND($D29,_xlfn.XLOOKUP($C29,tbl_Class[class],tbl_Class[weather_model])="yes"),_xlfn.XLOOKUP($C29,$C$16:$C$17,$E$16:$E$17)*(INDEX($C$23:$N$23,MONTH($B29))-INDEX($C$21:$N$21,MONTH($B29)))+_xlfn.XLOOKUP($C29,$C$16:$C$17,$F$16:$F$17)*(INDEX($C$24:$N$24,MONTH($B29))-INDEX($C$22:$N$22,MONTH($B29))),IF($D29,0,""))} -> -0.054412627 | P29: =IF($D29,IF(_xlfn.XLOOKUP($C29,tbl_Class[class],tbl_Class[weather_model])="yes",(K29-E29)*H29*I29,0),"") -> -74717.748 | Q29: =IF($D29,IF(_xlfn.XLOOKUP($C29,tbl_Class[class],tbl_Class[weather_model])="yes",K29*O29*I29,0),"") -> -8825256.9 | R29: {=IF($D29,IF(_xlfn.XLOOKUP($C29,tbl_Class[class],tbl_Class[weather_model])="yes",K29*(SAFEDIV(L29,K29)-H29-O29)*I29,(L29-G29)*I29),"")} -> -8901880.9 | S29: =IF($D29,L29*(N29-I29),"") -> -6860530.3 | T29: =IF($D29,P29+Q29+R29+S29-(M29-J29),"") -> 2.2351742e-08
B30: =DATE(PlanYear,MOD(ROWS($B$28:B30)-1,12)+1,1) -> 46082 | C30: residential | D30: =MONTH($B30)<=PlanClosed -> TRUE | E30: =_xlfn.XLOOKUP($C30,$C$9:$C$12,$D$9:$D$12)*_xlfn.XLOOKUP($C30,$C$9:$C$12,$F$9:$F$12)^(MONTH($B30)/12) -> 846636.47 | F30: {=IF(_xlfn.XLOOKUP($C30,tbl_Class[class],tbl_Class[weather_model])="yes",_xlfn.XLOOKUP($C30,$C$16:$C$17,$D$16:$D$17)+_xlfn.XLOOKUP($C30,$C$16:$C$17,$E$16:$E$17)*INDEX($C$21:$N$21,MONTH($B30))+_xlfn.XLOOKUP($C30,$C$16:$C$17,$F$16:$F$17)*INDEX($C$22:$N$22,MONTH($B30))+_xlfn.XLOOKUP($C30,$C$16:$C$17,$G$16:$G$17)*TRENDYEARS($B30),"")} -> 0.86126413 | G30: =IF(_xlfn.XLOOKUP($C30,tbl_Class[class],tbl_Class[weather_model])="yes",E30*F30,SUMIFS(tbl_Monthly[mwh],tbl_Monthly[class],$C30,tbl_Monthly[month],EDATE($B30,-12))*_xlfn.XLOOKUP($C30,$C$9:$C$12,$I$9:$I$12)) -> 729177.62 | H30: {=SAFEDIV(G30,E30)} -> 0.86126413 | I30: {=SAFEDIV(SUMIFS(tbl_Monthly[revenue],tbl_Monthly[class],$C30,tbl_Monthly[month],EDATE($B30,-12)),SUMIFS(tbl_Monthly[mwh],tbl_Monthly[class],$C30,tbl_Monthly[month],EDATE($B30,-12)))*_xlfn.XLOOKUP($C30,$C$9:$C$12,$L$9:$L$12)} -> 195.80519 | J30: =G30*I30 -> 1.4277676e+08 | K30: =IF($D30,SUMIFS(tbl_Monthly[customers],tbl_Monthly[class],$C30,tbl_Monthly[month],$B30),"") -> 845954 | L30: =IF($D30,SUMIFS(tbl_Monthly[mwh],tbl_Monthly[class],$C30,tbl_Monthly[month],$B30),"") -> 626969.58 | M30: =IF($D30,SUMIFS(tbl_Monthly[revenue],tbl_Monthly[class],$C30,tbl_Monthly[month],$B30),"") -> 113584646 | N30: {=IF($D30,SAFEDIV(M30,L30),"")} -> 181.16453 | O30: {=IF(AND($D30,_xlfn.XLOOKUP($C30,tbl_Class[class],tbl_Class[weather_model])="yes"),_xlfn.XLOOKUP($C30,$C$16:$C$17,$E$16:$E$17)*(INDEX($C$23:$N$23,MONTH($B30))-INDEX($C$21:$N$21,MONTH($B30)))+_xlfn.XLOOKUP($C30,$C$16:$C$17,$F$16:$F$17)*(INDEX($C$24:$N$24,MONTH($B30))-INDEX($C$22:$N$22,MONTH($B30))),IF($D30,0,""))} -> -0.079145639 | P30: =IF($D30,IF(_xlfn.XLOOKUP($C30,tbl_Class[class],tbl_Class[weather_model])="yes",(K30-E30)*H30*I30,0),"") -> -115091.01 | Q30: =IF($D30,IF(_xlfn.XLOOKUP($C30,tbl_Class[class],tbl_Class[weather_model])="yes",K30*O30*I30,0),"") -> -13109857 | R30: {=IF($D30,IF(_xlfn.XLOOKUP($C30,tbl_Class[class],tbl_Class[weather_model])="yes",K30*(SAFEDIV(L30,K30)-H30-O30)*I30,(L30-G30)*I30),"")} -> -6787917.3 | S30: =IF($D30,L30*(N30-I30),"") -> -9179252.8 | T30: =IF($D30,P30+Q30+R30+S30-(M30-J30),"") -> 7.4505806e-09
B31: =DATE(PlanYear,MOD(ROWS($B$28:B31)-1,12)+1,1) -> 46113 | C31: residential | D31: =MONTH($B31)<=PlanClosed -> TRUE | E31: =_xlfn.XLOOKUP($C31,$C$9:$C$12,$D$9:$D$12)*_xlfn.XLOOKUP($C31,$C$9:$C$12,$F$9:$F$12)^(MONTH($B31)/12) -> 847414.05 | F31: {=IF(_xlfn.XLOOKUP($C31,tbl_Class[class],tbl_Class[weather_model])="yes",_xlfn.XLOOKUP($C31,$C$16:$C$17,$D$16:$D$17)+_xlfn.XLOOKUP($C31,$C$16:$C$17,$E$16:$E$17)*INDEX($C$21:$N$21,MONTH($B31))+_xlfn.XLOOKUP($C31,$C$16:$C$17,$F$16:$F$17)*INDEX($C$22:$N$22,MONTH($B31))+_xlfn.XLOOKUP($C31,$C$16:$C$17,$G$16:$G$17)*TRENDYEARS($B31),"")} -> 0.74313884 | G31: =IF(_xlfn.XLOOKUP($C31,tbl_Class[class],tbl_Class[weather_model])="yes",E31*F31,SUMIFS(tbl_Monthly[mwh],tbl_Monthly[class],$C31,tbl_Monthly[month],EDATE($B31,-12))*_xlfn.XLOOKUP($C31,$C$9:$C$12,$I$9:$I$12)) -> 629746.3 | H31: {=SAFEDIV(G31,E31)} -> 0.74313884 | I31: {=SAFEDIV(SUMIFS(tbl_Monthly[revenue],tbl_Monthly[class],$C31,tbl_Monthly[month],EDATE($B31,-12)),SUMIFS(tbl_Monthly[mwh],tbl_Monthly[class],$C31,tbl_Monthly[month],EDATE($B31,-12)))*_xlfn.XLOOKUP($C31,$C$9:$C$12,$L$9:$L$12)} -> 195.96715 | J31: =G31*I31 -> 1.2340958e+08 | K31: =IF($D31,SUMIFS(tbl_Monthly[customers],tbl_Monthly[class],$C31,tbl_Monthly[month],$B31),"") -> 846300 | L31: =IF($D31,SUMIFS(tbl_Monthly[mwh],tbl_Monthly[class],$C31,tbl_Monthly[month],$B31),"") -> 529952.38 | M31: =IF($D31,SUMIFS(tbl_Monthly[revenue],tbl_Monthly[class],$C31,tbl_Monthly[month],$B31),"") -> 105039094 | N31: {=IF($D31,SAFEDIV(M31,L31),"")} -> 198.20478 | O31: {=IF(AND($D31,_xlfn.XLOOKUP($C31,tbl_Class[class],tbl_Class[weather_model])="yes"),_xlfn.XLOOKUP($C31,$C$16:$C$17,$E$16:$E$17)*(INDEX($C$23:$N$23,MONTH($B31))-INDEX($C$21:$N$21,MONTH($B31)))+_xlfn.XLOOKUP($C31,$C$16:$C$17,$F$16:$F$17)*(INDEX($C$24:$N$24,MONTH($B31))-INDEX($C$22:$N$22,MONTH($B31))),IF($D31,0,""))} -> -0.040250437 | P31: =IF($D31,IF(_xlfn.XLOOKUP($C31,tbl_Class[class],tbl_Class[weather_model])="yes",(K31-E31)*H31*I31,0),"") -> -162239.57 | Q31: =IF($D31,IF(_xlfn.XLOOKUP($C31,tbl_Class[class],tbl_Class[weather_model])="yes",K31*O31*I31,0),"") -> -6675414 | R31: {=IF($D31,IF(_xlfn.XLOOKUP($C31,tbl_Class[class],tbl_Class[weather_model])="yes",K31*(SAFEDIV(L31,K31)-H31-O31)*I31,(L31-G31)*I31),"")} -> -12718676 | S31: =IF($D31,L31*(N31-I31),"") -> 1185839.2 | T31: =IF($D31,P31+Q31+R31+S31-(M31-J31),"") -> -2.2351742e-08
B32: =DATE(PlanYear,MOD(ROWS($B$28:B32)-1,12)+1,1) -> 46143 | C32: residential | D32: =MONTH($B32)<=PlanClosed -> TRUE | E32: =_xlfn.XLOOKUP($C32,$C$9:$C$12,$D$9:$D$12)*_xlfn.XLOOKUP($C32,$C$9:$C$12,$F$9:$F$12)^(MONTH($B32)/12) -> 848192.34 | F32: {=IF(_xlfn.XLOOKUP($C32,tbl_Class[class],tbl_Class[weather_model])="yes",_xlfn.XLOOKUP($C32,$C$16:$C$17,$D$16:$D$17)+_xlfn.XLOOKUP($C32,$C$16:$C$17,$E$16:$E$17)*INDEX($C$21:$N$21,MONTH($B32))+_xlfn.XLOOKUP($C32,$C$16:$C$17,$F$16:$F$17)*INDEX($C$22:$N$22,MONTH($B32))+_xlfn.XLOOKUP($C32,$C$16:$C$17,$G$16:$G$17)*TRENDYEARS($B32),"")} -> 0.63152076 | G32: =IF(_xlfn.XLOOKUP($C32,tbl_Class[class],tbl_Class[weather_model])="yes",E32*F32,SUMIFS(tbl_Monthly[mwh],tbl_Monthly[class],$C32,tbl_Monthly[month],EDATE($B32,-12))*_xlfn.XLOOKUP($C32,$C$9:$C$12,$I$9:$I$12)) -> 535651.07 | H32: {=SAFEDIV(G32,E32)} -> 0.63152076 | I32: {=SAFEDIV(SUMIFS(tbl_Monthly[revenue],tbl_Monthly[class],$C32,tbl_Monthly[month],EDATE($B32,-12)),SUMIFS(tbl_Monthly[mwh],tbl_Monthly[class],$C32,tbl_Monthly[month],EDATE($B32,-12)))*_xlfn.XLOOKUP($C32,$C$9:$C$12,$L$9:$L$12)} -> 198.82101 | J32: =G32*I32 -> 1.0649869e+08 | K32: =IF($D32,SUMIFS(tbl_Monthly[customers],tbl_Monthly[class],$C32,tbl_Monthly[month],$B32),"") -> 846323 | L32: =IF($D32,SUMIFS(tbl_Monthly[mwh],tbl_Monthly[class],$C32,tbl_Monthly[month],$B32),"") -> 504999.75 | M32: =IF($D32,SUMIFS(tbl_Monthly[revenue],tbl_Monthly[class],$C32,tbl_Monthly[month],$B32),"") -> 101981458 | N32: {=IF($D32,SAFEDIV(M32,L32),"")} -> 201.94358 | O32: {=IF(AND($D32,_xlfn.XLOOKUP($C32,tbl_Class[class],tbl_Class[weather_model])="yes"),_xlfn.XLOOKUP($C32,$C$16:$C$17,$E$16:$E$17)*(INDEX($C$23:$N$23,MONTH($B32))-INDEX($C$21:$N$21,MONTH($B32)))+_xlfn.XLOOKUP($C32,$C$16:$C$17,$F$16:$F$17)*(INDEX($C$24:$N$24,MONTH($B32))-INDEX($C$22:$N$22,MONTH($B32))),IF($D32,0,""))} -> -0.020997531 | P32: =IF($D32,IF(_xlfn.XLOOKUP($C32,tbl_Class[class],tbl_Class[weather_model])="yes",(K32-E32)*H32*I32,0),"") -> -234713.9 | Q32: =IF($D32,IF(_xlfn.XLOOKUP($C32,tbl_Class[class],tbl_Class[weather_model])="yes",K32*O32*I32,0),"") -> -3533187.3 | R32: {=IF($D32,IF(_xlfn.XLOOKUP($C32,tbl_Class[class],tbl_Class[weather_model])="yes",K32*(SAFEDIV(L32,K32)-H32-O32)*I32,(L32-G32)*I32),"")} -> -2326225.2 | S32: =IF($D32,L32*(N32-I32),"") -> 1576897.4 | T32: =IF($D32,P32+Q32+R32+S32-(M32-J32),"") -> -3.7252903e-09
B33: =DATE(PlanYear,MOD(ROWS($B$28:B33)-1,12)+1,1) -> 46174 | C33: residential | D33: =MONTH($B33)<=PlanClosed -> TRUE | E33: =_xlfn.XLOOKUP($C33,$C$9:$C$12,$D$9:$D$12)*_xlfn.XLOOKUP($C33,$C$9:$C$12,$F$9:$F$12)^(MONTH($B33)/12) -> 848971.35 | F33: {=IF(_xlfn.XLOOKUP($C33,tbl_Class[class],tbl_Class[weather_model])="yes",_xlfn.XLOOKUP($C33,$C$16:$C$17,$D$16:$D$17)+_xlfn.XLOOKUP($C33,$C$16:$C$17,$E$16:$E$17)*INDEX($C$21:$N$21,MONTH($B33))+_xlfn.XLOOKUP($C33,$C$16:$C$17,$F$16:$F$17)*INDEX($C$22:$N$22,MONTH($B33))+_xlfn.XLOOKUP($C33,$C$16:$C$17,$G$16:$G$17)*TRENDYEARS($B33),"")} -> 0.57531459 | G33: =IF(_xlfn.XLOOKUP($C33,tbl_Class[class],tbl_Class[weather_model])="yes",E33*F33,SUMIFS(tbl_Monthly[mwh],tbl_Monthly[class],$C33,tbl_Monthly[month],EDATE($B33,-12))*_xlfn.XLOOKUP($C33,$C$9:$C$12,$I$9:$I$12)) -> 488425.61 | H33: {=SAFEDIV(G33,E33)} -> 0.57531459 | I33: {=SAFEDIV(SUMIFS(tbl_Monthly[revenue],tbl_Monthly[class],$C33,tbl_Monthly[month],EDATE($B33,-12)),SUMIFS(tbl_Monthly[mwh],tbl_Monthly[class],$C33,tbl_Monthly[month],EDATE($B33,-12)))*_xlfn.XLOOKUP($C33,$C$9:$C$12,$L$9:$L$12)} -> 195.8711 | J33: =G33*I33 -> 95668459 | K33: =IF($D33,SUMIFS(tbl_Monthly[customers],tbl_Monthly[class],$C33,tbl_Monthly[month],$B33),"") -> 846477 | L33: =IF($D33,SUMIFS(tbl_Monthly[mwh],tbl_Monthly[class],$C33,tbl_Monthly[month],$B33),"") -> 556176.63 | M33: =IF($D33,SUMIFS(tbl_Monthly[revenue],tbl_Monthly[class],$C33,tbl_Monthly[month],$B33),"") -> 110790293 | N33: {=IF($D33,SAFEDIV(M33,L33),"")} -> 199.19983 | O33: {=IF(AND($D33,_xlfn.XLOOKUP($C33,tbl_Class[class],tbl_Class[weather_model])="yes"),_xlfn.XLOOKUP($C33,$C$16:$C$17,$E$16:$E$17)*(INDEX($C$23:$N$23,MONTH($B33))-INDEX($C$21:$N$21,MONTH($B33)))+_xlfn.XLOOKUP($C33,$C$16:$C$17,$F$16:$F$17)*(INDEX($C$24:$N$24,MONTH($B33))-INDEX($C$22:$N$22,MONTH($B33))),IF($D33,0,""))} -> -0.0013049211 | P33: =IF($D33,IF(_xlfn.XLOOKUP($C33,tbl_Class[class],tbl_Class[weather_model])="yes",(K33-E33)*H33*I33,0),"") -> -281082.4 | Q33: =IF($D33,IF(_xlfn.XLOOKUP($C33,tbl_Class[class],tbl_Class[weather_model])="yes",K33*O33*I33,0),"") -> -216356.41 | R33: {=IF($D33,IF(_xlfn.XLOOKUP($C33,tbl_Class[class],tbl_Class[weather_model])="yes",K33*(SAFEDIV(L33,K33)-H33-O33)*I33,(L33-G33)*I33),"")} -> 13767907 | S33: =IF($D33,L33*(N33-I33),"") -> 1851365.6 | T33: =IF($D33,P33+Q33+R33+S33-(M33-J33),"") -> -7.4505806e-09
B34: =DATE(PlanYear,MOD(ROWS($B$28:B34)-1,12)+1,1) -> 46204 | C34: residential | D34: =MONTH($B34)<=PlanClosed -> FALSE | E34: =_xlfn.XLOOKUP($C34,$C$9:$C$12,$D$9:$D$12)*_xlfn.XLOOKUP($C34,$C$9:$C$12,$F$9:$F$12)^(MONTH($B34)/12) -> 849751.08 | F34: {=IF(_xlfn.XLOOKUP($C34,tbl_Class[class],tbl_Class[weather_model])="yes",_xlfn.XLOOKUP($C34,$C$16:$C$17,$D$16:$D$17)+_xlfn.XLOOKUP($C34,$C$16:$C$17,$E$16:$E$17)*INDEX($C$21:$N$21,MONTH($B34))+_xlfn.XLOOKUP($C34,$C$16:$C$17,$F$16:$F$17)*INDEX($C$22:$N$22,MONTH($B34))+_xlfn.XLOOKUP($C34,$C$16:$C$17,$G$16:$G$17)*TRENDYEARS($B34),"")} -> 0.75352106 | G34: =IF(_xlfn.XLOOKUP($C34,tbl_Class[class],tbl_Class[weather_model])="yes",E34*F34,SUMIFS(tbl_Monthly[mwh],tbl_Monthly[class],$C34,tbl_Monthly[month],EDATE($B34,-12))*_xlfn.XLOOKUP($C34,$C$9:$C$12,$I$9:$I$12)) -> 640305.33 | H34: {=SAFEDIV(G34,E34)} -> 0.75352106 | I34: {=SAFEDIV(SUMIFS(tbl_Monthly[revenue],tbl_Monthly[class],$C34,tbl_Monthly[month],EDATE($B34,-12)),SUMIFS(tbl_Monthly[mwh],tbl_Monthly[class],$C34,tbl_Monthly[month],EDATE($B34,-12)))*_xlfn.XLOOKUP($C34,$C$9:$C$12,$L$9:$L$12)} -> 192.19702 | J34: =G34*I34 -> 1.2306478e+08 | K34: =IF($D34,SUMIFS(tbl_Monthly[customers],tbl_Monthly[class],$C34,tbl_Monthly[month],$B34),"") | L34: =IF($D34,SUMIFS(tbl_Monthly[mwh],tbl_Monthly[class],$C34,tbl_Monthly[month],$B34),"") | M34: =IF($D34,SUMIFS(tbl_Monthly[revenue],tbl_Monthly[class],$C34,tbl_Monthly[month],$B34),"") | N34: {=IF($D34,SAFEDIV(M34,L34),"")} | O34: {=IF(AND($D34,_xlfn.XLOOKUP($C34,tbl_Class[class],tbl_Class[weather_model])="yes"),_xlfn.XLOOKUP($C34,$C$16:$C$17,$E$16:$E$17)*(INDEX($C$23:$N$23,MONTH($B34))-INDEX($C$21:$N$21,MONTH($B34)))+_xlfn.XLOOKUP($C34,$C$16:$C$17,$F$16:$F$17)*(INDEX($C$24:$N$24,MONTH($B34))-INDEX($C$22:$N$22,MONTH($B34))),IF($D34,0,""))} | P34: =IF($D34,IF(_xlfn.XLOOKUP($C34,tbl_Class[class],tbl_Class[weather_model])="yes",(K34-E34)*H34*I34,0),"") | Q34: =IF($D34,IF(_xlfn.XLOOKUP($C34,tbl_Class[class],tbl_Class[weather_model])="yes",K34*O34*I34,0),"") | R34: {=IF($D34,IF(_xlfn.XLOOKUP($C34,tbl_Class[class],tbl_Class[weather_model])="yes",K34*(SAFEDIV(L34,K34)-H34-O34)*I34,(L34-G34)*I34),"")} | S34: =IF($D34,L34*(N34-I34),"") | T34: =IF($D34,P34+Q34+R34+S34-(M34-J34),"")
B35: =DATE(PlanYear,MOD(ROWS($B$28:B35)-1,12)+1,1) -> 46235 | C35: residential | D35: =MONTH($B35)<=PlanClosed -> FALSE | E35: =_xlfn.XLOOKUP($C35,$C$9:$C$12,$D$9:$D$12)*_xlfn.XLOOKUP($C35,$C$9:$C$12,$F$9:$F$12)^(MONTH($B35)/12) -> 850531.52 | F35: {=IF(_xlfn.XLOOKUP($C35,tbl_Class[class],tbl_Class[weather_model])="yes",_xlfn.XLOOKUP($C35,$C$16:$C$17,$D$16:$D$17)+_xlfn.XLOOKUP($C35,$C$16:$C$17,$E$16:$E$17)*INDEX($C$21:$N$21,MONTH($B35))+_xlfn.XLOOKUP($C35,$C$16:$C$17,$F$16:$F$17)*INDEX($C$22:$N$22,MONTH($B35))+_xlfn.XLOOKUP($C35,$C$16:$C$17,$G$16:$G$17)*TRENDYEARS($B35),"")} -> 0.78936513 | G35: =IF(_xlfn.XLOOKUP($C35,tbl_Class[class],tbl_Class[weather_model])="yes",E35*F35,SUMIFS(tbl_Monthly[mwh],tbl_Monthly[class],$C35,tbl_Monthly[month],EDATE($B35,-12))*_xlfn.XLOOKUP($C35,$C$9:$C$12,$I$9:$I$12)) -> 671379.93 | H35: {=SAFEDIV(G35,E35)} -> 0.78936513 | I35: {=SAFEDIV(SUMIFS(tbl_Monthly[revenue],tbl_Monthly[class],$C35,tbl_Monthly[month],EDATE($B35,-12)),SUMIFS(tbl_Monthly[mwh],tbl_Monthly[class],$C35,tbl_Monthly[month],EDATE($B35,-12)))*_xlfn.XLOOKUP($C35,$C$9:$C$12,$L$9:$L$12)} -> 193.36354 | J35: =G35*I35 -> 1.298204e+08 | K35: =IF($D35,SUMIFS(tbl_Monthly[customers],tbl_Monthly[class],$C35,tbl_Monthly[month],$B35),"") | L35: =IF($D35,SUMIFS(tbl_Monthly[mwh],tbl_Monthly[class],$C35,tbl_Monthly[month],$B35),"") | M35: =IF($D35,SUMIFS(tbl_Monthly[revenue],tbl_Monthly[class],$C35,tbl_Monthly[month],$B35),"") | N35: {=IF($D35,SAFEDIV(M35,L35),"")} | O35: {=IF(AND($D35,_xlfn.XLOOKUP($C35,tbl_Class[class],tbl_Class[weather_model])="yes"),_xlfn.XLOOKUP($C35,$C$16:$C$17,$E$16:$E$17)*(INDEX($C$23:$N$23,MONTH($B35))-INDEX($C$21:$N$21,MONTH($B35)))+_xlfn.XLOOKUP($C35,$C$16:$C$17,$F$16:$F$17)*(INDEX($C$24:$N$24,MONTH($B35))-INDEX($C$22:$N$22,MONTH($B35))),IF($D35,0,""))} | P35: =IF($D35,IF(_xlfn.XLOOKUP($C35,tbl_Class[class],tbl_Class[weather_model])="yes",(K35-E35)*H35*I35,0),"") | Q35: =IF($D35,IF(_xlfn.XLOOKUP($C35,tbl_Class[class],tbl_Class[weather_model])="yes",K35*O35*I35,0),"") | R35: {=IF($D35,IF(_xlfn.XLOOKUP($C35,tbl_Class[class],tbl_Class[weather_model])="yes",K35*(SAFEDIV(L35,K35)-H35-O35)*I35,(L35-G35)*I35),"")} | S35: =IF($D35,L35*(N35-I35),"") | T35: =IF($D35,P35+Q35+R35+S35-(M35-J35),"")
B36: =DATE(PlanYear,MOD(ROWS($B$28:B36)-1,12)+1,1) -> 46266 | C36: residential | D36: =MONTH($B36)<=PlanClosed -> FALSE | E36: =_xlfn.XLOOKUP($C36,$C$9:$C$12,$D$9:$D$12)*_xlfn.XLOOKUP($C36,$C$9:$C$12,$F$9:$F$12)^(MONTH($B36)/12) -> 851312.68 | F36: {=IF(_xlfn.XLOOKUP($C36,tbl_Class[class],tbl_Class[weather_model])="yes",_xlfn.XLOOKUP($C36,$C$16:$C$17,$D$16:$D$17)+_xlfn.XLOOKUP($C36,$C$16:$C$17,$E$16:$E$17)*INDEX($C$21:$N$21,MONTH($B36))+_xlfn.XLOOKUP($C36,$C$16:$C$17,$F$16:$F$17)*INDEX($C$22:$N$22,MONTH($B36))+_xlfn.XLOOKUP($C36,$C$16:$C$17,$G$16:$G$17)*TRENDYEARS($B36),"")} -> 0.59850653 | G36: =IF(_xlfn.XLOOKUP($C36,tbl_Class[class],tbl_Class[weather_model])="yes",E36*F36,SUMIFS(tbl_Monthly[mwh],tbl_Monthly[class],$C36,tbl_Monthly[month],EDATE($B36,-12))*_xlfn.XLOOKUP($C36,$C$9:$C$12,$I$9:$I$12)) -> 509516.19 | H36: {=SAFEDIV(G36,E36)} -> 0.59850653 | I36: {=SAFEDIV(SUMIFS(tbl_Monthly[revenue],tbl_Monthly[class],$C36,tbl_Monthly[month],EDATE($B36,-12)),SUMIFS(tbl_Monthly[mwh],tbl_Monthly[class],$C36,tbl_Monthly[month],EDATE($B36,-12)))*_xlfn.XLOOKUP($C36,$C$9:$C$12,$L$9:$L$12)} -> 198.2253 | J36: =G36*I36 -> 1.00999e+08 | K36: =IF($D36,SUMIFS(tbl_Monthly[customers],tbl_Monthly[class],$C36,tbl_Monthly[month],$B36),"") | L36: =IF($D36,SUMIFS(tbl_Monthly[mwh],tbl_Monthly[class],$C36,tbl_Monthly[month],$B36),"") | M36: =IF($D36,SUMIFS(tbl_Monthly[revenue],tbl_Monthly[class],$C36,tbl_Monthly[month],$B36),"") | N36: {=IF($D36,SAFEDIV(M36,L36),"")} | O36: {=IF(AND($D36,_xlfn.XLOOKUP($C36,tbl_Class[class],tbl_Class[weather_model])="yes"),_xlfn.XLOOKUP($C36,$C$16:$C$17,$E$16:$E$17)*(INDEX($C$23:$N$23,MONTH($B36))-INDEX($C$21:$N$21,MONTH($B36)))+_xlfn.XLOOKUP($C36,$C$16:$C$17,$F$16:$F$17)*(INDEX($C$24:$N$24,MONTH($B36))-INDEX($C$22:$N$22,MONTH($B36))),IF($D36,0,""))} | P36: =IF($D36,IF(_xlfn.XLOOKUP($C36,tbl_Class[class],tbl_Class[weather_model])="yes",(K36-E36)*H36*I36,0),"") | Q36: =IF($D36,IF(_xlfn.XLOOKUP($C36,tbl_Class[class],tbl_Class[weather_model])="yes",K36*O36*I36,0),"") | R36: {=IF($D36,IF(_xlfn.XLOOKUP($C36,tbl_Class[class],tbl_Class[weather_model])="yes",K36*(SAFEDIV(L36,K36)-H36-O36)*I36,(L36-G36)*I36),"")} | S36: =IF($D36,L36*(N36-I36),"") | T36: =IF($D36,P36+Q36+R36+S36-(M36-J36),"")
B37: =DATE(PlanYear,MOD(ROWS($B$28:B37)-1,12)+1,1) -> 46296 | C37: residential | D37: =MONTH($B37)<=PlanClosed -> FALSE | E37: =_xlfn.XLOOKUP($C37,$C$9:$C$12,$D$9:$D$12)*_xlfn.XLOOKUP($C37,$C$9:$C$12,$F$9:$F$12)^(MONTH($B37)/12) -> 852094.56 | F37: {=IF(_xlfn.XLOOKUP($C37,tbl_Class[class],tbl_Class[weather_model])="yes",_xlfn.XLOOKUP($C37,$C$16:$C$17,$D$16:$D$17)+_xlfn.XLOOKUP($C37,$C$16:$C$17,$E$16:$E$17)*INDEX($C$21:$N$21,MONTH($B37))+_xlfn.XLOOKUP($C37,$C$16:$C$17,$F$16:$F$17)*INDEX($C$22:$N$22,MONTH($B37))+_xlfn.XLOOKUP($C37,$C$16:$C$17,$G$16:$G$17)*TRENDYEARS($B37),"")} -> 0.67778425 | G37: =IF(_xlfn.XLOOKUP($C37,tbl_Class[class],tbl_Class[weather_model])="yes",E37*F37,SUMIFS(tbl_Monthly[mwh],tbl_Monthly[class],$C37,tbl_Monthly[month],EDATE($B37,-12))*_xlfn.XLOOKUP($C37,$C$9:$C$12,$I$9:$I$12)) -> 577536.27 | H37: {=SAFEDIV(G37,E37)} -> 0.67778425 | I37: {=SAFEDIV(SUMIFS(tbl_Monthly[revenue],tbl_Monthly[class],$C37,tbl_Monthly[month],EDATE($B37,-12)),SUMIFS(tbl_Monthly[mwh],tbl_Monthly[class],$C37,tbl_Monthly[month],EDATE($B37,-12)))*_xlfn.XLOOKUP($C37,$C$9:$C$12,$L$9:$L$12)} -> 197.39045 | J37: =G37*I37 -> 1.1400014e+08 | K37: =IF($D37,SUMIFS(tbl_Monthly[customers],tbl_Monthly[class],$C37,tbl_Monthly[month],$B37),"") | L37: =IF($D37,SUMIFS(tbl_Monthly[mwh],tbl_Monthly[class],$C37,tbl_Monthly[month],$B37),"") | M37: =IF($D37,SUMIFS(tbl_Monthly[revenue],tbl_Monthly[class],$C37,tbl_Monthly[month],$B37),"") | N37: {=IF($D37,SAFEDIV(M37,L37),"")} | O37: {=IF(AND($D37,_xlfn.XLOOKUP($C37,tbl_Class[class],tbl_Class[weather_model])="yes"),_xlfn.XLOOKUP($C37,$C$16:$C$17,$E$16:$E$17)*(INDEX($C$23:$N$23,MONTH($B37))-INDEX($C$21:$N$21,MONTH($B37)))+_xlfn.XLOOKUP($C37,$C$16:$C$17,$F$16:$F$17)*(INDEX($C$24:$N$24,MONTH($B37))-INDEX($C$22:$N$22,MONTH($B37))),IF($D37,0,""))} | P37: =IF($D37,IF(_xlfn.XLOOKUP($C37,tbl_Class[class],tbl_Class[weather_model])="yes",(K37-E37)*H37*I37,0),"") | Q37: =IF($D37,IF(_xlfn.XLOOKUP($C37,tbl_Class[class],tbl_Class[weather_model])="yes",K37*O37*I37,0),"") | R37: {=IF($D37,IF(_xlfn.XLOOKUP($C37,tbl_Class[class],tbl_Class[weather_model])="yes",K37*(SAFEDIV(L37,K37)-H37-O37)*I37,(L37-G37)*I37),"")} | S37: =IF($D37,L37*(N37-I37),"") | T37: =IF($D37,P37+Q37+R37+S37-(M37-J37),"")
B38: =DATE(PlanYear,MOD(ROWS($B$28:B38)-1,12)+1,1) -> 46327 | C38: residential | D38: =MONTH($B38)<=PlanClosed -> FALSE | E38: =_xlfn.XLOOKUP($C38,$C$9:$C$12,$D$9:$D$12)*_xlfn.XLOOKUP($C38,$C$9:$C$12,$F$9:$F$12)^(MONTH($B38)/12) -> 852877.15 | F38: {=IF(_xlfn.XLOOKUP($C38,tbl_Class[class],tbl_Class[weather_model])="yes",_xlfn.XLOOKUP($C38,$C$16:$C$17,$D$16:$D$17)+_xlfn.XLOOKUP($C38,$C$16:$C$17,$E$16:$E$17)*INDEX($C$21:$N$21,MONTH($B38))+_xlfn.XLOOKUP($C38,$C$16:$C$17,$F$16:$F$17)*INDEX($C$22:$N$22,MONTH($B38))+_xlfn.XLOOKUP($C38,$C$16:$C$17,$G$16:$G$17)*TRENDYEARS($B38),"")} -> 0.82433608 | G38: =IF(_xlfn.XLOOKUP($C38,tbl_Class[class],tbl_Class[weather_model])="yes",E38*F38,SUMIFS(tbl_Monthly[mwh],tbl_Monthly[class],$C38,tbl_Monthly[month],EDATE($B38,-12))*_xlfn.XLOOKUP($C38,$C$9:$C$12,$I$9:$I$12)) -> 703057.41 | H38: {=SAFEDIV(G38,E38)} -> 0.82433608 | I38: {=SAFEDIV(SUMIFS(tbl_Monthly[revenue],tbl_Monthly[class],$C38,tbl_Monthly[month],EDATE($B38,-12)),SUMIFS(tbl_Monthly[mwh],tbl_Monthly[class],$C38,tbl_Monthly[month],EDATE($B38,-12)))*_xlfn.XLOOKUP($C38,$C$9:$C$12,$L$9:$L$12)} -> 195.69094 | J38: =G38*I38 -> 1.3758196e+08 | K38: =IF($D38,SUMIFS(tbl_Monthly[customers],tbl_Monthly[class],$C38,tbl_Monthly[month],$B38),"") | L38: =IF($D38,SUMIFS(tbl_Monthly[mwh],tbl_Monthly[class],$C38,tbl_Monthly[month],$B38),"") | M38: =IF($D38,SUMIFS(tbl_Monthly[revenue],tbl_Monthly[class],$C38,tbl_Monthly[month],$B38),"") | N38: {=IF($D38,SAFEDIV(M38,L38),"")} | O38: {=IF(AND($D38,_xlfn.XLOOKUP($C38,tbl_Class[class],tbl_Class[weather_model])="yes"),_xlfn.XLOOKUP($C38,$C$16:$C$17,$E$16:$E$17)*(INDEX($C$23:$N$23,MONTH($B38))-INDEX($C$21:$N$21,MONTH($B38)))+_xlfn.XLOOKUP($C38,$C$16:$C$17,$F$16:$F$17)*(INDEX($C$24:$N$24,MONTH($B38))-INDEX($C$22:$N$22,MONTH($B38))),IF($D38,0,""))} | P38: =IF($D38,IF(_xlfn.XLOOKUP($C38,tbl_Class[class],tbl_Class[weather_model])="yes",(K38-E38)*H38*I38,0),"") | Q38: =IF($D38,IF(_xlfn.XLOOKUP($C38,tbl_Class[class],tbl_Class[weather_model])="yes",K38*O38*I38,0),"") | R38: {=IF($D38,IF(_xlfn.XLOOKUP($C38,tbl_Class[class],tbl_Class[weather_model])="yes",K38*(SAFEDIV(L38,K38)-H38-O38)*I38,(L38-G38)*I38),"")} | S38: =IF($D38,L38*(N38-I38),"") | T38: =IF($D38,P38+Q38+R38+S38-(M38-J38),"")
B39: =DATE(PlanYear,MOD(ROWS($B$28:B39)-1,12)+1,1) -> 46357 | C39: residential | D39: =MONTH($B39)<=PlanClosed -> FALSE | E39: =_xlfn.XLOOKUP($C39,$C$9:$C$12,$D$9:$D$12)*_xlfn.XLOOKUP($C39,$C$9:$C$12,$F$9:$F$12)^(MONTH($B39)/12) -> 853660.46 | F39: {=IF(_xlfn.XLOOKUP($C39,tbl_Class[class],tbl_Class[weather_model])="yes",_xlfn.XLOOKUP($C39,$C$16:$C$17,$D$16:$D$17)+_xlfn.XLOOKUP($C39,$C$16:$C$17,$E$16:$E$17)*INDEX($C$21:$N$21,MONTH($B39))+_xlfn.XLOOKUP($C39,$C$16:$C$17,$F$16:$F$17)*INDEX($C$22:$N$22,MONTH($B39))+_xlfn.XLOOKUP($C39,$C$16:$C$17,$G$16:$G$17)*TRENDYEARS($B39),"")} -> 0.93185718 | G39: =IF(_xlfn.XLOOKUP($C39,tbl_Class[class],tbl_Class[weather_model])="yes",E39*F39,SUMIFS(tbl_Monthly[mwh],tbl_Monthly[class],$C39,tbl_Monthly[month],EDATE($B39,-12))*_xlfn.XLOOKUP($C39,$C$9:$C$12,$I$9:$I$12)) -> 795489.63 | H39: {=SAFEDIV(G39,E39)} -> 0.93185718 | I39: {=SAFEDIV(SUMIFS(tbl_Monthly[revenue],tbl_Monthly[class],$C39,tbl_Monthly[month],EDATE($B39,-12)),SUMIFS(tbl_Monthly[mwh],tbl_Monthly[class],$C39,tbl_Monthly[month],EDATE($B39,-12)))*_xlfn.XLOOKUP($C39,$C$9:$C$12,$L$9:$L$12)} -> 192.19316 | J39: =G39*I39 -> 1.5288767e+08 | K39: =IF($D39,SUMIFS(tbl_Monthly[customers],tbl_Monthly[class],$C39,tbl_Monthly[month],$B39),"") | L39: =IF($D39,SUMIFS(tbl_Monthly[mwh],tbl_Monthly[class],$C39,tbl_Monthly[month],$B39),"") | M39: =IF($D39,SUMIFS(tbl_Monthly[revenue],tbl_Monthly[class],$C39,tbl_Monthly[month],$B39),"") | N39: {=IF($D39,SAFEDIV(M39,L39),"")} | O39: {=IF(AND($D39,_xlfn.XLOOKUP($C39,tbl_Class[class],tbl_Class[weather_model])="yes"),_xlfn.XLOOKUP($C39,$C$16:$C$17,$E$16:$E$17)*(INDEX($C$23:$N$23,MONTH($B39))-INDEX($C$21:$N$21,MONTH($B39)))+_xlfn.XLOOKUP($C39,$C$16:$C$17,$F$16:$F$17)*(INDEX($C$24:$N$24,MONTH($B39))-INDEX($C$22:$N$22,MONTH($B39))),IF($D39,0,""))} | P39: =IF($D39,IF(_xlfn.XLOOKUP($C39,tbl_Class[class],tbl_Class[weather_model])="yes",(K39-E39)*H39*I39,0),"") | Q39: =IF($D39,IF(_xlfn.XLOOKUP($C39,tbl_Class[class],tbl_Class[weather_model])="yes",K39*O39*I39,0),"") | R39: {=IF($D39,IF(_xlfn.XLOOKUP($C39,tbl_Class[class],tbl_Class[weather_model])="yes",K39*(SAFEDIV(L39,K39)-H39-O39)*I39,(L39-G39)*I39),"")} | S39: =IF($D39,L39*(N39-I39),"") | T39: =IF($D39,P39+Q39+R39+S39-(M39-J39),"")
